Workbook
Name __FDS_HYPERLINK_TOGGLE_STATE__: "ON"
Name __IntlFixup: TRUE
Name _Order1: 255
Name _Order2: 255
Name _Regression_Int: 1
Name AccessDatabase: "C:\accts\AUD97_98.mdb"
Name anscount: 2
Name AS2DocOpenMode: "AS2DocumentEdit"
Name AS2HasNoAutoHeaderFooter: " "
Name AS2NamedRange: 2
Name AS2ReportLS: 1
Name AS2VersionLS: 300
Name BG_Del: 15
Name BG_Ins: 4
Name BG_Mod: 6
Name bkj: {"'Sheet1'!$A$5:$E$42"}
Name bkj: {"'Sheet1'!$A$5:$E$42"}
Name cenvat: {"'August 2000'!$A$1:$J$101"}
Name cenvat: {"'August 2000'!$A$1:$J$101"}
Name crador: {"'kpi2-1'!$E$4"}
Name crador: {"'kpi2-1'!$E$4"}
Name csczd: 0
Name dhakjs: {"'August 2000'!$A$1:$J$101"}
Name dhakjs: {"'August 2000'!$A$1:$J$101"}
Name EV__LASTREFTIME__: 40035.4476736111
Name Ext_EP: {"'kpi2-1'!$E$4"}
Name Ext_EP: {"'kpi2-1'!$E$4"}
Name gejsdfngjkosdnm: {"'Sheet1'!$A$5:$E$42"}
Name gejsdfngjkosdnm: {"'Sheet1'!$A$5:$E$42"}
Name H_1: {"'Sheet1'!$A$5:$E$42"}
Name H_1: {"'Sheet1'!$A$5:$E$42"}
Name H_1_1: {"'Sheet1'!$A$5:$E$42"}
Name H_1_1: {"'Sheet1'!$A$5:$E$42"}
Name H_1_2: {"'Sheet1'!$A$5:$E$42"}
Name H_1_2: {"'Sheet1'!$A$5:$E$42"}
Name H_1_3: {"'Sheet1'!$A$5:$E$42"}
Name H_1_3: {"'Sheet1'!$A$5:$E$42"}
Name H_2: {"'Sheet1'!$A$5:$E$42"}
Name H_2: {"'Sheet1'!$A$5:$E$42"}
Name H_3: {"'Sheet1'!$A$5:$E$42"}
Name H_3: {"'Sheet1'!$A$5:$E$42"}
Name H_4: {"'Sheet1'!$A$5:$E$42"}
Name H_4: {"'Sheet1'!$A$5:$E$42"}
Name html: {"'kpi2-1'!$E$4"}
Name html: {"'kpi2-1'!$E$4"}
Name HTML_CodePage: 949
Name HTML_CodePage: 1252
Name HTML_Control: {"'kpi2-1'!$E$4"}
Name HTML_Control: {"'I-1 and I-2'!$A$1:$G$190"}
Name HTML_Control: {"'kpi2-1'!$E$4"}
Name HTML_Control_1: {"'August 2000'!$A$1:$J$101"}
Name HTML_Control_1: {"'August 2000'!$A$1:$J$101"}
Name HTML_Control_1_1: {"'Sheet1'!$A$5:$E$42"}
Name HTML_Control_1_1: {"'Sheet1'!$A$5:$E$42"}
Name HTML_Control_1_2: {"'Sheet1'!$A$5:$E$42"}
Name HTML_Control_1_2: {"'Sheet1'!$A$5:$E$42"}
Name HTML_Control_1_3: {"'Sheet1'!$A$5:$E$42"}
Name HTML_Control_1_3: {"'Sheet1'!$A$5:$E$42"}
Name HTML_Control_2: {"'Sheet1'!$A$5:$E$42"}
Name HTML_Control_2: {"'Sheet1'!$A$5:$E$42"}

Sheet BS
B2: Balance Sheet as at 31 March 2025
B3: (Amounts are stated in ₹ lakhs, except share and per share data, unless ottherwise stated) | H3: BS | I3: =E31-E64 -> -0.081383736 | J3: =F31-F64 -> -0.22206287
H4: Cash flow | I4: =Cashflow!D50-Cashflow!D58 -> -0.30940571 | J4: =Cashflow!E50-Cashflow!E58 -> 0.002824503
B5: Particulars | C5: Notes | E5: As at 31 March 2025 | F5: As at 31 March 2024
B7: Assets
B9: Non-current assets
B10: Property,plant and equipment | C10: ='3-4'!A5 -> 3 | E10: ='3-4'!H28 -> 381.66709 | F10: ='3-4'!H29 -> 589.31208
B11: Other Intangible assets | C11: ='3-4'!A33 -> 4 | E11: ='3-4'!E56 -> 3913.8615 | F11: ='3-4'!E57 -> 3214.71
B12: Right-of-use of assets | C12: ='Leases 29'!A5 -> 29 | E12: ='Leases 29'!E33 -> 752.24662 | F12: ='Leases 29'!E34 -> 754.68761
B13: Intangible assets under development | C13: ='3-4'!A33 -> 4 | E13: ='3-4'!D56 -> 0 | F13: ='3-4'!D57 -> 589
B14: Other intangible assets | C14: ='3-4'!A33 -> 4 | E14: ='Standalone TB'!X182+'Standalone TB'!X175 -> 0 | F14: 0
B15: Financial assets
B16: Other financial assets | C16: ='5-7'!A6 -> 5 | E16: ='5-7'!D17 -> 443.52744 | F16: ='5-7'!E17 -> 773
B17: Deferred tax assets (net) | C17: ='26-27'!A5 -> 26 | E17: ='26-27'!F90 -> 398.71987 | F17: ='26-27'!G120 -> 398.51987
B18: Income tax assets (net) | C18: ='26-27'!A5 -> 26 | E18: ='26-27'!F72 -> 981.25818 | F18: ='26-27'!G72 -> 1849.6468
B19: Total non-current assets | D19: =SUM(D10:D18) -> 0 | E19: =SUM(E10:E18) -> 6871.2807 | F19: =SUM(F10:F18)+1 -> 8169.8763
B21: Current assets
B22: Financial assets
B23: Investments | C23: 7 | D23: 0 | E23: 0 | F23: 0
B24: Trade receivables | C24: ='8-10'!$A$5 -> 8 | E24: ='8-10'!I17 -> 9350.3619 | F24: ='8-10'!$J$17 -> 11738.93
B25: Cash and cash equivalents | C25: ='8-10'!$A$53 -> 9 | E25: ='8-10'!$I$60 -> 5497.6528 | F25: ='8-10'!$J$60 -> 3886.7736
B26: Bank balances other than cash and cash equivalents above | C26: ='8-10'!A67 -> 10 | E26: ='8-10'!$I$70 -> 2.402056 | F26: ='8-10'!$J$70 -> 2247.8618
B27: Other financial assets | C27: ='5-7'!A6 -> 5 | E27: ='5-7'!D25 -> 204.39541 | F27: ='5-7'!E25 -> 129
B28: Other current assets | C28: ='5-7'!A30 -> 6 | E28: ='5-7'!D45 -> 2176.4271 | F28: ='5-7'!E45 -> 2591.132
B29: Total current assets | D29: =SUM(D22:D28) -> 0 | E29: =SUM(E24:E28) -> 17231.239 | F29: =SUM(F22:F28) -> 20593.697
B31: Total assets | D31: =+D19+D29 -> 0 | E31: =+E19+E29 -> 24102.52 | F31: =+F19+F29 -> 28763.573
B34: Equity and liabilities
B36: Equity
B37: Share capital | C37: ='11-13'!$A$5 -> 11 | E37: =('11-13'!H28+'11-13'!H35) -> 50.6183 | F37: =5061830/10^5 -> 50.6183
B38: Other equity | C38: ='11-13'!$A$109 -> 12 | E38: ='11-13'!G113 -> 11476.706 | F38: ='11-13'!H113 -> 11364.975
B39: c) Share application pending allotment | C39: 12 | D39: 0 | E39: 0 | F39: 0
B40: Total equity | D40: =SUM(D37:D39) -> 0 | E40: =SUM(E37:E39) -> 11527.325 | F40: =SUM(F37:F39)+0.3 -> 11415.893
B42: Liabilities
B43: Non-current liabilities
B44: Employee benefit obligations | C44: ='11-13'!$A$142 -> 13 | E44: ='11-13'!G146 -> 0 | F44: ='11-13'!H146 -> 897.06919
B45: Financial liabilities
B46: Lease liabilities | C46: ='Leases 29'!A5 -> 29 | E46: ='Leases 29'!$D$81 -> 691.50412 | F46: ='Leases 29'!E81 -> 690.21247
B47: b) Other long-term liabilities | E47: 0 | F47: 0
B48: Total non-current liabilities | D48: =SUM(D44:D47) -> 0 | E48: =SUM(E44:E47) -> 691.50412 | F48: =SUM(F44:F47) -> 1587.2817
B50: Current liabilities
B51: Financial liabilities
B52: Lease liabilities | C52: ='Leases 29'!A5 -> 29 | E52: ='Leases 29'!D82 -> 326.74237 | F52: ='Leases 29'!E82 -> 314.57408
B53: Trade payables
B54: Total outstanding dues of micro enterprises and small enterprises; and | C54: ='14-16'!$A$5 -> 14 | E54: ='14-16'!I8 -> 0.9547465 | F54: ='14-16'!J8 -> 78.55814
B55: Total outstanding dues of creditors other than micro enterprises and small enterprises | C55: ='14-16'!$A$5 -> 14 | E55: ='14-16'!I16-E54 -> 5144.5249 | F55: ='14-16'!J16-F54 -> 8312.7246
B56: Other financial liabilities | C56: ='14-16'!$A$49 -> 15 | E56: ='14-16'!I53 -> 4189.1737 | F56: ='14-16'!J53 -> 5272.3365
B57: Employee benefit obligations | C57: ='11-13'!$A$142 -> 13 | E57: ='11-13'!G152 -> 1329.9226 | F57: ='11-13'!H152 -> 467.33622
B58: Other current liabilities | C58: ='14-16'!A57 -> 16 | E58: ='14-16'!I67 -> 892.45427 | F58: ='14-16'!J67 -> 1315.111
B59: d) Income tax liabilities(net) | C59: 27 | D59: 0 | E59: 0 | F59: 0
B60: Total current liabilities | D60: =SUM(D51:D59) -> 0 | E60: =SUM(E51:E59) -> 11883.773 | F60: =SUM(F51:F59)+0.2 -> 15760.841
B62: Total liabilities | D62: =D48+D60 -> 0 | E62: =E48+E60 -> 12575.277 | F62: =F48+F60 -> 17348.122
B64: Total equity and liabilities | D64: =D62+D40 -> 0 | E64: =E62+E40 -> 24102.601 | F64: =F62+F40-0.22 -> 28763.795
B66: Summary of material accounting policies | C66: ='Note 1-2'!B7 -> 2 | F66: =F64-F31 -> 0.22206287
B67: The accompanying notes are an integral part of the financial statements
B68: As per our report of even date
B70: For Walker Chandiok & Co LLP | E70: For and on behalf of the Board of Directors of
B71: Chartered Accountants
B72: Firm's Registration No: 001076N/N500013 | E72: CIN: U72200TN2018FTC120862

Sheet Cash flow Working
A1: Paladion Networks Private Limited | AI1: Legends:
A2: Cash Flow Statement for the year ended 31 March 2023 | AI2: a | AJ2: Traced from CY FS
AI3: b | AJ3: Traced from PY FS
AI4: e | AJ4: Recomputed
A7: Particulars | B7: Cash Flow | C7: Share Capital | D7: Securities premium | E7: Retained earning | F7: Current Year Profit | G7: Employee benefit obligations (Non- Current) | H7: Employee benefit obligations (Current) | I7: Lease liabilities | J7: Trade payables | K7: Other financial liabilities | L7: Other current liabilities | N7: Property, Plant and Equipment | O7: Other intangible assets | P7: CWIP-Internal Software Development | Q7: Right-of-use of assets | R7: Security deposits (Current) | S7: Security deposits (Non-Current) | T7: Deposits with banks (Non-Current) | U7: Deposits with banks (Current) | V7: Interest accrued on deposits (Non-Current) | W7: Interest accrued on deposits (Current) | X7: Deferred tax assets (Non-Current) | Y7: Lease receivable(Non -Current) | Z7: Advance tax (Non-Current) | AA7: Trade receivables | AB7: Advance to suppliers (Current) | AC7: Loans and advance to employees (Current) | AD7: Receivable from related parties | AE7: Other receivables | AF7: Balance with government authorities (Current) | AG7: Prepaid expenses (Current) | AH7: Cash effect | AI7: Total
A8: Balance 31 March 2025 (Amount in INR) | C8: =-'11-13'!F18 -> -50.6183 | D8: =-'11-13'!G125 -> -41916.54 | E8: =E10 -> 30551.565 | F8: =-F9 -> -111.73127 | G8: ='11-13'!G146 -> 0 | H8: =-'11-13'!G152 -> -1329.9226 | I8: =-'Leases 29'!D83 -> -1018.2465 | J8: =-'14-16'!I16 -> -5145.4797 | K8: =-'14-16'!I53 -> -4189.1737 | L8: =-'14-16'!I67 -> -892.45427 | N8: ='3-4'!H28 -> 381.66709 | O8: ='3-4'!E56 -> 3913.8615 | P8: ='3-4'!D56 -> 0 | Q8: =BS!E12 -> 752.24662 | R8: ='5-7'!D22 -> 181.35703 | S8: ='5-7'!D12+'5-7'!D11 -> 172.52744 | T8: ='5-7'!D13 -> 31 | U8: ='5-7'!D23+'8-10'!I69 -> 25.402056 | V8: ='5-7'!D14 -> 1 | W8: ='5-7'!D24 -> 0.038374 | X8: ='26-27'!F90 -> 398.71987 | Y8: ='5-7'!D16 -> 239 | Z8: =BS!E18 -> 981.25818 | AA8: ='8-10'!I17 -> 9350.3619 | AB8: ='5-7'!D44 -> 0 | AC8: ='5-7'!D41 -> 20.809125 | AD8: ='5-7'!D39 -> 142.90723 | AE8: ='5-7'!D40 -> 101.11986 | AF8: ='5-7'!D42 -> 1617.808 | AG8: ='5-7'!D43 -> 293.78288 | AH8: ='8-10'!I60 -> 5497.6528 | AI8: =SUM(C8:AH8) -> -0.081383736 | AJ8: a
B9: =-PL!D45 -> -111.73127 | F9: =-B9 -> 111.73127 | AI9: 0
A10: Balance 31 March 2024 (Amount in INR) | C10: =-'11-13'!H18 -> -50.6183 | D10: =-'11-13'!H125 -> -41916.54 | E10: =-'11-13'!H134 -> 30551.565 | G10: =-'11-13'!H146 -> -897.06919 | H10: =-'11-13'!H152 -> -467.33622 | I10: =-'Leases 29'!E83 -> -1004.7865 | J10: =-'14-16'!J16 -> -8391.2828 | K10: =-'14-16'!J53 -> -5272.3365 | L10: =-'14-16'!J67 -> -1315.111 | N10: ='3-4'!H29 -> 589.31208 | O10: ='3-4'!E57 -> 3214.71 | P10: ='3-4'!D57 -> 589 | Q10: ='Leases 29'!C34 -> 754.68761 | R10: ='5-7'!E22 -> 120 | S10: ='5-7'!E12+'5-7'!E11 -> 216 | T10: ='5-7'!E13 -> 170 | U10: ='5-7'!E23+'8-10'!J69 -> 2249.8618 | V10: ='5-7'!E14 -> 12 | W10: ='5-7'!E24 -> 7 | X10: ='26-27'!G90 -> 398.71987 | Y10: ='5-7'!E16 -> 375 | Z10: =BS!F18 -> 1849.6468 | AA10: ='8-10'!J17 -> 11738.93 | AB10: ='5-7'!E44 -> 39.614499 | AC10: ='5-7'!E41 -> 39.911882 | AD10: ='5-7'!E39 -> 1978.3663 | AE10: ='5-7'!E40+1 -> 41.237245 | AF10: ='5-7'!E42 -> 372.40413 | AG10: ='5-7'!E43 -> 120.59794 | AH10: ='8-10'!J60 -> 3886.7736 | AI10: =SUM(B10:AH10) -> 0.25793713 | AJ10: b
A11: Change during the year | B11: =B10-B8-B9 -> 111.73127 | C11: =C10-C8-C9 -> 0 | D11: =D10-D8-D9 -> 0 | E11: =E10-E8-E9 -> 0 | G11: =G10-G8-G9 -> -897.06919 | H11: =H10-H8-H9 -> 862.58639 | I11: =I10-I8-I9 -> 13.459945 | J11: =J10-J8-J9 -> -3245.8031 | K11: =K10-K8-K9 -> -1083.1627 | L11: =L10-L8-L9 -> -422.65675 | N11: =N10-N8-N9 -> 207.64498 | O11: =O10-O8-O9 -> -699.1515 | P11: =P10-P8-P9 -> 589 | Q11: =Q10-Q8-Q9 -> 2.4409936 | R11: =R10-R8-R9 -> -61.357035 | S11: =S10-S8-S9 -> 43.472556 | T11: =T10-T8-T9 -> 139 | U11: =U10-U8-U9 -> 2224.4597 | ... AI11: =AI10-AI8-AI9 -> 0.33932087 | AJ11: e
A12: Non Cash adjustments in balance sheet | AI12: =SUM(B12:AH12) -> 0
A13: Transfer to Gratuity | B13: =-SUM(C13:AH13) -> 115.36426 | G13: =-PL!D37 -> -115.36426 | X13: =PL!D38 -> 0 | AI13: =SUM(B13:AH13) -> 0
A14: Tax charge | B14: =-SUM(C14:AH14) -> 0 | X14: =-PL!D28 -> 0 | AI14: =SUM(B14:AH14) -> 0
A15: Reclass | B15: =-SUM(C15:AH15) -> 0 | O15: =589 -> 589 | P15: =-589 -> -589 | R15: =0 -> 0 | V15: =-V11 -> -11 | W15: =-V15 -> 11 | Y15: =-Q15 -> 0 | AI15: =SUM(B15:AH15) -> 0
A16: New leases | B16: =-SUM(C16:AH16) -> 0 | I16: =-'Leases 29'!D70 -> -379.14853 | Q16: =-I16 -> 379.14853 | AI16: =SUM(B16:AH16) -> 0
A17: Transfer of Security Deposit to RoU As prepaid asset | B17: =-SUM(C17:AH17) -> 0 | Q17: =143847.940133968/10^5 -> 1.4384794 | S17: =-Q17 -> -1.4384794 | AI17: =SUM(B17:AH17) -> 0
A18: Modification of lease | B18: =-SUM(C18:AH18) -> 0 | AI18: =SUM(B18:AH18) -> 0
B19: =-SUM(C19:AH19) -> 0 | AI19: =SUM(B19:AH19) -> 0
A20: Profit Before Tax, prior period and exceptional | B20: =SUM(B11:B18) -> 227.09553
A21: Exceptional items | B21: =-SUM(C21:AH21) -> 0
A22: Profit Before Tax, prior period | B22: =B20+B21 -> 227.09553
A23: Non-cash items | AI23: =SUM(B23:AH23) -> 0
A24: Depreciation and amortization | B24: =-SUM(C24:AH24) -> 2477.7009 | N24: =-'17-25'!$D$139 -> -183.31775 | O24: =-'3-4'!E51 -> -1952.3551 | Q24: =-'17-25'!D141 -> -342.02812 | AI24: =SUM(B24:AH24) -> 0
A25: Finance income on financial assets measured at amortised cost | B25: =-SUM(C25:AH25) -> -27.46033 | Q25: =0 -> 0 | Y25: ='17-25'!C80/10^5 -> 27.46033 | AI25: =SUM(B25:AH25) -> 0
A26: Provision for diminushing investments in Subsidiary | B26: =-SUM(C26:AH26) -> 0 | AI26: =SUM(B26:AH26) -> 0
A27: Interest income on bank deposits | B27: =-SUM(C27:AH27) -> 0 | AI27: =SUM(B27:AH27) -> 0
A28: Exchange impact | B28: =-SUM(C28:AH28) -> 0 | AI28: =SUM(B28:AH28) -> 0
A29: Finance cost | B29: =-SUM(C29:AH29) -> 106.28668 | I29: =-'Leases 29'!E71 -> -106.28668 | AI29: =SUM(B29:AH29) -> 0
A30: Provision for doubtful trade receivables(net of reversal/utilisation) | B30: =-SUM(C30:AH30) -> 26.32863 | AA30: =-'17-25'!D177 -> -26.32863 | AI30: =SUM(B30:AH30) -> 0
A31: Provision / liabilities no longer required written back | B31: =-SUM(C31:AH31) -> 0 | AI31: =SUM(B31:AH31) -> 0
A32: Gain on sublease/sale of PPE | B32: =-SUM(C32:AH32) -> 0 | AI32: =SUM(B32:AH32) -> 0
AI33: =SUM(B33:AH33) -> 0
A34: Increase/Decrease in Current Assets and Liabilities | AI34: =SUM(B34:AH34) -> 0
A35: Movement of working capital | AI35: =SUM(B35:AH35) -> 0
A36: Decrease/(Increase) in trade receivables | B36: =-SUM(C36:AH36) -> 2362.2392 | AA36: =-AA11-AA30 -> -2362.2392 | AI36: =SUM(B36:AH36) -> 0
A37: Decrease/(Increase) in bank balance other than cash and cash equivalent | B37: =-SUM(C37:AH37) -> 0 | AI37: =SUM(B37:AH37) -> 0
A38: Decrease/(Increase) in loans and advances | B38: =-SUM(C38:AH38) -> 19.102757 | AC38: =-AC11 -> -19.102757 | AI38: =SUM(B38:AH38) -> 0
A39: Decrease/(Increase) in Other financial assets | B39: =-SUM(C39:AH39) -> 39.614499 | AB39: =-AB11 -> -39.614499 | AI39: =SUM(B39:AH39) -> 0
A40: Decrease/(Increase) in other assets | B40: =-SUM(C40:AH40) -> 356.98764 | AD40: =-AD11 -> -1835.459 | AE40: =-AE11 -> 59.882612 | AF40: =-AF11 -> 1245.4039 | AG40: =-AG11 -> 173.18494 | AI40: =SUM(B40:AH40) -> 0
A41: (Decrease)/Increase in trade payables | B41: =-SUM(C41:AH41) -> -3245.8031 | J41: =-J11 -> 3245.8031 | AI41: =SUM(B41:AH41) -> 0
A42: (Decrease)/Increase in other financial liabilities | B42: =-SUM(C42:AH42) -> -1144.5198 | K42: =-K11 -> 1083.1627 | R42: =-R11 -> 61.357035 | AI42: =SUM(B42:AH42) -> 0
A43: (Decrease)/Increase in other liabilities | B43: =-SUM(C43:AH43) -> -422.65675 | L43: =-L11-L31 -> 422.65675 | AI43: =SUM(B43:AH43) -> 0
A44: (Decrease)/Increase in provisions | B44: =-SUM(C44:AH44) -> -149.84706 | G44: =-G13-G11 -> 1012.4334 | H44: =-H11 -> -862.58639 | AI44: =SUM(B44:AH44) -> 0
AI45: =SUM(B45:AH45) -> 0
A46: Tax paid / refund | B46: =-SUM(C46:AH46) -> 868.38859 | Z46: =-Z11 -> -868.38859 | AI46: =SUM(B46:AH46) -> 0
AI47: =SUM(B47:AH47) -> 0
A48: Investing Activities | AI48: =SUM(B48:AH48) -> 0
A49: Purchase of property, plant and equipment | B49: =-SUM(C49:AH49) -> -2079.336 | N49: ='3-4'!H14 -> 16.82946 | O49: ='3-4'!E40 -> 2062.5066 | P49: ='3-4'!D40 -> 0 | AI49: =SUM(B49:AH49) -> 0
A50: Disposall of PPE | B50: =-SUM(C50:AH50) -> 41.52816 | N50: =('3-4'!H15-'3-4'!H24) -> -41.52816
A51: Interest received on deposits | B51: =-SUM(C51:AH51) -> 17.961626 | W51: =-SUM(W11:W49) -> -17.961626 | AI51: =SUM(B51:AH51) -> 0
A52: Investment in deposits | B52: =-SUM(C52:AH52) -> 2405.4938 | S52: =-S11-S17 -> -42.034076 | T52: =-T11 -> -139 | U52: =-U11 -> -2224.4597 | AI52: =SUM(B52:AH52) -> 0
A53: Financing Activities | B53: =-SUM(C53:AH53) -> 0 | AI53: =SUM(B53:AH53) -> 0
A54: Repayment of finance lease liability | B54: =-SUM(C54:AH54) -> -432.80307 | I54: =-'Leases 29'!E72-I29 -> 432.80307 | AI54: =SUM(B54:AH54) -> 0
A55: Receipt of finance lease | B55: =-SUM(C55:AH55) -> 163.465 | Y55: =-163-0.465 -> -163.465 | AI55: =SUM(B55:AH55) -> 0
A56: Abatement | I56: =-'Leases 29'!E74 -> 40.17219 | Q56: ='Leases 29'!E18 -> -40.17219 | AI56: =SUM(B56:AH56) -> 0
AI57: =SUM(B57:AH57) -> 0
A58: Increase in cash | B58: =-SUM(C58:AH58) -> -1610.8792 | AH58: =-AH11 -> 1610.8792 | AI58: =SUM(B58:AH58) -> 0
A59: Total | B59: =SUM(B22:B58) -> -1.1122302 | C59: =SUM(C11:C58) -> 0 | D59: =SUM(D11:D58) -> 0 | E59: =SUM(E11:E58) -> 0 | G59: =SUM(G11:G58) -> 0 | H59: =SUM(H11:H58) -> 0 | I59: =SUM(I11:I58) -> 1 | J59: =SUM(J11:J58) -> 0 | K59: =SUM(K11:K58) -> 0 | L59: =SUM(L11:L58) -> 0 | N59: =SUM(N11:N58) -> -0.37147133 | O59: =SUM(O11:O58) -> 0 | P59: =SUM(P11:P58) -> 0 | Q59: =SUM(Q11:Q58) -> 0.82768941 | R59: =SUM(R11:R58) -> 0 | S59: =SUM(S11:S58) -> 0 | T59: =SUM(T11:T58) -> 0 | U59: =SUM(U11:U58) -> 0 | ... AI59: =SUM(AI11:AI58) -> 0.33932087

Sheet PL
B2: Statement of Profit and Loss for the year ended 31 March 2025
B3: =BS!B3 -> (Amounts are stated in ₹ lakhs, except share and per share data, unless ottherwise stated)
B5: Particulars | C5: Notes | D5: For the year ended 31 March 2025 | E5: For the year ended 31 March 2024
B7: Revenue
B8: Revenue from contracts with the customers | C8: ='17-25'!$A$5 -> 17 | D8: ='17-25'!D12 -> 23301.29 | E8: ='17-25'!E12 -> 28077.967 | F8: =D8/E8-1 -> -0.1701219 | H8: =D8*10^5 -> 2.330129e+09
B9: Other Income | C9: ='17-25'!$A$73 -> 18 | D9: ='17-25'!D90 -> 261.95673 | E9: ='17-25'!E90 -> 385.02038 | F9: =D9/E9-1 -> -0.31962891 | H9: =D9*10^5 -> 26195673
B10: Total Income | D10: =SUM(D8:D9) -> 23563.246 | E10: =SUM(E8:E9) -> 28462.987 | H10: =SUM(H8:H9) -> 2.3563246e+09
B12: Expenses
B13: Cost of software packages | C13: ='17-25'!$A$93 -> 19 | D13: ='17-25'!D97 -> 1483.5182 | E13: ='17-25'!E97 -> 1510.2087 | F13: =D13/E13-1 -> -0.017673401 | H13: =D13*10^5 -> 1.4835182e+08
B14: Technical contract charges | C14: ='17-25'!$A$99 -> 20 | D14: ='17-25'!D104 -> 7381.0085 | E14: ='17-25'!E104 -> 8924.3992 | F14: =D14/E14-1 -> -0.17294057 | H14: =D14*10^5 -> 7.3810085e+08
B15: Employee benefits expense | C15: ='17-25'!$A$110 -> 21 | D15: ='17-25'!D121 -> 8727.4152 | E15: ='17-25'!E121 -> 11030.44 | F15: =D15/E15-1 -> -0.20878812 | H15: =D15*10^5 -> 8.7274152e+08
B16: Finance costs | C16: ='17-25'!$A$123 -> 22 | D16: ='17-25'!D133 -> 140.66685 | E16: ='17-25'!E133 -> 92.783532 | F16: =D16/E16-1 -> 0.51607558 | H16: =D16*10^5 -> 14066685
B17: Depreciation and amortisation | C17: ='17-25'!$A$137 -> 23 | D17: ='17-25'!D142 -> 2477.7009 | E17: ='17-25'!E142 -> 740.7639 | F17: =D17/E17-1 -> 2.3447917 | H17: =D17*10^5 -> 2.4777009e+08
B18: Other expenses | C18: ='17-25'!$A$151 -> 24 | D18: ='17-25'!D190 -> 2702.0666 | E18: ='17-25'!E190 -> 2956 | F18: =D18/E18-1 -> -0.0859044 | H18: =D18*10^5 -> 2.7020666e+08
B19: Total expenses | D19: =SUM(D13:D18) -> 22912.376 | E19: =SUM(E13:E18)-1 -> 25253.595 | H19: =SUM(H13:H18) -> 2.2912376e+09
B21: Profit / (Loss) before exceptional items and tax | D21: =D10-D19 -> 650.87006 | E21: =E10-E19 -> 3209.3917
B22: Exceptional item | C22: ='17-25'!A201 -> 25 | D22: ='17-25'!D203 -> 0 | E22: 18242
B23: (Loss) before tax | D23: =D21-D22 -> 650.87006 | E23: =E21-E22 -> -15032.608 | H23: =D23*10^5 -> 65087006
H24: =H10-H19 -> 65087006
B25: Tax expense
B26: Current tax | C26: ='26-27'!A5 -> 26 | D26: ='26-27'!$F$14 -> 654.50305 | E26: 8.6358
B27: Prior year's tax adjustments | D27: 0 | E27: 0
B28: Deferred tax charge / (credit) | C28: ='26-27'!A5 -> 26 | D28: =0 -> 0 | E28: 1082.1538
D29: =SUM(D26:D28) -> 654.50305 | E29: =SUM(E26:E28) -> 1090.7896
B31: (Loss) / Profit for the year after tax | D31: =D23-D29 -> -3.6329941 | E31: =E23-E29 -> -16123.398 | H31: =D31*10^5 -> -363299.41
B35: Other comprehensive income / (loss)
B36: (i) Items that will not be reclassified to profit or loss
A37: OCI | B37: - Remeasurment of defined benefit plan | D37: =-SUMIF('Standalone TB'!$Z:$Z,PL!A37,'Standalone TB'!$X:$X)/10^5 -> 115.36426 | E37: 49.89188
B38: - Income tax relating to above | D38: =-D37*0 -> 0 | E38: -12.556788
B40: (ii) Items that will be reclassified to profit or loss
B41: - Income tax relating to above | D41: - | E41: -
B43: Other comprehensive income / (loss) for the year (net of tax) | D43: =SUM(D37:D38) -> 115.36426 | E43: =SUM(E37:E38) -> 37.335092
B45: Total comprehensive (loss) / income for the year (net of tax) | D45: =D31+D43 -> 111.73127 | E45: =E31+E43 -> -16086.063 | F45: =ROUND(D45,0) -> 112 | H45: =D45*10^5 -> 11173127 | I45: =SUMIF('Standalone TB'!D:D,"PL",'Standalone TB'!X:X) -> -11173127 | J45: =H45+I45 -> -1.2852252e-07
C47: 26
B48: Basic earnings per equity share (Face value of ₹ 10 each) | D48: ='26-27'!$F$130 -> -36.329941 | E48: ='26-27'!$G$130 -> -161241.98
B49: Diluted Earnings per equity share (Face value of ₹ 10 each) | D49: ='26-27'!$F$133 -> 0 | E49: ='26-27'!$G$133 -> -3.8410993
B51: Summary of material accounting policies | C51: 2 | E51: =E49-E12 -> -3.8410993
B52: The accompanying notes are an integral part of the financial statements
B53: As per our report of even date
B55: For Walker Chandiok & Co LLP | D55: For and on behalf of the Board of Directors of
B56: Chartered Accountants
B57: Firm's Registration No: 001076N/N500013 | D57: CIN: U72200TN2018FTC120862

Sheet SOCE 
B1: Paladion Networks Private Limited
B2: Statement of Change in Equity for the year ended 31 March 2025
B3: =PL!B3 -> (Amounts are stated in ₹ lakhs, except share and per share data, unless ottherwise stated)
B5: (A) Share capital
B7: Particulars | E7: Note | F7: No. of shares | G7: Amount
B8: Issued, subscribed and fully paid up
B9: Equity shares of ₹ 10 each | E9: ='11-13'!$A$5 -> 11
B10: Property and equipment
B11: Balance as at 31 March 2023 | F11: ='11-13'!G24 -> 10000 | G11: =F11*10/10^5 -> 1
B12: Changes in equity share capital during the year | F12: - | G12: -
B13: Balance as at 31 March 2024 | F13: =SUM(F11:F12) -> 10000 | G13: =SUM(G11:G12) -> 1
B14: Changes in equity share capital during the year | F14: - | G14: -
B15: Balance as at 31 March 2025 | F15: =SUM(F13:F14) -> 10000 | G15: =SUM(G13:G14) -> 1
B17: Preference shares of ₹ 10 each | E17: ='11-13'!$A$5 -> 11
B19: Balance as at 31 March 2023 | F19: ='11-13'!E17 -> 496183 | G19: =F19*10/10^5 -> 49.6183
B20: Changes in equity share capital during the year | F20: ='11-13'!G32 -> 0 | G20: =(F20*10)/10^5 -> 0
B21: Balance as at 31 March 2024 | F21: =SUM(F19:F20) -> 496183 | G21: =SUM(G19:G20) -> 49.6183
B22: Changes in equity share capital during the year | F22: 0 | G22: 0
B23: Balance as at 31 March 2025 | F23: =SUM(F21:F22) -> 496183 | G23: =SUM(G21:G22) -> 49.6183
B26: (B) Other equity (Refer Note 12) | E26: Reserves and Surplus
B28: Particulars | E28: Securities Premium | F28: Retained earnings | G28: Total
B29: =B11 -> Balance as at 31 March 2023 | E29: ='11-13'!H123 -> 41916.54 | F29: ='11-13'!H131 -> -14464.702 | G29: =SUM(E29:F29) -> 27451.838
B30: Profit for the year | E30: - | F30: ='11-13'!H132 -> -16124.198 | G30: =SUM(E30:F30) -> -16124.198
B31: Other comprehensive loss | E31: - | F31: ='11-13'!H133 -> 37.335092 | G31: =SUM(E31:F31) -> 37.335092
B32: Additions during the year | E32: - | F32: - | G32: -
B33: =B13 -> Balance as at 31 March 2024 | E33: =SUM(E29:E32) -> 41916.54 | F33: =SUM(F29:F32)+0.1 -> -30551.465 | G33: =SUM(G29:G32) -> 11364.975 | H33: =F33*10^5 -> -3.0551465e+09 | I33: =SUMIF('Standalone TB'!Z:Z,"Retained earnings",'Standalone TB'!X:X) -> 3.0551465e+09 | J33: =H33+I33 -> 0
B34: Profit for the year | E34: 0 | F34: ='11-13'!G132 -> -3.6329941 | G34: =SUM(E34:F34) -> -3.6329941
B35: Other comprehensive loss | E35: 0 | F35: ='11-13'!G133 -> 115.36426 | G35: =SUM(E35:F35) -> 115.36426
B36: Additions during the year | E36: 0 | F36: 0 | G36: 0
B37: =B15 -> Balance as at 31 March 2025 | E37: =SUM(E33:E36) -> 41916.54 | F37: =SUM(F33:F36) -> -30439.734 | G37: =SUM(G33:G36)+0.5 -> 11477.206
B39: This is the Statement of Changes in Equity referred to in our report of even date
B41: The accompanying notes are an integral part of the financial statements
B42: As per our report of even date
B44: For Walker Chandiok & Co LLP | F44: For and on behalf of the Board of Directors of
B45: Chartered Accountants | F45: Paladion Networks Private Limited
B46: Firm's Registration No: 001076N/N500013 | F46: CIN: U72200TN2018FTC120862
B50: =PL!#REF! -> #REF! | F50: Arvind Jugalkishor Bajaj | G50: =PL!#REF! -> #REF!
B51: =PL!#REF! -> #REF! | F51: Director | G51: =PL!#REF! -> #REF!
B52: =PL!#REF! -> #REF! | F52: DIN : 08051490 | G52: =PL!#REF! -> #REF!
B54: =PL!#REF! -> #REF! | F54: Place: Mumbai | G54: Place: Mumbai
B55: =PL!#REF! -> #REF! | F55: Date: | G55: Date:

Sheet Cashflow
B1: ='SOCE '!B1 -> Paladion Networks Private Limited
B2: Statement of Cash Flow for the year ended 31 March 2025
B3: ='SOCE '!B3 -> (Amounts are stated in ₹ lakhs, except share and per share data, unless ottherwise stated)
B5: Particulars | D5: Year ended 31 March 2025 | E5: Year ended 31 March 2024
B7: Cash flow from operating activities
B8: Profit before tax | D8: ='Cash flow Working'!B20 -> 227.09553 | E8: -14942.46 | AA8: =D8-Z8 -> 227.09553
B9: Adjustments to reconcile loss before tax to net cashflow :
B10: Depreciation and amortization | D10: ='Cash flow Working'!B24 -> 2477.7009 | E10: 740.7639
B11: Impairmemt of Goodwill | D11: =PL!D22 -> 0 | E11: 18242
B12: Provision for diminution (other than temporary) in value of investments | D12: =0 -> 0 | E12: 54.567653
B13: Interest income on bank deposits | D13: ='Cash flow Working'!B27 -> 0 | E13: 0
B14: Finance income on financial assets measured at amortised cost | D14: =+'Cash flow Working'!B25 -> -27.46033 | E14: -20.082086
B15: Unrealised exchange impact | D15: ='Cash flow Working'!B28 -> 0 | E15: 0
B16: Finance charges under leases | D16: ='Cash flow Working'!B29 -> 106.28668 | E16: 67.661123
B17: Provision / liabilities no longer required written back | D17: ='Cash flow Working'!B31 -> 0 | E17: 0
B18: Provision for doubtful trade receivables and advances(net of reversal/utilisation) | D18: ='17-25'!D177 -> 26.32863 | E18: -77
B19: Gain on sublease | D19: ='Cash flow Working'!B32 -> 0 | E19: -66.197828
B20: Operating profit/(loss) before working capital changes | D20: =SUM(D8:D19) -> 2809.9514 | E20: =SUM(E8:E19) -> 3999.2524
B22: Working Capital Adjustments:
B23: Decrease/(Increase) in trade receivables | D23: ='Cash flow Working'!B36 -> 2362.2392 | E23: -2659
B24: Decrease/(Increase) in loans and advances | D24: ='Cash flow Working'!B38 -> 19.102757 | E24: -32.413883
B25: Decrease/(Increase) in other financial assets | D25: ='Cash flow Working'!B39 -> 39.614499 | E25: -39.614499
B26: Decrease/(Increase) in other assets | D26: ='Cash flow Working'!B40 -> 356.98764 | E26: -1403.3933
B27: (Decrease)/Increase in trade payables | D27: ='Cash flow Working'!B41 -> -3245.8031 | E27: 1392.9887
B28: (Decrease)/Increase in other financial liabilities | D28: ='Cash flow Working'!B42 -> -1144.5198 | E28: 3733.9804
B29: (Decrease)/Increase in other liabilities | D29: ='Cash flow Working'!B43 -> -422.65675 | E29: 37.29762
B30: (Decrease)/Increase in provisions | D30: ='Cash flow Working'!B44 -> -149.84706 | E30: 197.7424
B31: Operating profit after working capital changes | D31: =SUM(D20:D30)+0.5 -> 625.56891 | E31: =SUM(E20:E30)+0.7 -> 5227.5398
B32: Taxes paid (taxes refund received) | D32: ='Cash flow Working'!B46 -> 868.38859 | E32: 5.6546934
B33: Net cash generated from operating activities (A) | D33: =SUM(D31:D32)+0.4 -> 1494.3575 | E33: =SUM(E31:E32)+1 -> 5234.1945
B35: Cash flow from investing activities
B37: Purchase of property, plant and equipment | D37: ='Cash flow Working'!B49 -> -2079.336 | E37: -4216.5908
B38: Proceeds from sale of property,plant and equipment | D38: ='Cash flow Working'!B50 -> 41.52816 | E38: 4.00035
B39: Interest received on deposits | D39: ='Cash flow Working'!B51 -> 17.961626 | E39: 3.209044
B40: Investment in deposits | D40: ='Cash flow Working'!B52 -> 2405.4938 | E40: -2382.0539
B41: Net cash generated/ (used in) investing activities (B) | D41: =SUM(D37:D40)-0.1 -> 385.54755 | E41: =SUM(E37:E40)-1 -> -6592.4354
B43: Cash flow from financing activities
B44: Payment of finance lease liability | D44: ='Cash flow Working'!B54 -> -432.80307 | E44: -309.16161
B45: Receipt of finance lease | D45: ='Cash flow Working'!B55 -> 163.465
B46: Net cash used in financing activities (C) | D46: =SUM(D44:D45) -> -269.33807 | E46: =SUM(E44:E44) -> -309.16161
B48: Net(decrease) /increase in cash and cash equivalents (A+B+C) | D48: =D33+D41+D46 -> 1610.567 | E48: =E33+E41+E46 -> -1667.4025
B49: Cash and cash equivalents at the beginning of the year | D49: =E50 -> 3886.7764 | E49: 5553.6789
B50: Cash and cash equivalents at the end of the year | D50: =SUM(D48:D49) -> 5497.3434 | E50: =SUM(E48:E49)+0.5 -> 3886.7764
B52: Cash and cash equivalents comprise of :
B53: Cash on hand | D53: 0 | E53: 0 | N53: 0 | O53: 137925490
B54: Balance with banks
B55: (i) In current accounts | D55: ='8-10'!I56 -> 4786.6036 | E55: 2722.5792
B56: (ii) In EEFC accounts | D56: ='8-10'!I57 -> 711.04921 | E56: 64.194416
B57: (iii) In deposit accounts | D57: ='8-10'!I58 -> 0 | E57: 1100
B58: Cash and cash equivalents as per Note 9 to the financial statements | D58: =SUM(D53:D57) -> 5497.6528 | E58: =SUM(E53:E57) -> 3886.7736
B60: For Walker Chandiok & Co LLP | D60: For and on behalf of the Board of Directors of
B61: Chartered Accountants | D61: Paladion Networks Private Limited
B62: Firm's Registration No: 001076N/N500013 | D62: CIN: U72200TN2018FTC120862
B68: ='SOCE '!B50 -> #REF! | D68: Arvind Jugalkishor Bajaj | E68: ='SOCE '!G50 -> #REF!
B69: ='SOCE '!B51 -> #REF! | D69: Director | E69: ='SOCE '!G51 -> #REF!
B70: ='SOCE '!B52 -> #REF! | D70: DIN : 08051490 | E70: ='SOCE '!G52 -> #REF!
B72: ='SOCE '!B54 -> #REF! | D72: Place: Mumbai | E72: Place: Mumbai | Z72: =D58-D50 -> 0.30940571
B73: ='SOCE '!B55 -> #REF! | D73: =B73 -> #REF! | E73: =B73 -> #REF!

Sheet Note 1-2
B1: Paladion Networks Private Limited
B2: Summary of material accounting policies and other explanatory information
B5: 1 | C5: General information
C6: Paladion Networks Private Limited (‘the Company’) is a Company incorporated on February 16, 2018 under the provisions of the Companies Act, 2013.The Company is in the business of providing assurance services, compliance services, risk mitigation services, training services, on-site security management and other consultancy services relating to networking and development of software products.
B7: 2 | C7: Summary of material accounting policies :
B9: 2.1 | C9: Basis of preparation and presentation of financial statements
C10: The standalone financial statements have been prepared in all material aspect with an Indian Accounting Standards (Ind AS) notified under Sec 133 of Companies Act 2013 and Companies (accounting standards) Rules, 2015 have been prepared on a the historical cost basis except for certain financial instruments that are measured at fair values at the end of each reporting period, as explained in the accounting policies below.
C11: Monetary amounts are expressed in Indian Rupee (₹) and are rounded off to millions, except for earning per share. Due to rounding off, the numbers presented throughout the document may not add up precisely to the totals and percentages may not precisely reflect the absolute figures.
C12: The Company has uniformly applied the accounting policies during the period presented. The Standalone Financial statements correspond to the classification provisions contained in Ind AS 1 "Presentation of financial statement" for clarity various items are aggregated in the statement of profit and loss and balance sheet. These items are disaggregated separately in the notes to the financial statement where applicable.
B14: 2.2 | C14: Significant management judgements and estimates
C16: The preparation of the financial statements in conformity with generally accepted accounting requires management to make estimates, judgements and assumptions. These estimates, judgements and assumptions affect the application of accounting policies and the reported amounts of assets and liabilities, the disclosures of contingent liabilities at the date of the financial statements and reported amounts of revenues and expenses during the period. Accounting estimates could change from period to period. Actual results could differ from those estimates. Appropriate changes in estimates are made as management becomes aware of changes in circumstances surrounding the estimates. Changes in estimates are reflected in the financial statements in the period in which changes are made and, if material, their effects are disclosed in the notes to the financial statements.
C18: The following are significant management judgements / estimates in applying the accounting policies of the Company that have the most significant effect on the financial statements.
C20: Expected cost of completing fixed price contracts
C21: The Company uses the percentage-of-completion method in accounting for its fixed-price contracts. Use of the percentage-of-completion method requires the Company to estimate the efforts or costs expended to date as a proportion of the total efforts or costs to be expended. Efforts or costs expended have been used to measure progress towards completion as there is a direct relationship between input and productivity. Estimated cost to be incurred are derived by way of budgeting process and assessing the input and productivity. Provisions for estimated losses, if any, on uncompleted contracts are recorded in the period in which such losses become probable based on the expected contract estimates at the reporting date.
C23: Liquidated damages
C24: Company assesses the ability of the Company to deliver contracts within budgeted timelines and exposures. Liquidated damages for late delivery are computed on the basis on contract terms, history of liquidated damages and management expectation.
C26: Evaluation of principal vs agent
C27: The Company recognized revenue from resale of products, i.e. software. In this Paladion performs solution design in addition to installation or simple set-up directly linked to the resale item (ranges from 2 – 3 percent of total project value), The management has assessed that accounting for the sale of such software on gross basis is primarily on account of -
C29: (a) | D29: Paladion does take control over the software license and has risk attached to it. The Company does not have any physical inventory.
C30: (b) | D30: Paladion is the primary obligor for software in this situation as the Company does take responsibility of third-party items.
C31: (c) | D31: Services provided by the Paladion are not complex and hence it does not create separate deliverable for the customer, it only enhances the value of the product. This is not a complex implementation project which creates a composite output for the customer. Here, sale of services are separate performance obligations where the service portion is clearly identifiable and not material to the total transaction price.
C33: Recognition of deferred tax asset
C34: Deferred tax assets are recognized to the extent that it is probable that the underlying tax loss or deductible temporary difference will be utilized against future taxable income.
C37: Evaluation of Indicators for impairment of assets
C38: The evaluation of applicability of Indicators of impairment of assets requires assessment of several external and internal factors which could result in deterioration of recoverable amount of the assets.
C40: Useful lives of depreciable/amortisable assets
C41: Management reviews its estimate of the useful lives of depreciable/amortisable assets at each reporting date, based on the expected utility of the assets. Uncertainties in these estimates relate to technical and economic obsolescence that may change the utility of certain items of property and equipment.
C43: Defined benefit obligation(DBO)
C44: Management’s estimate of the DBO is based on a number of critical underlying assumptions such as standard rates of inflation, medical cost trends, mortality, discount rate and anticipation of future salary increases. Variation in these assumptions may significantly impact the DBO amount and the annual defined benefit expenses.
C46: Fair value measurements
C47: Management applies valuation techniques to determine the fair value of financial instruments (where active market quotes are not available) and non-financial assets. This involves developing estimates and assumptions consistent with how market participants would price the instrument. Management uses the best information available. Estimated fair values may vary from the actual prices that would be achieved in an arm’s length transaction at the reporting date.
C49: Provisions and liabilities
C50: Provisions and liabilities are recognized in the period when it becomes probable that there will be a future outflow of funds resulting from past operations or events that can reasonably be estimated. The timing of recognition requires application of judgement to existing facts and circumstances which may be subject to change. The amounts are determined by discounting the expected future cash flows at a pre-tax rate that reflects current market assessments of the time value of money and the risks specific to the liability.
... C58: The principal risks that the Company is impacted include uncertainty around delay in awarding the projects under negotiation by government and private customers, compliance with service level arrangement and related liquidated damages outflow, increase in discounts to customer as well as credit risk that might arise due to adverse market conditions on account of COVID 19 pandemic. The uncertainties arising from the aforesaid risk are mitigated primarily on account of certain ongoing long-term revenue agreement as well as constant monitoring of the cash in and cash out ratio. Further, the Company quickly adopted to alternate business continuity scenario, including but not limited to detailed monitoring of compliance with service level agreement and Work From Home (WFH) in near to medium term, the uncertainty still prevail in respect of timelines for resumption of normal workings conditions. Notwithstanding these safeguards, the business has drawn up contingency plans for reduction of operating expenses. In preparation of these results, the Company has taken into account internal and external sources of information to assess possible impacts of the pandemic, including but not limited to assessment of liquidity and going concern, recoverable values of its financial and non-financial assets, impact on revenues and estimates of operating costs. Based on current indicators of future economic conditions, the Company has sufficient liquidity and expects to fully recover the carrying amount of its assets. In addition, the management has reasonable expectation that the Company has adequate resources to continue in operational existence for the foreseeable future, being a period of not less than twelve months from the date of approval of these financial statements. The Company therefore continues to adopt the going concern basis in preparing its financial statements. However, due to the evolving nature of the pandemic, its actual impact in future could be different from that estimated as at the date of approval of these financial results. The Company will continue to monitor any material changes to future economic conditions.
B60: Paladion Networks Private Limited
B61: Summary of material accounting policies and other explanatory information
B64: 2.2 | C64: Significant management judgements and estimates (Contd.)
C66: Estimated value and useful life of ROU asset
C67: Ind AS 116 defines a lease term as the non-cancellable period for which the lessee has the right to use an underlying asset including optional periods, when an entity is reasonably certain to exercise an option to extend (or not to terminate) a lease. The Company considers all relevant facts and circumstances that create an economic incentive for the lessee to exercise the option when determining the lease term. The option to extend the lease term is included in the lease term, if it is reasonably certain that the lessee would exercise the option. The Company reassesses the option when significant events or changes in circumstances occur that are within the control of the lessee. The lease term in future periods is reassessed to ensure that the lease term reflects the current economic circumstances. The Company has applied an incremental borrowing rate for the purpose of computing lease liabilities based on the rate prevailing in India.
B81: (Space left blank intentionally)
B83: 2.3 | C83: Revenue recognition
C85: The core principle of Ind AS 115 is that a Company should recognize revenue to depict the transfer of promised goods or services to customers in an amount that reflects the consideration to which the entity expects to be entitled in exchange for those goods or services. The Company derives revenue primarily from service of setting up security operations center (SOC), security consulting and related services, security testing, penetration testing and other testing, coding etc and value added resale of IT products. Revenue is recognised to the extent that it is probable that the economic benefits will flow to the Company and the revenue can be reliably measured. Revenue is recognized at gross flow of economic benefits where the Company is acting as a principal in contract. Incase where Company acts as an agent, revenue is recognised to the extent of commission and does not include amounts collected on behalf of principal. The following specific recognition criteria must also be met before revenue is recognized:
C86: Software services
C87: The Company recognises revenue when the significant terms of the arrangement are enforceable, services have been delivered and the collectability is reasonably assured. The method for recognizing revenues and costs depends on the nature of the services rendered:
C88: (i) | D88: Time and materials contracts
D89: Revenue from time and material contracts is recognised at the contractual rates as and when the services are performed.
C90: (ii) | D90: Fixed-price contracts
D91: Revenues from fixed-price contracts, including big data and security contracts are recognised using the “percentage of completion” method. Use of the percentage of completion method requires the Company to estimate the efforts or costs expended to date as a proportion of the total efforts or costs to be expended. Efforts or costs expended have been used to measure progress towards completion as there is a direct relationship between input and productivity. If the Company is not able to reasonably measure the progress of completion, revenue is recognised only to the extent of costs incurred for which recoverability is probable. When total cost estimates exceed revenues in an arrangement, the estimated losses are recognised in the consolidated statement of profit and loss in the period in which such losses become probable based on the current contract estimates as an onerous contract provision. Billing is done on the basis of milestones mentioned in the contracts with customers.
C93: (iii) | D93: Maintanance contracts
D94: Revenues related to fixed-price maintenance, testing and business process services are recognised based on the Company's right to invoice for services performed for contracts in which the invoicing is representative of the value being delivered. If the Company's invoicing is not consistent with value delivered, revenues are recognised as the service is performed using the percentage of completion method. When services are performed through an indefinite number of repetitive acts over a specified period, revenue is recognised on a straight-line basis over the specified period unless some other method better represents the stage of completion. In certain projects, a fixed quantum of service or output units is agreed at a fixed price for a fixed term. In such contracts, revenue is recognised with respect to the actual output achieved till date as a percentage of total contractual output. Any residual service unutilised by the customer is recognised as revenue on completion of the term.
C96: (iv) | D96: Multiple element arrangements
D97: The Company allocates the arrangement consideration to separately identifiable components based on their relative fair values or on the residual method. Fair values are determined based on sale prices for the components when it is regularly sold separately, third-party prices for similar components or cost plus an appropriate business-specific profit margin related to the relevant component.
C99: (v) | D99: unbilled and deferred revenue
D100: ‘Unbilled revenues’ represent cost and earnings in excess of billings as at the end of the reporting period. ‘Unearned revenues’ represent billing in excess of revenue recognised. Advance payments received from customers for which no services have been rendered are presented as ‘Advance from customers’.
C104: (vi) | D104: Warranty provisions
D105: The Company accrues the estimated cost of warranties at the time when the revenue is recognised. The accruals are based on the Company’s historical experience of material usage and service delivery costs.
C108: (vii) | D108: Interest Income
D109: Interest on bank deposits is recognised on the time proportion method, using the underlying interest rates. Interest income is included under the head “Other income” in the Statement of Profit and Loss.
C111: (viii) | D111: Interest income on financial asset
D112: Interest income is recorded using the effective interest rate ('EIR') method. EIR is the rate that exactly discounts the estimated future cash payments or receipts over the expected life of the financial instrument or over a shorter period, where appropriate, to the gross carrying amount of the financial asset or to the amortized cost of the financial liability. Interest income is included under the head "finance income" in the statement of profit and loss account.
C114: (ix) | D114: Others
D115: Revenues are shown net of applicable taxes, discounts and allowances.
B116: Paladion Networks Private Limited
B117: Summary of material accounting policies and other explanatory information
B120: 2.4 | C120: Leases
C121: The Company evaluates each contract or arrangement, whether it qualifies as lease as defined under Ind AS 116.
C123: Company as a lessee
C124: The Company enters into an arrangement for lease of office premises. Such arrangements are generally for a fixed period but may have extension or termination options. The Company assesses, whether the contract is, or contains, a lease, at its inception. A contract is, or contains, a lease if the contract conveys the right to – (a) control the use of an identified asset, (b) obtain substantially all the economic benefits from use of the identified asset, and (c) direct the use of the identified asset.
C125: The Company determines the lease term as the non-cancellable period of a lease, together with periods covered by an option to extend the lease, where the Company is reasonably certain to exercise that option.
C126: The Company recognizes a Right-of-Use (ROU) asset at cost and corresponding lease liability, except for leases with term of less than twelve months (short term leases) and low-value assets. For these short-term and low-value leases, the Company recognizes the lease payments as an operating expense on a straight-line basis over the lease term or where rentals are structured to increase in line with the expected general inflation, such increase are recognised in the year which they accrue.
C128: The cost of the ROU assets comprises the amount of the initial measurement of the lease liability, any lease payments made at or before the inception date of the lease plus any initial direct costs, less any lease incentives received. Subsequently, the ROU assets are measured at cost less any accumulated depreciation and accumulated impairment losses, if any. ROU asset are depreciated using the straight-line method from the commencement date over the shorter of lease term or useful life of ROU assets. The estimated useful lives of ROU assets are determined on the same basis as those of property and equipment.
B129: 2.4 | C129: Leases (continued)
B130: 2.4 | C130: Leases (continued)
C131: For lease liabilities at the commencement of the lease, the Company measures the lease liability at the present value of the lease payments that are not paid at that date. The lease payments are discounted using the interest rate implicit in the lease, if that rate is readily determined, if that rate is not readily determined, the lease payments are discounted using the incremental borrowing rate that the Company would have to pay to borrow funds, including the consideration of factors such as the nature of the asset and location, collateral, market terms and conditions, as applicable in a similar economic environment. After the commencement date, the amount of lease liabilities is increased to reflect the accretion of interest and reduced for the lease payments made. The Company recognizes the amount of the re-measurement of lease liability as an adjustment to the right-of-use assets. Where the carrying amount of the right-of-use assets is reduced to zero and there is a further reduction in the measurement of the lease liability, the Company recognizes any remaining amount of the remeasurement in consolidated statement of income. Lease liability payments are classified as cash used in financing activities in the consolidated statement of cash flows. Lease expense related to short term and low value leases are debited to profit and loss account.
B133: 2.5 | C133: Property and equipment
C134: The cost of property and equipment comprises its purchase price net of any trade discounts and rebates, any import duties and other taxes (other than those subsequently recoverable from the tax authorities), any directly attributable expenditure on making the asset ready for its intended use, including relevant borrowing costs for qualifying assets and any expected costs of decommissioning. Expenditure incurred after the property and equipment have been put into operation, such as repairs and maintenance, are charged to the Statement of Profit and Loss in the period in which the costs are incurred.
C137: An item of property and equipment is derecognised upon disposal or when no future economic benefits are expected to arise from the continued use of the asset. Any gain or loss arising on the disposal or retirement of an item of property and equipment is determined as the difference between the sales proceeds and the carrying amount of the asset and is recognized in Statement of Profit and Loss.
C140: Subsequent expenditures relating to property and equipment is capitalised only when it is probable that future economic benefits associated with these will flow to the Company and the cost of the item can be measured reliably.
C143: An item of property and equipment is derecognised upon disposal or when no future economic benefits are expected to arise from the continued use of the asset. Any gain or loss arising on the disposal or retirement of an item of property and equipment is determined as the difference between the sales proceeds and the carrying amount of the asset and is recognised in profit or loss.
C144: On transition to Ind AS the Company has elected to continue with the carrying value of all its property, plant and equipment recognized as at 01 April 2019, measured as per previous GAAP, and use that carrying value as the deemed cost of such property, plant and equipment.
B146: 2.6 | C146: Other Intangible Assets
C147: Intangible assets with finite useful lives that are acquired separately are carried at cost less accumulated amortisation and accumulated impairment losses. Amortisation is recognised on a straight line basis over their estimated useful lives so as to reflect the pattern in which the assets economic benefits are consumed. The estimated useful life and amortisation method are reviewed at the end of each reporting period, with the effect of any changes in estimate being accounted for on a prospective basis. The amortisation of intangible asset is included in Depreciation and amortisation expense in Statement of Profit and Loss.
C148: On transition to Ind AS the Company has elected to continue with the carrying value of all intangible assets recognized as at 01 April 2019, measured as per previous GAAP, and use that carrying value as the deemed cost of such intangible assets.
B160: (Space left blank intentionally)
B162: Paladion Networks Private Limited
B163: Summary of material accounting policies and other explanatory information
B166: 2.7 | C166: Depreciation and amortisation
C167: Depreciation is provided using the straight-line method over the estimated useful lives of assets. The estimated useful lives are as follows:
C168: When significant parts of property and equipment are required to be replaced at intervals, the Company depreciates them separately based on their specific useful lives. As per the Company's evaluation of the accounting prescribed under Schedule II of the Companies Act, 2013, the management has not identified any significant component having different useful lives.
C169: Capital work-in-progress comprises of the cost of property and equipment that are not yet ready for their intended use at the reporting date.
C170: Estimated useful life till 31 March 2021 are as follows
C172: Asset | F172: Years
C173: Building | F173: 60 Years
C174: Leasehold Improvements | F174: 10 Years
C175: Computers
C176: - Computer | F176: 10 Years
C177: - Software purchased | F177: 10 Years
C178: Electrical Installations | F178: 10 Years
C179: Furniture, Fixtures & Equipments | F179: 10 Years
C180: Office Equipments | F180: 7 Years
...

Sheet 3-4
B1: ='SOCE '!B1 -> Paladion Networks Private Limited
B2: Summary of Material accounting policies and other explanatory information
B3: ='SOCE '!B3 -> (Amounts are stated in ₹ lakhs, except share and per share data, unless ottherwise stated)
A5: 3 | B5: ="Note "&A5&": Property,plant and equipment" -> Note 3: Property,plant and equipment
C7: Building | D7: Leasehold improvements | E7: Furniture & fixtures | F7: Office equipments | G7: Computers | H7: Total
B9: Gross block
B10: As at 01 April 2023 | C10: 229.87798 | D10: 19.4365 | E10: 107.92661 | F10: 48.141443 | G10: 959.25204 | H10: =ROUND(SUM(C10:G10),2) -> 1364.63
B11: Additions | C11: - | D11: 63.64232 | E11: 109.53549 | F11: 21.896099 | G11: 3.3169341 | H11: =ROUND(SUM(C11:G11),2) -> 198.39
B12: Disposals | C12: - | D12: - | E12: -50.948056 | F12: -8.6110291 | G12: -262.50035 | H12: =ROUND(SUM(C12:G12),2) -> -322.06 | K12: Gross value of Asset sold | L12: 203.69816
B13: As at 31 March 2024 | C13: =SUM(C10:C12) -> 229.87798 | D13: =SUM(D10:D12) -> 83.07882 | E13: =SUM(E10:E12) -> 166.51404 | F13: =SUM(F10:F12) -> 61.426513 | G13: =SUM(G10:G12) -> 700.06863 | H13: =SUM(H10:H12)-0.5 -> 1240.46 | K13: Acc.dep of Asset sold | L13: -162.17
B14: Additions | C14: - | E14: =8.84505 -> 8.84505 | F14: =0.19 -> 0.19 | G14: =5.89495+1.811+0.08846 -> 7.79441 | H14: =SUM(C14:G14) -> 16.82946 | K14: Net book value of asset sold | L14: =SUM(L12:L13) -> 41.52816
B15: Disposals | C15: - | G15: =-203.69816 -> -203.69816 | H15: =SUM(C15:G15) -> -203.69816
B16: As at 31 March 2025 | C16: =SUM(C13:C15) -> 229.87798 | D16: =SUM(D13:D15) -> 83.07882 | E16: =SUM(E13:E15) -> 175.35909 | F16: =SUM(F13:F15) -> 61.616513 | G16: =SUM(G13:G15) -> 504.16488 | H16: =SUM(H13:H15) -> 1053.5913
B18: Accumulated depreciation
B19: =B10 -> As at 01 April 2023 | C19: 17.918793 | D19: 19.047226 | E19: 80.39274 | F19: 41.162229 | G19: 524.00202 | H19: =SUM(C19:G19) -> 682.523
B20: Depreciation charge for the year | C20: 4.5964025 | D20: 3.9775214 | E20: 14.534848 | F20: 8.7166786 | G20: 255.96398 | H20: =SUM(C20:G20) -> 287.78943
B21: Disposals | C21: - | D21: - | E21: -50.655344 | F21: -6.4283864 | G21: -262.08078 | H21: =SUM(C21:G21) -> -319.16451
B22: =+B13 -> As at 31 March 2024 | C22: =SUM(C19:C21) -> 22.515195 | D22: =SUM(D19:D21) -> 23.024747 | E22: =SUM(E19:E21) -> 44.272244 | F22: =SUM(F19:F21) -> 43.450521 | G22: =SUM(G19:G21) -> 517.88522 | H22: =SUM(H19:H21) -> 651.14792
B23: Depreciation charge for the year | C23: 4.5964025 | D23: 9.2972211 | E23: 24.175962 | F23: 7.0345818 | G23: =135.179618+2.11762+0.91635+0.03451 -> 138.2481 | H23: =SUM(C23:G23) -> 183.35227 | J23: ='17-25'!D139 -> 183.31775 | K23: =H23-J23 -> 0.034511203
B24: Disposals | G24: =-162.17 -> -162.17 | H24: =SUM(C24:G24) -> -162.17
B25: =+B16 -> As at 31 March 2025 | C25: =SUM(C22:C24) -> 27.111598 | D25: =SUM(D22:D24) -> 32.321969 | E25: =SUM(E22:E24) -> 68.448206 | F25: =SUM(F22:F24)+0.1 -> 50.585103 | G25: =SUM(G22:G24) -> 493.96331 | H25: =SUM(H22:H24) -> 672.33019
B27: Net block
B28: =+B16 -> As at 31 March 2025 | C28: =C16-C25 -> 202.76638 | D28: =D16-D25 -> 50.756851 | E28: =E16-E25 -> 106.91089 | F28: =F16-F25 -> 11.031411 | G28: =G16-G25 -> 10.201561 | H28: =SUM(C28:G28) -> 381.66709 | J28: =SUMIF('Standalone TB'!AB:AB,"PPE",'Standalone TB'!X:X)/10^5 -> 381.90062 | K28: =H28-J28 -> -0.23352376
B29: =+B13&"(#)" -> As at 31 March 2024(#) | C29: =C13-C22 -> 207.36278 | D29: =D13-D22 -> 60.054072 | E29: =E13-E22 -> 122.2418 | F29: =F13-F22 -> 17.975992 | G29: =G13-G22 -> 182.18341 | H29: =H13-H22 -> 589.31208
B31: #) Zero represents less than ₹0.5 Lakhs
A33: =A5+1 -> 4 | B33: ="Note "&A33&":Intangible assets" -> Note 4:Intangible assets
D34: Internal Assets Under Development | E34: Internal Software Developed | F34: Software purchased | G34: Acquired goodwill | H34: Total
B35: Gross block
B36: =B10 -> As at 01 April 2023 | D36: 0 | E36: 0 | F36: 11.23 | G36: 36484.21 | H36: =D36+E36+F36+G36 -> 36495.44
B37: Additions | D37: 589 | E37: 3429 | F37: 0 | G37: 0 | H37: =D37+E37+F37+G37 -> 4018
B38: Disposals | E38: 0 | F38: 0 | G38: 0 | H38: =E38+F38+G38 -> 0
B39: =B13 -> As at 31 March 2024 | D39: =ROUND(SUM(D36:D38),2) -> 589 | E39: =ROUND(SUM(E36:E38),2) -> 3429 | F39: =ROUND(SUM(F36:F38),2) -> 11.23 | G39: =ROUND(SUM(G36:G38),2) -> 36484.21 | H39: =ROUND(SUM(H36:H38),2) -> 40513.44
B40: Additions | D40: =ROUND('Standalone TB'!X186/10^5,0) -> 0 | E40: =2651.5065679-E41 -> 2062.5066 | F40: 0 | G40: 0 | H40: =E40+F40+G40+D40 -> 2062.5066
B41: Capitalized | D41: =-589 -> -589 | E41: =589 -> 589 | H41: =E41+F41+G41+D41 -> 0
B42: Disposals | D42: =0 -> 0 | E42: =0 -> 0 | F42: 0 | G42: 0 | H42: =E41+F42+G42+D41 -> 0
B43: =B16 -> As at 31 March 2025 | D43: =SUM(D39:D41) -> 0 | E43: =SUM(E39:E41) -> 6080.5066 | F43: =SUM(F39:F42) -> 11.23 | G43: =SUM(G39:G42) -> 36484.21 | H43: =SUM(H39:H42) -> 42575.947
B45: Accumulated amortisation
B46: =B36 -> As at 01 April 2023 | D46: 0 | E46: 0 | F46: 11.23 | G46: 18242.105 | H46: =(F46+G46+E46) -> 18253.335
B47: Amortisation charge for the year | D47: 0 | E47: 214.29473 | F47: 0 | G47: 0 | H47: =(F47+G47+E47) -> 214.29473
B48: Disposals | D48: 0 | E48: 0 | F48: 0 | G48: 0 | H48: =(F48+G48+E48) -> 0
B49: Impairmemt loss charge for the year | G49: 18242 | H49: =(F49+G49+E49) -> 18242
B50: =+B39 -> As at 31 March 2024 | D50: =ROUND(SUM(D46:D48),2) -> 0 | E50: =ROUND(SUM(E46:E48),2) -> 214.29 | F50: =ROUND(SUM(F46:F49),2) -> 11.23 | G50: =ROUND(SUM(G46:G49),2) -> 36484.11 | H50: =ROUND(SUM(H46:H49),2) -> 36709.63
B51: Amortisation | D51: 0 | E51: ='17-25'!D140 -> 1952.3551 | F51: 0 | G51: =0 -> 0 | H51: =(F51+G51+E51) -> 1952.3551 | J51: ='17-25'!D140 -> 1952.3551 | K51: =E51-J51 -> 0
B52: Disposals | D52: 0 | E52: 0 | F52: 0 | G52: 0 | H52: =(F52+G52+E52) -> 0
B53: =+B43 -> As at 31 March 2025 | D53: =SUM(D50:D52) -> 0 | E53: =SUM(E50:E52) -> 2166.6451 | F53: =SUM(F50:F52) -> 11.23 | G53: =SUM(G50:G52) -> 36484.11 | H53: =SUM(H50:H52) -> 38661.985
B55: Net block
B56: =+B43 -> As at 31 March 2025 | D56: =D43-D53 -> 0 | E56: =E43-E53 -> 3913.8615 | F56: =F43-F53 -> 0 | G56: =0 -> 0 | H56: =H43-H53 -> 3913.9615 | J56: =SUMIF('Standalone TB'!Z:Z,"Intangible assets",'Standalone TB'!X:X)/10^5 -> 3913.5724 | K56: =E56-J56 -> 0.2891138 | L56: =H56+H28 -> 4295.6286
B57: =+B39 -> As at 31 March 2024 | D57: =D39-D50 -> 589 | E57: =E39-E50 -> 3214.71 | F57: =F39-F50 -> 0 | G57: =G39-G50 -> 0.1 | H57: =H39-H50 -> 3803.81
B61: Internal assets Under Development-Ageing Schedule
B63: As at 31 March 2025
B64: Particulars | D64: Less than 1 year | E64: 1-2 years | F64: 2-3 years | G64: More than 3 years | H64: Total
B65: Projects in Progress | D65: =D40 -> 0 | E65: =0 -> 0 | F65: 0 | G65: 0 | H65: =E65+F65+G65+D65 -> 0
B66: Projects temporarily Suspended | D66: =0 -> 0 | E66: 0 | F66: 0 | G66: 0 | H66: =E66+F66+G66 -> 0
B67: Total | D67: =SUM(D65:D66) -> 0 | E67: =SUM(E65:E66) -> 0 | F67: =SUM(F65:F66) -> 0 | G67: =SUM(G65:G66) -> 0 | H67: =SUM(H65:H66) -> 0
B69: As at 31 March 2024
B70: Particulars | D70: Less than 1 year | E70: 1-2 years | F70: 2-3 years | G70: More than 3 years | H70: Total
B71: Projects in Progress | D71: 589 | E71: =0 -> 0 | F71: 0 | G71: 0 | H71: =E71+F71+G71+D71 -> 589
B72: Projects temporarily Suspended | D72: =0 -> 0 | E72: 0 | F72: 0 | G72: 0 | H72: =E72+F72+G72 -> 0
B73: Total | D73: =SUM(D71:D72) -> 589 | E73: =SUM(E71:E72) -> 0 | F73: =SUM(F71:F72) -> 0 | G73: =SUM(G71:G72) -> 0 | H73: =SUM(H71:H72) -> 589
B75: During the years ended 31 March 2025 and 31 March 2024 there are no projects whose completion is overdue or has exceeded its cost compared to its original plan
B78: Net Book Value | G78: 31 Mach 2025 | H78: 31 Mach 2024
B80: Goodwill | G80: =0 -> 0 | H80: =G57 -> 0.1
B81: Other Intangible assets | G81: =E56 -> 3913.8615 | H81: =E57 -> 3214.71
B82: Intangible assets under development | G82: =D56 -> 0 | H82: =D57 -> 589
B97: (Space left blank intentionally)

Sheet 5-7
B1: ='3-4'!B1 -> Paladion Networks Private Limited
B2: ='3-4'!B2 -> Summary of Material accounting policies and other explanatory information
B3: ='3-4'!B3 -> (Amounts are stated in ₹ lakhs, except share and per share data, unless ottherwise stated)
A6: ='3-4'!A33+1 -> 5 | B6: ="Note "&A6&": Other financial assets" -> Note 5: Other financial assets
B8: Non Current | C8: As at 31 March 2025 | D8: As at 31 March 2025 | E8: As at 31 March 2024 | G8: Mar 23
B9: Unsecured, considered good | G9: FD-Margin Money | I9: FD Maturity | L9: Accrued Interest
B10: Security deposits | G10: <12M | H10: >12M | I10: <3M | J10: >3M & <12M | K10: >12M | L10: <3M | M10: <12M | N10: >12M
B11: ="- Related parties (refer note "&'30 RPT'!A5&")" -> - Related parties (refer note 30) | C11: 12436488 | D11: =C11/10^5 -> 124.36488 | E11: 117 | G11: 2266175 | H11: 2111275 | J11: =2506381-G11 -> 240206 | K11: =3072031.66-H11 -> 960756.66 | M11: 3837 | N11: 135828
A12: Security deposits | B12: - others | C12: =SUMIFS('Standalone TB'!$X:$X,'Standalone TB'!$Z:$Z,'5-7'!$A12)-C11-C22 -> 4816256.3 | D12: =C12/10^5 -> 48.162563 | E12: 99
B13: Deposits with banks (*) | C13: =H11+K11 -> 3072031.7 | D13: =ROUND(C13/10^5,0) -> 31 | E13: 170
B14: Interest accrued on deposits | C14: =N11 -> 135828 | D14: =ROUND(C14/10^5,0) -> 1 | E14: 12
B15: Lease receivable
A16: Lease receivable | B16: ="- Related parties (refer note "&'30 RPT'!A5&")" -> - Related parties (refer note 30) | C16: =SUMIFS('Standalone TB'!$X:$X,'Standalone TB'!$Z:$Z,'5-7'!$A16) -> 23935012 | D16: =ROUND(C16/10^5,0) -> 239 | E16: 375
B17: Total | C17: =SUM(C10:C16) -> 44395616 | D17: =SUM(D10:D16) -> 443.52744 | E17: =SUM(E10:E16) -> 773
B19: Current | C19: =C8 -> As at 31 March 2025 | D19: =D8 -> As at 31 March 2025 | E19: =E8 -> As at 31 March 2024
B20: Unsecured, considered good
A22: Security deposits | B22: Security deposits | C22: 18135703 | D22: =C22/10^5 -> 181.35703 | E22: 120
B23: Deposits with banks (*) | C23: =G11 -> 2266175 | D23: =ROUND(C23/10^5,0) -> 23 | E23: 2
A24: Interest accrued on deposits | B24: Interest accrued on deposits | C24: =SUMIFS('Standalone TB'!$X:$X,'Standalone TB'!$Z:$Z,'5-7'!$A24)-C14 -> 3837.4 | D24: =C24/10^5 -> 0.038374 | E24: 7
B25: Total | C25: =SUM(C22:C24) -> 20405716 | D25: =SUM(D22:D24) -> 204.39541 | E25: =SUM(E22:E24) -> 129
B27: Note:
B28: (*)Fixed deposits are kept under lien for performance bank guarantees for various projects amounting to ₹ 29 (31 March 2024 : ₹29).
A30: =A6+1 -> 6 | B30: ="Note "&A30&": Other Current assets" -> Note 6: Other Current assets
C32: Non-current | D32: =D19 -> As at 31 March 2025 | E32: =E19 -> As at 31 March 2024
B33: Unsecured, considered good
B34: Deposits with banks having maturity period of more than 12 months from the balance sheet date (refer note below) | D34: 0
B35: Interest accrued on deposits | D35: 0
B36: Advance to suppliers-
B37: - for capital goods | D37: 0
B38: - others | D38: 0
A39: Receivable from related parties | B39: ="Receivable from related parties" & " (refer note "&'30 RPT'!A5&")" -> Receivable from related parties (refer note 30) | C39: =SUMIFS('Standalone TB'!$X:$X,'Standalone TB'!$Z:$Z,'5-7'!$A39) -> 14290723 | D39: =C39/10^5 -> 142.90723 | E39: 1978.3663
A40: Other receivables | B40: Receivables form others | C40: =SUMIFS('Standalone TB'!$X:$X,'Standalone TB'!$Z:$Z,'5-7'!$A40) -> 10111986 | D40: =C40/10^5 -> 101.11986 | E40: 40.237245
A41: Loans & Advances to Employees | B41: Loans and advance to employees | C41: =SUMIFS('Standalone TB'!$X:$X,'Standalone TB'!$Z:$Z,'5-7'!$A41) -> 2080912.5 | D41: =C41/10^5 -> 20.809125 | E41: 39.911882
A42: Balance with govt. authorities | B42: Balance with government authorities | C42: =SUMIFS('Standalone TB'!$X:$X,'Standalone TB'!$Z:$Z,'5-7'!$A42) -> 1.617808e+08 | D42: =C42/10^5 -> 1617.808 | E42: 372.40413
A43: Prepaid | B43: Prepaid expenses | C43: =SUMIFS('Standalone TB'!$X:$X,'Standalone TB'!$Z:$Z,'5-7'!$A43) -> 29378288 | D43: =C43/10^5 -> 293.78288 | E43: 120.59794
A44: Advance to suppliers | B44: Advance to suppliers | C44: =SUMIFS('Standalone TB'!$X:$X,'Standalone TB'!$Z:$Z,'5-7'!$A44) -> 0 | D44: =C44/10^5 -> 0 | E44: 39.614499
B45: Total | C45: =SUM(C33:C44) -> 2.1764271e+08 | D45: =SUM(D33:D44) -> 2176.4271 | E45: =SUM(E33:E44) -> 2591.132
A47: =A30+1 -> 7 | B47: ="Note "&A47&": Investments" -> Note 7: Investments
C48: =C19 -> As at 31 March 2025 | D48: =D32 -> As at 31 March 2025 | E48: =E32 -> As at 31 March 2024
B49: Non-current
B50: Investments in equity instruments of subsidiaries at cost (unquoted) (Refer Note 30)
B52: Paladion Networks LLC, Abu Dhabi
A53: Investments | B53: 49 shares of AED 1500 each (31 March 2024 : 49) | C53: =SUMIFS('Standalone TB'!$X:$X,'Standalone TB'!$Z:$Z,'5-7'!$A53)-C56-C59-C62 -> 1488294 | D53: =C53/10^5 -> 14.88294 | E53: 14.88294
B54: Less : Impairment of investments for Paladion Networks LLC, Abu Dhabi | C54: =-C53 -> -1488294 | D54: =-D53 -> -14.88294 | E54: -14.88294
B55: Paladion Qatar WLL, Qatar
B56: 98,000 shares of QAR 1 each (31 March 2024 : 98,000) | C56: =1984079 -> 1984079 | D56: =C56/10^5 -> 19.84079 | E56: 19.84079
B57: Less : Impairment of investments for Paladion Qatar WLL, Qatar | C57: =-C56 -> -1984079 | D57: =-D56 -> -19.84079 | E57: -19.84079
B58: Paladion Networks LLC, Dubai
B59: 98 shares of AED 1000 each (31 March 2024 : 98) | C59: =1984392 -> 1984392 | D59: =C59/10^5 -> 19.84392 | E59: 19.84392
B60: Less : Impairment of investments for Paladion Networks LLC, Dubai | C60: =-C59 -> -1984392 | D60: =-D59 -> -19.84392 | E60: -19.84392
B61: Paladion Networks (Thailand) Company Limited
B62: 599,998 partly paid shares of THB 5 each (31 March 2024 : 599,998) | C62: =1382153.26 -> 1382153.3 | D62: =C62/10^5 -> 13.821533 | E62: 13.821533
B63: Less : Impairment of investments for Paladion Networks (Thailand) Company Limited | C63: =-1382153.26 -> -1382153.3 | D63: =C63/10^5 -> -13.821533 | E63: -13.821533
B65: Total | C65: =SUM(C53:C63) -> 0 | D65: =SUM(D53:D63) -> 0 | E65: =SUM(E53:E63) -> 0
B67: Aggregate amount of quoted investments | D67: - | E67: -
B68: Aggregate amount of unquoted investments | C68: =C53+C56+C59+C62 -> 6838918.3 | D68: =D53+D56+D59+D62 -> 68.389183 | E68: 68.389183
B69: Aggregate amount of impairment/fair value loss in value of investments | C69: =-C68 -> -6838918.3 | D69: =D54+D57+D60+D63 -> -68.389183 | E69: -68.389183
B71: Total Investments in Subsidiaries | D71: =D68 -> 68.389183 | E71: 68.389183
B72: Less: Impairment of investments | D72: =D69 -> -68.389183 | E72: -68.389183
B73: Net Investment of subsidiaries | D73: =SUM(D70:D72) -> 0 | E73: =SUM(E70:E72) -> 0

Sheet 8-10
B1: ='3-4'!B1 -> Paladion Networks Private Limited | N1: ER | O1: 23.2939 | P1: 85.563771
B2: ='3-4'!B2 -> Summary of Material accounting policies and other explanatory information
B3: ='3-4'!B3 -> (Amounts are stated in ₹ lakhs, except share and per share data, unless ottherwise stated)
P4: -
A5: ='5-7'!A47+1 -> 8 | B5: ="Note "&A5&": Trade receivables" -> Note 8: Trade receivables | M5: 355868.54 | N5: 4.3960565e+08
H6: As at 31 March 2025 | I6: As at 31 March 2025 | J6: As at 31 March 2024
B7: Trade receivables considered good - secured | I7: 0 | J7: 0
B8: Trade receivables considered good - unsecured | N8: India | O8: Sharjah | P8: US | Q8: Total
B9: ="- Related parties (refer note "&'30 RPT'!A5&")" -> - Related parties (refer note 30) | H9: =ROUND(SUM(Q9:Q11),0) -> 519781051 | I9: =(SUM(H9:H9))/10^5 -> 5197.8105 | J9: 8621.049 | K9: =ROUND(J9,0) -> 8621 | L9: Done | M9: IR | N9: =439605648.39+355868.54 -> 4.3996152e+08 | O9: =(35863055.71-465059.225)*$O$1 -> 8.245574e+08 | P9: =17200*P1 -> 1471696.9 | Q9: =SUM(N9:P9) -> 1.2659906e+09
A10: Debtors | B10: - Others | H10: =SUMIFS('Standalone TB'!$X:$X,'Standalone TB'!$Z:$Z,'8-10'!$A10)-H9 -> 78599307 | I10: =(SUM(H10:H10))/10^5 -> 785.99307 | J10: 1239.7168 | K10: =ROUND(J10,0) -> 1240 | M10: IR-Elimination | N10: -11837173 | O10: =-31649862.21*$O$1 -> -7.3724873e+08 | Q10: =SUM(N10:P10) -> -7.490859e+08
B11: Trade Receivables which have significant increase in credit risk | H11: =-SUM('Standalone TB'!X204:X206) -> 7549549.6 | I11: =(SUM(H11:H11))/10^5 -> 75.495496 | J11: 48.649991 | K11: =ROUND(J11,0) -> 49 | M11: IR-Forex | N11: =2876344.35 -> 2876344.4 | O11: =0 -> 0 | Q11: =SUM(N11:P11) -> 2876344.4
B12: Less: Expected credit losses (Refer note 8.2) | H12: =-H11 -> -7549549.6 | I12: =(SUM(H12:H12))/10^5 -> -75.495496 | J12: -48.649991 | K12: =ROUND(J12,0) -> -49 | M12: ER | N12: 58824055 | O12: =1201472.35*$O$1 -> 27986977 | P12: =-14458.04*P1 -> -1237084.4 | Q12: =SUM(N12:P12) -> 85573947
B13: Unbilled revenue | K13: =ROUND(J13,0) -> 0 | M13: ER-Forex | N13: =27058 -> 27058 | O13: =23519.11*$O$1 -> 547851.8 | Q13: =SUM(N13:P13) -> 574909.8 | R13: =SUM(Q9:Q13) -> 6.0592991e+08
B14: ="- Related parties (refer note "&'30 RPT'!A5&")" -> - Related parties (refer note 30) | H14: =SUM(Q15,Q16) -> 3.035998e+08 | I14: =(SUM(H14:H14))/10^5 -> 3035.998 | J14: 1532.6633 | K14: =ROUND(J14,0) -> 1533 | M14: Unbilled-ER | N14: =30421417.98+860505.38 -> 31281923 | O14: =76162*O1 -> 1774110 | Q14: =SUM(N14:P14) -> 33056033
A15: Unbilled Revenue | B15: - others | H15: =SUMIFS('Standalone TB'!$X:$X,'Standalone TB'!$Z:$Z,'8-10'!$A15)-H14 -> 33056030 | I15: =(SUM(H15:H15))/10^5 -> 330.5603 | J15: 345.5007 | K15: =ROUND(J15,0) -> 346 | M15: Unbilled -IR | N15: 3.0360936e+08 | O15: =0 -> 0 | Q15: =SUM(N15:P15) -> 3.0360936e+08
M16: Unbilled -IR-forex | N16: =-2816.09-6744 -> -9560.09 | Q16: =SUM(N16:P16) -> -9560.09
B17: Total | H17: =SUM(H7:H16) -> 9.3503619e+08 | I17: =SUM(I7:I16) -> 9350.3619 | J17: =SUM(J7:J16) -> 11738.93 | K17: =SUM(K7:K16) -> 11740 | N17: =SUM(N9:N16) -> 8.2473353e+08 | O17: =SUM(O9:O16) -> 1.176176e+08 | P17: =SUM(P9:P16) -> 234612.44 | Q17: =SUM(Q9:Q16) -> 9.4258575e+08
M18: As per TB | N18: =SUMIF('Standalone TB'!$AB:$AB,"Trade receivables",'Standalone TB'!$H:$H) -> 8.1938547e+08 | O18: =SUMIF('Standalone TB'!$AB:$AB,"Trade receivables",'Standalone TB'!$N:$N) -> 1.1541611e+08 | P18: =SUMIF('Standalone TB'!$AB:$AB,"Trade receivables",'Standalone TB'!$U:$U) -> 234612.44 | Q18: =SUMIF('Standalone TB'!$AB:$AB,"Trade receivables",'Standalone TB'!$X:$X) -> 9.3503619e+08
B19: Trade receivables are non interest bearing and are generally on terms of 30 to 90 days. | N19: =N17-N18 -> 5348059.2 | O19: =O17-O18 -> 2201494.5 | P19: =P17-P18 -> 0 | Q19: =Q17-Q18 -> 7549553.8 | R19: Provision for doubtful debts
B20: No trade receivable are due from directors or other officers of the company either severally or jointly with any other person. Nor any trade receivable are due from firms or private companies respectively in which any director is a partner, a director or a member.
A22: =A5&".1" -> 8.1 | B22: ="Note "&A22&": Trade receivables Ageing as at 31 March 2025" -> Note 8.1: Trade receivables Ageing as at 31 March 2025
D23: Outstanding for following periods from due date of payment
C24: Unbilled (not due) | D24: Total unbilled | E24: < 6 months | F24: 6 months - 1 year | G24: 1-2 years | H24: 2-3 years | I24: > 3 years | J24: Total | N24: India | O24: Sharjah | P24: US | Q24: Total
B25: Undisputed trade receivables - considered good | C25: =I15+I14 -> 3366.5583 | D25: =C25 -> 3366.5583 | E25: =Q26/10^5-E26 -> 4184.2566 | F25: =Q27/10^5-F26 -> 952.35949 | G25: =SUM(Q28/10^5) -> 844.59797 | H25: =Q29/10^5 -> 2.5895289 | I25: =Q30/10^5 -> 0 | J25: =SUM(D25:I25) -> 9350.3619
B26: Undisputed trade receivables – which have significant increase in credit risk | E26: =2082213.69374969/10^5 -> 20.822137 | F26: =5467335.87068808/10^5 -> 54.673359 | I26: =0 -> 0 | J26: =SUM(D26:I26) -> 75.495496 | M26: Less than 6 Months | N26: 3.8363694e+08 | O26: =1559338.635*$O$1+547852 -> 36870931 | Q26: =SUM(N26:P26) -> 4.2050787e+08
B27: Undisputed trade receivables – credit impaired | E27: =-E26 -> -20.822137 | F27: =-F26 -> -54.673359 | I27: 0 | J27: =SUM(D27:I27) -> -75.495496 | M27: 6 M to 1 Year | N27: 75382302 | O27: =1087022.05*O1 -> 25320983 | Q27: =SUM(N27:P27) -> 1.0070329e+08
B28: Disputed trade receivables – considered good | I28: 0 | J28: =SUM(D28:I28) -> 0 | M28: 1-2 Years | N28: 30801850 | O28: =2293447.4*O1 -> 53423335 | P28: =2741.96*P1 -> 234612.44 | Q28: =SUM(N28:P28) -> 84459797
B29: Disputed trade receivables – which have significant increase in credit risk | I29: 0 | J29: =SUM(D29:I29) -> 0 | M29: 2-3 Years | N29: 30706.68 | O29: =9798.54*O1 -> 228246.21 | Q29: =SUM(N29:P29) -> 258952.89
B30: Disputed trade receivables – credit impaired | I30: 0 | J30: =SUM(D30:I30) -> 0 | M30: More than 3 Years | Q30: =SUM(N30:P30) -> 0
B31: Total | C31: =SUM(C25:C30) -> 3366.5583 | D31: =SUM(D25:D30) -> 3366.5583 | E31: =SUM(E25:E30) -> 4184.2566 | F31: =SUM(F25:F30) -> 952.35949 | G31: =SUM(G25:G30) -> 844.59797 | H31: =SUM(H25:H30) -> 2.5895289 | I31: =SUM(I25:I30) -> 0 | J31: =SUM(J25:J30) -> 9350.3619 | M31: Total | N31: =SUM(N26:N30) -> 4.898518e+08 | O31: =SUM(O26:O30) -> 1.1584349e+08 | P31: =SUM(P26:P30) -> 234612.44 | Q31: =SUM(Q26:Q30) -> 6.0592991e+08
B33: Trade receivables Ageing as at 31 March 2024
D34: Outstanding for following periods from due date of payment | N34: =SUM(N9:N13)-N31 -> 0.22000003 | O34: =SUM(O9:O13)-O31 -> -0.19922371 | P34: =P17-P31 -> 0 | Q34: =SUM(Q9:Q13)-Q31 -> 0.020776272
C35: Unbilled (not due) | D35: Total unbilled | E35: < 6 months | F35: 6 months - 1 year | G35: 1-2 years | H35: 2-3 years | I35: > 3 years | J35: Total
B36: Undisputed trade receivables - considered good | C36: 1878.164 | D36: 1878.164 | E36: 8970.4153 | F36: 260.26892 | G36: 153.48361 | H36: 476.59799 | I36: 0 | J36: =SUM(D36:I36) -> 11738.93
B37: Undisputed trade receivables – which have significant increase in credit risk | C37: 0 | D37: 0 | E37: 44.814613 | F37: 3.835378 | G37: 0 | I37: 0 | J37: =SUM(E37:I37) -> 48.649991
B38: Undisputed trade receivables – credit impaired | C38: 0 | D38: 0 | E38: -44.814613 | F38: -3.835378 | G38: 0 | I38: 0 | J38: =SUM(E38:I38) -> -48.649991
B39: Disputed trade receivables – considered good | C39: 0 | D39: 0 | E39: 0 | F39: 0 | G39: 0 | I39: 0 | J39: =SUM(E39:I39) -> 0
B40: Disputed trade receivables – which have significant increase in credit risk | C40: 0 | D40: 0 | E40: 0 | F40: 0 | G40: 0 | I40: 0 | J40: =SUM(E40:I40) -> 0
B41: Disputed trade receivables – credit impaired | C41: 0 | D41: 0 | E41: 0 | F41: 0 | G41: 0 | I41: 0 | J41: =SUM(E41:I41) -> 0
B42: Total | C42: =SUM(C36:C41) -> 1878.164 | D42: =SUM(D36:D41) -> 1878.164 | E42: =SUM(E36:E41) -> 8970.4153 | F42: =SUM(F36:F41) -> 260.26892 | G42: =SUM(G36:G41) -> 153.48361 | H42: =SUM(H36:H41) -> 476.59799 | I42: =SUM(I36:I41) -> 0 | J42: =SUM(J36:J41) -> 11738.93
A45: =A5&".2" -> 8.2 | B45: ="Note "&A45&": Movement of expected credit loss" -> Note 8.2: Movement of expected credit loss
H46: =H6 -> As at 31 March 2025 | I46: =I6 -> As at 31 March 2025 | J46: =J6 -> As at 31 March 2024
B47: Opening | H47: =I47*10^5 -> 4864999.4 | I47: =J51 -> 48.649994 | J47: 123.7785
B48: Provision made during the year | H48: ='17-25'!C177 -> 2632863 | I48: =H48/10^5 -> 26.32863 | J48: 52.628683
B49: Provision reversed / utilised during the year | I49: =H49/10^5 -> 0 | J49: -128.93394
B50: Exchange (gain) / loss Impact | H50: =51687.15 -> 51687.15 | I50: =H50/10^5 -> 0.5168715 | J50: 1.17675
B51: Closing | H51: =SUM(H47:H50) -> 7549549.6 | I51: =SUM(I47:I50) -> 75.495496 | J51: =SUM(J47:J50) -> 48.649994
A53: =A5+1 -> 9 | B53: ="Note "&A53&": Cash and cash equivalents" -> Note 9: Cash and cash equivalents
H54: =H46 -> As at 31 March 2025 | I54: =I46 -> As at 31 March 2025 | J54: =J6 -> As at 31 March 2024
B55: Balance with banks
A56: Current accounts | B56: (i) In current accounts | H56: =SUMIFS('Standalone TB'!$X:$X,'Standalone TB'!$Z:$Z,'8-10'!$A56) -> 4.7866036e+08 | I56: =H56/10^5 -> 4786.6036 | J56: 2722.5792
A57: EEFC | B57: (ii) In EEFC accounts | H57: =SUMIFS('Standalone TB'!$X:$X,'Standalone TB'!$Z:$Z,'8-10'!$A57) -> 71104921 | I57: =H57/10^5 -> 711.04921 | J57: 64.194416
B58: (iii) In deposit accounts with original maturity of less than 3 months | H58: =0 -> 0 | I58: =H58/10^5 -> 0 | J58: 1100
B59: Cash on hand | H59: =0 -> 0 | I59: =H59/10^5 -> 0 | J59: 0
B60: Total | H60: =SUM(H55:H59) -> 5.4976528e+08 | I60: =SUM(I55:I59) -> 5497.6528 | J60: =SUM(J55:J59) -> 3886.7736
B62: During the year the group has obtained sanction of non fund based working capital limit amounting to ₹25 from bank on the basis of security of current assets, the Company has not utilised such limit as on 31 March 2025. The company has pledged a part of its short term deposits to fulfill collateral requirements(Refer Note 6 for futher details).
B64: Short term deposits are made for varying period of between one day and three months ,depending on the immediate cash requirement of the company,and earn interest at the respective short term deposit rate.
A67: =A53+1 -> 10 | B67: ="Note "&A67&": Bank balances other than cash and cash equivalents" -> Note 10: Bank balances other than cash and cash equivalents
H68: =H6 -> As at 31 March 2025 | I68: =I6 -> As at 31 March 2025 | J68: =J6 -> As at 31 March 2024
A69: Deposits with Banks | B69: Bank balances other than cash and cash equivalents | H69: =SUMIFS('Standalone TB'!$X:$X,'Standalone TB'!$Z:$Z,'8-10'!$A69)-'5-7'!C13-'5-7'!C23 -> 240205.6 | I69: =H69/10^5 -> 2.402056 | J69: 2247.8618 | K69: =H69+H58+'5-7'!C23+'5-7'!C13 -> 5578412.3 | L69: =J69+J58+'5-7'!E23+'5-7'!E13 -> 3519.8618 | M69: =L69*10^5 -> 3.5198618e+08
B70: (In deposit account with original maturity of greater for 3 months but less than 12 months) | H70: =SUM(H69:H69) -> 240205.6 | I70: =SUM(I69:I69) -> 2.402056 | J70: =SUM(J69:J69) -> 2247.8618
B75: (Space has been left intentionally)

Sheet 11-13
B1: ='3-4'!B1 -> Paladion Networks Private Limited
B2: ='3-4'!B2 -> Summary of Material accounting policies and other explanatory information
B3: ='3-4'!B3 -> (Amounts are stated in ₹ lakhs, except share and per share data, unless ottherwise stated)
A5: ='8-10'!A67+1 -> 11 | B5: ="Note "&A5&": Share capital" -> Note 11: Share capital
C7: Authorised share capital
E8: As at 31 March 2025 | G8: As at 31 March 2024
E9: Number of shares | F9: Amount | G9: Number of shares | H9: Amount
C10: Equity shares of ₹10 each | E10: =G10 -> 10000 | F10: =H10 -> 1 | G10: 10000 | H10: =H16 -> 1
C11: Preference shares of ₹10 each | E11: =G11 -> 1000000 | F11: =H11 -> 100 | G11: 1000000 | H11: =10000000/10^5 -> 100
C13: Issued, subscribed and fully paid up
E14: =E8 -> As at 31 March 2025 | G14: =G8 -> As at 31 March 2024
E15: Number of shares | F15: Amount | G15: Number of shares | H15: Amount
C16: Equity shares of ₹10 each | E16: =G16 -> 10000 | F16: =H16 -> 1 | G16: 10000 | H16: =H28 -> 1
C17: Preference shares of ₹10 each | E17: =G17 -> 496183 | F17: =H17 -> 49.6183 | G17: 496183 | H17: =H33 -> 49.6183
E18: =SUM(E16:E17) -> 506183 | F18: =SUM(F16:F17) -> 50.6183 | G18: =SUM(G16:G17) -> 506183 | H18: =SUM(H16:H17) -> 50.6183
C20: Issued Equity share capital
B21: a) | C21: Reconciliation of shares outstanding at the beginning and at the end of the period
G22: Number of shares | H22: Amount
C23: Equity shares of ₹10 each issued, subscribed and fully paid up
C24: Balance as at 01 April 2023 | G24: 10000 | H24: =(G24*10)/10^5 -> 1
C25: Change during the year | G25: - | H25: -
C26: Balance as at 31 March 2024 | G26: =SUM(G24:G25) -> 10000 | H26: =SUM(H24:H25) -> 1
C27: Change during the year | G27: - | H27: -
C28: Shares issued and fully paid as at 31 March 2025 | G28: =SUM(G26:G27) -> 10000 | H28: =SUM(H26:H27) -> 1
C30: Equity component of preference shares of ₹10 each issued and fully paid up
C31: Balance as at 01 April 2023 | G31: 496183 | H31: =(G31*10)/10^5 -> 49.6183
C32: Change during the year | G32: 0 | H32: =(G32*10)/10^5 -> 0
C33: Balance as at 31 March 2024 | G33: =SUM(G31:G32) -> 496183 | H33: =SUM(H31:H32) -> 49.6183
C34: Change during the year | G34: - | H34: -
C35: Shares issued and fully paid as at 31 March 2025 | G35: =SUM(G33:G34) -> 496183 | H35: =SUM(H33:H34) -> 49.6183
B37: b) | C37: Rights, preferences and restrictions attached to the equity shares
C38: The Company has only one class of equity shares with voting rights (one vote per share). The Company declares and pays dividend in Indian rupees. The dividend proposed by board of directors is subject to approval by the shareholders at the ensuing annual general meeting. In the event of liquidation of the Company, the equity shareholders are entitled to receive only the residual assets of the Company after distribution of all preferential amount. The distribution will be in proportion to the number of equity shares held by the shareholder. Other rights attached to the equity shares are as per the articles of the Company.
B42: c) | C42: Rights, preferences and restrictions attached to the compulsorily convertible non-cumulative preference shares
C43: The Company has only one class of compulsorily convertible non-cumulative preference shares. In the event of liquidation of the Company, Compulsorily convertible non-cumulative preference shares will be preference over equity shareholders. The distribution will be in proportion to the number of preference shares held by the preference shareholders. Other rights attached to the preference shares are as per the articles of the Company. The shares are compulsorily convertible within 20 years from the date of allotment and are non-cumulative. The Preference shares rank ahead of Equity shares in the event of liquidation of the company.
B48: Summary of significant accounting policies and other explanatory information as at and for the year ended 31 March 2022
B49: (Amounts are stated in ₹ lakhs unless otherwise stated)
B51: d) | C51: Shares held by holding/ ultimate holding company and/ or their subsidiaries/ associates
E52: =E8 -> As at 31 March 2025 | G52: =G8 -> As at 31 March 2024
E53: Number of shares | F53: % of holding | G53: Number of shares | H53: % of holding
C54: Equity shares of ₹10 each
C55: Paladion Technologies Inc (Holding company) | E55: 9999 | F55: =E55/$E$57 -> 0.9999 | G55: 9999 | H55: =G55/$E$57 -> 0.9999
C56: Eviden India Private Limited (formerly known as Atos India Private Limited) | E56: 1 | F56: =E56/E57 -> 0.0001 | G56: 1 | H56: =G56/G57 -> 0.0001
E57: =SUM(E55:E56) -> 10000 | F57: =SUM(F55:F56) -> 1 | G57: =SUM(G55:G56) -> 10000 | H57: =SUM(H55:H56) -> 1
C58: Preference shares of ₹10 each
C59: Nadathur Estates Private Limited | E59: 0 | F59: =E59/$E$72 -> 0 | G59: 83800 | H59: =G59/$G$72 -> 0.08444465
C60: Amita Partners | E60: 0 | F60: =E60/$E$72 -> 0 | G60: 210297 | H60: =G60/$G$72 -> 0.21191476
C61: Rajat Mohanty | E61: 0 | F61: =E61/$E$72 -> 0 | G61: 32131 | H61: =G61/$G$72 -> 0.032378175
C62: Vinod Vasudevan | E62: 0 | F62: =E62/$E$72 -> 0 | G62: 28639 | H62: =G62/$G$72 -> 0.028859312
C63: Binu Mathew Thomas | E63: 0 | F63: =E63/$E$72 -> 0 | G63: 28639 | H63: =G63/$G$72 -> 0.028859312
C64: Jose Varghese | E64: 0 | F64: =E64/$E$72 -> 0 | G64: 28639 | H64: =G64/$G$72 -> 0.028859312
C65: Sreeraj Gopinathan Nair | E65: 0 | F65: =E65/$E$72 -> 0 | G65: 28639 | H65: =G65/$G$72 -> 0.028859312
C66: Firosh C Ummer | E66: 0 | F66: =E66/$E$72 -> 0 | G66: 28639 | H66: =G66/$G$72 -> 0.028859312
C67: Roshan R Chandran | E67: 0 | F67: =E67/$E$72 -> 0 | G67: 3394 | H67: =G67/$G$72 -> 0.0034201091
C68: Rohit Girish Kumar | E68: 0 | F68: =E68/$E$72 -> 0 | G68: 11683 | H68: =G68/$G$72 -> 0.011772874
C69: Sachin Paul Varghese | E69: 0 | F69: =E69/$E$72 -> 0 | G69: 11683 | H69: =G69/$G$72 -> 0.011772874
C70: Atos Global IT Solutions & Services Private Limited | G70: 496183 | H70: 1
C71: Syntel Private Limited | E71: 496183 | F71: =E71/$E$72 -> 1 | G71: 496183 | H71: =G71/$E$72 -> 1
E72: =SUM(E70:E71) -> 496183 | F72: =SUM(F70:F71) -> 1 | G72: =SUM(G70:G71) -> 992366 | H72: =SUM(H70:H71) -> 2
C73: During the year preference shares of the company are sold by Atos Global IT Solutions and Services Private Limited to Syntel Private Limited on 26 April 2023.
C74: The Company has accounted preference shares as 100% equity component.
B75: =B1 -> Paladion Networks Private Limited
B76: =B2 -> Summary of Material accounting policies and other explanatory information
B77: =B3 -> (Amounts are stated in ₹ lakhs, except share and per share data, unless ottherwise stated)
A79: ='8-10'!A143+11 -> 11 | B79: ="Note "&A79&": Share capital (Contd.)" -> Note 11: Share capital (Contd.)
B81: e) | C81: Details of equity shares held by each shareholder holding more than 5% shares
C82: Name of shareholder | E82: As at 31 March 2025 | G82: As at 31 March 2024
E83: Number of shares | F83: % of holding | G83: Number of shares | H83: % of holding
C84: Equity shares of ₹10 each
C85: Paladion Technologies Inc | E85: 9999 | F85: =E85/10000 -> 0.9999 | G85: 9999 | H85: =G85/10000 -> 0.9999
E86: =SUM(E85:E85) -> 9999 | F86: =SUM(F85:F85) -> 0.9999 | G86: =SUM(G85:G85) -> 9999 | H86: =SUM(H85:H85) -> 0.9999
C87: Preference shares of ₹10 each
C88: Nadathur Estates Private Limited | E88: 0 | F88: =E88/$E$72 -> 0 | G88: 0 | H88: =G88/496183 -> 0
C89: Amita Partners | E89: 0 | F89: =E89/$E$72 -> 0 | G89: 0 | H89: =G89/496183 -> 0
C90: Rajat Mohanty | E90: 0 | F90: =E90/$E$72 -> 0 | G90: 0 | H90: =G90/496183 -> 0
C91: Vinod Vasudevan | E91: 0 | F91: =E91/$E$72 -> 0 | G91: 0 | H91: =G91/496183 -> 0
C92: Binu Mathew Thomas | E92: 0 | F92: =E92/$E$72 -> 0 | G92: 0 | H92: =G92/496183 -> 0
C93: Jose Varghese | E93: 0 | F93: =E93/$E$72 -> 0 | G93: 0 | H93: =G93/496183 -> 0
C94: Sreeraj Gopinathan Nair | E94: 0 | F94: =E94/$E$72 -> 0 | G94: 0 | H94: =G94/496183 -> 0
C95: Firosh C Ummer | E95: 0 | F95: =E95/$E$72 -> 0 | G95: 0 | H95: =G95/496183 -> 0
C96: Syntel Private Limited | E96: 496183 | F96: =E96/E98 -> 1 | G96: 496183 | H96: =G96/G98 -> 1
C97: Atos Global IT Solutions & Services Private Limited | E97: 0 | F97: - | G97: 0 | H97: -
E98: =SUM(E88:E97) -> 496183 | F98: =SUM(F88:F97) -> 1 | G98: =SUM(G88:G97) -> 496183 | H98: =SUM(H88:H97) -> 1
B100: f) | C100: The Company has not issued any bonus shares or shares for consideration other than cash nor has there been any buy back of shares during five years immediately preceding 31 March 2025.
B102: g) | C102: Promoter's holding | E102: =E82 -> As at 31 March 2025 | G102: =G82 -> As at 31 March 2024
E103: Number of shares | F103: % of holding | G103: Number of shares | H103: % of holding
C104: Equity shares of ₹ 10 each
C105: Paladion Technologies Inc | E105: 9999 | F105: =E105/E107 -> 0.9999 | G105: 9999 | H105: =G105/G107 -> 0.9999
C106: =C56 -> Eviden India Private Limited (formerly known as Atos India Private Limited) | E106: 1 | F106: =E106/E107 -> 0.0001 | G106: 1 | H106: =G106/G107 -> 0.0001
E107: =SUM(E105:E106) -> 10000 | F107: =SUM(F105:F106) -> 1 | G107: =SUM(G105:G106) -> 10000 | H107: =SUM(H105:H106) -> 1
A109: =A5+1 -> 12 | B109: ="Note "&A109&": Other equity" -> Note 12: Other equity | G109: =E8 -> As at 31 March 2025 | H109: =G8 -> As at 31 March 2024
C111: Securities premium {Refer Note (a) below} | G111: =(G125) -> 41916.54 | H111: 41916.54
C112: Retained earnings {Refer Note (b) below} | G112: =(G134) -> -30439.834 | H112: -30551.565
C113: Total | G113: =SUM(G111:G112) -> 11476.706 | H113: =SUM(H111:H112) -> 11364.975
B117: Summary of significant accounting policies and other explanatory information as at and for the year ended 31 March 2021
B118: (All amounts are stated in ₹ unless otherwise stated)
B121: (a) | C121: Securities premium | G121: =G109 -> As at 31 March 2025 | H121: =H109 -> As at 31 March 2024
C123: Balance at the beginning of the year | G123: =H125 -> 41916.54 | H123: =41917.53984*100000/10^5-1 -> 41916.54
C124: Additions during the year | G124: - | H124: -
C125: Balance at the end of the year | G125: =SUM(G123:G124) -> 41916.54 | H125: =SUM(H123:H124) -> 41916.54
B129: (b) | C129: Retained earnings | G129: =G121 -> As at 31 March 2025 | H129: =H121 -> As at 31 March 2024
...

Sheet 14-16
B1: ='3-4'!B1 -> Paladion Networks Private Limited | M1: =N1*O1 -> 0 | O1: ='8-10'!O1 -> 23.2939 | P1: ='8-10'!P1 -> 85.563771
B2: ='3-4'!B2 -> Summary of Material accounting policies and other explanatory information
B3: ='3-4'!B3 -> (Amounts are stated in ₹ lakhs, except share and per share data, unless ottherwise stated)
A5: ='11-13'!A142+1 -> 14 | B5: ="Note "&A5&": Trade payables" -> Note 14: Trade payables | H5: As at 31 March 2025 | I5: As at 31 March 2025 | J5: As at 31 March 2024 | M5: Creditors | N5: India | O5: Sharjah | P5: US | Q5: Total
B7: Dues to (*) | M7: Internal | N7: =925285887.61-7208998+4519847-846292+2131502 -> 9.2388195e+08 | O7: =(4776844.01000001+3995+59042)*O1 -> 1.1273971e+08 | P7: =(310466.94)*$P$1 -> 26564722 | Q7: =SUM(N7:P7) -> 1.0631864e+09
B8: - micro enterprises and small enterprises (refer note 14.2 below) | H8: 95474.65 | I8: =(SUM(H8:H8))/10^5 -> 0.9547465 | J8: 78.55814 | M8: Internal-Elimination | N8: -7.2128282e+08 | O8: =-248959.3*O1 -> -5799233.1 | P8: =-69998.44*$P$1 -> -5989330.5 | Q8: =SUM(N8:P8) -> -7.3307139e+08
B9: - creditors other than micro enterprises and small enterprises | M9: Internal Forex | N9: =2740730.20952922 -> 2740730.2 | O9: =13403.2*O1 -> 312212.8 | Q9: =SUM(N9:P9) -> 3052943
B10: (i) To related parties (refer note 30) | H10: =SUM(Q7:Q9) -> 3.3316793e+08 | I10: =(SUM(H10:H10))/10^5 -> 3331.6793 | J10: 6409.1245 | M10: External | N10: =7735522.49-1267006 -> 6468516.5 | O10: =1188524.79*O1 -> 27685378 | P10: =4906.25*P1 -> 419797.25 | Q10: =SUM(N10:P10) -> 34573692
A11: Sundry Creditors | B11: (ii) To other than related parties | H11: =-SUMIFS('Standalone TB'!$X:$X,'Standalone TB'!$Z:$Z,'14-16'!$A11)-H8-H10-H62 -> 34445492 | I11: =(SUM(H11:H11))/10^5 -> 344.45492 | J11: 428.21045 | M11: Capex Creditors | Q11: =SUM(N11:P11) -> 0
H12: 0 | I12: =SUM(H12:H12) -> 0 | J12: 0
B13: Accrued expenses | M13: External Forex | N13: =-33148.8700000002 -> -33148.87 | O13: =18.3*O1 -> 426.27837 | Q13: =SUM(N13:P13) -> -32722.592
B14: (i) Related parties (refer note 30) | H14: 30335322 | I14: =(SUM(H14:H14))/10^5 -> 303.35322 | J14: 287.92318 | M14: Total | N14: =SUM(N7:N13) -> 2.1177522e+08 | O14: =SUM(O7:O13) -> 1.3493849e+08 | P14: =SUM(P7:P13) -> 20995189 | Q14: =SUM(Q7:Q13) -> 3.677089e+08
A15: Accrued exp | B15: (ii) others | H15: =-SUMIFS('Standalone TB'!$X:$X,'Standalone TB'!$Z:$Z,'14-16'!$A15)-H14 -> 1.1650375e+08 | I15: =(SUM(H15:H15))/10^5 -> 1165.0375 | J15: 1187.4664
B16: Total | H16: =SUM(H8:H15) -> 5.1454797e+08 | I16: =SUM(I8:I15) -> 5145.4797 | J16: =SUM(J8:J15) -> 8391.2828 | M16: As per TB | N16: =-SUMIF('Standalone TB'!$Z$8:$Z$623,"Sundry Creditors",'Standalone TB'!$H$8:$H$623) -> 2.1177522e+08 | O16: =-SUMIF('Standalone TB'!$Z$8:$Z$623,"Sundry Creditors",'Standalone TB'!$N$8:$N$623) -> 1.3493849e+08 | P16: =-SUMIF('Standalone TB'!$Z$8:$Z$623,"Sundry Creditors",'Standalone TB'!$U$8:$U$623) -> 20995189 | Q16: =SUM(N16:P16) -> 3.677089e+08
B17: (*) There are no disputed dues as on 31 March 2025. (31 March 2024 : NIL) | M17: Difference | N17: =N14-N16 -> -0.52742654 | O17: =O14-O16 -> 2.5623293 | P17: =P14-P16 -> 0 | Q17: =Q14-Q16 -> 2.0349028
B18: Trade payables are non interest bearing and are generally settled on 60 day terms.
A20: =A5&".1" -> 14.1 | B20: ="Note "&A20&" : " -> Note 14.1 : | N20: - | O20: -
B21: Trade payables ageing as at 31 March 2025 | C21: Accrued expenses (not due) | D21: Total Accrued expenses | E21: < 1 year | F21: 1-2 years | G21: 2-3 years | I21: > 3 years | J21: Total | O21: -
B22: Total outstanding dues of micro enterprises and small enterprises | E22: =95474.65/10^5 -> 0.9547465 | J22: =SUM(D22:I22) -> 0.9547465 | N22: India | O22: Sharjah | P22: US | Q22: Total
B23: Total outstanding dues of creditors other than micro enterprises and small enterprises | C23: =I14+I15 -> 1468.3907 | D23: =C23 -> 1468.3907 | E23: =Q23/10^5-E22 -> 2940.9315 | F23: =Q24/10^5 -> 126.56016 | G23: =Q25/10^5 -> 527.59129 | I23: =Q26/10^5 -> 81.051286 | J23: =SUM(D23:I23) -> 5144.5249 | M23: Less than 1 year | N23: =206156180+2707582-846292+2131502 -> 210148972 | O23: =2693058.02*O1+312639 -> 63044464 | P23: =(245374.75)*P1 -> 20995189 | Q23: =SUM(N23:P23) -> 2.9418862e+08
B24: Disputed dues of micro enterprises and small enterprises | J24: =SUM(D24:I24) -> 0 | M24: 1-2 year | N24: 1626251 | O24: =473504.43*O1 -> 11029765 | Q24: =SUM(N24:P24) -> 12656016
B25: Disputed dues of creditors other than micro enterprises and small enterprises | J25: =SUM(D25:I25) -> 0 | M25: 2-3 year | O25: =2264933.25*O1 -> 52759129 | Q25: =SUM(N25:P25) -> 52759129
B26: Total | C26: =SUM(C22:C25) -> 1468.3907 | D26: =SUM(D22:D25) -> 1468.3907 | E26: =SUM(E22:E25) -> 2941.8862 | F26: =SUM(F22:F25) -> 126.56016 | G26: =SUM(G22:G25) -> 527.59129 | I26: =SUM(I22:I25) -> 81.051286 | J26: =SUM(J22:J25) -> 5145.4797 | M26: More than 3 year | O26: =347950.69*O1 -> 8105128.6 | Q26: =SUM(N26:P26) -> 8105128.6
N27: =SUM(N23:N26) -> 211775223 | O27: =SUM(O23:O26) -> 1.3493849e+08 | P27: =SUM(P23:P26) -> 20995189 | Q27: =SUM(Q23:Q26) -> 3.677089e+08
B28: Trade payables ageing as at 31 March 2024 | C28: Accrued expenses (not due) | D28: Total Accrued expenses | E28: < 1 year | F28: 1-2 years | G28: 2-3 years | I28: > 3 years | J28: Total | N28: =N27-N16 -> 0.29304421 | O28: =O27-O16 -> -0.081330806 | P28: =P27-P16 -> 0
B29: Total outstanding dues of micro enterprises and small enterprises | C29: 0 | D29: 0 | E29: 78.55814 | F29: 0 | G29: 0 | I29: 0 | J29: =SUM(D29:I29) -> 78.55814
B30: Total outstanding dues of creditors other than micro enterprises and small enterprises | C30: 1475.3896 | D30: 1475.3896 | E30: 6451.1573 | F30: 384.14315 | G30: 2.03457 | I30: 0 | J30: =SUM(D30:I30) -> 8312.7246
B31: Disputed dues of micro enterprises and small enterprises | C31: 0 | D31: 0 | E31: 0 | F31: 0 | G31: 0 | I31: 0 | J31: =SUM(D31:I31) -> 0
B32: Disputed dues of creditors other than micro enterprises and small enterprises | C32: 0 | D32: 0 | E32: 0 | F32: 0 | G32: 0 | I32: 0 | J32: =SUM(D32:I32) -> 0
B33: Total | C33: =SUM(C29:C32) -> 1475.3896 | D33: =SUM(D29:D32) -> 1475.3896 | E33: =SUM(E29:E32) -> 6529.7154 | F33: =SUM(F29:F32) -> 384.14315 | I33: =SUM(I29:I32) -> 0 | J33: =SUM(J29:J32) -> 8391.2828
A36: =A5&".2" -> 14.2 | B36: ="Note "&A36&" : Micro and Small Enterprises" -> Note 14.2 : Micro and Small Enterprises
B37: The Company has amounts due to micro and small suppliers registered under the Micro, Small and Medium Enterprises Development Act 2006 (MSMED Act), as at 31 March 2025
B38: The disclosure pursuant to the said Act is as under:
B39: Particulars | H39: =H5 -> As at 31 March 2025 | I39: =I5 -> As at 31 March 2025 | J39: =J5 -> As at 31 March 2024
B40: The amount remaining unpaid to micro and small suppliers at the end of the year
B41: - Principal | H41: ='14-16'!H8 -> 95474.65 | I41: =H41/10^5 -> 0.9547465 | J41: 78.55814
B42: - Interest on above | I42: 0 | J42: 0
B43: Payment made to suppliers (other than interest) beyond appointed day during the year | I43: 0 | J43: 0
B44: Interest due and payable to suppliers under MSMED Act towards payments already made(#) | H44: 461.03611 | I44: =H44/10^5 -> 0.0046103611 | J44: 0.40588746
B45: Interest accrued and remaining unpaid at the end of the accounting year | H45: 1081905.9 | I45: =H45/10^5 -> 10.819059 | J45: 10.814449
B46: The amount of further interest remaining due and payable even in the succeeding years, until such date when the interest dues as above are actually paid to the small enterprise for the purpose of disallowance as a deductible expenditure under section 23 of the MSMED Act.(#) | I46: =H46/10^5 -> 0 | J46: 0.010331176
B47: #) Zero represents less than ₹0.5 Lakhs
A49: =A5+1 -> 15 | B49: ="Note "&A49&": Other financial liabilities" -> Note 15: Other financial liabilities | H49: =H39 -> As at 31 March 2025 | I49: =I39 -> As at 31 March 2025 | J49: =J5 -> As at 31 March 2024
A50: Employees Payable | B50: Accrued employee related expenses | H50: =-SUMIFS('Standalone TB'!$X:$X,'Standalone TB'!$Z:$Z,'14-16'!$A50) -> 52497699 | I50: =(SUM(H50:H50))/10^5 -> 524.97699 | J50: 689.46914
A51: Payable to Group | B51: Payable to group companies (refer note 30) | H51: =-SUMIFS('Standalone TB'!$X:$X,'Standalone TB'!$Z:$Z,'14-16'!$A51) -> 3.6283708e+08 | I51: =(SUM(H51:H51))/10^5 -> 3628.3708 | J51: 4549.2901
A52: SD Repayable | B52: Security deposit refundable to related party(refer note 30) | H52: =-SUMIFS('Standalone TB'!$X:$X,'Standalone TB'!$Z:$Z,'14-16'!$A52) -> 3582592.7 | I52: =(SUM(H52:H52))/10^5 -> 35.825927 | J52: 33.577196
B53: Total | H53: =SUM(H50:H52) -> 4.1891737e+08 | I53: =SUM(I50:I52) -> 4189.1737 | J53: =SUM(J50:J52) -> 5272.3365
A57: =A49+1 -> 16 | B57: ="Note "&A57&": Other current liabilities" -> Note 16: Other current liabilities | H57: =H49 -> As at 31 March 2025 | I57: =I49 -> As at 31 March 2025 | J57: =J5 -> As at 31 March 2024
A58: Stat dues | B58: Statutory dues payable | H58: =-SUMIFS('Standalone TB'!$X:$X,'Standalone TB'!$Z:$Z,'14-16'!$A58) -> 22083003 | I58: =(SUM(H58:H58))/10^5+0.4 -> 221.23003 | J58: 631.25136 | K58: =ROUND(I58,0) -> 221
B59: Advances from customers | K59: =ROUND(I59,0) -> 0
A60: Advance from Customers | B60: ="- Related parties (refer note "&'30 RPT'!A5&")" -> - Related parties (refer note 30) | H60: =-SUMIFS('Standalone TB'!$X:$X,'Standalone TB'!$Z:$Z,'14-16'!$A60)-H61 -> 21312521 | I60: =H60/10^5 -> 213.12521 | J60: 2.1062501 | K60: =ROUND(I60,0) -> 213
B61: - Others | H61: =-ROUND('Standalone TB'!X211+'Standalone TB'!X210,0) -> 0 | I61: =H61/10^5 -> 0 | J61: 12.50083 | K61: =ROUND(I61,0) -> 0
B62: Capital creditors | I62: =H62/10^5 -> 0 | J62: 8.912376 | K62: =ROUND(I62,0) -> 0
A63: Deferred Rent-inter co | B63: Deferred Rent - Related Parties (refer note 30) | H63: =-SUMIFS('Standalone TB'!$X:$X,'Standalone TB'!$Z:$Z,'14-16'!$A63) -> 606973.23 | I63: =H63/10^5 -> 6.0697323 | J63: 8.4656821 | K63: =ROUND(I63,0) -> 6
B64: Unearned revenue | K64: =ROUND(I64,0) -> 0
A65: Unearned income-inter co | B65: ="- Related parties (refer note "&'30 RPT'!A5&")" -> - Related parties (refer note 30) | H65: =-SUMIFS('Standalone TB'!$X:$X,'Standalone TB'!$Z:$Z,'14-16'!$A65) -> 0 | I65: =H65/10^5 -> 0 | J65: 155.81267 | K65: =ROUND(I65,0) -> 0
A66: Unearned income | B66: - Others | H66: =-SUMIFS('Standalone TB'!$X:$X,'Standalone TB'!$Z:$Z,'14-16'!$A66) -> 45202930 | I66: =H66/10^5 -> 452.0293 | J66: 496.06185 | K66: =ROUND(I66,0) -> 452
B67: Total | H67: =SUM(H58:H66) -> 89205427 | I67: =SUM(I58:I66) -> 892.45427 | J67: =SUM(J58:J66) -> 1315.111

Sheet 17-25
B1: ='3-4'!B1 -> Paladion Networks Private Limited
B2: ='3-4'!B2 -> Summary of Material accounting policies and other explanatory information
B3: ='3-4'!B3 -> (Amounts are stated in ₹ lakhs, except share and per share data, unless ottherwise stated)
A5: ='14-16'!A57+1 -> 17 | B5: ="Note "&A5&": Revenue from contract with customers" -> Note 17: Revenue from contract with customers | C5: For the year ended 31 March 2025 | D5: For the year ended 31 March 2025 | E5: For the year ended 31 March 2024
B6: Revenue from contract with customers
B7: Sale of services
B8: ="- Related parties (refer note "&'30 RPT'!A5&")" -> - Related parties (refer note 30) | C8: =1690580687.09239 -> 1.6905807e+09 | D8: =(SUM(C8:C8))/10^5 -> 16905.807 | E8: 18783.095 | F8: ok | G8: 1.6940301e+09 | H8: =C8-G8 -> -3449417.2
A9: Revenue from operations | B9: - Others | C9: =-SUMIFS('Standalone TB'!$X:$X,'Standalone TB'!$Z:$Z,'17-25'!$A9)-C8 -> 6.3954828e+08 | D9: =(SUM(C9:C9))/10^5 -> 6395.4828 | E9: 9294.8721 | G9: 6.4002134e+08 | H9: =C9-G9 -> -473060.38
B10: Other operating revenue | C10: 0 | D10: =(SUM(C10:C10))/10^5 -> 0 | E10: 0
B12: Total | C12: =SUM(C6:C11) -> 2.330129e+09 | D12: =SUM(D6:D11) -> 23301.29 | E12: =SUM(E6:E11) -> 28077.967
B14: =A5&".1 Disaggregated revenue information" -> 17.1 Disaggregated revenue information
B16: (i) Revenue (by location of customers) | C16: =C5 -> For the year ended 31 March 2025 | D16: =D5 -> For the year ended 31 March 2025 | E16: =E5 -> For the year ended 31 March 2024
B18: Middle East | C18: =542482447.523959 -> 5.4248245e+08 | D18: =(SUM(C18:C18))/10^5 -> 5424.8245 | E18: 6213.977
B19: India | C19: =495599735.83 -> 4.9559974e+08 | D19: =(SUM(C19:C19))/10^5 -> 4955.9974 | E19: 6756.5608
B20: USA | C20: =360072124.453192 -> 3.6007212e+08 | D20: =(SUM(C20:C20))/10^5 -> 3600.7212 | E20: 8009.7931
B21: Germany | C21: =574931206.614334 -> 5.7493121e+08 | D21: =(SUM(C21:C21))/10^5 -> 5749.3121 | E21: 4101.0867
B22: Mexico | C22: =141338903.28 -> 1.413389e+08 | D22: =(SUM(C22:C22))/10^5 -> 1413.389 | E22: 1140.3034
B23: Rest of world | C23: =215704545.789825 -> 2.1570455e+08 | D23: =(SUM(C23:C23))/10^5 -> 2157.0455 | E23: 1856.2456
B24: Total | C24: =SUM(C18:C23) -> 2.330129e+09 | D24: =SUM(D18:D23) -> 23301.29 | E24: =SUM(E18:E23) -> 28077.967
B26: (ii) Revenue (by contract type) | C26: =C16 -> For the year ended 31 March 2025 | D26: =D16 -> For the year ended 31 March 2025 | E26: =E5 -> For the year ended 31 March 2024
B28: Time and material | C28: =198115661.937855 -> 1.9811566e+08 | D28: =C28/10^5 -> 1981.1566 | E28: 3841.7367
B29: Fixed price contracts | C29: =2001794164.86674 -> 2.0017942e+09 | D29: =C29/10^5 -> 20017.942 | E29: 21743.139
B30: Others | C30: =130219136.686713 -> 1.3021914e+08 | D30: =C30/10^5 -> 1302.1914 | E30: 2492.091
B31: Total | C31: =SUM(C28:C30) -> 2.330129e+09 | D31: =SUM(D28:D30) -> 23301.29 | E31: =SUM(E28:E30) -> 28076.967
B33: (iii) Revenue (by service) | C33: =C26 -> For the year ended 31 March 2025 | D33: =D26 -> For the year ended 31 March 2025 | E33: =E26 -> For the year ended 31 March 2024
B35: Managed Detection and Response (MDR) | C35: =1416253280.33104 -> 1.4162533e+09 | D35: =(SUM(C35:C35))/10^5 -> 14162.533 | E35: 16028.83
B36: Others | C36: =C12-C35 -> 9.1387568e+08 | D36: =(SUM(C36:C36))/10^5 -> 9138.7568 | E36: 12049.137
B38: (iv) Timing of revenue recognition
B40: (a) Services transferred at a point in time | C40: =C12 -> 2.330129e+09 | D40: =D24-D41 -> 23301.29 | E40: 24438.8
B41: (b) Services transferred over a period of time | C41: =0 -> 0 | D41: =C41/10^5 -> 0 | E41: 3639.1667
B43: (iii) Contract balances | C43: =C5 -> For the year ended 31 March 2025 | D43: =D5 -> For the year ended 31 March 2025 | E43: =E5 -> For the year ended 31 March 2024
B45: Contract assets(Unbilled revenue) | D45: ='8-10'!I14+'8-10'!I15 -> 3366.5583 | E45: 1878.164
B46: Contract liabilities(Unearned revenue and Advances from customers) | D46: ='14-16'!I65+'14-16'!I66+'14-16'!I60+'14-16'!I61 -> 665.15451 | E46: 666.4816
B49: Note :
B50: Trade receivables
B51: The contract assets are in form of receivables, which are included in income receivable, primarily relate to company right to receive the consideration for services given to the customers but not billed at the reporting date. The contract assets are transfered to receivables when it is billed subsequently.
B52: Contract liabilties
B53: The contract liabilities are in the form of advance received from customer for which the obligation of supply of goods/services is not completed at the year end.
B55: (iv) Movement of contract assets and contract liabilities
D56: =D43 -> For the year ended 31 March 2025 | E56: =E5 -> For the year ended 31 March 2024
B57: Opening Balance of contract liabilities | D57: =E60 -> 666.4816 | E57: 843.60373
B58: Addition in balance of contract liabilities for current year | D58: =D46 -> 665.15451 | E58: 666.4816
B59: Amount of revenue recognised against opening contract liabilities | D59: =-D57 -> -666.4816 | E59: -843.60373
B60: Closing Balance of contract liabilities | D60: =SUM(D57:D59) -> 665.15451 | E60: =SUM(E57:E59) -> 666.4816
B63: Opening Balance of contract assets | D63: =E45 -> 1878.164 | E63: 1806.1719
B64: Addition in balance of contract assets for current year | D64: =D45 -> 3366.5583 | E64: 1878.164
B65: Amount of revenue recognised against opening contract assets | D65: =-D63 -> -1878.164 | E65: -1806.1719
B66: Closing Balance of contract assets | D66: =SUM(D63:D65) -> 3366.5583 | E66: =SUM(E63:E65) -> 1878.164
B69: =B1 -> Paladion Networks Private Limited
B70: =B2 -> Summary of Material accounting policies and other explanatory information
B71: =B3 -> (Amounts are stated in ₹ lakhs, except share and per share data, unless ottherwise stated)
A73: =A5+1 -> 18 | B73: ="Note "&A73&": Other income" -> Note 18: Other income | C73: =C43 -> For the year ended 31 March 2025 | D73: =D43 -> For the year ended 31 March 2025 | E73: =E5 -> For the year ended 31 March 2024
B75: Interest income on
A76: Interest income on bank dep | B76: bank deposits | C76: =-SUMIFS('Standalone TB'!$X:$X,'Standalone TB'!$Z:$Z,'17-25'!$A76) -> 13158240 | D76: =C76/10^5 -> 131.5824 | E76: 225.15439 | G76: =D76*10^5 -> 13158240
A77: Interest income on IT refund | B77: income tax refund | C77: =-SUMIFS('Standalone TB'!$X:$X,'Standalone TB'!$Z:$Z,'17-25'!$A77) -> 3709905 | D77: =C77/10^5 -> 37.09905 | E77: 55.27825 | G77: =D77*10^5 -> 3709905
A78: Interest Income on PL | B78: employee loan | C78: =-SUMIFS('Standalone TB'!$X:$X,'Standalone TB'!$Z:$Z,'17-25'!$A78) -> 25368 | D78: =C78/10^5 -> 0.25368 | E78: 0.21159 | G78: =D78*10^5 -> 25368
A79: other financial assets measured at amortised cost | B79: other financial assets measured at amortised cost | C79: =-SUMIFS('Standalone TB'!$X:$X,'Standalone TB'!$Z:$Z,'17-25'!$A79) -> 1248351.8 | D79: =C79/10^5 -> 12.483518 | E79: 9.5146339 | G79: =D79*10^5 -> 1248351.8
A80: Interest income on Lease receivable | B80: interest income on lease receivable - Related parties (refer note 30) | C80: =-SUMIFS('Standalone TB'!$X:$X,'Standalone TB'!$Z:$Z,'17-25'!$A80) -> 2746033 | D80: =C80/10^5 -> 27.46033 | E80: 20.082086 | G80: =D80*10^5 -> 2746033
A81: Amortization of Deferred Rent | B81: Amorisation of deferred rent - Related parties(refer note 30) | C81: =-SUMIFS('Standalone TB'!$X:$X,'Standalone TB'!$Z:$Z,'17-25'!$A81) -> 239594.78 | D81: =C81/10^5 -> 2.3959478 | E81: 1.5972985 | G81: =D81*10^5 -> 239594.78
A82: Gain on derecognition on ROU | B82: Gain on derecognition of right of use asset - Related parties (refer note 30) | C82: =-SUMIFS('Standalone TB'!$X:$X,'Standalone TB'!$Z:$Z,'17-25'!$A82) -> 0 | D82: =C82/10^5 -> 0 | E82: 66.197828 | G82: =D82*10^5 -> 0
B83: Foreign exchange gain on transactions and translations (net) | C83: 0 | D83: - | E83: -
A84: Written back | B84: Provision / liabilities no longer required written back | C84: =-SUMIFS('Standalone TB'!$X:$X,'Standalone TB'!$Z:$Z,'17-25'!$A84) -> 0 | D84: - | E84: -
B85: Gain on disposal of property, plant and equipment | G85: =D85*10^5 -> 0
A86: Gain on sale of assets | B86: ="- Related parties (refer note "&'30 RPT'!A5&")" -> - Related parties (refer note 30) | C86: =-SUMIFS('Standalone TB'!$X:$X,'Standalone TB'!$Z:$Z,'17-25'!$A86) -> 2102692.9 | D86: =C86/10^5 -> 21.026929 | E86: -1.05199 | G86: =D86*10^5 -> 2102692.9
B87: - others | D87: =C87/10^5 -> 0 | E87: 8.0295476 | G87: =D87*10^5 -> 0
A88: Misc Income | B88: Miscellaneous income(refer note 30) | C88: =-SUMIFS('Standalone TB'!$X:$X,'Standalone TB'!$Z:$Z,'17-25'!$A88) -> 2965488.2 | D88: =C88/10^5 -> 29.654882 | E88: 0.0067412 | G88: =D88*10^5 -> 2965488.2
B90: Total | C90: =SUM(C76:C89) -> 26195673 | D90: =SUM(D76:D89) -> 261.95673 | E90: =SUM(E75:E89) -> 385.02038
A93: =A73+1 -> 19 | B93: ="Note "&A93&": Cost of software packages" -> Note 19: Cost of software packages | C93: =C5 -> For the year ended 31 March 2025 | D93: =D5 -> For the year ended 31 March 2025 | E93: =E5 -> For the year ended 31 March 2024
B95: Hardware bought for service delivery to clients | C95: 0 | D95: =C95/10^5 -> 0 | E95: 0
A96: Cost of material Consumed | B96: Software for service delivery | C96: =SUMIFS('Standalone TB'!$X:$X,'Standalone TB'!$Z:$Z,'17-25'!$A96) -> 1.4835182e+08 | D96: =C96/10^5 -> 1483.5182 | E96: 1510.2087
B97: Total | C97: =SUM(C95:C96) -> 1.4835182e+08 | D97: =SUM(D95:D96) -> 1483.5182 | E97: =SUM(E95:E96) -> 1510.2087
A99: =A93+1 -> 20 | B99: ="Note "&A99&": Technical contract charges" -> Note 20: Technical contract charges | C99: =C5 -> For the year ended 31 March 2025 | D99: =D5 -> For the year ended 31 March 2025 | E99: =E5 -> For the year ended 31 March 2024
B101: Technical contract charges
B102: ="- Related parties (refer note "&'30 RPT'!A5&")" -> - Related parties (refer note 30) | C102: 6.7076543e+08 | D102: =(SUM(C102:C102))/10^5 -> 6707.6543 | E102: 6120.4983
A103: Technical Contract Charges | B103: - others | C103: =SUMIFS('Standalone TB'!$X:$X,'Standalone TB'!$Z:$Z,'17-25'!$A103)-C102 -> 67335427 | D103: =(SUM(C103:C103))/10^5 -> 673.35427 | E103: 2803.9009
B104: Total | C104: =SUM(C101:C103) -> 7.3810085e+08 | D104: =SUM(D101:D103) -> 7381.0085 | E104: =SUM(E101:E103) -> 8924.3992
B107: Summary of significant accounting policies and other explanatory information as at and for the year ended 31 March 2023
B108: (All amounts are stated in ₹ unless otherwise stated)
A110: =A99+1 -> 21 | B110: ="Note "&A110&": Employee benefits expense" -> Note 21: Employee benefits expense | C110: =C5 -> For the year ended 31 March 2025 | D110: =D5 -> For the year ended 31 March 2025 | E110: =E5 -> For the year ended 31 March 2024
B112: Salaries, wages and bonus | F112: 4127137
B113: ="- Related parties (refer note "&'30 RPT'!A5&")" -> - Related parties (refer note 30) | C113: -4127137 | D113: =SUM(C113:C113)/10^5 -> -41.27137 | E113: -70
A114: Salaries and Wages | B114: - others | C114: =SUMIFS('Standalone TB'!$X:$X,'Standalone TB'!$Z:$Z,'17-25'!$A114)-C113 -> 7.9655694e+08 | D114: =SUM(C114:C114)/10^5 -> 7965.5694 | E114: 9994.43
A115: Gratuity | B115: ="Contribution to gratuity (refer note "&'E''ee Benefits 28 '!A5&"(b)(I))" -> Contribution to gratuity (refer note 28(b)(I)) | C115: =SUMIFS('Standalone TB'!$X:$X,'Standalone TB'!$Z:$Z,'17-25'!$A115) -> 25500682 | D115: =SUM(C115:C115)/10^5 -> 255.00682 | E115: 211
A116: Leave encashment | B116: ="Compensated absences (refer note "&'E''ee Benefits 28 '!A5&"(b)(II))" -> Compensated absences (refer note 28(b)(II)) | C116: =SUMIFS('Standalone TB'!$X:$X,'Standalone TB'!$Z:$Z,'17-25'!$A116) -> 9311114.3 | D116: =SUM(C116:C116)/10^5 -> 93.111143 | E116: 210 | F116: 800684072
A117: Contribution | B117: ="Contribution to provident and other funds (refer note "&'E''ee Benefits 28 '!A5&"(a))" -> Contribution to provident and other funds (refer note 28(a)) | C117: =SUMIFS('Standalone TB'!$X:$X,'Standalone TB'!$Z:$Z,'17-25'!$A117) -> 42830494 | D117: =SUM(C117:C117)/10^5 -> 428.30494 | E117: 574.01
B118: Staff welfare expenses | D118: =SUM(C118:C118)/10^5 -> 0
B119: ="- Related parties (refer note "&'30 RPT'!A5&")" -> - Related parties (refer note 30) | C119: 19858 | D119: =SUM(C119:C119)/10^5 -> 0.19858 | E119: 3
A120: Staff Welfare | B120: - others | C120: =SUMIFS('Standalone TB'!$X:$X,'Standalone TB'!$Z:$Z,'17-25'!$A120)-C119 -> 2649570.4 | D120: =SUM(C120:C120)/10^5 -> 26.495704 | E120: 108
B121: Total | C121: =SUM(C113:C120) -> 8.7274152e+08 | D121: =SUM(D113:D120) -> 8727.4152 | E121: =SUM(E113:E120) -> 11030.44
A123: =A110+1 -> 22 | B123: ="Note "&A123&": Finance costs" -> Note 22: Finance costs | C123: =C5 -> For the year ended 31 March 2025 | D123: =D5 -> For the year ended 31 March 2025 | E123: =E5 -> For the year ended 31 March 2024
A125: Bank Charges | B125: Bank charges | C125: =SUMIFS('Standalone TB'!$X:$X,'Standalone TB'!$Z:$Z,'17-25'!$A125) -> 1820867.8 | D125: =(SUM(C125:C125))/10^5 -> 18.208678 | E125: 16.766581
B126: Interest expenses on
A127: Interest on LL | B127: ="- Lease liability (refer note "&'Leases 29'!A5&")" -> - Lease liability (refer note 29) | C127: =SUMIFS('Standalone TB'!$X:$X,'Standalone TB'!$Z:$Z,'17-25'!$A127) -> 10628668 | D127: =(SUM(C127:C127))/10^5 -> 106.28668 | E127: 67.661123
A128: Other fin exp | B128: - Dues to MSME (refer note 14.2) (#) | C128: =SUMIFS('Standalone TB'!$X:$X,'Standalone TB'!$Z:$Z,'17-25'!$A128) -> 461.03611 | D128: =(SUM(C128:C128))/10^5 -> 0.0046103611 | E128: 0.40589
B129: - Other interest costs | C129: =SUMIFS('Standalone TB'!$X:$X,'Standalone TB'!$Z:$Z,'17-25'!$A129) -> 0 | D129: =(SUM(C129:C129))/10^5 -> 0 | E129: 0
B130: ="- Related parties (refer note "&'30 RPT'!A5&")" -> - Related parties (refer note 30) | C130: 224872.7 | D130: =(SUM(C130:C130))/10^5 -> 2.248727 | E130: 1.4201769
A131: Other intersest cost | B131: - others | C131: =SUMIFS('Standalone TB'!$X:$X,'Standalone TB'!$Z:$Z,'17-25'!$A131)-C130 -> 1391815.5 | D131: =(SUM(C131:C131))/10^5 -> 13.918155 | E131: 6.529761
B133: Total | C133: =SUM(C125:C132) -> 14066685 | D133: =SUM(D125:D132) -> 140.66685 | E133: =SUM(E125:E132) -> 92.783532
B135: (#) Zero represents less than ₹0.5 Lakhs
A137: =A123+1 -> 23 | B137: ="Note "&A137&": Depreciation and amortisation expense" -> Note 23: Depreciation and amortisation expense | C137: =C5 -> For the year ended 31 March 2025 | D137: =D5 -> For the year ended 31 March 2025 | E137: =E5 -> For the year ended 31 March 2024
...

Sheet 26-27
B1: ='17-25'!B1 -> Paladion Networks Private Limited
B2: ='17-25'!B2 -> Summary of Material accounting policies and other explanatory information
B3: ='17-25'!B3 -> (Amounts are stated in ₹ lakhs, except share and per share data, unless ottherwise stated)
A5: ='17-25'!A201+1 -> 26 | B5: ="Note "&A5&": Deferred and Income tax " -> Note 26: Deferred and Income tax
B7: (a) Deferred and Income-tax expense through the statement of profit and loss
B9: Particulars | F9: For the year ended 31 March 2025 | G9: For the year ended 31 March 2024
A10: Property and equipment | B10: Profit or loss section
B12: Current tax:
A13: IT | B13: Current tax on profits for the year | F13: =SUMIFS('Standalone TB'!$X:$X,'Standalone TB'!$Z:$Z,A13)/10^5 -> 654.50305 | G13: 8.6358
F14: =SUM(F13:F13) -> 654.50305 | G14: -
B15: Deferred tax charge/ (credit):
B16: In respect of current year origination and reversal of temporary differences | F16: =-E104 -> 398.71987 | G16: 1082.1452
B18: Total tax expense | F18: =SUM(F14:F16) -> 1053.2229 | G18: =SUM(G14:G16) -> 1082.1452
B20: (b) Income-tax on other comprehensive income
B21: Particulars | F21: =$F$9 -> For the year ended 31 March 2025 | G21: =$G$9 -> For the year ended 31 March 2024
B23: (Benefit) on re-measurements of defined benefit plans | F23: =-PL!D38 -> 0 | G23: 12.556788
B24: Total tax expense recognised in other comprehensive income | F24: =F23 -> 0 | G24: =G23 -> 12.556788
B26: (c) Reconciliation of tax expense and the accounting profit /(loss) multiplied by India’s tax rate:
F27: =F9 -> For the year ended 31 March 2025 | G27: =G9 -> For the year ended 31 March 2024
B28: Accounting profit/ (loss) before taxes | F28: =PL!D23 -> 650.87006 | G28: -15033.408
B29: Applicable income tax rate | F29: 0.25168 | G29: 0.25168 | K29: =F29 -> 0.25168 | L29: =G29 -> 0.25168
B30: Tax as per statutory income tax rate | F30: =F28*F29 -> 163.81098 | G30: -3783.6082
B31: Add/(Less): Impact of Permanent difference
B32: Non-deductible interest and taxes | G32: 3 | K32: =F32/F28 -> 0 | L32: =G32/G28 -> -0.00019955555
B33: Difference on account of adoption of new tax rate (*) | G33: 0 | L33: =G33/G28 -> 0
B34: Taxes on exceptional items | G34: 4591
B35: DTA Reversal on business loss | G35: 276
B36: Other differences | G36: 4.4 | K36: =F36/F28 -> 0 | L36: =G36/G28 -> -0.00029268147
B37: Efffective tax | F37: =SUM(F30:F36) -> 163.81098 | G37: =SUM(G30:G36) -> 1090.7918 | I37: =F37/F28 -> 0.25168 | J37: =G37/G28 -> -0.07255785 | K37: =F37/F28 -> 0.25168 | L37: =G37/G28 -> -0.07255785
B39: (d) Reconciliation of tax expense in terms of % | F39: =F27 -> For the year ended 31 March 2025 | G39: =G27 -> For the year ended 31 March 2024
B40: Applicable income tax rate | F40: =-F29 -> -0.25168 | G40: =-G29 -> -0.25168
B41: Add/(Less): Impact of Permanent difference
B42: =B32 -> Non-deductible interest and taxes | F42: =F32/-$F$28 -> 0 | G42: =G32/-$G$28 -> 0.00019955555
B43: =B33 -> Difference on account of adoption of new tax rate (*) | F43: =F33/-$F$28 -> 0 | G43: =G33/-$G$28 -> 0
B44: =B34 -> Taxes on exceptional items | F44: =F34/-$F$28 -> 0 | G44: =G34/-$G$28 -> 0.3053865
B45: =B35 -> DTA Reversal on business loss | F45: =F35/-$F$28 -> 0 | G45: =G35/-$G$28 -> 0.01835911
B46: =B36 -> Other differences | F46: =F36/-$F$28 -> 0 | G46: =G36/-$G$28 -> 0.00029268147
B47: Efffective tax rate | F47: =SUM(F40:F46) -> -0.25168 | G47: =SUM(G40:G46) -> 0.07255785
B49: Computed
B50: - current tax | F50: =PL!D26 -> 654.50305 | G50: 8.6358
B51: - deferred tax | F51: =F16 -> 398.71987 | G51: 1082.1452
B52: Total Tax | F52: =SUM(F50:F51) -> 1053.2229 | G52: =SUM(G50:G51) -> 1090.781
B53: Deferred tax not recognised last year | F53: - | G53: -
B54: Adjustments for current tax of prior periods | F54: 0 | G54: -
B55: Net Amount | F55: =SUM(F52:F53) -> 1053.2229 | G55: =SUM(G52:G53) -> 1090.781
B57: (*) The Company has opted for new tax regime u/s 115BAA from the year i.e. FY 2021-22 as it was beneficial to the Company.
B59: (e) Tax assets:
F60: ='14-16'!H49 -> As at 31 March 2025 | G60: ='14-16'!J49 -> As at 31 March 2024
B62: Tax paid under protest | F62: 0 | G62: 0
B63: Advance tax (net of provision for taxation) | F63: =F69 -> 533.64168 | G63: 740.02419
B64: Total | F64: =SUM(F61:F63) -> 533.64168 | G64: =SUM(G61:G63) -> 740.02419
B65: (f) Reconciliation of provision for taxation
B67: Particulars | F67: =F60 -> As at 31 March 2025 | G67: =G60 -> As at 31 March 2024
B68: Opening | F68: =G72 -> 1849.6468 | G68: 1855.3026 | J68: 53397727
B69: Add: Tax paid (including tax deducted at source and payment under protest) | F69: =J69/10^5 -> 533.64168 | G69: 740.02419 | H69: =G69*10^5 -> 74002419 | J69: 53364168 | L69: 84292810 | M69: =L69/10^5 -> 842.9281
B70: Less: Provision recognised during the year | F70: =-PL!D26 -> -654.50305 | G70: -8.6358
B71: Less: Refund received | F71: =-J71/10^5 -> -805.82904 | G71: -737.04418 | J71: 80582904 | K71: -79005241 | L71: 67533704 | M71: 13049200
A72: Income tax assets | B72: Closing | F72: =SUMIFS('Standalone TB'!$X:$X,'Standalone TB'!$AB:$AB,A72)/10^5 -> 981.25818 | G72: =SUM(G68:G71) -> 1849.6468 | H72: =G72*10^5 -> 1.8496468e+08
J73: =SUM(F68:F71) -> 922.95635 | K73: =F72 -> 981.25818 | L73: =K73-J73 -> 58.301826
B74: =B1 -> Paladion Networks Private Limited
B75: =B2 -> Summary of Material accounting policies and other explanatory information
B76: =B3 -> (Amounts are stated in ₹ lakhs, except share and per share data, unless ottherwise stated)
A78: =A5 -> 26 | B78: ="Note "&A78&": Current tax (Contd.)" -> Note 26: Current tax (Contd.)
B80: (g) Deferred tax assets (net)
F81: =F9 -> For the year ended 31 March 2025 | G81: =G9 -> For the year ended 31 March 2024
B82: Deferred tax asset/ (liability) arising on account of :
B83: Difference in written down value of property and equipment | G83: -103.62856 | H83: =F83-G83 -> 103.62856
B84: Provision for employees benefits | G84: 447.59948 | H84: =F84-G84 -> -447.59948
B85: Provision for advances / trade receivables | G85: 12.24423 | H85: =F85-G85 -> -12.24423
B86: Unabsorbed depreciation | G86: 0 | H86: =F86-G86 -> 0
B87: Brought forward losses | G87: 0 | H87: =F87-G87 -> 0
B88: Section 40(a) disallowance on account of non-deduction of TDS | G88: 49.430775
B89: Others | G89: -6.9260538
A90: Deferred Tax Assets | B90: Net deferred tax asset | F90: =SUMIFS('Standalone TB'!$X:$X,'Standalone TB'!$Z:$Z,A90)/10^5 -> 398.71987 | G90: =SUM(G83:G89) -> 398.71987
B92: (i) Movement in deferred tax assets and deferred tax liabilities from 01 April 2024 to 31 March 2025
B94: Particulars | D94: Opening balance as on 01 April 2024 | E94: Recognised in statement of profit and loss | F94: Recognised in other comprehensive income | G94: Closing balance as on 31 March 2025
B96: Deferred tax asset/ (liability) arising on account of :
B97: =B83 -> Difference in written down value of property and equipment | D97: =G113 -> -103.62856 | E97: =-G83+F83 -> 103.62856 | F97: - | G97: =SUM(D97:F97) -> 0
B98: =B84 -> Provision for employees benefits | D98: =G114 -> 447.59948 | E98: =-G84+F84-F98 -> -447.59948 | F98: =PL!D38 -> 0 | G98: =SUM(D98:F98) -> 0
B99: =B85 -> Provision for advances / trade receivables | D99: =G115 -> 12.24423 | E99: =-G85+F85 -> -12.24423 | F99: - | G99: =SUM(D99:F99) -> 0
B100: =B86 -> Unabsorbed depreciation | D100: =G116 -> 0 | E100: =-G86+F86 -> 0 | F100: - | G100: =SUM(D100:F100) -> 0
B101: =B87 -> Brought forward losses | D101: =G117 -> -0.2 | E101: =-G87+F87 -> 0 | F101: - | G101: =SUM(D101:F101) -> -0.2
B102: =B88 -> Section 40(a) disallowance on account of non-deduction of TDS | D102: =G118 -> 49.430775 | E102: =-G88+F88 -> -49.430775 | F102: - | G102: =SUM(D102:F102) -> 0
B103: =B89 -> Others | D103: =G119 -> -6.9260538 | E103: =-G89+F89 -> 6.9260538 | F103: - | G103: =SUM(D103:F103) -> 0
D104: =SUM(D97:D103) -> 398.51987 | E104: =SUM(E97:E103) -> -398.71987 | F104: =SUM(F97:F103) -> 0 | G104: =SUM(G97:G103) -> -0.2 | I104: =G104-D104 -> -398.71987
B108: (ii) Movement in deferred tax assets and deferred tax liabilities from 1 April 2023 to 31 March 2024
B110: Particulars | D110: Opening balance as on 1 April 2023 | E110: Recognised in statement of profit and loss | F110: Recognised in other comprehensive income | G110: Closing balance as on 31 March 2024
B112: Deferred tax asset/ (liability) arising on account of :
B113: Difference in written down value of property and equipment | D113: -3.8770392 | E113: -99.751521 | F113: - | G113: =SUM(D113:F113) -> -103.62856
B114: Provision for employees benefits | D114: 400.99979 | E114: 59.156476 | F114: -12.556788 | G114: =SUM(D114:F114) -> 447.59948
B115: Provision for Advances / Trade Receivables | D115: 31.278412 | E115: -19.034182 | F115: - | G115: =SUM(D115:F115) -> 12.24423
B116: Unabsorbed depreciation | D116: 532.47892 | E116: -532.47892 | F116: - | G116: =SUM(D116:F116) -> 0
B117: Brought forward losses | D117: 357.36507 | E117: -357.56507 | F117: - | G117: =SUM(D117:F117) -> -0.2
B118: Section 40(a) disallowance on account of non-deduction of TDS | D118: 171.92335 | E118: -122.49258 | F118: - | G118: =SUM(D118:F118) -> 49.430775
B119: Others | D119: 3.0533767 | E119: -9.9794305 | F119: - | G119: =SUM(D119:F119) -> -6.9260538
D120: =SUM(D113:D119) -> 1493.2219 | E120: =SUM(E113:E119)+0.5 -> -1081.6452 | F120: =SUM(F113:F119) -> -12.556788 | G120: =SUM(G113:G119) -> 398.51987
B121: Note : Deferred tax assets are recognised for timing differences of items other than unabsorbed depreciation and carry forward losses only to the extent that reasonable certainty exists that sufficient future taxable income will be available against which these can be realised. However, if there are unabsorbed depreciation and carry forward of losses, and items related to capital losses, deferred tax assets are recognised only if there is virtual certainty, supported by convincing evidence, that there will be sufficient future taxable income available to realise the assets. Deferred tax assets are reviewed at each balance sheet date for their realisability.
A123: =A78+1 -> 27 | B123: ="Note "&A123&": Earnings / (loss) per share" -> Note 27: Earnings / (loss) per share
B125: Particulars | F125: =F9 -> For the year ended 31 March 2025 | G125: =G9 -> For the year ended 31 March 2024
B126: The numerators and denominators used to calculate the basic and diluted earnings per share are as follows:
...

Sheet E'ee Benefits 28 
B1: ='26-27'!B1 -> Paladion Networks Private Limited
B2: ='26-27'!B2 -> Summary of Material accounting policies and other explanatory information
B3: ='26-27'!B3 -> (Amounts are stated in ₹ lakhs, except share and per share data, unless ottherwise stated)
A5: ='26-27'!A123+1 -> 28 | B5: ="Note "&A5&": Employee benefit obligations" -> Note 28: Employee benefit obligations
K6: 100000
B7: a) | C7: Defined contribution plans
B8: The Company's defined contribution plans are provident fund, employee state insurance and employees’ pension scheme (under the provisions of the Employees’ Provident Funds and Miscellaneous Provisions Act, 1952).
B9: The Company has recognised the following amounts in the statement of profit and loss for the year:
H11: 31 March 2025 | I11: 31 March 2024
B12: Contribution to provident and other funds | H12: ='17-25'!$D$117 -> 428.30494 | I12: ='17-25'!$E$117 -> 574.01
B14: b) | C14: Defined benefit plans
B15: (I) | C15: Gratuity (unfunded)
B16: The gratuity plan is governed by the Payment of Gratuity Act, 1972 under which an employee who has completed five years of service is entitled to specific benefits. The level of benefits provided depends on the member’s length of service and salary at retirement age.
B17: There is no compulsion on the part of the Company to pre fund the liability of the plan. The Company’s philosophy is to not externally fund these liabilities but instead create an accounting provisions in its books of accounts and pay the gratuity to its employees directly from its own resources as and when the employee leaves the Company.
B18: The following tables summarize the components of net benefit expense recognised in the statement of profit and loss and the amount recognised in the balance sheet for the defined benefit plan.
H21: Gratuity benefits
H22: =H11 -> 31 March 2025 | I22: =I11 -> 31 March 2024
B23: Change in the present value of the defined benefit obligation:
B24: Opening defined benefit obligation | I24: 727.07733
B25: Interest cost | I25: 50.55283
B26: Current service cost | I26: 140.49522
B27: Past service cost | I27: - | N27: -6147529
B28: Benefits paid | I28: -49.90933 | N28: =-17183 -> -17183
B29: Actuarial losses/(gains) on obligation | I29: -49.89188 | N29: =1175524 -> 1175524
B30: Closing defined benefit obligation | H30: =SUM(F24:H29) -> 0 | I30: =SUM(I24:I29) -> 818.32417 | N30: =SUM(N27:N29) -> -4989188
B32: Amount recognised in the balance sheet
B33: Present value of defined benefit obligation at the end of the period | H33: =H30 -> 0 | I33: =I30 -> 818.32417
B34: Fair value of plan assets at the end of the period | H34: - | I34: -
B35: Net liability for India | H35: =SUM(H33:H34) -> 0 | I35: =SUM(I33:I34) -> 818.32417
B36: Net liability for Middle East | I36: 164
B37: Amount recognised in the balance sheet | H37: =H35+H36 -> 0 | I37: =I35+I36-0.5 -> 981.82417
B39: Classification
B40: Amount recognised in the balance sheet
B41: Non current | H41: ='11-13'!G144 -> 0 | I41: 661.32786
B42: Current | H42: ='11-13'!G150 -> 1012.0736 | I42: 320.76122
B43: Amount recognised as liability | H43: =H41+H42 -> 1012.0736 | I43: =I41+I42 -> 982.08908
B45: Paladion Networks Private Limited
B46: (Amounts are stated in ₹ unless otherwise stated)
B48: Expense recognised in the statement of profit and loss:
B49: Current service cost | H49: =H26 -> 0 | I49: =I26 -> 140.49522
B50: Interest cost | H50: =H25 -> 0 | I50: =I25 -> 50.55283
B51: Past service cost | H51: =H27 -> 0 | I51: =I27 -> -
B52: Amount of expense for India | H52: =SUM(H49:H51) -> 0 | I52: =SUM(I49:I51) -> 191.04805
B53: Middle East cost | I53: 20
B54: Expense recognised in the statement of profit and loss | H54: =H52+H53 -> 0 | I54: =I52+I53 -> 211.04805
B56: Expense recognised in the other comprehensive income:
B57: Opening amount recognized in other comprehensive income | H57: =I59 -> 152.68698 | I57: 202.57886
B58: Actuarial (gain) / loss on defined benefit obligations | H58: =-PL!D37 -> -115.36426 | I58: -49.89188
B59: Net expense recognised in the total comprehensive income | H59: =SUM(H57:H58) -> 37.32272 | I59: =SUM(I57:I58) -> 152.68698
B61: Breakup of actuarial (gain) /loss
B62: Actuarial (gain) /loss on defined benefit obligation
B63: Changes in demographic assumptions | I63: -0.17183 | N63: -6147529
B64: Changes in financial assumptions | I64: 11.75524 | N64: -17183
B65: Changes in experience adjustments | I65: -61.47529 | N65: 1175524
B66: Actuarial (gain)/loss | H66: =SUM(H63:H65) -> 0 | I66: =SUM(I63:I65) -> -49.89188
B67: =B1 -> Paladion Networks Private Limited
B68: =B2 -> Summary of Material accounting policies and other explanatory information
B69: =B3 -> (Amounts are stated in ₹ lakhs, except share and per share data, unless ottherwise stated)
A71: =A5 -> 28 | B71: ="Note "&A5&": Employee benefits (Contd.)" -> Note 28: Employee benefits (Contd.)
B73: Actuarial assumptions used
H74: =H11 -> 31 March 2025 | I74: =I11 -> 31 March 2024
B76: Discount rate (per annum) | I76: 0.069
B77: Salary escalation rate (per annum) | I77: 0.09
B78: Rate of employee turnover
B85: Mortality Rate During Employment | I85: Indian Assured Lives Mortality (2006-08) Urban | K85: 930 | L85: =849 -> 849
B87: Sensitivity analysis
F90: =H22 -> 31 March 2025 | H90: =I22 -> 31 March 2024
F91: Increase by 1% | G91: Decrease by 1% | H91: Increase by 1% | I91: Decrease by 1%
B92: Discount rate
B93: Increase/ (decrease) in the defined benefit liability | H93: -19.39148 | I93: 20.43655
K94: 100000
B95: Salary escalation rate
B96: Increase/ (decrease) in the defined benefit liability | H96: 14.75707 | I96: -14.66753
B98: Employee Turnover rate
B99: Increase/ (decrease) in the defined benefit liability | H99: -2.87533 | I99: 2.91761
B101: The sensitivity analysis is based on a change in one assumption while not changing all other assumptions. This analysis may not be representative of the actual change in the defined benefit obligation as it is unlikely that the change in the assumptions would occur in isolation of one another since some of the assumptions may be co-related.
B102: Maturity Analysis of defined benefit obligations:
I103: =F90 -> 31 March 2025
B104: Defined benefits payable in future years from the date of reporting
B105: 1st following year
B106: 2nd following year
B107: 3rd following year
B108: 4th following year
B109: 5th following year
B110: Sum of years 6 to 10
B112: (II) | C112: Compensated absences
B114: Compensated absences cover the Company's liability for sick and earned leaves. The amount of provision with respect of compensated absences is ₹ ... (31 March 2024: ₹ 382) is presented as current liability as per the provisions note. The Company has recognised charge of ₹... (31 March 2024: ₹ 210) in the statement of profit and loss.
B116: Actuarial assumptions used | H116: Year Ended | I116: Year Ended
H117: 31 March 2025 | I117: 31 March 2024
B119: Discount rate (per annum) | I119: 0.069
B120: Salary escalation rate (per annum) | I120: 0.09
B121: Rate of employee turnover
B128: Mortality Rate During Employment | I128: =I85 -> Indian Assured Lives Mortality (2006-08) Urban

Sheet Leases 29
B1: ='E''ee Benefits 28 '!B1 -> Paladion Networks Private Limited
B2: ='E''ee Benefits 28 '!B2 -> Summary of Material accounting policies and other explanatory information
B3: ='E''ee Benefits 28 '!B3 -> (Amounts are stated in ₹ lakhs, except share and per share data, unless ottherwise stated)
A5: ='E''ee Benefits 28 '!A5+1 -> 29 | B5: ="Note "&A5&": Leases" -> Note 29: Leases
B6: a) Right-of-use assets
B8: The carrying amount of right-of-use asset by class can be analysed as follows:
C9: Leasehold premises
C10: India | D10: USA | E10: Total
B11: Gross block
B12: As at 01 April 2023 | C12: 390.10813 | D12: 0 | E12: 390.10813
B13: Additions | C13: 713.77318 | E13: =SUM(C13:D13) -> 713.77318
B14: Deletions | E14: =SUM(C14:D14) -> 0
B15: As at 31 March 2024 | C15: =SUM(C12:C14) -> 1103.8813 | D15: 0 | E15: =SUM(E12:E14) -> 1103.8813
B16: Additions | D16: 380.58701 | E16: =SUM(C16:D16) -> 380.58701
B17: Deletions | C17: 0 | D17: 0 | E17: =SUM(C17:D17) -> 0
B18: Abatement | D18: -40.17219 | E18: =SUM(C18:D18) -> -40.17219
B19: As at 31 March 2025 | C19: =SUM(C15:C18) -> 1103.8813 | D19: =SUM(D15:D18) -> 340.41482 | E19: =SUM(E15:E18) -> 1444.2961
B21: Accumulated depreciation
B22: =B12 -> As at 01 April 2023 | C22: 110.51395 | D22: 0 | E22: 110.51395
B23: Depreciation charge for the year | C23: 238.67975 | E23: =SUM(C23:D23) -> 238.67975
B24: Deletions | E24: =SUM(C24:D24) -> 0
B25: Exchange Impact(*) | E25: =SUM(C25:D25) -> 0
B26: =+B15 -> As at 31 March 2024 | C26: =SUM(C22:C25) -> 349.1937 | D26: =SUM(D22:D25) -> 0 | E26: =SUM(E22:E25) -> 349.1937
B27: Depreciation charge for the year | C27: 280.87131 | D27: 61.157198 | E27: =SUM(C27:D27) -> 342.02851
B28: Deletions | C28: 0 | D28: 0 | E28: =SUM(C28:D28) -> 0
B29: Exchange Impact | D29: 0.82730163 | E29: =SUM(C29:D29) -> 0.82730163
B30: =B19 -> As at 31 March 2025 | C30: =SUM(C26:C29) -> 630.06501 | D30: =SUM(D26:D29) -> 61.9845 | E30: =SUM(E26:E29) -> 692.04951
B32: Net block
B33: =B30 -> As at 31 March 2025 | C33: =C19-C30 -> 473.8163 | D33: =D19-D30 -> 278.43032 | E33: =E19-E30 -> 752.24662
B34: =+B15 -> As at 31 March 2024 | C34: =C15-C26 -> 754.68761 | D34: =D15-D26 -> 0 | E34: =E15-E26 -> 754.68761
B49: (Space has been left intentionally)
B53: Paladion Networks Private Limited
B54: Summary of significant accounting policies and other explanatory information as at and for the year ended 31 March 2023
B55: (Amounts are stated in ₹ lakhs unless otherwise stated)
A57: 28 | B57: ="Note "&A5&": Leases (Contd.)" -> Note 29: Leases (Contd.)
B60: b) Lease liabilities
C61: Leasehold premises
C62: India | D62: USA | E62: Total
B63: Gross carrying value
B64: As at 01 April 2023 | C64: 278.03888 | D64: - | E64: =SUM(C64:D64) -> 278.03888
B65: Additions | C65: 967.65816 | D65: 0 | E65: =SUM(C65:D65) -> 967.65816
B66: Interest expense | C66: 67.661123 | D66: 0 | E66: =SUM(C66:D66) -> 67.661123
B67: Repayment of lease liability | C67: -240.91049 | D67: 0 | E67: =SUM(C67:D67) -> -240.91049
B68: Payment of interest | C68: -67.661123 | D68: 0 | E68: =SUM(C68:D68) -> -67.661123
B69: As at 31 March 2024 | C69: =SUM(C64:C68) -> 1004.7865 | D69: =SUM(D64:D68) -> 0 | E69: =SUM(E64:E68) -> 1004.7865
B70: Additions | D70: 379.14853 | E70: =SUM(C70:D70) -> 379.14853
B71: Interest expense | C71: 80.123783 | D71: 26.162895 | E71: =SUM(C71:D71) -> 106.28668
B72: Repayment of lease liability | C72: -314.57408 | D72: -11.942315 | E72: =SUM(C72:D72) -> -326.51639
B73: Payment of interest | C73: -80.123783 | D73: -26.162895 | E73: =SUM(C73:D73) -> -106.28668
B74: Abatement | D74: -40.17219 | E74: =SUM(C74:D74) -> -40.17219
B75: As at 31 March 2025 | C75: =SUM(C69:C74) -> 690.21247 | D75: =SUM(D69:D74) -> 327.03402 | E75: =SUM(E69:E74) -> 1017.2465
B77: (*) Represents exchange difference resulting from translation of ROU relating to foreign branches.
D79: As at 31 March 2025 | E79: As at 31 March 2024
B81: Non-Current | D81: =(E75-D82)+1 -> 691.50412 | E81: 690.21247
B82: Current | D82: =325.742373979693+1 -> 326.74237 | E82: 314.57408
D83: =SUM(D81:D82) -> 1018.2465 | E83: =SUM(E81:E82) -> 1004.7865
B85: Undiscounted finance lease liabilities are repayable as follows: | D85: =D79 -> As at 31 March 2025 | E85: =E79 -> As at 31 March 2024
B87: Within 1 year | D87: 407.30901 | E87: 394.69786
B88: Over 1 year | D88: 765.73743 | E88: 775.29846
B89: Less: interest | D89: -155.75936 | E89: -165.20977
D90: =SUM(D87:D89) -> 1017.2871 | E90: =SUM(E87:E89) -> 1004.7865 | G90: =D83-D90 -> 0.9594079
B92: Amount recognised in statement of profit and loss account | D92: =D79 -> As at 31 March 2025 | E92: =E79 -> As at 31 March 2024
B93: Depreciation on right-of-use assets | D93: =E27 -> 342.02851 | E93: 238.67975
B94: Interest on lease liabilities | D94: =E71 -> 106.28668 | E94: 67.661123
B95: Rent expenses | D95: =SUM('17-25'!D181:D182) -> 0.4851628 | E95: 74
D96: =SUM(D93:D95) -> 448.80035 | E96: =SUM(E93:E95) -> 380.34087
B98: c).Net investement details(Intermediate lessor) | D98: =D92 -> As at 31 March 2025 | E98: =E92 -> As at 31 March 2024
B99: As at 01 April 2024 | D99: =E103 -> 375.09718 | E99: 0
B100: Additions | E100: 355.0151
B101: Interest income | D101: ='17-25'!D80 -> 27.46033 | E101: 20.082086
B102: Receipt | D102: 0 | E102: 0
B103: As at 31 March 2025 | D103: =SUM(D98:D102) -> 402.55751 | E103: =SUM(E98:E102) -> 375.09718
B105: Interest rates used for discounting (per annum) | D105: =D98 -> As at 31 March 2025 | E105: =E98 -> As at 31 March 2024
B106: JP Nagar | D106: 0.08 | E106: 0.08
B107: Whitefield | D107: 0.0947 | E107: 0.0947
B108: Mumbai | D108: =0 -> 0 | E108: 0.084
B109: USA | D109: 0.085 | E109: 0

Sheet 30 RPT
B1: ='Leases 29'!B1 -> Paladion Networks Private Limited
B2: ='Leases 29'!B2 -> Summary of Material accounting policies and other explanatory information
B3: ='Leases 29'!B3 -> (Amounts are stated in ₹ lakhs, except share and per share data, unless ottherwise stated)
A5: ='Leases 29'!A5+1 -> 30 | B5: ="Note "&A5&": Related party transactions" -> Note 30: Related party transactions
B6: In accordance with the requirement of Indian Accounting Standard (Ind AS) 24 "Related Party Disclosures", names of the related parties, related party relationships, transactions and outstanding balances including commitments where control exists and with whom transactions have taken place during the reported period are as follows:
B10: (a) | C10: Names of the related parties and the nature of relationship:
C12: Relationship | F12: Name of the Related Party
C13: Ultimate Holding company | F13: Atos SE
C14: Intermediary Holding company | F14: Syntel Private Limited( w.e.f 26 April 2023) | J14: 960115
F15: Atos Global IT Solutions & Services private limited (up to 25 April 2023) | J15: 960924
F16: Paladion Technologies Inc., USA | J16: 960A19
C17: Subsidiary (from 08.10.2020) | F17: Paladion Networks (Thailand) Co. Limited. | J17: 960A27
F18: Paladion Networks LLC, Dubai | J18: 960A23
F19: Paladion Networks LLC, Abu Dhabi | J19: 960A25
F20: Paladion Qatar WLL, Qatar | J20: 960A26
C21: Fellow subsidiary | F21: Atos France SAS | J21: 960022
F22: Atos International S.A.S | J22: 960024
F23: Atos Meda SAS | J23: 960093
F24: Atos Syntel Inc. (US) | J24: 960099
F25: Atos Information Technology GmbH Berlin | J25: 960100
F26: Eviden Nederland B.V. | J26: 960222
F27: Atos Luxembourg PSF S.A. | J27: 960330
F28: Eviden AG (Zurich) | J28: 960360
F29: Eviden USA Inc. | J29: 960B72
F30: Eviden India Private Limited | J30: 960396
F31: Atos Information Technology | J31: 960401
F32: Eviden Belgium NV/SA | J32: 960503
F33: Atos Information Technology HK Limited | J33: 960535
... F72: Eagle Creek Software Services, Inc | J72: 960A49
C73: Step down subsiiary | F73: Paladion Information Technology LLC, Saudi | J73: 960A24
C74: Key Management Personnel (KMP) | F74: Arvind Jugalkishor Bajaj (w.e.f 08 October 2020)
F75: Umar Ali Sheikh (w.e.f 08 October 2020 to 26 June 2023)
F76: Rakesh Khanna (w.e.f 23 June 2023)
C77: Entity over which the KMP exercises significant influence. | F77: Paladion Qatar WLL, Qatar | J77: 960A26
F78: Paladion Information Technology LLC, Saudi | J78: 960A24
F79: Paladion Network LLC, Dubai, UAE | J79: 960A23
F80: Paladion Networks LLC, Abu Dhabi, UAE | J80: 960A25
C81: The above information has been determined to the extent such parties have been identified on the basis of information available with the Company, which has been relied upon by the auditors.
B84: =B1 -> Paladion Networks Private Limited
B85: =B2 -> Summary of Material accounting policies and other explanatory information
B86: =B3 -> (Amounts are stated in ₹ lakhs, except share and per share data, unless ottherwise stated)
A88: =A5 -> 30 | B88: ="Note "&A88&": Related party transactions (Contd.)" -> Note 30: Related party transactions (Contd.)
B90: (b) | C90: Transactions with related parties
C92: Nature of transaction | D92: Name of the related party | F92: Country | G92: Relationship with the related party | H92: For the year ended 31 March 2025 | I92: For the year ended 31 March 2024
C93: Sale of services (Revenue) | D93: Paladion Technologies Inc., USA | F93: USA | G93: Intermediary Holding company | H93: -208.47886 | I93: 1943.0299 | J93: 960A19 | K93: ='17-25'!D8 -> 16905.807 | L93: =K93-SUM(H93:H147) -> -3.2741809e-11
D94: Paladion Network LLC, Dubai, UAE | F94: Dubai | G94: Subsidiary | H94: 1383.497 | I94: 868.0645 | J94: 960A23
D95: Paladion Qatar WLL, Qatar | F95: Qatar | G95: Subsidiary | H95: 497.77173 | I95: 464.31488 | J95: 960A26
D96: Paladion Information Technology LLC, Saudi | F96: Saudi Arabia | G96: Fellow subsidiary | H96: -18.104397 | I96: 387.15891 | J96: 960A24
D97: Atos It Solutions and Services, Inc. | F97: USA | G97: Fellow subsidiary | H97: 994.34002 | I97: 3324.6937 | J97: 960376
D98: Atos France SAS | F98: France | G98: Fellow subsidiary | H98: - | I98: 0.6852649 | J98: 960022
D99: Eviden India Private Limited | F99: India | G99: Fellow subsidiary | H99: 1950.9953 | I99: 2782.4438 | J99: 960396
D100: Syntel Canada Inc. | F100: Canada | G100: Fellow subsidiary | H100: 2.3762052 | I100: =0 -> 0 | J100: 960141
D101: Atos Qatar LLC | F101: Qatar | G101: Fellow subsidiary | H101: 775.89812 | I101: 1265.8907 | J101: 960782
D102: Atos International S.A.S | F102: France | G102: Fellow subsidiary | H102: 1.9216213 | I102: 139.97906 | J102: 960024
D103: Eviden Netherlands B.V | F103: Nederlands | G103: Fellow subsidiary | H103: - | I103: 0.5120582 | J103: 960222
D104: Atos Luxembourg PSF S.A. | F104: Luxembourg | G104: Fellow subsidiary | H104: 0.17394 | I104: 2.9657183 | J104: 960330
D105: Eviden AG (Zurich) | F105: Switzerland | G105: Fellow subsidiary | H105: 11.156291 | I105: 29.82985 | J105: 960360
D106: Atos Information Technology | F106: Singapore | G106: Fellow subsidiary | H106: - | I106: 2.35e-05 | J106: 960401
D107: Eviden Belgium NV/SA | F107: Belgium | G107: Fellow subsidiary | H107: 8.705652 | I107: 4.5092262 | J107: 960503
D108: Atos Information Technology HK Limited | F108: Hongkong | G108: Fellow subsidiary | H108: - | I108: 9.8e-06 | J108: 960535
D109: Atos IT Services UK Limited | F109: United Kingdom | G109: Fellow subsidiary | H109: 11.486715 | I109: 156.04834 | J109: 960584
D110: Atos IT Services SARL | F110: Morocco | G110: Fellow subsidiary | H110: -3.5155097 | I110: =0 -> 0 | J110: 960642
D111: Atos Saudi Riyadh | F111: Saudi Arabia | G111: Fellow subsidiary | H111: 329.52607 | I111: 34.886254 | J111: 960697
D112: Atos Origin FZ LLC | F112: Dubai | G112: Fellow subsidiary | H112: 3.1092628 | I112: 80.917687 | J112: 960698 / 685
D113: Atos (Australia) Pty Ltd | F113: Australia | G113: Fellow subsidiary | H113: 10.188533 | I113: =0 -> 0 | J113: 960710
D114: Eviden Canada, Inc | F114: Canada | G114: Fellow subsidiary | H114: 1.8382196 | I114: 39.516659 | J114: 960723
D115: Atos IT Solutions and Servcies A/S | F115: Denmark | G115: Fellow subsidiary | H115: - | I115: 2.89e-05 | J115: 960728
D116: Atos Information Technology GmbH | F116: Germany | G116: Fellow subsidiary | H116: 22.929396 | I116: 387.39837 | J116: 960735
D117: Atos IT solutions and Services Ltd Dublin | F117: Ireland | G117: Fellow subsidiary | H117: - | I117: -0.06982 | J117: 960741
D118: Atos IT Solutions and Services | F118: Mexico | G118: Fellow subsidiary | H118: 920.92955 | I118: 616.44156 | J118: 960745
D119: BULL SAS | F119: France | G119: Fellow subsidiary | H119: 38.991339 | I119: 184.44798 | J119: 960846
D120: Bull Algérie | F120: Algeria | G120: Fellow subsidiary | H120: - | I120: 0.153327 | J120: 960827
D121: Bull ITD SAO Paulo | F121: Brazil | G121: Fellow subsidiary | H121: =25.9738884865575 -> 25.973888 | I121: 64.26102 | J121: 960833
D122: Atos Global IT Solutions & Services Pvt Ltd | F122: India | G122: Fellow subsidiary | H122: - | I122: -4.28019 | J122: 960924
D123: Eviden IT Services Private Limited | F123: India | G123: Fellow subsidiary | H123: 24.133788 | I123: 23.999871 | J123: 960928
D124: Atos IT Outsourcing Services, LLC | F124: USA | G124: Fellow subsidiary | H124: 7.5709291 | I124: 9.4309927 | J124: 960931
D125: Atos Meda Sas | F125: France | G125: Fellow subsidiary | H125: 188.69458 | I125: 136.27595 | J125: 960093
D126: EVIDEN IT Solutions and Services Limited | F126: Thailand | G126: Fellow subsidiary | H126: - | I126: 0.0712652 | J126: 960760
D127: Atos Syntel Inc. (US) | F127: USA | G127: Fellow subsidiary | H127: 74.506627 | I127: 19.519899 | J127: 960099
D128: Atos Spain SA | F128: Spain | G128: Fellow subsidiary | H128: - | I128: -0.0007596 | J128: 960560
D129: Atos Poland R&D Sp zoo | F129: Poland | G129: Fellow subsidiary | H129: 18.939077 | I129: =0 -> 0 | J129: 960A03
D130: SEC Consult Thailand | F130: Thailand | G130: Fellow subsidiary | H130: 0.420238 | I130: =0 -> 0 | J130: 960A45
D131: SEC Consult Malaysia | F131: Malaysia | G131: Fellow subsidiary | H131: 0.5915172 | I131: =0 -> 0 | J131: 960A47
D132: Motiv IT Masters B.V. | F132: Nederlands | G132: Fellow subsidiary | H132: 32.943472 | I132: 2.0181782 | J132: 960A53
D133: Atos (Pty) Ltd | F133: South Africa | G133: Fellow subsidiary | H133: -1.9658751 | I133: 11.613309 | J133: 960559
D134: Atos Integration S.A.S | F134: Abu Dhabi | G134: Fellow subsidiary | H134: 112.74734 | I134: 14.568509 | J134: 960096
D135: Atos Information Technology GmbH | F135: Germany | G135: Fellow subsidiary | H135: - | I135: -0.01117 | J135: 960100
D136: Syntel Pvt Ltd | F136: India | G136: Intermediary Holding company | H136: 4.16557 | I136: 35.17804 | J136: 960115
D137: Atos Brazil LTDA | F137: Brazil | G137: Fellow subsidiary | H137: =111.3942879 -> 111.39429 | I137: 56.80106 | J137: 960372
D138: Atos IT SAE | F138: Egypt | G138: Fellow subsidiary | H138: =179.616129191598 -> 179.61613 | I138: 49.483107 | J138: 960696
D139: Atos Investessement 22 | F139: France | G139: Fellow subsidiary | H139: 1213.0176 | I139: 612.88115 | J139: 960816
D140: SEC Consult Singapore Pte. Ltd | F140: Singapore | G140: Fellow subsidiary | H140: 25.38523 | I140: 30.260264 | J140: 960A46
D141: Atos Technologies Canada Inc | F141: Canada | G141: Fellow subsidiary | H141: 4.8470493 | I141: 99.477881 | J141: 960B28
D142: Atos AG | F142: Switzerland | G142: Fellow subsidiary | H142: 0.1104084 | I142: 0.7444341 | J142: 960B29
D143: Atos Belgium BV | F143: Belgium | G143: Fellow subsidiary | H143: 22.388693 | I143: 9.108465 | J143: 960B43
D144: Eviden Technology Services Limited | F144: United Kingdom | G144: Fellow subsidiary | H144: 0.1210698 | I144: 0.0693541 | J144: 960B53
D145: Eviden Technologies Mexio | F145: Mexico | G145: Fellow subsidiary | H145: 492.45949 | I145: 523.86185 | J145: 960B61
D146: Eviden USA Inc. | F146: USA | G146: Fellow subsidiary | H146: 1821.152 | I146: 660.24459 | J146: 960B72
D147: Eviden Germany GM | F147: Germany | G147: Fellow subsidiary | H147: 5810.8576 | I147: 3713.6995 | J147: 960B76
C149: Nature of transaction | D149: Name of the related party | F149: Country | G149: Relationship with the related party | H149: For the year ended 31 March 2024 | I149: For the year ended 31 March 2023
...

Sheet 31 FVM
B1: ='Leases 29'!B1 -> Paladion Networks Private Limited
B2: ='Leases 29'!B2 -> Summary of Material accounting policies and other explanatory information
B3: ='Leases 29'!B3 -> (Amounts are stated in ₹ lakhs, except share and per share data, unless ottherwise stated)
A5: ='30 RPT'!A5+1 -> 31 | B5: ="Note "&A5&": Financial instruments : Classifications and Fair value measurements" -> Note 31: Financial instruments : Classifications and Fair value measurements
C7: A | D7: Financial assets and financial liabilities
A8: Property and equipment
C10: a) | D10: Financial assets at fair value through profit and loss | G10: Carrying value | I10: Fair value
G11: As at 31 March 2025 | H11: As at 31 March 2024 | I11: As at 31 March 2025 | J11: As at 31 March 2024
D13: Investments in instruments of subsidiary | G13: ='5-7'!D65 -> 0 | H13: ='5-7'!E65 -> 0 | I13: =G13 -> 0 | J13: =H13 -> 0
D15: Total | G15: =SUM(G13:G14) -> 0 | H15: =SUM(H13:H14) -> 0 | I15: =SUM(I13:I14) -> 0 | J15: =SUM(J13:J14) -> 0
C18: b) | D18: Financial assets and liabilities at amortized cost | G18: Carrying value | I18: Fair value
G19: =G11 -> As at 31 March 2025 | H19: =H11 -> As at 31 March 2024 | I19: =I11 -> As at 31 March 2025 | J19: =J11 -> As at 31 March 2024
D21: Financial assets - non-current
D22: Other financial assets | G22: =BS!E16 -> 443.52744 | H22: 773 | I22: =G22 -> 443.52744 | J22: =H22 -> 773
D23: Financial assets - current
D24: Trade receivable | G24: =BS!E24 -> 9350.3619 | H24: 11738.93 | I24: =G24 -> 9350.3619 | J24: =H24 -> 11738.93
D25: Cash and cash equivalents | G25: =BS!E25 -> 5497.6528 | H25: 3886.7736 | I25: =G25 -> 5497.6528 | J25: =H25 -> 3886.7736
D26: Bank balances other than cash and cash equivalents | G26: =BS!E26 -> 2.402056 | H26: 2247.8618 | I26: =G26 -> 2.402056 | J26: =H26 -> 2247.8618
D27: Other financial assets | G27: =BS!E27 -> 204.39541 | H27: 129 | I27: =G27 -> 204.39541 | J27: =H27 -> 129
D28: Total financial assets | G28: =SUM(G21:G27) -> 15498.34 | H28: =SUM(H21:H27) -> 18775.565 | I28: =SUM(I21:I27) -> 15498.34 | J28: =SUM(J21:J27) -> 18775.565
D30: Financial liabilities - non-current
D31: Lease liabilities | G31: =BS!E46 -> 691.50412 | H31: =BS!F46 -> 690.21247 | I31: =G31 -> 691.50412 | J31: =H31 -> 690.21247
D32: Financial liabilities - current
D33: Lease liabilities | G33: =BS!E52 -> 326.74237 | H33: =BS!F52 -> 314.57408 | I33: =G33 -> 326.74237 | J33: =H33 -> 314.57408
D34: Trade payables | G34: =BS!E54+BS!E55 -> 5145.4797 | H34: =BS!F54+BS!F55 -> 8391.2828 | I34: =G34 -> 5145.4797 | J34: =H34 -> 8391.2828
D35: Other financial liabilties | G35: =BS!E56 -> 4189.1737 | H35: =BS!F56 -> 5272.3365 | I35: =G35 -> 4189.1737 | J35: =H35 -> 5272.3365
D36: Total liabilities | G36: =SUM(G31:G35) -> 10352.9 | H36: =SUM(H31:H35) -> 14668.406 | I36: =SUM(I31:I35) -> 10352.9 | J36: =SUM(J31:J35) -> 14668.406
D38: Notes
C39: 1 | D39: Financial assets include cash and cash equivalents, tax free deposits, trade receivables, unbilled receivables and Financial liabilities includes finance lease liabilities, employee and other advances, trade payables, and eligible current liabilities and non-current liabilities. The fair value of cash and cash equivalents, trade receivables, unbilled receivables, trade payables, other current financial assets and liabilities approximate their carrying amount largely due to the short-term nature of these instruments.
C45: 2 | D45: The fair values of lease liabilities, security deposits, loans and other financial assets and liabilities are considered to be the same as their carrying values, as there is an immaterial change in the lending rates.
C47: c) | D47: Fair value hierarchy for assets and liabilities
D49: Fair value is the price that would be received to sell an asset or paid to transfer a liability in an orderly transaction between market participants at the measurement date under current market conditions.
D51: The Group categorizes assets and liabilities measured at fair value into one of three levels depending on the ability to observe inputs employed in their measurement which are described as follows:
D53: Level 1: Quoted (unadjusted) prices in active markets for identical assets or liablities.
D54: Level 2: Other techniques for which all inputs which have a signifcant effect on the recorded fair values are observable, either directly or indirectly.
D55: Level 3: Techniques which use inputs that have a signifcant effect on the recorded fair value that are not based on observable market data. The following table provides the fair value measurements hierarchy of the Group’s assets and liabilities:
D57: Fair value measurements hierarchy of the Company's assets and liabilities as at 31 March 2025:
D59: Particulars | G59: Quoted prices in active market (Level 1) | H59: Significant observable inputs (Level 2) | I59: Significant unobservable inputs (Level 3) | J59: Total
D60: Financial assets
D61: Investments in instruments of subsidiary | G61: =G13 -> 0 | H61: 0 | I61: 0 | J61: =SUM(G61:I61) -> 0
D63: Total financial assets | G63: =SUM(G60:G61) -> 0 | H63: =SUM(H60:H61) -> 0 | I63: =SUM(I60:I61) -> 0 | J63: =SUM(J60:J61) -> 0
B65: Paladion Networks Private Limited
B66: Summary of significant accounting policies and other explanatory information as at and for the year ended 31 March 2021
B67: (All amounts are stated in ₹ unless otherwise stated)
D69: Fair value measurements hierarchy of the Company's assets and liabilities as at 31 March 2024:
D71: Particulars | G71: Quoted prices in active market (Level 1) | H71: Significant observable inputs (Level 2) | I71: Significant unobservable inputs (Level 3) | J71: Total
D72: Financial assets
D73: Investments in instruments of subsidiary | G73: =H13 -> 0 | H73: 0 | I73: 0 | J73: =SUM(G73:I73) -> 0
D75: Total financial assets | G75: =SUM(G73:G74) -> 0 | H75: =SUM(H73:H74) -> 0 | I75: =SUM(I73:I74) -> 0 | J75: =SUM(J73:J74) -> 0
C77: There have been no transfer between Level 1, Level 2 and Level 3 during the period 31 March 2025 and 31 March 2024.

Sheet 32-33 FRM
B1: ='31 FVM'!B1 -> Paladion Networks Private Limited
B2: ='31 FVM'!B2 -> Summary of Material accounting policies and other explanatory information
B3: ='31 FVM'!B3 -> (Amounts are stated in ₹ lakhs, except share and per share data, unless ottherwise stated)
A5: ='31 FVM'!A5+1 -> 32 | B5: ="Note "&A5&": Financial risk management" -> Note 32: Financial risk management
C6: A wide range of risks may affect the Company's business and financial results. Amongst other risks that could have significant influence on the Company are market risk, credit risk and liquidity risk. The Board of Directors of the Company manage and review the affairs of the Company by setting up short term and long term budgets by monitoring the same and taking suitable actions to minimise potential adverse effects on its operational and financial performance. This transaction has no impact on the financial statements for the year ended 31 March 2025.
B8: (a) | C8: Market risk
C9: Market risk is the risk that the fair value of future cash flows of a financial instrument will fluctuate because of changes in market prices. Market risk comprises of three types of risks: currency risk, interest rate risk and other price risk such as equity price risk and commodity risk.
B11: (i) | C11: Currency risk
C12: The Company is exposed to currency risk on receivables and payables that are denominated in foreign currencies.
C14: The carrying amounts of the Company's foreign currency denominated monetary assets and liabilities at the end of the reporting period are as follows:
C15: Particulars | D15: Foreign currency denomination | E15: As at 31 March 2025 | G15: As at 31 March 2024
E16: Foreign currency | F16: Rupee equivalent | G16: Foreign currency | H16: Rupee equivalent
C17: Trade receivables | D17: USD | G17: 51.197493 | H17: 4266.083
D18: AED | G18: 29.79527 | H18: 676.03382
D19: EUR | G19: 38.796132 | H19: 3489.4385
D20: KWD | G20: 0.05198 | H20: 14.049882
D21: GBP | G21: 0 | H21: 0
D22: CHF | G22: 0.0281656 | H22: 2.6013467
D23: MXN | G23: 0 | H23: 0
D24: QAR | G24: 7.9764211 | H24: 182.19748
D25: DZD (#) | G25: 0.6814453 | H25: 0.41940914
D26: CAD(#) | G26: 0.0006062 | H26: 0.037295061
D27: OMR | G27: 0 | H27: 0
D28: SAR | G28: 0.035776 | H28: 0.7941628
C29: Other receivables | D29: USD | G29: 21.935148 | H29: 1833.2321
D30: EUR | G30: 11.234543 | H30: 1012.3895
D31: GBP | G31: - | H31: 0
D32: QAR | G32: - | H32: 0
D33: AED | G33: 13.282072 | H33: 321.16322
C34: Bank Balances | D34: USD | G34: 17.320411 | H34: 1443.496
D35: EUR | G35: 0.3996762 | H35: 35.948077
D36: AED | G36: 22.390378 | H36: 508.02201
C37: Trade payables | D37: USD | G37: 18.846176 | H37: 1570.5991
D38: AED | G38: 21.635601 | H38: 490.89664
D39: PLN (#) | G39: 0.00085757152 | H39: 0.01793
D40: GBP | G40: 1.3028207 | H40: 137.02983
D41: KWD | G41: 0 | H41: 0
D42: EUR | G42: 39.132104 | H42: 3519.6295
C43: Other Payable | D43: USD | G43: 55.45016 | H43: 4621.2773
D44: AED | G44: 61.484761 | H44: 1395.0462
D45: GBP | G45: 0.8122595 | H45: 85.43292
D46: EUR | G46: 8.7093351 | H46: 783.34373
C49: Trade receivables include balance outstanding in INR amounting to ₹ ...(31 March 2024: ₹ 3107 ); Trade payable include balance outstanding in INR amounting to ₹ ... (31 March 2024 : ₹ 2673 ); Bank Balance include balance outstanding in INR amounting to ₹ ... (31 March 2024 : ₹ 735 ); for which the Company does not carry any currency risk; Other receivables include balance outstanding in INR amounting to ₹.... (31 March 2024 ₹ 327); Other payables include balance outstanding in INR amounting ₹.....(31 March 2024 ₹ 170) | I49: =SUM(F17:F28) -> 0 | J49: 3107 | K49: =SUM(I49:J49) -> 3107 | L49: =BS!E24 -> 9350.3619 | M49: =L49-K49 -> 6243.3619
I50: =SUM(F29:F33) -> 0 | J50: 327 | K50: =SUM(I50:J50) -> 327 | L50: =SUM(BS!E27+BS!E28)+BS!E16 -> 2824.3499 | M50: =L50-K50 -> 2497.3499
C51: (ii) Foreign currency sensitivity | I51: =SUM(F34:F36) -> 0 | J51: 735 | K51: =SUM(I51:J51) -> 735 | L51: ='8-10'!I56 -> 4786.6036 | M51: =L51-K51 -> 4051.6036
C52: Particulars | E52: =E15 -> As at 31 March 2025 | G52: =G15 -> As at 31 March 2024 | I52: =SUM(F43:F46) -> 0 | J52: 170 | K52: =SUM(I52:J52) -> 170 | L52: =BS!E56+BS!E58+BS!E57 -> 6411.5506 | M52: =L52-K52 -> 6241.5506
E53: 5% increase | F53: 5% decrease | G53: 5% increase | H53: 5% decrease
C54: USD | E54: =SUM(F17+F29+F34-F37-F43)*5% -> 0 | F54: =-E54 -> 0 | G54: 52.933787 | H54: -52.933787
C55: EUR | E55: =SUM(F19+F30+F35-F42-F46)*5% -> 0 | F55: =-E55 -> 0 | G55: 73.727852 | H55: -73.727852
C56: AED | E56: =SUM(F18+F33+F36-F38-F44)*5% -> 0 | F56: =-E56 -> 0 | G56: 6.3373585 | H56: -6.3373585
C57: GBP | E57: =SUM(F21+F31-F40-F45)*5% -> 0 | F57: =-E57 -> 0 | G57: - | H57: -
C58: MXN | E58: - | F58: - | G58: 0.041628877 | H58: -0.041628877
C59: QAR | E59: =SUM(F24+F32)*5% -> 0 | F59: =-E59 -> 0 | G59: 8.7536667 | H59: -8.7536667
C60: DZD(#) | E60: =SUM(F25)*5% -> 0 | F60: =-E60 -> 0 | G60: 0.014411248 | H60: -0.014411248
C61: OMR | E61: 0 | F61: =-E61 -> 0 | G61: 0.55345556 | H61: -0.55345556
C62: KWD | E62: =SUM(F20-F41)*5% -> 0 | F62: =-E62 -> 0 | G62: -0.71181721 | H62: 0.71181721
C63: CHF(#) | E63: =SUM(F22)*5% -> 0 | F63: =-E63 -> 0 | G63: - | H63: -
C64: CAD(#) | E64: =SUM(F26)*5% -> 0 | F64: =-E64 -> 0 | G64: - | H64: -
C65: PLN(#) | E65: =-SUM(F39)*5% -> 0 | F65: =-E65 -> 0 | G65: - | H65: -
C66: SAR(#) | E66: =SUM(F28)*5% -> 0 | F66: =-E66 -> 0 | G66: 0.083768946 | H66: -0.083768946
E67: =SUM(E54:E66) -> 0 | F67: =SUM(F54:F66) -> 0 | G67: =SUM(G54:G66) -> 141.73411 | H67: =SUM(H54:H66) -> -141.73411
C68: (#) Zero represents less than ₹0.5 Lakhs
C70: (iii) Interest rate risk
C71: Interest rate risk is the risk that the fair value or future cash flows of a financial instrument will fluctuate because of changes in market interest rates. The Company is not significantly exposed to interest rate risk as the future cash flows are based on fixed rate on bank deposits.
B72: =B1 -> Paladion Networks Private Limited
B73: =B2 -> Summary of Material accounting policies and other explanatory information
B74: =B3 -> (Amounts are stated in ₹ lakhs, except share and per share data, unless ottherwise stated)
A76: =A5 -> 32 | B76: ="Note "&A76&": Financial risk management (Contd.)" -> Note 32: Financial risk management (Contd.)
B78: (b) | C78: Credit risk
C79: Credit risk refers to the risk of default on its obligation by the counterparty resulting in a financial loss. The maximum exposure of the financial assets are contributed by trade receivables, unbilled revenue and cash and cash equivalents.
C80: The Company’s credit risk management policies and procedures is consistent with and leverages the risk management policies and procedures of the Atos Group which includes established framework for ensuring transparency of material credit risks, ensuring compliance with established limits and escalation of risk concentrations to appropriate senior management.
C82: Trade receivables and unbilled revenue
C83: Trade receivables and unbilled revenue are majorly from its group companies, hence reducing credit risk on the receivables. Breakup of trade receivables and unbilled revenue is as follows:
C84: Particulars | G84: =E15 -> As at 31 March 2025 | H84: =G15 -> As at 31 March 2024
C85: Trade receivables
C86: Related party | G86: ='8-10'!I9 -> 5197.8105 | H86: ='8-10'!J9 -> 8621.049
C87: Others | G87: ='8-10'!$I$10 -> 785.99307 | H87: ='8-10'!J10 -> 1239.7168
C88: Unbilled revenue
C89: Related party | G89: ='8-10'!I14 -> 3035.998 | H89: ='8-10'!J14 -> 1532.6633
C90: Others | G90: ='8-10'!I15 -> 330.5603 | H90: ='8-10'!J15 -> 345.5007
C91: Total | G91: =SUM(G86:G90) -> 9350.3619 | H91: =SUM(H86:H90) -> 11738.93
B93: (c) | C93: Liquidity risk
C94: Liquidity risk refers to the risk that the Company will be unable to finance its operations due to difficulty in liquidating its assets. Liquidity risk encompasses the risk that the Company’s financial condition is adversely affected by an inability or perceived inability to meet its financial obligations in a timely manner. It also includes the associated funding risks triggered by the market or idiosyncratic stress events that may cause unexpected changes in funding needs or an inability to realise the trade receivables. The Company consistently generates sufficient cash flows from operations to meet its financial obligations as and when they fall due.
C96: Particulars | D96: On Demand | E96: Less than 1 year | F96: 1 to 5 years | G96: More than 5 years | H96: Total
C97: As on 31 March 2025
C98: Trade payables | D98: 0 | E98: ='14-16'!E26 -> 2941.8862 | F98: =SUM('14-16'!F26:I26) -> 735.20274 | G98: 0 | H98: =SUM(D98:G98) -> 3677.089
C99: Other financial liabilities | D99: 0 | E99: =BS!E52 -> 326.74237 | F99: =BS!E46 -> 691.50412 | G99: 0 | H99: =SUM(D99:G99) -> 1018.2465
D100: =SUM(D98:D99) -> 0 | E100: =SUM(E98:E99) -> 3268.6286 | F100: =SUM(F98:F99) -> 1426.7069 | G100: =SUM(G98:G99) -> 0 | H100: =SUM(H98:H99) -> 4695.3355
C102: As on 31 March 2024
C103: Trade payables | D103: 0 | E103: 3564.8765 | F103: 1541.2564 | G103: 0 | H103: =SUM(D103:G103) -> 5106.1329
C104: Other financial liabilities | D104: 0 | E104: 163.28669 | F104: 114.71793 | G104: 0 | H104: =SUM(D104:G104) -> 278.00462
C105: Total | D105: =SUM(D103:D104) -> 0 | E105: =SUM(E103:E104) -> 3728.1632 | F105: =SUM(F103:F104) -> 1655.9743 | G105: =SUM(G103:G104) -> 0 | H105: =SUM(H103:H104) -> 5384.1375
A109: =A5+1 -> 33 | B109: ="Note "&A109&": Contingent liabilities and capital commitments" -> Note 33: Contingent liabilities and capital commitments
G110: =E15 -> As at 31 March 2025 | H110: =G15 -> As at 31 March 2024
B111: i) | C111: Contingent liabilities
C112: Claims against the Company not acknowledged as debt
C113: - Service tax (disallowance of input credit) | G113: 168.22611 | H113: 168.22611
C114: - Bank guarantees | G114: =2906175/10^5 -> 29.06175 | H114: 29.06175
C116: FEMA Compliance (refer note (b)) | G116: Amount not determinable | H116: Amount not determinable
G117: =SUM(G112:G116) -> 197.28786 | H117: =SUM(H112:H116) -> 197.28786
...

Sheet Note 34-43
B1: ='3-4'!B1 -> Paladion Networks Private Limited
B2: ='3-4'!B2 -> Summary of Material accounting policies and other explanatory information
B3: ='3-4'!B3 -> (Amounts are stated in ₹ lakhs, except share and per share data, unless ottherwise stated)
B5: 1 : Remeasurement of post-employment benefit obligations
B6: Under the previous GAAP, these remeasurement were forming part of the profit or loss for the year. Under Ind AS, remeasurement i.e. actuarial gains and losses, excluding amounts included in the net interest expense on the net defined benefit liability are recognised in other comprehensive income instead of the statement of profit and loss.
B8: 2. Financial instruemnt measured at amortised cost
B9: Under Previous GAAP, financial assets and financial liabilities were typically carried at the contractual amount receivable or payable. Under Ind AS, financial instruments carried at amortised cost are initially recognised at fair value, and subsequently measured at amortised cost, at effective interest rate. For certain financial assets and financial liabilities, the fair value thereof at the date of transition to Ind AS has been considered as the new amortised cost of that financial asset and financial liability at the date of transition to Ind AS.
A10: Property and equipment
B11: 3. Expected credit loss on ECL
B12: Under Ind AS, impairment allowance has been determined based on Expected Credit Loss model (ECL)
B14: 4 : Deferred tax
B15: Under previous GAAP, deferred tax was accounted as per the income statement approach which required creation of deferred tax asset/ liability on timing differences between taxable income and accounting income. Under Ind AS, deferred tax is accounted as per the balance sheet approach which requires creation of deferred tax asset/ liability on temporary differences between the carrying amount of an asset/ liability in the Balance Sheet and its corresponding tax base. The adjustments in equity and net profit, as discussed previously, resulted in additional temporary differences on which deferred taxes are calculated.
B17: 5. There are no material changes in the statement of cash flows upon transition to Ind AS.
A20: ='32-33 FRM'!A109+1 -> 34 | B20: ="Note "&A20&":"&" "&"Events after the reporting period" -> Note 34: Events after the reporting period
B21: The Company has evaluated all subsequent events that occurred after the balance sheet date up to ...., the date on which these financial statements are being issued and there are no significant subsequent events.
A23: =A20+1 -> 35 | B23: ="Note "&A23&":"&" Previous year figures" -> Note 35: Previous year figures
B24: Previous year figures have been regrouped / reclassified, where applicable, to confirm to current year’s classification.
A26: =A23+1 -> 36 | B26: ="Note "&A26&":" -> Note 36:
B27: The Code on Social Security, 2020 (‘Code’) relating to employee benefits during employment and post employment benefits received Presidential assent in September 2020. The Code has been published in the Official Gazette of India. Certain sections of the Code came into effect on 3 May 2023. However, the final rules/interpretation have not yet been issued. Based on a preliminary assessment, the entity believes the impact of the change will not be significant.
A29: =A26+1 -> 37 | B29: ="Note "&A29&":"&" Ratio analysis and its elements" -> Note 37: Ratio analysis and its elements
B30: The ratios for the years ended 31 March 2025 and 31 March 2024 are as follows :
B32: Ratios | D32: Numerator | E32: Denominator | F32: =F104 -> As at 31 March 2025 | G32: =G104 -> As at 31 March 2024 | H32: Change in %
B34: Current ratio (in times) | D34: Currents assets | E34: Current liabilities | F34: ='Ratios Working'!D3/'Ratios Working'!D4 -> 1.4499806 | G34: 1.306637 | H34: =((G34-F34)/G34)*100 -> -10.970421
B35: Debt – Equity ratio (in times) | D35: Total debt (*) | E35: Shareholder’s equity | F35: ='Ratios Working'!D6/'Ratios Working'!D7 -> 0.088333289 | G35: 0.088016463 | H35: =((G35-F35)/G35)*100 -> -0.35996253
B36: Debt service coverage ratio (in times) (1) | D36: Earnings available for debt service=Net profit after taxes+Non cash operating expenses | E36: Debt service=Interest payments and lease payments | F36: ='Ratios Working'!D9/'Ratios Working'!D10 -> -7.5536383 | G36: -13.099517 | H36: =((G36-F36)/G36)*100 -> 42.336512
B37: Return on Equity (ROE) (in times) (2) | D37: Net profit after tax | E37: Average shareholder equity | F37: ='Ratios Working'!D12/'Ratios Working'!D13 -> -0.0003180952 | G37: -0.83076497 | H37: =((G37-F37)/G37)*100 -> 99.961711
B38: Trade receivable turnover ratio (in times)(3) | D38: Revenue | E38: Average trade receivable | F38: ='Ratios Working'!D15/'Ratios Working'!D16 -> 2.2097745 | G38: 2.7073971 | H38: =((G38-F38)/G38)*100 -> 18.380112
B39: Trade payables turnover ratio (in times) (4) | D39: Purchases of services & other expenses | E39: Average trade payable | F39: ='Ratios Working'!D18/'Ratios Working'!D19 -> 1.3096967 | G39: 1.5461409 | H39: =((G39-F39)/G39)*100 -> 15.292538
B40: Net capital turnover ratio (in times)(5) | D40: Revenue | E40: Working capital | F40: ='Ratios Working'!D21/'Ratios Working'!D22 -> 4.3574446 | G40: 5.8098076 | H40: =((G40-F40)/G40)*100 -> 24.998469
B41: Net profit ratio (in times) (6) | D41: Net profit after tax | E41: Revenue | F41: ='Ratios Working'!D24/'Ratios Working'!D25 -> -0.00015591386 | G41: -0.57426516 | H41: =((G41-F41)/G41)*100 -> 99.97285
B42: Return on Capital Employed (ROCE) (in times) (7) | D42: Earnings before interest and taxes | E42: Capital employed | F42: ='Ratios Working'!D27/'Ratios Working'!D28 -> 0.26755917 | G42: 0.31084927 | H42: =((G42-F42)/G42)*100 -> 13.926397
B45: (*) represents lease liabilities
B47: (1) Decrease in ratio is due to decrease in earnings during the year
B48: (2) Decrease in ratio is due to decrease in the accumulated profit on account of transfer of profit for current year.
B49: (3) Decrease in Turnover days is majorly due to early collection from customers
B50: (4) Decrease in Turnover days is majorly due to early payments to vendors
B51: (5) Increase in ratio is due to increase in revenue
B52: (6) Decrease in ratio is due to increase in Cost as compared to increase in revenue during the year
B53: (7) Increase in ratio is due to increase in earnings during the year
B55: Paladion Networks Private Limited
B56: Summary of significant accounting policies and other explanatory information
B57: =B3 -> (Amounts are stated in ₹ lakhs, except share and per share data, unless ottherwise stated)
A59: =A29+1 -> 38 | B59: ="Note "&A59&":"&" Audit Trial" -> Note 38: Audit Trial
B60: The Ministry of Corporate Affairs (MCA) has prescribed a new requirement for companies under the proviso to Rule 3(1) of the Companies (Accounts) Rules, 2014, inserted by the Companies (Accounts) Amendment Rules 2021 requiring companies, which uses accounting software for maintaining its books of account, shall only use such accounting software which has a feature of recording audit trail of each and every transaction, creating an edit log of each change made in the books of account along with the date when such changes were made and ensuring that the audit trail cannot be disabled. The Holding Company and its subsidiary companies have used an accounting software for maintaining their books of account which has a feature of recording audit trail (edit log) facility and the same have been enabled throughout the year at the application level. The software is operated by a third-party software service provider and in the absence of any information on the existence of audit trail feature in the ‘Independent Service Auditor’s Report on a Description of the Service Organization’s System and the Suitability of the Design and Operating Effectiveness of Controls’ (‘Type 2 report’ issued in accordance with ISAE 3402, Assurance Reports on Controls at a Service Organization), we are unable to assess whether the audit trail feature was enabled and operated throughout the year at database the level to log any direct data changes.
B72: =B1 -> Paladion Networks Private Limited
B73: =B2 -> Summary of Material accounting policies and other explanatory information
B74: =B3 -> (Amounts are stated in ₹ lakhs, except share and per share data, unless ottherwise stated)
A76: =A59+1 -> 39 | B76: ="Note "&A76&":"&" Going concern evaluation" -> Note 39: Going concern evaluation
B77: Atos S.E., the Ultimate Holding Company, along with its subsidiaries (collectively referred to as ‘the Group’ or ‘Group entities’), is currently facing liquidity challenges and undergoing financial restructuring. The shareholders of the Ultimate Holding Company have approved the proposed draft accelerated safeguard plan (the “Draft Plan”) by a majority vote. However, under French law, the Ultimate Holding Company must apply to the specialized Commercial Court of Nanterre (the “Court”) for approval of the Draft Plan. The plan will only become enforceable against all parties upon the Court’s approval, allowing the Group to proceed with its financial restructuring in line with its corporate interests. The auditor of the Ultimate Holding Company included a Material Uncertainty Related to Going Concern paragraph in their review report dated 2 August 2024 for the half year ended 30 June 2024, due to uncertainties surrounding the implementation of the proposed financial restructuring plan. This situation may significantly impact the Company’s ability to continue as a going concern due to its high dependency on transactions with other Group entities. However, given the progress of the Draft Plan, the Company’s management is confident of continued operational and financial support from Group Companies for the services provided. Additionally, after the year-end, the Company has already received ₹...... out of the total ₹...... receivables outstanding from the Group entities as of 31 March 2025. Based on these factors, the management believes that it is appropriate to prepare these financial statements on a going concern basis.
A89: =A76+1 -> 40 | B89: ="Note "&A89&":"&" Segment Reporting" -> Note 40: Segment Reporting
B90: The Company has only one reportable business segment which is provision of services relating to networking and development of software products. The information relating to the segment has been presented in the Holding Company's consolidated financial statements in accordance with Ind AS 108 - 'Operating Segments'. No disclosures relating to the segment is therefore presented in these standalone financial statements.
A94: =A89+1 -> 41 | B94: ="Note "&A94&":"&" Capital Management" -> Note 41: Capital Management
B95: The Company’s objectives when managing capital is to safeguard continuity as a going concern and provide adequate return to shareholders through continuing growth and maintain an optimal capital structure to reduce the cost of capital. The Company sets the amount of capital required on the basis of annual business plan and long-term operating plans which include capital investments. The Company monitors capital on basis of total debt to total equity on a periodic basis. The Company does not have any debt or financial covenants as on 31 March 2025. For the purpose of the Group’s capital management, capital includes issued equity capital and all other equity reserves attributable to the equity holders of the parent. The primary objective of the Group’s capital management is to maximise the shareholder value, continue as a going concern and maintain an optimal capital structure to reduce the cost of capital. The Group manages its capital structure and makes adjustments in light of changes in economic conditions and the requirements of the financial covenants. To maintain or adjust the capital structure, the Group may adjust the dividend payment to shareholders, return capital to shareholders or issue new shares. The Group monitors capital using a gearing ratio, which is net debt divided by total capital plus net debt. The Group includes within net debt, interest bearing loans and borrowings, lease liabilities less cash and cash equivalents.
B103: The following table summarises the capital of the Company:
F104: As at 31 March 2025 | G104: As at 31 March 2024
B105: Borrowings | F105: 0 | G105: 0
B106: Less: cash and cash equivalent | F106: =-BS!E25 -> -5497.6528 | G106: =-BS!F25 -> -3886.7736
B107: Net debt | F107: =SUM(F105:F106) -> -5497.6528 | G107: =SUM(G105:G106) -> -3886.7736
B109: Equity share capital | F109: =BS!E37 -> 50.6183 | G109: =BS!F37 -> 50.6183
B110: Other equity
B111: Capital reserve
B112: General reserve
B113: Securities Premium | F113: ='SOCE '!E37 -> 41916.54 | G113: =F113 -> 41916.54
B114: Retained earnings
B115: Total equity | F115: =SUM(F109:F114) -> 41967.158 | G115: =SUM(G109:G114) -> 41967.158
B117: Capital and net debt | F117: =F107+F115 -> 36469.505 | G117: =G107+G115 -> 38080.385
B119: Gearing ratio | F119: =F107/F117 -> -0.15074657 | G119: =G107/G117 -> -0.1020676
B122: =B72 -> Paladion Networks Private Limited
B123: =B73 -> Summary of Material accounting policies and other explanatory information
B124: =B74 -> (Amounts are stated in ₹ lakhs, except share and per share data, unless ottherwise stated)
A126: =A94+1 -> 42 | B126: ="Note "&A126&":"&" Other Information" -> Note 42: Other Information
B127: (i) The Company has not granted any loans or advances in the nature of loan to promoters, directors, key managerial personnels and related parties either severally or jointly with any other person, that are repayable on demand or without specifying any terms or period of repayment.
B129: (ii) During the year ended 31 March 2025 and 31 March 2024, no funds have been advanced or loaned or invested (either from borrowed funds or share premium or any other sources or kind of funds) by the Company to or in any other person or entity, including foreign entities (“intermediaries”) with the understanding, whether recorded in writing or otherwise, that the intermediary shall lend or invest in party identified by or on behalf of the Company (ultimate beneficiaries).
B131: (iii) During the year ended 31 March 2025 and 31 March 2024, the Company has not received any fund from any party (funding party) with the understanding that the Company shall whether, directly or indirectly lend or invest in other persons or entities identified by or on behalf of the Company (“ultimate beneficiaries”) or provide any guarantee, security or the like on behalf of the ultimate beneficiaries.
B133: (iv) There have been no transactions with companies whose name have been struck off by the registrar in accordance with Companies Act, 2013.
B135: (v) The Company did not have any transactions to report against the following disclosure requirements as notified by MCA pursuant to amended Schedule III: a) Benami Property held under Prohibition of Benami Property Transactions Act, 1988 and rules made thereunder. b) Registration of charges or satisfaction with Registrar of Companies. c) The Company has not traded or invested in crypto currency or virtual currency during the year. d) Relating to borrowed funds: - Wilful defaulter - Utilisation of borrowed funds & share premium - Borrowings obtained on the basis of security of current assets - Discrepancy in Utilisation of borrowings
B137: (vi) During the year company has not declared any dividend.
B139: (vii) Information with regards to other matters specified in Schedule III to the Act is either nil or not applicable to the Company for the year.
B141: (viii) During the year, the Company has not surrendered or disclosed any income in the tax assessments under the Income Tax Act, 1961 (such as, search or survey or any other relevant provisions of the Income Tax Act, 1961). Accordingly, there are no transaction which are not recorded in the books of accounts.
B142: (viii) There are no charges or satisfaction of charges which is yet to be registered with ROC beyond the statutory period.
B144: (ix) The company has not entered into any cryptocurrency transactions during the year.
B146: (x) During the year, the Company has incurred a toatal of ₹7,237 as Research and development cost,out of which ₹3219 is expensed as it fails to meet the definition of capitalization.
B150: For Walker Chandiok & Co LLP
... B152: Firm's Registration Number: 001076N/N500013
B156: Shashi Tadwalkar | F156: Arvind Jugalkishor Bajaj | H156: =BS!#REF! -> #REF!
B157: Partner | F157: Director | H157: =BS!#REF! -> #REF!
B158: Membership No. : 101797 | F158: DIN : 08051490 | H158: =BS!#REF! -> #REF!
B161: =Cashflow!B72 -> #REF! | F161: Place: Mumbai | H161: Place: Mumbai
B162: =Cashflow!B73 -> #REF! | F162: Date: | H162: Date:

Sheet Elimination - PL
A2: Paladion Networks Pvt Limited
A3: Statutory Audit for the year ended 31 March 2025
A4: Interco elimination | G4: =SUBTOTAL(9,G7:G45) -> 88820138 | H4: =SUBTOTAL(9,H7:H45) -> 32134692 | I4: =SUBTOTAL(9,I7:I45) -> 70472049 | K4: =SUBTOTAL(9,K7:K45) -> -2285990.7
G5: Local Currency | K5: INR
A6: Entity Code | B6: Entity | C6: ICP | D6: GL Code | E6: PL GL Description | F6: Currency | G6: Debit | H6: Credit | I6: Amount | J6: Exchange Rate | K6: Amount
A7: EA21 | B7: Paladion Networks Private Limited-EA21 | C7: EA22 | D7: 604160 | E7: OP S/C T&M. Interco | F7: INR | H7: 203000.05 | I7: =G7-H7 -> -203000.05 | J7: 1 | K7: =I7*J7 -> -203000.05 | L7: K
A8: EA21 | B8: Paladion Networks Private Limited-EA21 | C8: EA22 | D8: 713400 | E8: Work In Process | F8: INR | H8: 398816.36 | I8: =G8-H8 -> -398816.36 | J8: 1 | K8: =I8*J8 -> -398816.36 | L8: K
A9: EA21 | B9: Paladion Networks Private Limited-EA21 | C9: EA22 | D9: 779000 | E9: Revenue Offshore Netting Billing | F9: INR | G9: =8571333.48 -> 8571333.5 | I9: =G9-H9 -> 8571333.5 | J9: 1 | K9: =I9*J9 -> 8571333.5 | L9: K
A10: EA21 | B10: Paladion Networks Private Limited-EA21 | C10: EA22 | D10: 702311 | E10: Indirect IC Reinvoicing Export | F10: INR | G10: =4022024.48 -> 4022024.5 | I10: =G10-H10 -> 4022024.5 | J10: 1 | K10: =I10*J10 -> 4022024.5 | L10: K
A11: EA21 | B11: Paladion Networks Private Limited-EA21 | C11: EA22 | D11: 706101 | E11: Sale of Services-Export | F11: INR | G11: =39287677.97 -> 39287678 | I11: =G11-H11 -> 39287678 | J11: 1 | K11: =I11*J11 -> 39287678 | L11: K
A12: EA21 | B12: Paladion Networks Private Limited-EA21 | C12: EA22 | D12: 706361 | E12: Sale of Services. Interco Expo | F12: INR | G12: =212005.55 -> 212005.55 | I12: =G12-H12 -> 212005.55 | J12: 1 | K12: =I12*J12 -> 212005.55 | L12: K
A13: EA21 | B13: Paladion Networks Private Limited-EA21 | C13: EA22 | D13: 666000 | E13: EXCHANGE LOSSES | F13: INR | H13: 2307033.5 | J13: 1 | K13: =I13*J13 -> 0 | L13: Realised
A14: EA21 | B14: Paladion Networks Private Limited-EA21 | C14: EA22 | D14: 666400 | E14: Forex fluctuation on Receivables | F14: INR | H14: 14680105 | J14: 1 | K14: =I14*J14 -> 0 | L14: Forex
A15: EA21 | B15: Paladion Networks Private Limited-EA21 | C15: EA22 | D15: 766000 | E15: EXCHANGE GAINS | F15: INR | G15: =3444568.69 -> 3444568.7 | J15: 1 | K15: =I15*J15 -> 0 | L15: Realised
A16: EA21 | B16: Paladion Networks Private Limited-EA21 | C16: EA22 | D16: 766400 | E16: Forex fluctuation on Receivables | F16: INR | H16: 186322.05 | J16: 1 | K16: =I16*J16 -> 0 | L16: Forex
A17: EA21 | B17: Paladion Networks Private Limited-EA21 | C17: EA22 | D17: 603610 | E17: Offshore Netting Billing | F17: INR | H17: 19691.52 | I17: =G17-H17 -> -19691.52 | J17: 1 | K17: =I17*J17 -> -19691.52 | L17: K
A18: EA22 | B18: Paladion Networks Private Limited-EA22 | C18: EA21 | D18: 603610 | E18: Offshore Netting Billing | F18: AED | G18: 0 | H18: 373783.8 | I18: =G18-H18 -> -373783.8 | J18: 22.983572 | K18: =I18*J18 -> -8590886.8 | L18: K
A19: EA22 | B19: Paladion Networks Private Limited-EA22 | C19: EA21 | D19: 604100 | E19: OPERATING SUB-CONTRACTING - FIXED PRICE | F19: AED | G19: 0 | H19: 1717266.1 | I19: =G19-H19 -> -1717266.1 | J19: 22.983572 | K19: =I19*J19 -> -39468908 | L19: K
A20: EA22 | B20: Paladion Networks Private Limited-EA22 | C20: EA21 | D20: 604160 | E20: OP S/C T&M. Interco | F20: AED | G20: 0 | H20: 63631.27 | I20: =G20-H20 -> -63631.27 | J20: 22.983572 | K20: =I20*J20 -> -1462473.9 | L20: K
A21: EA22 | B21: Paladion Networks Private Limited-EA22 | C21: EA21 | D21: 604360 | E21: 604360 OP&PROD S/C. Interco | F21: AED | G21: 17634.73 | H21: 0 | I21: =G21-H21 -> 17634.73 | J21: 22.983572 | K21: =I21*J21 -> 405309.08 | L21: K
A22: EA22 | B22: Paladion Networks Private Limited-EA22 | C22: EA21 | D22: 618100 | E22: ADMINISTRATIVE SUB-CONTRACTING | F22: AED | G22: 0 | H22: 120534 | I22: =G22-H22 -> -120534 | J22: 22.983572 | K22: =I22*J22 -> -2770301.8 | L22: K
A23: EA22 | B23: Paladion Networks Private Limited-EA22 | C23: EA21 | D23: 666000 | E23: EXCHANGE LOSSES | F23: AED | G23: 0 | H23: 161126.7 | J23: 22.983572 | K23: =I23*J23 -> 0 | L23: Realised
A24: EA22 | B24: Paladion Networks Private Limited-EA22 | C24: EA21 | D24: 666400 | E24: Forex fluctuation on Receivables | F24: AED | G24: 10972.22 | H24: 0 | J24: 22.983572 | K24: =I24*J24 -> 0 | L24: Forex
A25: EA22 | B25: Paladion Networks Private Limited-EA22 | C25: EA21 | D25: 706361 | E25: 706361 Sales of Services. Interco EXP | F25: AED | G25: 8867.53 | H25: 0 | I25: =G25-H25 -> 8867.53 | J25: 22.983572 | K25: =I25*J25 -> 203807.51 | L25: K
A26: EA22 | B26: Paladion Networks Private Limited-EA22 | C26: EA21 | D26: 766000 | E26: EXCHANGE GAINS | F26: AED | G26: 29380.17 | H26: 0 | J26: 22.983572 | K26: =I26*J26 -> 0 | L26: Realised
A27: EA22 | B27: Paladion Networks Private Limited-EA22 | C27: EA21 | D27: 766400 | E27: Forex fluctuation on Receivables | F27: AED | G27: 0 | H27: 10257.96 | J27: 22.983572 | K27: =I27*J27 -> 0 | L27: Forex
A28: EA22 | B28: Paladion Networks Private Limited-EA22 | C28: EA21 | D28: 779000 | E28: Revenue Offshore Netting Billing | F28: AED | G28: 846.34 | H28: 0 | I28: =G28-H28 -> 846.34 | J28: 22.983572 | K28: =I28*J28 -> 19451.916 | L28: K | M28: =SUM(K7:K28) -> -192468.75
A29: EA21 | B29: Paladion Networks Private Limited-EA21 | C29: EA20 | D29: 706100 | E29: Sale of Services.LOCAL | F29: INR | G29: 17173651 | H29: 0 | I29: =G29-H29 -> 17173651 | J29: 1 | K29: =I29*J29 -> 17173651 | L29: k
A30: EA21 | B30: Paladion Networks Private Limited-EA21 | C30: EA20 | D30: 706101 | E30: SALES OF SERVICES - EXPORT 3rd party | F30: INR | G30: 0 | H30: 83817.82 | I30: =G30-H30 -> -83817.82 | J30: 1 | K30: =I30*J30 -> -83817.82 | L30: k
A31: EA21 | B31: Paladion Networks Private Limited-EA21 | C31: EA20 | D31: 706360 | E31: Sale of Services.Interco LOC | F31: INR | G31: 0 | H31: 2860.5 | I31: =G31-H31 -> -2860.5 | J31: 1 | K31: =I31*J31 -> -2860.5 | L31: k
A32: EA21 | B32: Paladion Networks Private Limited-EA21 | C32: EA20 | D32: 708811 | E32: Indirect IC Reinvoicing | F32: INR | G32: 6923715.6 | H32: 0 | I32: =G32-H32 -> 6923715.6 | J32: 1 | K32: =I32*J32 -> 6923715.6 | L32: k
A33: EA21 | B33: Paladion Networks Private Limited-EA21 | C33: EA20 | D33: 713400 | E33: Work In Process | F33: INR | G33: 0 | H33: 1308275.1 | I33: =G33-H33 -> -1308275.1 | J33: 1 | K33: =I33*J33 -> -1308275.1 | L33: k
A34: EA21 | B34: Paladion Networks Private Limited-EA21 | C34: EA20 | D34: 779000 | E34: Revenue Offshore Netting Billing | F34: INR | G34: 7472931 | H34: 0 | I34: =G34-H34 -> 7472931 | J34: 1 | K34: =I34*J34 -> 7472931 | L34: k
A35: EA21 | B35: Paladion Networks Private Limited-EA21 | C35: EA20 | D35: 604100 | E35: OPERATING SUB-CONTRACTING - FIXED PRICE | F35: INR | G35: 0 | H35: 3456.96 | I35: =G35-H35 -> -3456.96 | J35: 1 | K35: =I35*J35 -> -3456.96 | L35: k
A36: EA21 | B36: Paladion Networks Private Limited-EA21 | C36: EA20 | D36: 622501 | E36: Other Consultancy | F36: INR | G36: 0 | H36: 8643699.2 | I36: =G36-H36 -> -8643699.2 | J36: 1 | K36: =I36*J36 -> -8643699.2 | L36: k
A37: EA21 | B37: Paladion Networks Private Limited-EA21 | C37: EA20 | D37: 666000 | E37: EXCHANGE LOSSES | F37: INR | G37: 0 | H37: 1331076.4 | J37: 1 | K37: =I37*J37 -> 0 | L37: Realised
A38: EA21 | B38: Paladion Networks Private Limited-EA21 | C38: EA20 | D38: 766000 | E38: EXCHANGE GAINS | F38: INR | G38: 1541151.3 | H38: 0 | J38: 1 | K38: =I38*J38 -> 0 | L38: Realised
A39: EA21 | B39: Paladion Networks Private Limited-EA21 | C39: EA20 | D39: 666400 | E39: Forex fluctuation on Receivables | F39: INR | G39: 0 | H39: 86726.32 | J39: 1 | K39: =I39*J39 -> 0 | L39: Forex
A40: EA21 | B40: Paladion Networks Private Limited-EA21 | C40: EA20 | D40: 766400 | E40: Forex fluctuation on Receivables | F40: INR | G40: 0 | H40: 50027.21 | J40: 1 | K40: =I40*J40 -> 0 | L40: Forex
A41: EA20 | B41: Paladion Networks Private Limited-EA20 | C41: EA21 | D41: 603610 | E41: 603610 Offshore Netting Billing | F41: USD | G41: 0 | H41: =116324.11+9435.78 -> 125759.89 | I41: =G41-H41 -> -125759.89 | J41: 84.421759 | K41: =I41*J41 -> -10616871 | L41: k
A42: EA20 | B42: Paladion Networks Private Limited-EA20 | C42: EA21 | D42: 706101 | E42: SALES OF SERVICES - EXPORT 3rd party | F42: USD | G42: 103378 | H42: 0 | I42: =G42-H42 -> 103378 | J42: 84.421759 | K42: =I42*J42 -> 8727352.6 | L42: k
A43: EA20 | B43: Paladion Networks Private Limited-EA20 | C43: EA21 | D43: 604160 | E43: 604160 OP S/C T&M. Interco | F43: USD | G43: 0 | H43: 80278.08 | I43: =G43-H43 -> -80278.08 | J43: 84.421759 | K43: =I43*J43 -> -6777216.7 | L43: k
A44: EA20 | B44: Paladion Networks Private Limited-EA20 | C44: EA21 | D44: 604300 | E44: 604300 OPERATING AND PRODUCTION SUB-CONTRACTING | F44: USD | G44: 0 | H44: 175637.73 | I44: =G44-H44 -> -175637.73 | J44: 84.421759 | K44: =I44*J44 -> -14827646 | L44: k
A45: EA20 | B45: Paladion Networks Private Limited-EA20 | C45: EA21 | D45: 604150 | E45: 604150 OPERATING SUB-CONTRACTING -TIME AND MATERIALS | F45: USD | G45: 0 | H45: 1508.25 | I45: =G45-H45 -> -1508.25 | J45: 84.421759 | K45: =I45*J45 -> -127329.12 | L45: k | M45: =SUM(K29:K45) -> -2093522 | N45: =M45+M28 -> -2285990.7

Sheet Elimination - BS
A2: Paladion Networks Pvt Limited
A3: Statutory Audit for the year ended 31 March 2025
A4: Branch Elimination | I4: =SUBTOTAL(9,I6:I21) -> 6.7109887e+08
G5: Local Currency | K5: =SUBTOTAL(9,K7:K21) -> 1959301.3
A6: Entity code | B6: Entity | C6: ICP | D6: GL Code | E6: BS GL Description | F6: Currency | G6: Debit | H6: Credit | I6: Net Amt | J6: Forex Rate | K6: Amount (INR)
A7: EA21 | B7: Paladion Networks Private Limited-EA21 | C7: EA22 | D7: 401450 | E7: interco foreign Vendors | F7: INR | G7: 7.2128282e+08 | H7: 0 | I7: =G7-H7 -> 7.2128282e+08 | J7: 1 | K7: =I7*J7 -> 7.2128282e+08 | L7: ok
A8: EA21 | B8: Paladion Networks Private Limited-EA21 | C8: EA22 | D8: 411450 | E8: Foreign Interco customers | F8: INR | G8: 0 | H8: 5769555 | I8: =G8-H8 -> -5769555 | J8: 1 | K8: =I8*J8 -> -5769555 | L8: ok
A9: EA21 | B9: Paladion Networks Private Limited-EA21 | C9: EA22 | D9: 418150 | E9: TRADE DEBTORS - SALES INVOICE ACCRUALS - INTERCO | F9: INR | G9: 0 | H9: 92977.92 | I9: =G9-H9 -> -92977.92 | J9: 1 | K9: =I9*J9 -> -92977.92 | L9: ok
A10: EA21 | B10: Paladion Networks Private Limited-EA21 | C10: EA22 | D10: 401998 | E10: TRADE PAYABLES - FOREIGN CURRENCY REVAL | F10: INR | G10: 85434003 | H10: 85434003 | I10: =G10-H10 -> 0 | J10: 1 | K10: =I10*J10 -> 0 | L10: ok
A11: EA21 | B11: Paladion Networks Private Limited-EA21 | C11: EA22 | D11: 401996 | E11: Trade payables - Foreign Currency revaluation Inte | F11: INR | G11: 14544432 | H11: 0 | I11: =G11-H11 -> 14544432 | J11: 1 | K11: =I11*J11 -> 14544432 | L11: forex
A12: EA21 | B12: Paladion Networks Private Limited-EA21 | C12: EA22 | D12: 411996 | E12: Trade recev. Foreign Curr revaluation Intercompany | F12: INR | G12: 0 | H12: 10276.85 | I12: =G12-H12 -> -10276.85 | J12: 1 | K12: =I12*J12 -> -10276.85 | L12: forex
A13: EA22 | B13: Paladion Networks Private Limited-EA21 | C13: EA21 | D13: 401996 | E13: Trade payables - Foreign Currency revaluation Inte | F13: AED | G13: 3345.29 | H13: 0 | I13: =G13-H13 -> 3345.29 | J13: 23.2939 | K13: =I13*J13 -> 77924.851 | L13: ok
A14: EA22 | B14: Paladion Networks Private Limited-EA22 | C14: EA21 | D14: 401450 | E14: INTERCO FOREIGN VENDORS | F14: AED | G14: 248959.3 | H14: 0 | I14: =G14-H14 -> 248959.3 | J14: 23.2939 | K14: =I14*J14 -> 5799233.1 | L14: ok
A15: EA22 | B15: Paladion Networks Private Limited-EA22 | C15: EA21 | D15: 411450 | E15: Foreign Interco customers | F15: AED | G15: 0 | H15: 31649862 | I15: =G15-H15 -> -31649862 | J15: 23.2939 | K15: =I15*J15 -> -7.3724873e+08 | L15: ok | M15: =SUM(K7:K15) -> -1417128.8
A16: EA21 | B16: Paladion Networks Private Limited-EA21 | C16: EA20 | D16: 411450 | E16: Foreign Interco customers | F16: INR | G16: 0 | H16: 6067618.7 | I16: =G16-H16 -> -6067618.7 | J16: 1 | K16: =I16*J16 -> -6067618.7 | L16: ok
A17: EA21 | B17: Paladion Networks Private Limited-EA21 | C17: EA20 | D17: 467000 | E17: Other Accounts in Debit | F17: INR | G17: 0 | H17: 21035525 | I17: =G17-H17 -> -21035525 | J17: 1 | K17: =I17*J17 -> -21035525 | L17: ok
A18: EA21 | B18: Paladion Networks Private Limited-EA21 | C18: EA20 | D18: 418150 | E18: TRADE DEBTORS - SALES INVOICE ACCRUALS - INTERCO | F18: INR | G18: 0 | H18: 806223.85 | I18: =G18-H18 -> -806223.85 | J18: 1 | K18: =I18*J18 -> -806223.85 | L18: ok
A19: EA21 | B19: Paladion Networks Private Limited-EA21 | C19: EA20 | D19: 411996 | E19: Trade recev. Foreign Curr revaluation Intercompany | F19: INR | G19: 86726.32 | H19: 0 | I19: =G19-H19 -> 86726.32 | J19: 1 | K19: =I19*J19 -> 86726.32 | L19: ok
A20: EA20 | B20: Paladion Networks Private Limited-EA20 | C20: EA21 | D20: 401450 | E20: 401450 TRADE PAYABLES - FOREIGN | F20: USD | G20: 79434.22 | I20: =G20-H20 -> 79434.22 | J20: 85.563771 | K20: =I20*J20 -> 6796691.4 | L20: k
A21: EA20 | B21: Paladion Networks Private Limited-EA20 | C21: EA21 | D21: 455000 | E21: 455000 Intercompany current accounts liabilities - us branch | F21: USD | G21: 285195.24 | I21: =G21-H21 -> 285195.24 | J21: 85.563771 | K21: =I21*J21 -> 24402380 | L21: k | M21: =SUM(K16:K21) -> 3376430.1 | N21: =M21+M15 -> 1959301.3
G25: Exchange difference due to
G26: Intercompany elimination | J26: BS & PL rates diff | K26: Total difference | L26: As per TB | M26: Check
F27: Entity | G27: BS | H27: PL | I27: Net
F28: EA21 | G28: =SUMIF($A$7:$A$21,F28,$K$7:$K$21) -> 7.021318e+08 | H28: =SUMIF('Elimination - PL'!$A$7:$A$45,'Elimination - BS'!F28,'Elimination - PL'!$K$7:$K$45) -> 72999722 | I28: =G28+H28 -> 7.7513153e+08 | J28: 0 | K28: =I28+J28 -> 7.7513153e+08 | L28: ='Standalone TB'!G4 -> 0 | M28: =K28-L28 -> 7.7513153e+08
F29: EA22 | G29: =SUMIF($A$7:$A$21,F29,$K$7:$K$21) -> -7.3137157e+08 | H29: =SUMIF('Elimination - PL'!$A$7:$A$45,'Elimination - BS'!F29,'Elimination - PL'!$K$7:$K$45) -> -51664002 | I29: =G29+H29 -> -7.8303558e+08 | J29: =203016+87710-62335-26992+14409 -> 215808 | K29: =I29+J29 -> -7.8281977e+08 | L29: ='Standalone TB'!N4 -> 0 | M29: =K29-L29 -> -7.8281977e+08
F30: EA20 | G30: =SUMIF($A$7:$A$21,F30,$K$7:$K$21) -> 31199072 | H30: =SUMIF('Elimination - PL'!$A$7:$A$45,'Elimination - BS'!F30,'Elimination - PL'!$K$7:$K$45) -> -23621710 | I30: =G30+H30 -> 7577361.1 | J30: =-96946.993617993+21836-33702 -> -108812.99 | K30: =I30+J30 -> 7468548.1 | L30: ='Standalone TB'!U4 -> -3.480507e+08 | M30: =K30-L30 -> 3.5551925e+08 | O30: -
F31: Total | G31: =SUM(G28:G30) -> 1959301.3 | H31: =SUM(H28:H30) -> -2285990.7 | I31: =SUM(I28:I30) -> -326689.37 | J31: =SUM(J28:J30) -> 106995.01 | K31: =SUM(K28:K30) -> -219694.36 | L31: =SUM(L28:L30) -> -3.480507e+08

Sheet Standalone TB
N1: AED | P1: 23-24 | U1: USD | W1: 23-24
H2: 364337092 | I2: =H2/10^5 -> 3643.3709 | J2: 6.2207017 | K2: =J2*100000 -> 622070.17 | N2: BS | O2: 23.2939 | P2: 22.6893 | Q2: =(Q4+R4)*V3 -> -3.434053e+08 | U2: BS | V2: 85.563771 | W2: 83.3411 | X2: =X4/10^5 -> -3628.3708
H3: =H4/10^5 -> -147.86381 | I3: =I2-H3 -> 3791.2347 | N3: PL | O3: 22.983572 | P3: 22.5386 | U3: PL | V3: 84.421759 | W3: 82.7942
E4: =SUBTOTAL(9,E8:E623) -> -14656106 | F4: =SUBTOTAL(9,F8:F623) -> -130275 | G4: =SUBTOTAL(9,G8:G623) -> 0 | H4: =SUBTOTAL(9,H8:H623) -> -14786381 | I4: =SUBTOTAL(9,I8:I623) -> -14656106 | J4: =SUBTOTAL(9,J8:J623) -> 0 | K4: =SUBTOTAL(9,K8:K623) -> 0 | L4: =SUBTOTAL(9,L8:L623) -> 0 | ... Y4: =SUBTOTAL(9,Y8:Y623) -> -2.7682614e+08
E5: A21 | J5: A22 | Q5: A20
E6: 45747 | F6: OBE | G6: Elimination | H6: 45717 | I6: 45382 | J6: 45717 | K6: OBE | L6: Elimination | M6: 45717 | N6: 45717 | O6: 45352 | P6: 45352 | Q6: 45717 | R6: OBE | S6: Elimination | T6: 45717 | U6: 45717 | V6: 45352 | W6: 45352 | X6: Consol-March 25 | Y6: Consol-March 24
B7: GL Code | C7: Name | D7: NT | E7: INR | F7: INR | G7: INR | H7: INR | I7: INR | J7: AED | K7: AED | L7: AED | M7: AED | N7: INR | O7: AED | P7: INR | Q7: USD | R7: USD | S7: USD | T7: USD | U7: INR | V7: USD | W7: INR | X7: INR | Y7: INR | Z7: Group 1 | AA7: Group 2 | AB7: FS Group
B8: 101300 | C8: CAPITAL SUBSCRIBED - CALLED AND PAID | D8: BS | E8: -5061830 | F8: =SUMIFS(OBE!$H:$H,OBE!$C:$C,'Standalone TB'!$B8,OBE!$B:$B,"A21") -> 0 | G8: =SUMIFS('Elimination - BS'!I:I,'Elimination - BS'!D:D,'Standalone TB'!B8,'Elimination - BS'!A:A,"EA21") -> 0 | H8: =SUM(E8:G8) -> -5061830 | I8: -5061830 | J8: 0 | K8: =SUMIFS(OBE!$H:$H,OBE!$C:$C,'Standalone TB'!$B8,OBE!$B:$B,"A22") -> 0 | L8: =SUMIFS('Elimination - BS'!I:I,'Elimination - BS'!D:D,'Standalone TB'!B8,'Elimination - BS'!A:A,"EA22") -> 0 | M8: =SUM(J8:L8) -> 0 | N8: =M8*$O$2 -> 0 | O8: 0 | P8: 0 | Q8: 0 | R8: =SUMIFS(OBE!$H:$H,OBE!$C:$C,'Standalone TB'!$B8,OBE!$B:$B,"A20") -> 0 | S8: =SUMIFS('Elimination - BS'!I:I,'Elimination - BS'!D:D,'Standalone TB'!B8,'Elimination - BS'!A:A,"EA20") -> 0 | T8: =SUM(Q8:S8) -> 0 | U8: =T8*$V$2 -> 0 | V8: 0 | W8: 0 | X8: =H8+N8+U8 -> -5061830 | Y8: =I8+P8+W8 -> -5061830 | Z8: Shareholders Fund | AA8: Equity | AB8: Share Capital
B9: 106800 | C9: OTHER RESERVES | D9: BS | E9: 0 | F9: =SUMIFS(OBE!$H:$H,OBE!$C:$C,'Standalone TB'!$B9,OBE!$B:$B,"A21") -> 0 | G9: =SUMIFS('Elimination - BS'!I:I,'Elimination - BS'!D:D,'Standalone TB'!B9,'Elimination - BS'!A:A,"EA21") -> 0 | H9: =SUM(E9:G9) -> 0 | I9: 0 | J9: 0 | K9: =SUMIFS(OBE!$H:$H,OBE!$C:$C,'Standalone TB'!$B9,OBE!$B:$B,"A22") -> 0 | L9: =SUMIFS('Elimination - BS'!I:I,'Elimination - BS'!D:D,'Standalone TB'!B9,'Elimination - BS'!A:A,"EA22") -> 0 | M9: =SUM(J9:L9) -> 0 | N9: =M9*$O$2 -> 0 | O9: 0 | P9: 0 | Q9: 0 | R9: =SUMIFS(OBE!$H:$H,OBE!$C:$C,'Standalone TB'!$B9,OBE!$B:$B,"A20") -> 0 | S9: =SUMIFS('Elimination - BS'!I:I,'Elimination - BS'!D:D,'Standalone TB'!B9,'Elimination - BS'!A:A,"EA20") -> 0 | T9: =SUM(Q9:S9) -> 0 | U9: =T9*$V$2 -> 0 | V9: 0 | W9: 0 | X9: =H9+N9+U9 -> 0 | Y9: =I9+P9+W9 -> 0 | Z9: Shareholders Fund | AA9: Equity | AB9: Other equity
