Workbook
Name \0: [1]BS!#REF!
Name \a: #REF!
Name \B: #REF!
Name \b: #REF!
Name \c: #REF!
Name \d: #REF!
Name \E: #REF!
Name \f: #REF!
Name \i: #REF!
Name \m: #REF!
Name \N: #REF!
Name \P: #REF!
Name \P: #REF!
Name \Q: #REF!
Name \q: #REF!
Name \S: #REF!
Name \s: #REF!
Name ____________DAT3: [3]depit!#REF!
Name ___________DAT3: [3]depit!#REF!
Name __________DAT3: [3]depit!#REF!
Name _________DAT3: [3]depit!#REF!
Name ________DAT3: [3]depit!#REF!
Name _______DAT3: [3]depit!#REF!
Name ______8749600_Guj_State_energy: #REF!
Name ______DAT3: [3]depit!#REF!
Name _____8749600_Guj_State_energy: #REF!
Name _____DAT1: #REF!
Name _____DAT10: #REF!
Name _____DAT11: #REF!
Name _____DAT12: #REF!
Name _____DAT13: #REF!
Name _____DAT14: #REF!
Name _____DAT15: #REF!
Name _____DAT16: #REF!
Name _____DAT17: #REF!
Name _____DAT18: #REF!
Name _____DAT19: #REF!
Name _____DAT2: #REF!
Name _____DAT20: #REF!
Name _____DAT21: #REF!
Name _____DAT22: #REF!
Name _____DAT23: #REF!
Name _____DAT3: #REF!
Name _____DAT4: #REF!
Name _____DAT5: #REF!
Name _____DAT6: #REF!
Name _____DAT7: #REF!
Name _____DAT8: #REF!
Name _____DAT9: #REF!
Name ____8749600_Guj_State_energy: #REF!
Name ____DAT1: #REF!
Name ____DAT10: #REF!
Name ____DAT11: #REF!
Name ____DAT12: #REF!
Name ____DAT13: #REF!
Name ____DAT14: #REF!
Name ____DAT15: #REF!
Name ____DAT16: #REF!
Name ____DAT17: #REF!
Name ____DAT18: #REF!

Sheet Master
A2: Name of Entity | B2: Syntel Solutions (India) Private Limited
A3: Current Financial Year | B3: =YEAR(B10)&"-"&YEAR(B4) -> 2024-2025
A4: Current Period End Date | B4: 45747
A5: Formattted Current Period | B5: =IF(DAY(B4)=31,DAY(B4)&"st"&" "&TEXT(B4,"mmmm")&" "&YEAR(B4),DAY(B4)&"th"&" "&TEXT(B4,"mmmm")&" "&YEAR(B4)) -> 31st March 2025
B6: =TEXT(B4,"mmmm")&" "&DAY(B4)&", "&YEAR(B4) -> March 31, 2025
B7: =YEAR(B4) -> 2025
B8: =TEXT(B4+1,"mmmm")&" "&DAY(B4+1)&", "&YEAR(B4) -> April 1, 2025
A9: Previous Financial Year | B9: =YEAR(B16)&"-"&YEAR(B10) -> 2023-2024
A10: Prevous Period End Date | B10: =+B4-366 -> 45381
A11: Formattted Prevous Period | B11: =IF(DAY(B10)=31,DAY(B10)&"st"&" "&TEXT(B10,"mmmm")&" "&YEAR(B10),DAY(B10)&"th"&" "&TEXT(B10,"mmmm")&" "&YEAR(B10)) -> 30th March 2024
B12: =TEXT(B10,"mmmm")&" "&DAY(B10)&", "&YEAR(B10) -> March 30, 2024
B13: =YEAR(B10) -> 2024
B14: =TEXT(B10+1,"mmmm")&" "&DAY(B10+1)&", "&YEAR(B10+1) -> March 31, 2024
A15: Previous Financial Year | B15: =YEAR(B16-365)&"-"&YEAR(B16) -> 2022-2023
A16: Prevous Period End Date | B16: =+B10-365 -> 45016
A17: Formattted Prevous Period | B17: =IF(DAY(B16)=31,DAY(B16)&"st"&" "&TEXT(B16,"mmmm")&" "&YEAR(B16),DAY(B16)&"th"&" "&TEXT(B16,"mmmm")&" "&YEAR(B16)) -> 31st March 2023
B18: =TEXT(B16,"mmmm")&" "&DAY(B16)&", "&YEAR(B16) -> March 31, 2023
B19: =YEAR(B16) -> 2023
B20: =TEXT(B16+1,"mmmm")&" "&DAY(B16+1)&", "&YEAR(B16+1) -> April 1, 2023
A21: Date of Signing | B21: =TODAY() -> 46183
B22: =TEXT(B21,"mmmm")&" "&DAY(B21)&", "&YEAR(B21) -> June 10, 2026
A23: Actual amount converted into | B23: 1
B24: =IF(B23=1,"(Rs.)",IF(B23=100,"(Rs. Hundreds)",IF(B23=1000,"(Rs. Thousands)",IF(B23=100000,"(Rs. Lakhs)",IF(B23=1000000,"(Rs. Millions)",IF(B23=10000000,"(Rs. Crores)")))))) -> (Rs.)
A29: Manual | B29: Manual Input

Sheet Cover page
B6: Syntel Solutions (India) Private Limited
B9: Financial Statements
B10: For the year ended 31 March 2025
A71: Sanjay Banthia
A73: Membership No. 061068

Sheet Index
B4: Syntel Solutions (India) Private Limited
B7: Contents | I7: Page
B9: Independents Auditor's Report | I9: 3 - 10
B11: Balance Sheet | I11: 11
B13: Statement of Profit and Loss | I13: 12
B15: Cash Flow Statements | I15: 13
B17: Statements of Equity | I17: 14
B19: Summary of material accounting policies and other explanatory information | I19: 15 - 41
A70: Sanjay Banthia
A72: Membership No. 061068

Sheet Restatement
A1: =+BS!A1 -> 0
A4: (Amounts are stated in ₹ Lakhs unless otherwise stated)
A6: 1. Restatement of Balancesheet
B8: Balance Sheet as at 31 March 2019
A9: Particular | B9: Audited Balance Sheet | C9: Restatement effect | D9: Restated Balance Sheet
A10: Assets
A11: Non current assets
A12: Property and equipment | B12: =ROUND(0/Master!$B$23,0) -> 0 | D12: =+B12+C12 -> 0
A13: Capital work-in-progress | B13: =ROUND(0/Master!$B$23,0) -> 0 | D13: =+B13+C13 -> 0
A14: Intangible assets | B14: =ROUND(0/Master!$B$23,0) -> 0 | D14: =+B14+C14 -> 0
A15: Investment property | B15: =ROUND(0/Master!$B$23,0) -> 0 | D15: =+B15+C15 -> 0
A16: Financial assets
A17: Investments | B17: =ROUND(0/Master!$B$23,0) -> 0 | D17: =+B17+C17 -> 0
A18: Loans | B18: =ROUND(0/Master!$B$23,0) -> 0 | D18: =+B18+C18 -> 0
A19: Other financial assets | B19: =ROUND(1774555/Master!$B$23,0) -> 1774555 | D19: =+B19+C19 -> 1774555
A20: Deferred tax assets (net) | B20: =ROUND(16141408/Master!$B$23,0) -> 16141408 | C20: =-C100 -> 0 | D20: =+B20+C20 -> 16141408
A21: Other non-current assets | B21: =ROUND(11468027/Master!$B$23,0) -> 11468027 | D21: =+B21+C21 -> 11468027
A22: Income tax assets (net) | B22: =ROUND(41974602/Master!$B$23,0) -> 41974602 | D22: =+B22+C22 -> 41974602
A23: Total non-current assets | B23: =SUM(B12:B22) -> 71358592 | C23: =SUM(C12:C22) -> 0 | D23: =SUM(D12:D22) -> 71358592
A25: Current assets
A26: Financial assets
A27: Investments | B27: =ROUND(58216239/Master!$B$23,0) -> 58216239 | D27: =+B27+C27 -> 58216239
A28: Trade receivables | B28: =ROUND(16242010/Master!$B$23,0) -> 16242010 | D28: =+B28+C28 -> 16242010
A29: Cash and cash equivalents | B29: =ROUND(133191580/Master!$B$23,0) -> 133191580 | D29: =+B29+C29 -> 133191580
A30: Other bank balances | B30: =ROUND(0/Master!$B$23,0) -> 0 | D30: =+B30+C30 -> 0
A31: Loans | B31: =ROUND(0/Master!$B$23,0) -> 0 | D31: =+B31+C31 -> 0
A32: Other financial assets | B32: =ROUND(1523636/Master!$B$23,0) -> 1523636 | D32: =+B32+C32 -> 1523636
A33: Other current assets | B33: =ROUND(311366/Master!$B$23,0) -> 311366 | D33: =+B33+C33 -> 311366
A34: Total current assets | B34: =SUM(B27:B33) -> 209484831 | C34: =SUM(C27:C33) -> 0 | D34: =SUM(D27:D33) -> 209484831
A36: Total assets | B36: =B23+B34 -> 280843423 | C36: =C23+C34 -> 0 | D36: =D23+D34 -> 280843423
A38: Equity and Liabilities
A39: Equity
A40: Equity share capital | B40: =ROUND(100000/Master!$B$23,0) -> 100000 | D40: =+B40+C40 -> 100000
A41: Other equity | B41: =ROUND(81440201/Master!$B$23,0) -> 81440201 | C41: =-C100 -> 0 | D41: =+B41+C41 -> 81440201
A42: Total equity | B42: =SUM(B40:B41) -> 81540201 | C42: =SUM(C40:C41) -> 0 | D42: =SUM(D40:D41) -> 81540201
A44: Liabilities
A45: Non current liabilities
A46: Financial liabilities
A47: Preference shares | B47: =ROUND(187488357/Master!$B$23,0) -> 187488357 | D47: =+B47+C47 -> 187488357
A48: Trade payables | B48: =ROUND(0/Master!$B$23,0) -> 0 | D48: =+B48+C48 -> 0
A49: Other financial liabilities | B49: =ROUND(0/Master!$B$23,0) -> 0 | D49: =+B49+C49 -> 0
A50: Employee benefit obligations | B50: =ROUND(3202278/Master!$B$23,0) -> 3202278 | D50: =+B50+C50 -> 3202278
A51: Deferred tax liabilities (net) | B51: =ROUND(0/Master!$B$23,0) -> 0 | D51: =+B51+C51 -> 0
A52: Other non-current liabilities | B52: =ROUND(285151/Master!$B$23,0) -> 285151 | C52: =+C100*0 -> 0 | D52: =+B52+C52 -> 285151
A53: Total non-current liabilities | B53: =SUM(B47:B52) -> 190975786 | C53: =SUM(C47:C52) -> 0 | D53: =SUM(D47:D52) -> 190975786
A55: Current liabilities
A56: Financial liabilities
A57: Trade payables | B57: =ROUND(5578902/Master!$B$23,0)+1 -> 5578903 | D57: =+B57+C57 -> 5578903
A58: Preference shares | B58: =ROUND(0/Master!$B$23,0) -> 0 | D58: =+B58+C58 -> 0
A59: Other financial liabilities | B59: =ROUND(543852/Master!$B$23,0) -> 543852 | D59: =+B59+C59 -> 543852
A60: Other current liabilities | B60: =ROUND(617247/Master!$B$23,0)-1 -> 617246 | D60: =+B60+C60 -> 617246
A61: Provisions | B61: =ROUND(0/Master!$B$23,0) -> 0 | D61: =+B61+C61 -> 0
A62: Employee benefit obligations | B62: =ROUND(1586819/Master!$B$23,0) -> 1586819 | D62: =+B62+C62 -> 1586819
A63: Income tax liabilities (net) | B63: =ROUND(618/Master!$B$23,0) -> 618 | D63: =+B63+C63 -> 618
A64: Total current liabilities | B64: =SUM(B57:B63) -> 8327438 | C64: =SUM(C57:C63) -> 0 | D64: =SUM(D57:D63) -> 8327438
A66: Total equity and liabilities | B66: =B42+B53+B64 -> 280843425 | C66: =C42+C53+C64 -> 0 | D66: =D42+D53+D64 -> 280843425
A71: 1. Restatement of Statement of profit and loss
A73: Particular
A75: Revenue from operations
A76: - Rental income | B76: =ROUND(0/Master!$B$23,0) -> 0 | D76: =+B76+C76 -> 0
A77: - Software services | B77: =ROUND(17881802/Master!$B$23,0) -> 17881802 | D77: =+B77+C77 -> 17881802
A78: Other income | B78: =ROUND(13982830/Master!$B$23,0)+1 -> 13982831 | D78: =+B78+C78 -> 13982831
A79: Total income | B79: =SUM(B75:B78) -> 31864633 | C79: =SUM(C75:C78) -> 0 | D79: =SUM(D75:D78) -> 31864633
A81: Expenses
A82: Employee benefits | B82: =ROUND(9100894/Master!$B$23,0) -> 9100894 | D82: =+B82+C82 -> 9100894
A83: Depreciation and amortization | B83: =ROUND(2960/Master!$B$23,0) -> 2960 | D83: =+B83+C83 -> 2960
A84: Others | B84: =ROUND(10553508/Master!$B$23,0)-1 -> 10553507 | D84: =+B84+C84 -> 10553507
A85: Technical consultancy charges | B85: =ROUND(0/Master!$B$23,0) -> 0 | D85: =+B85+C85 -> 0
A86: Finance | B86: =ROUND(10269953/Master!$B$23,0) -> 10269953 | D86: =+B86+C86 -> 10269953
A87: Others | B87: =ROUND(0/Master!$B$23,0) -> 0 | D87: =+B87+C87 -> 0
A88: Total expenses | B88: =SUM(B82:B87) -> 29927314 | C88: =SUM(C82:C87) -> 0 | D88: =SUM(D82:D87) -> 29927314
A90: Profit before tax | B90: =+B79-B88 -> 1937319 | C90: =+C79-C88 -> 0 | D90: =+D79-D88 -> 1937319
A92: Extra Ordinary item
A93: Profit before tax | B93: =B90-SUM(B91:B92) -> 1937319 | C93: =C90-SUM(C91:C92) -> 0 | D93: =D90-SUM(D91:D92) -> 1937319
A95: Tax expenses
A96: Current tax | B96: =ROUND(0/Master!$B$23,0) -> 0 | D96: =+B96+C96 -> 0
A97: Minimum Alternate Tax credit entitlement | B97: =ROUND(0/Master!$B$23,0) -> 0 | D97: =+B97+C97 -> 0
A98: MAT credit entitlement written off | B98: =ROUND(0/Master!$B$23,0) -> 0 | D98: =+B98+C98 -> 0
A99: Deferred tax [(including MAT charge of ₹ 39)] | B99: =ROUND(3493007/Master!$B$23,0) -> 3493007 | D99: =+B99+C99 -> 3493007
A100: Buy back tax | B100: =ROUND(0/Master!$B$23,0) -> 0 | C100: =ROUND(+'PL Gr'!G453/Master!$B$23,0) -> 0 | D100: =+B100+C100 -> 0
A101: Total tax expenses | B101: =SUM(B96:B100) -> 3493007 | C101: =SUM(C96:C100) -> 0 | D101: =SUM(D96:D100) -> 3493007
A103: Loss after tax (A) | B103: =+B93-B101 -> -1555688 | C103: =+C93-C101 -> 0 | D103: =+D93-D101 -> -1555688
A105: Other comprehensive income
A106: Items that will not be reclassified subsequently to profit or loss | D106: =+B106+C106 -> 0
A107: Remeasurement of the actuarial gain/loss on defined benefit obligation | B107: =ROUND(-170898/Master!$B$23,0) -> -170898 | D107: =+B107+C107 -> -170898
A108: Tax impact on above items | B108: =ROUND(44433/Master!$B$23,0) -> 44433 | D108: =+B108+C108 -> 44433
A109: Items that will be reclassified subsequently to profit or loss | B109: =ROUND(0/Master!$B$23,0) -> 0 | D109: =+B109+C109 -> 0
A111: Other comprehensive income for the year(B) | B111: =SUM(B107:B109) -> -126465 | C111: =SUM(C107:C109) -> 0 | D111: =SUM(D107:D109) -> -126465
A113: Total Other comprehensive loss for the year (A+B) | B113: =B103+B111 -> -1682153 | C113: =C103+C111 -> 0 | D113: =D103+D111 -> -1682153

Sheet BS
A3: Balance Sheet as at 31 March 2025
A4: (Amounts are stated in ₹ Lakhs unless otherwise stated)
G6: As at | I6: As at
A7: Particular | C7: Notes | G7: 45747 | I7: 45382
A9: Assets
A10: Non current assets | Y10: 24.08.2021 version | Z10: Difference
A11: Property and equipment | C11: ='3-4'!A7 -> 3 | E11: =ROUND(G11/10^5,0) -> 0 | G11: ='Sch - BS'!G9 -> -1 | I11: ='Sch - BS'!I9 -> -1 | J11: =+G11-I11 -> 0 | L11: =+J11+K11 -> 0 | Q11: =ROUND(G11,0) -> -1 | W11: =+G11-I11 -> 0 | X11: =+G11-W11 -> -1 | Y11: 0 | Z11: =+G11-Y11 -> -1
A12: Capital work-in-progress | C12: ='3-4'!A7 -> 3 | E12: =ROUND(G12/10^5,0) -> 0 | G12: ='Sch - BS'!G11 -> 0 | I12: ='Sch - BS'!I11 -> 0 | J12: =+G12-I12 -> 0 | L12: =+J12-K12 -> 0 | Q12: =ROUND(G12,0) -> 0 | W12: 0 | X12: =+G12-W12 -> 0 | Y12: 0 | Z12: =+G12-Y12 -> 0
A13: Intangible assets | C13: ='3-4'!A7 -> 3 | E13: =ROUND(G13/10^5,0) -> 0 | G13: ='Sch - BS'!G10 -> 0 | I13: ='Sch - BS'!I10 -> 0 | J13: =+G13-I13 -> 0 | L13: =+J13-K13 -> 0 | Q13: =ROUND(G13,0) -> 0 | W13: 0 | X13: =+G13-W13 -> 0 | Y13: 0 | Z13: =+G13-Y13 -> 0
A14: Right-of-use asset | C14: =+'3-4'!A47 -> 3A | E14: =ROUND(G14/10^5,0) -> 32 | G14: ='3-4'!J69 -> 3218600.4 | I14: ='3-4'!J70 -> 6258296 | J14: =+G14-I14 -> -3039695.6 | K14: =+CF!F13 -> 3206674 | L14: =+J14+K14 -> 166978.4 | Q14: =ROUND(G14,0) -> 3218600 | S14: 3218601 | T14: =G14-S14 -> -0.6 | W14: =+G14-I14 -> -3039695.6 | X14: =+G14-W14 -> 6258296 | Y14: 158 | Z14: =+G14-Y14 -> 3218442.4 | AA14: =+G14+PL!F17-827641 -> 5597633.4
A15: Financial assets | E15: =ROUND(G15/10^5,0) -> 0 | L15: =+J15+K15 -> 0 | Q15: =ROUND(G15,0) -> 0 | X15: =+G15-W15 -> 0 | Z15: =+G15-Y15 -> 0 | AA15: =+W48+W60 -> -3415049
A16: Investments | E16: =ROUND(G16/10^5,0) -> 0 | G16: ='Sch - BS'!G31 -> 0 | I16: ='Sch - BS'!I31 -> 0 | L16: =+J16-K16 -> 0 | Q16: =ROUND(G16,0) -> 0 | W16: 0 | X16: =+G16-W16 -> 0 | Y16: 0 | Z16: =+G16-Y16 -> 0
A17: Loans | E17: =ROUND(G17/10^5,0) -> 0 | G17: ='Sch - BS'!G35 -> 0 | I17: ='Sch - BS'!I35 -> 0 | L17: =+J17-K17 -> 0 | Q17: =ROUND(G17,0) -> 0 | W17: 0 | X17: =+G17-W17 -> 0 | Y17: 0 | Z17: =+G17-Y17 -> 0
A18: Other financial assets | C18: ='3-4'!A74 -> 4 | E18: =ROUND(G18/10^5,0) -> 0 | G18: ='Sch - BS'!G47 -> 0 | I18: ='Sch - BS'!I47 -> 2602786 | J18: =+G18-I18 -> -2602786 | L18: =+J18+K18 -> -2602786 | Q18: =ROUND(G18,0) -> 0 | W18: =+G18-I18 -> -2602786 | X18: =+G18-W18 -> 2602786 | Y18: 0 | Z18: =+G18-Y18 -> 0 | AA18: =+AA14-AA15 -> 9012682.4
A19: Deferred tax assets (net) | C19: =+'5-9'!A7*0+'10-17'!A232 -> 14 | E19: =ROUND(G19/10^5,0) -> 33 | G19: =-'Sch - BS'!G53 -> 3328863 | I19: =-'Sch - BS'!I53 -> 6767874 | L19: =+J19-K19 -> 0 | Q19: =ROUND(G19,0) -> 3328863 | W19: 0 | X19: =+G19-W19 -> 3328863 | Y19: 0 | Z19: =+G19-Y19 -> 3328863
A20: Other non-current assets | C20: ='5-9'!A40 -> 5 | E20: =ROUND(G20/10^5,0) -> 113 | G20: ='Sch - BS'!G76 -> 11303080 | I20: ='Sch - BS'!I76 -> 11303080 | J20: =+G20-I20 -> 0 | L20: =+J20+K20 -> 0 | Q20: =ROUND(G20,0) -> 11303080 | W20: =+G20-I20 -> 0 | X20: =+G20-W20 -> 11303080 | Y20: 113 | Z20: =+G20-Y20 -> 11302967
A21: Income tax assets (net) | C21: =+'18-26'!A189 -> 25 | E21: =ROUND(G21/10^5,0) -> -8 | G21: ='Sch - BS'!G82 -> -839640 | I21: ='Sch - BS'!I82 -> 40668266 | J21: =+G21-I21 -> -41507906 | K21: =+CF!F45 -> -1105803 | L21: =+J21+K21 -> -42613709 | O21: 42020656 | P21: =O21-I21 -> 1352390 | Q21: =ROUND(G21,0) -> -839640 | W21: =+G21-I21 -> -41507906 | X21: =+G21-W21 -> 40668266 | Y21: 418 | Z21: =+G21-Y21 -> -840058
A22: Total non-current assets | E22: =SUM(E11:E21) -> 170 | G22: =SUM(G11:G21) -> 17010902 | I22: =SUM(I11:I21) -> 67600301 | Q22: =SUM(Q11:Q21) -> 17010902 | W22: =+G22-I22 -> -50589399 | X22: =+G22-W22 -> 67600301 | Y22: 689 | Z22: =+G22-Y22 -> 17010213
X23: =+G23-W23 -> 0 | Z23: =+G23-Y23 -> 0
A24: Current assets | X24: =+G24-W24 -> 0 | Z24: =+G24-Y24 -> 0
A25: Financial assets | X25: =+G25-W25 -> 0 | Z25: =+G25-Y25 -> 0
A26: Investments | C26: ='5-9'!A62 -> 6 | E26: =G26/10^5 -> -0.0001 | G26: ='Sch - BS'!G96 -> -10 | I26: ='Sch - BS'!I96 -> -10 | Q26: 0 | W26: 0 | X26: =+G26-W26 -> -10 | Y26: 0 | Z26: =+G26-Y26 -> -10
A27: Trade receivables | C27: ='5-9'!A84 -> 6 | E27: =ROUND(G27/10^5,0) -> 86 | G27: ='Sch - BS'!G114+0.12 -> 8607499.1 | I27: ='Sch - BS'!I114 -> 2012487 | J27: =+G27-I27 -> 6595012.1 | K27: =CF!F36 -> -6693443.1 | L27: =+J27+K27 -> -98431 | M27: 75 | N27: =I27-M27 -> 2012412 | Q27: =ROUND(G27,0) -> 8607499 | T27: =G27-I27 -> 6595012.1 | W27: =+G27-I27 -> 6595012.1 | X27: =+G27-W27 -> 2012487 | Y27: 25 | Z27: =+G27-Y27 -> 8607474.1
A28: Cash and cash equivalents | C28: =+'5-9'!A127 -> 7 | E28: =ROUND(G28/10^5,0) -> 2437 | G28: ='Sch - BS'!G122 -> 243659518 | I28: ='Sch - BS'!I122 -> 243805184 | J28: =+G28-I28 -> -145666 | L28: =+J28+K28 -> -145666 | M28: 2218 | N28: =I28-M28 -> 243802966 | Q28: =ROUND(G28,0) -> 243659518 | W28: =+G28-I28 -> -145666 | X28: =+G28-W28 -> 243805184 | Y28: 2193 | Z28: =+G28-Y28 -> 243657325
A29: Bank balances | E29: =ROUND(G29/10^5,0) -> 0 | G29: ='Sch - BS'!G128*0 -> 0 | I29: ='Sch - BS'!I128*0 -> 0 | J29: =+G29-I29 -> 0 | L29: =+J29-K29 -> 0 | Q29: =ROUND(G29,0) -> 0 | W29: =+G29-I29 -> 0 | X29: =+G29-W29 -> 0 | Y29: 0 | Z29: =+G29-Y29 -> 0
A30: Loans | E30: =ROUND(G30/10^5,0) -> 0 | G30: ='Sch - BS'!G132 -> 0 | I30: ='Sch - BS'!I132 -> 0 | J30: =+G30-I30 -> 0 | L30: =+J30-K30 -> 0 | Q30: =ROUND(G30,0) -> 0 | W30: =+G30-I30 -> 0 | X30: =+G30-W30 -> 0 | Y30: 0 | Z30: =+G30-Y30 -> 0
A31: Other financial assets | C31: ='5-9'!A162 -> 8 | E31: =ROUND(G31/10^5,0) -> 55 | G31: ='Sch - BS'!G148 -> 5526491 | I31: ='Sch - BS'!I148 -> 2678928 | J31: =+G31-I31 -> 2847563 | K31: =+CF!F37 -> 182600 | L31: =+J31+K31 -> 3030163 | M31: 20 | N31: =I31-M31 -> 2678908 | Q31: =ROUND(G31,0) -> 5526491 | W31: =+G31-I31 -> 2847563 | X31: =+G31-W31 -> 2678928 | Y31: 32 | Z31: =+G31-Y31 -> 5526459
A32: Other current assets | C32: =+'5-9'!A196 -> 9 | E32: =ROUND(G32/10^5,0) -> 5 | G32: ='Sch - BS'!G169 -> 506907 | I32: ='Sch - BS'!I169 -> 345410 | J32: =+G32-I32 -> 161497 | K32: =+CF!F38 -> -161497 | L32: =+J32+K32 -> 0 | M32: 1 | N32: =I32-M32 -> 345409 | Q32: =ROUND(G32,0) -> 506907 | W32: =+G32-I32 -> 161497 | X32: =+G32-W32 -> 345410 | Y32: 1 | Z32: =+G32-Y32 -> 506906
A33: Income tax assets (net) | C33: =+'18-26'!A189 -> 25 | E33: =G33/10^5 -> 0 | G33: =ROUND('BS Gr'!H522/Master!$B$23,0) -> 0 | I33: =ROUND('BS Gr'!L522/Master!$B$23,0) -> 0 | Q33: =ROUND(G33,0) -> 0 | W33: =+G33-I33 -> 0 | X33: =+G33-W33 -> 0 | Y33: 0 | Z33: =+G33-Y33 -> 0
A34: Total current assets | E34: =SUM(E26:E33) -> 2582.9999 | G34: =SUM(G26:G33) -> 2.5830041e+08 | I34: =SUM(I26:I33) -> 248841999 | Q34: =SUM(Q26:Q33) -> 258300415 | W34: =+G34-I34 -> 9458406.1 | X34: =+G34-W34 -> 248841999 | Y34: 2251 | Z34: =+G34-Y34 -> 2.5829815e+08
X35: =+G35-W35 -> 0 | Z35: =+G35-Y35 -> 0
A36: Total assets | E36: =E22+E34 -> 2752.9999 | G36: =G22+G34 -> 2.7531131e+08 | I36: =I22+I34 -> 316442300 | Q36: =Q22+Q34 -> 275311317 | W36: =+G36-I36 -> -41130992 | X36: =+G36-W36 -> 316442300 | Y36: 2940 | Z36: =+G36-Y36 -> 2.7530837e+08
J37: =G31-G20 -> -5776589 | X37: =+G37-W37 -> 0 | Z37: =+G37-Y37 -> 0
A38: Equity and Liabilities | X38: =+G38-W38 -> 0 | Z38: =+G38-Y38 -> 0
A39: Equity | X39: =+G39-W39 -> 0 | Z39: =+G39-Y39 -> 0
A40: Share capital | C40: ='10-17'!A8 -> 10 | E40: =ROUND(G40/10^5,0) -> 1 | G40: ='Sch - BS'!G181 -> 100000 | I40: ='Sch - BS'!I181 -> 100000 | J40: =+G40-I40 -> 0 | L40: =+J40-K40 -> 0 | Q40: =ROUND(G40,0) -> 100000 | W40: =+G40-I40 -> 0 | X40: =+G40-W40 -> 100000 | Y40: 1 | Z40: =+G40-Y40 -> 99999
A41: Other equity | E41: =ROUND(G41/10^5,0) -> 170 | G41: ='Sch - BS'!G226 -> 17022765 | I41: ='Sch - BS'!I226-75824 -> 66078334 | J41: =+G41-I41 -> -49055569 | L41: =+J41-K41 -> -49055569 | Q41: =ROUND(G41,0) -> 17022765 | W41: =+G41-I41 -> -49055569 | X41: =+G41-W41 -> 66078334 | Y41: 482 | Z41: =+G41-Y41 -> 17022283
A42: Total equity | E42: =SUM(E40:E41) -> 171 | G42: =SUM(G40:G41) -> 17122765 | I42: =SUM(I40:I41) -> 66178334 | Q42: =SUM(Q40:Q41) -> 17122765 | W42: =+G42-I42 -> -49055569 | X42: =+G42-W42 -> 66178334 | Y42: 483 | Z42: =+G42-Y42 -> 17122282
W43: =+PL!F48 -> -49055769 | X43: =+G43-W43 -> 49055769 | Z43: =+G43-Y43 -> 0
A44: Liabilities | W44: =+W42-W43 -> 200 | X44: =+G44-W44 -> -200 | Z44: =+G44-Y44 -> 0
A45: Non current liabilities | X45: =+G45-W45 -> 0 | Z45: =+G45-Y45 -> 0
A46: Financial liabilities | Q46: 0 | X46: =+G46-W46 -> 0 | Z46: =+G46-Y46 -> 0
A47: Preference shares | C47: =+'10-17'!A76 -> 11 | E47: =ROUND(G47/10^5,0) -> 0 | G47: ='BS Gr'!I891 -> 0 | I47: ='10-17'!K112 -> 2.3532516e+08 | J47: =+G47-I47 -> -2.3532516e+08 | K47: =+CF!F27 -> 11355848 | L47: =+J47-K47 -> -2.4668101e+08 | Q47: =ROUND(G47,0) -> 0 | W47: =+G47-I47 -> -2.3532516e+08 | X47: =+G47-W47 -> 2.3532516e+08 | Y47: 2132 | Z47: =+G47-Y47 -> -2132
A48: Lease liabilities | C48: ='10-17'!A153 -> 12 | E48: =ROUND(G48/10^5,0) -> 0 | G48: ='Sch - BS'!G241 -> 0 | I48: ='Sch - BS'!I241 -> 3875173 | J48: =+G48-I48 -> -3875173 | L48: =+J48-K48 -> -3875173 | Q48: =ROUND(G48,0) -> 0 | W48: =+G48-I48 -> -3875173 | X48: =+G48-W48 -> 3875173 | Y48: 129 | Z48: =+G48-Y48 -> -129 | AB48: =+G48+G60 -> 3875013
A49: Employee benefit obligations | C49: ='10-17'!A210 -> 13 | E49: =ROUND(G49/10^5,0) -> 12 | G49: ='Sch - BS'!G249 -> 1222499 | I49: ='Sch - BS'!I249 -> 1484197 | J49: =+G49-I49 -> -261698 | L49: =+J49-K49 -> -261698 | Q49: =ROUND(G49,0) -> 1222499 | W49: =+G49-I49 -> -261698 | X49: =+G49-W49 -> 1484197 | Y49: 28 | Z49: =+G49-Y49 -> 1222471 | AB49: =+G14 -> 3218600.4
A50: Deferred tax liabilites (net) | C50: ='10-17'!A232 -> 14 | E50: =ROUND(G50/10^5,0) -> 0 | G50: =ROUND('BS Gr'!M871/Master!$B$23,0)*0+'Sch - BS'!G53*0 -> 0 | I50: =(ROUND('BS Gr'!R871/Master!$B$23,0)*0+'Sch - BS'!I53)*0 -> 0 | J50: =+G50-I50 -> 0 | L50: =+J50-K50 -> 0 | Q50: =ROUND(G50,0) -> 0 | W50: =+G50-I50 -> 0 | X50: =+G50-W50 -> 0 | Y50: 83 | Z50: =+G50-Y50 -> -83 | AB50: =+AB49-AB48 -> -656412.6
A51: Other non-current liabilities | C51: ='10-17'!A260 -> 15 | E51: =G51/10^5 -> 0 | G51: ='Sch - BS'!G262 -> 0 | I51: ='Sch - BS'!I262 -> 0 | J51: =+G51-I51 -> 0 | Q51: 0 | W51: =+G51-I51 -> 0 | X51: =+G51-W51 -> 0 | Y51: 0 | Z51: =+G51-Y51 -> 0
A52: Total non-current liabilities | E52: =SUM(E47:E51) -> 12 | G52: =SUM(G47:G51) -> 1222499 | I52: =SUM(I47:I51) -> 2.4068453e+08 | Q52: =SUM(Q47:Q51) -> 1222499 | W52: =+G52-I52 -> -2.3946203e+08 | X52: =+G52-W52 -> 2.4068453e+08 | Y52: 2372 | Z52: =+G52-Y52 -> 1220127
X53: =+G53-W53 -> 0 | Z53: =+G53-Y53 -> 0
A54: Current liabilities | X54: =+G54-W54 -> 0 | Z54: =+G54-Y54 -> 0
A55: Financial liabilities | X55: =+G55-W55 -> 0 | Z55: =+G55-Y55 -> 0
A56: Preference shares | C56: =C47 -> 11 | E56: =ROUND(G56/10^5,0) -> 2467 | G56: ='BS Gr'!H891 -> 2.4668101e+08 | I56: 0
A57: Trade payables | C57: ='10-17'!A273 -> 15 | E57: =ROUND(G57/10^5,0) -> 0 | X57: =+G57-W57 -> 0
A58: Total outstanding dues to creditors micro and small enterprises | E58: =ROUND(G58/10^5,0) -> 0 | G58: 0 | I58: 0 | J58: =+G58-I58 -> 0 | Q58: =ROUND(G58,0) -> 0 | W58: =+G58-I58 -> 0 | X58: =+I58-W58 -> 0 | AA58: Total outstanding dues to creditors micro and small enterprises
A59: Total outstanding dues to creditors other than micro and small enterprises | E59: =ROUND(G59/10^5,0) -> 41 | G59: ='Sch - BS'!G271 -> 4084430 | I59: ='Sch - BS'!I271 -> 3086080 | J59: =+G59-I59 -> 998350 | K59: =+CF!F39 -> 865724 | L59: =+J59-K59 -> 132626 | Q59: =ROUND(G59,0) -> 4084430 | W59: =+G59-I59 -> 998350 | X59: =+I59-W59 -> 2087730 | Y59: 37 | Z59: =+G59-Y59 -> 4084393 | AA59: Total outstanding dues to creditors other than micro and small enterprises
A60: Lease liabilities | C60: ='10-17'!A153 -> 12 | E60: =ROUND(G60/10^5,0) -> 39 | G60: ='Sch - BS'!G282 -> 3875013 | I60: ='Sch - BS'!I282 -> 3414889 | J60: =+G60-I60 -> 460124 | L60: =+J60-K60 -> 460124 | Q60: =ROUND(G60,0) -> 3875013 | W60: =+G60-I60 -> 460124 | X60: =+I60-W60 -> 2954765 | Y60: 23 | Z60: =+G60-Y60 -> 3874990
A61: Other financial liabilities | C61: ='10-17'!A336 -> 16 | E61: =ROUND(G61/10^5,0) -> 6 | G61: ='Sch - BS'!G284-G60-G56 -> 574907.6 | I61: ='Sch - BS'!I284-I60 -> 830147 | J61: =+G61-I61 -> -255239.4 | K61: =+CF!F40 -> -255239.4 | L61: =+J61-K61 -> 0 | Q61: =ROUND(G61,0) -> 574908 | W61: =+G61-I61 -> -255239.4 | X61: =+I61-W61 -> 1085386.4 | Y61: 8 | Z61: =+G61-Y61 -> 574899.6
A62: Other current liabilities | C62: ='10-17'!A354 -> 17 | E62: =ROUND(G62/10^5,0) -> 13 | G62: ='Sch - BS'!G297 -> 1280596 | I62: ='Sch - BS'!I297 -> 1316327 | J62: =+G62-I62 -> -35731 | K62: =+CF!F41 -> -35731 | L62: =+J62-K62 -> 0 | Q62: =ROUND(G62,0) -> 1280596 | W62: =+G62-I62 -> -35731 | X62: =+I62-W62 -> 1352058 | Y62: 1 | Z62: =+G62-Y62 -> 1280595
A63: Provisions | E63: =ROUND(G63/10^5,0) -> 0 | G63: ='Sch - BS'!G302 -> 0 | I63: ='Sch - BS'!I302 -> 0 | J63: =+G63-I63 -> 0 | L63: =+J63-K63 -> 0 | Q63: =ROUND(G63,0) -> 0 | W63: =+G63-I63 -> 0 | X63: =+I63-W63 -> 0 | Y63: 0 | Z63: =+G63-Y63 -> 0
A64: Employee benefit obligations | C64: ='10-17'!A210 -> 13 | E64: =ROUND(G64/10^5,0) -> 5 | G64: ='Sch - BS'!G309 -> 470091 | I64: ='Sch - BS'!I309 -> 931995 | J64: =+G64-I64 -> -461904 | K64: =+CF!F42 -> -770367 | L64: =+J64-K64 -> 308463 | Q64: =ROUND(G64,0) -> 470091 | W64: =+G64-I64 -> -461904 | X64: =+I64-W64 -> 1393899 | Y64: 16 | Z64: =+G64-Y64 -> 470075
A65: Income tax liabilities (net) (#) | C65: =+'18-26'!A189 -> 25 | E65: =ROUND(G65/10^5,0) -> 0 | G65: ='Sch - BS'!G316 -> 0 | I65: ='Sch - BS'!I316 -> 0 | J65: =+G65-I65 -> 0 | L65: =+J65-K65 -> 0 | Q65: =ROUND(G65,0) -> 0 | W65: =+G65-I65 -> 0 | X65: =+I65-W65 -> 0 | Y65: 0 | Z65: =+G65-Y65 -> 0
A66: Total current liabilities | E66: =SUM(E56:E65) -> 2571 | G66: =SUM(G56:G65) -> 256966044 | I66: =SUM(I56:I65) -> 9579438 | Q66: =SUM(Q59:Q65) -> 10285038 | W66: =+G66-I66 -> 247386606 | X66: =+I66-W66 -> -237807168 | Y66: 85 | Z66: =+G66-Y66 -> 256965959
X67: =+I67-W67 -> 0 | Z67: =+G67-Y67 -> 0
A68: Total equity and liabilities | E68: =E42+E52+E66 -> 2754 | G68: =G42+G52+G66 -> 275311308 | I68: =I42+I52+I66 -> 3.164423e+08 | Q68: =Q42+Q52+Q66 -> 28630302 | W68: =+G68-I68 -> -41130992 | X68: =+I68-W68 -> 3.5757329e+08 | Y68: 2940 | Z68: =+G68-Y68 -> 275308368
G69: =G68-G36 -> 0.48000002 | I69: =I68-I36 -> -0.3816511
G70: =IF(G68-G36=0,"",G68-G36) -> 0.48000002 | I70: =IF(I68-I36=0,"",I68-I36) -> -0.3816511 | J70: =+G70-I70 -> 0.86165112 | K70: =+J70/2 -> 0.43082556
G71: =IF(G68=G36," ",G68-G36) -> 0.48000002 | I71: =IF(I68=I36," ",I68-I36) -> -0.3816511 | W71: =+G71-I71 -> 0.86165112
A73: (#) Zero represents amount less than ₹ 0.5 lakhs
A74: Summary of material accounting policies and other explanatory information | C74: 2
A75: The accompanying notes are integral part of the financial statements
A76: As per our report of even date
A78: For Walker Chandiok & Co LLP | I78: For and on behalf of the Board of Directors of
A79: Chartered Accountants
A80: Firm Registration No: 001076N/N500013 | I80: CIN: U72900PN2010FTC137168

Sheet Sheet1

Sheet BS Gr
A1: =+Master!B2 -> Syntel Solutions (India) Private Limited | D1: Ind AS account codes
A2: ="Balance sheet Grouping as at " &Master!$B$5 -> Balance sheet Grouping as at 31st March 2025 | H2: ="Current and Non Current as at " &Master!$B$5 -> Current and Non Current as at 31st March 2025 | L2: ="Current and Non Current as at " &Master!$B$11 -> Current and Non Current as at 30th March 2024
A4: GL Code | B4: Account description | D4: As at | F4: As at | H4: Current | I4: Non Current | J4: Difference | L4: Current | M4: Non Current | N4: Difference | U4: Nature of | AC4: Balance as per 31 Mar 23 IFRS TB | AE4: Remarks
D5: =Master!B4 -> 45747 | F5: =Master!B10 -> 45381 | U5: Balance | W5: BS Gr_Current | X5: BS Gr_Non Current | Z5: Main Head | AA5: BS Gr_Current | AB5: BS Gr_Non Current | AD5: Difference | AE5: Remarks | AQ5: Assets | AR5: Liability
A7: 100000 | B7: =VLOOKUP(A7,'TB for financial'!A:B,2,0) -> TDR reclassed > 3 months | D7: =VLOOKUP(A7,'TB for financial'!A:F,6,0) -> 0 | F7: =VLOOKUP(A7,'TB for financial'!A:K,10,0) -> 0 | H7: =D7-I7 -> 0 | I7: 0 | J7: =+D7-H7-I7 -> 0 | L7: =F7-M7 -> 0 | M7: 0 | N7: =+F7-L7-M7 -> 0 | U7: Cur | W7: Current investments | Y7: Current Assets | Z7: Financial Assets | AA7: Investments | AC7: 0 | AD7: =+D7-AC7 -> 0 | AF7: 100000
A8: 100518 | B8: =VLOOKUP(A8,'TB for financial'!A:B,2,0) -> Taurus Mutual Fund | D8: =VLOOKUP(A8,'TB for financial'!A:F,6,0) -> 0 | F8: =VLOOKUP(A8,'TB for financial'!A:K,11,0) -> 0 | H8: =D8-I8 -> 0 | I8: 0 | J8: =+D8-H8-I8 -> 0 | L8: =F8-M8 -> 0 | M8: 0 | N8: =+F8-L8-M8 -> 0 | U8: Cur | W8: Current investments | Y8: Current Assets | Z8: Financial Assets | AA8: Investments | AC8: 0 | AD8: =+D8-AC8 -> 0 | AF8: 100518
A9: 100529 | B9: =VLOOKUP(A9,'TB for financial'!A:B,2,0) -> Reliance Floating Rate Fund | D9: =VLOOKUP(A9,'TB for financial'!A:F,6,0) -> 0 | F9: =VLOOKUP(A9,'TB for financial'!A:K,11,0) -> 0 | H9: =D9-I9 -> 0 | I9: 0 | J9: =+D9-H9-I9 -> 0 | L9: =F9-M9 -> 0 | M9: 0 | N9: =+F9-L9-M9 -> 0 | U9: Cur | W9: Current investments | Y9: Current Assets | Z9: Financial Assets | AA9: Investments | AC9: 0 | AD9: =+D9-AC9 -> 0 | AF9: 100529
A10: 100543 | B10: =VLOOKUP(A10,'TB for financial'!A:B,2,0) -> Axis Mutual Fund | D10: =VLOOKUP(A10,'TB for financial'!A:F,6,0) -> 0 | F10: =VLOOKUP(A10,'TB for financial'!A:K,11,0) -> 0 | H10: =D10-I10 -> 0 | I10: 0 | J10: =+D10-H10-I10 -> 0 | L10: =F10-M10 -> 0 | M10: 0 | N10: =+F10-L10-M10 -> 0 | U10: Cur | W10: Current investments | Y10: Current Assets | Z10: Financial Assets | AA10: Investments | AC10: 0 | AD10: =+D10-AC10 -> 0 | AF10: 100543
A11: 100544 | B11: =VLOOKUP(A11,'TB for financial'!A:B,2,0) -> IDBI Mutual Fund | D11: =VLOOKUP(A11,'TB for financial'!A:F,6,0) -> 0 | F11: =VLOOKUP(A11,'TB for financial'!A:K,11,0) -> 0 | H11: =D11-I11 -> 0 | I11: 0 | J11: =+D11-H11-I11 -> 0 | L11: =F11-M11 -> 0 | M11: 0 | N11: =+F11-L11-M11 -> 0 | U11: Cur | W11: Current investments | Y11: Current Assets | Z11: Financial Assets | AA11: Investments | AC11: 0 | AD11: =+D11-AC11 -> 0 | AF11: 100544
A12: 100547 | B12: =VLOOKUP(A12,'TB for financial'!A:B,2,0) -> Peerlees Mutual Fund | D12: =VLOOKUP(A12,'TB for financial'!A:F,6,0) -> 0.0099999998 | F12: =VLOOKUP(A12,'TB for financial'!A:K,11,0) -> 0.0099999998 | H12: =D12-I12 -> 0.0099999998 | I12: 0 | J12: =+D12-H12-I12 -> 0 | L12: =F12-M12 -> 0.0099999998 | M12: 0 | N12: =+F12-L12-M12 -> 0 | U12: Cur | W12: Current investments | Y12: Current Assets | Z12: Financial Assets | AA12: Investments | AC12: 0 | AD12: =+D12-AC12 -> 0.0099999998 | AF12: 100547 | AQ12: =D12 -> 0.0099999998
A13: 100548 | B13: =VLOOKUP(A13,'TB for financial'!A:B,2,0) -> L & T Mutual Fund | D13: =VLOOKUP(A13,'TB for financial'!A:F,6,0) -> 0 | F13: =VLOOKUP(A13,'TB for financial'!A:K,11,0) -> 0 | H13: =D13-I13 -> 0 | I13: 0 | J13: =+D13-H13-I13 -> 0 | L13: =F13-M13 -> 0 | M13: 0 | N13: =+F13-L13-M13 -> 0 | U13: Cur | W13: Current investments | Y13: Current Assets | Z13: Financial Assets | AA13: Investments | AC13: 0 | AD13: =+D13-AC13 -> 0 | AF13: 100548
A14: 100549 | B14: =VLOOKUP(A14,'TB for financial'!A:B,2,0) -> Canara Robeco Mutual Fund | D14: =VLOOKUP(A14,'TB for financial'!A:F,6,0) -> 0 | F14: =VLOOKUP(A14,'TB for financial'!A:K,11,0) -> 0 | H14: =D14-I14 -> 0 | I14: 0 | J14: =+D14-H14-I14 -> 0 | L14: =F14-M14 -> 0 | M14: 0 | N14: =+F14-L14-M14 -> 0 | U14: Cur | W14: Current investments | Y14: Current Assets | Z14: Financial Assets | AA14: Investments | AC14: 0 | AD14: =+D14-AC14 -> 0 | AF14: 100549
A15: 100550 | B15: =VLOOKUP(A15,'TB for financial'!A:B,2,0) -> Baroda Pioneer Mutual Fund | D15: =VLOOKUP(A15,'TB for financial'!A:F,6,0) -> -1.18 | F15: =VLOOKUP(A15,'TB for financial'!A:K,11,0) -> -1.18 | H15: =D15-I15 -> -1.18 | I15: 0 | J15: =+D15-H15-I15 -> 0 | L15: =F15-M15 -> -1.18 | M15: 0 | N15: =+F15-L15-M15 -> 0 | U15: Cur | W15: Current investments | Y15: Current Assets | Z15: Financial Assets | AA15: Investments | AC15: 0 | AD15: =+D15-AC15 -> -1.18 | AF15: 100550 | AQ15: =D15 -> -1.18
A16: 100551 | B16: =VLOOKUP(A16,'TB for financial'!A:B,2,0) -> HDFC High Int. Fund - Reg. Gr | D16: =VLOOKUP(A16,'TB for financial'!A:F,6,0) -> 0 | F16: =VLOOKUP(A16,'TB for financial'!A:K,11,0) -> 0 | H16: =D16-I16 -> 0 | I16: 0 | J16: =+D16-H16-I16 -> 0 | L16: =F16-M16 -> 0 | M16: 0 | N16: =+F16-L16-M16 -> 0 | U16: Cur | W16: Current investments | Y16: Current Assets | Z16: Financial Assets | AA16: Investments | AC16: 0 | AD16: =+D16-AC16 -> 0 | AF16: 100551
A17: 100552 | B17: =VLOOKUP(A17,'TB for financial'!A:B,2,0) -> Templeton India Inc. Fund - Gr | D17: =VLOOKUP(A17,'TB for financial'!A:F,6,0) -> 0 | F17: =VLOOKUP(A17,'TB for financial'!A:K,11,0) -> 0 | H17: =D17-I17 -> 0 | I17: 0 | J17: =+D17-H17-I17 -> 0 | L17: =F17-M17 -> 0 | M17: 0 | N17: =+F17-L17-M17 -> 0 | U17: Cur | W17: Current investments | Y17: Current Assets | Z17: Financial Assets | AA17: Investments | AC17: 0 | AD17: =+D17-AC17 -> 0 | AF17: 100552
A18: 100553 | B18: =VLOOKUP(A18,'TB for financial'!A:B,2,0) -> Templeton Floating Fund - ST | D18: =VLOOKUP(A18,'TB for financial'!A:F,6,0) -> 0 | F18: =VLOOKUP(A18,'TB for financial'!A:K,11,0) -> 0 | H18: =D18-I18 -> 0 | I18: 0 | J18: =+D18-H18-I18 -> 0 | L18: =F18-M18 -> 0 | M18: 0 | N18: =+F18-L18-M18 -> 0 | U18: Cur | W18: Current investments | Y18: Current Assets | Z18: Financial Assets | AA18: Investments | AC18: 0 | AD18: =+D18-AC18 -> 0 | AF18: 100553
A19: 100554 | B19: =VLOOKUP(A19,'TB for financial'!A:B,2,0) -> DSP ML - Bond Fund - Gr. | D19: =VLOOKUP(A19,'TB for financial'!A:F,6,0) -> 0 | F19: =VLOOKUP(A19,'TB for financial'!A:K,11,0) -> 0 | H19: =D19-I19 -> 0 | I19: 0 | J19: =+D19-H19-I19 -> 0 | L19: =F19-M19 -> 0 | M19: 0 | N19: =+F19-L19-M19 -> 0 | U19: Cur | W19: Current investments | Y19: Current Assets | Z19: Financial Assets | AA19: Investments | AC19: 0 | AD19: =+D19-AC19 -> 0 | AF19: 100554
A20: 100555 | B20: =VLOOKUP(A20,'TB for financial'!A:B,2,0) -> DSP ML Liquidity Fund - Gr | D20: =VLOOKUP(A20,'TB for financial'!A:F,6,0) -> 0 | F20: =VLOOKUP(A20,'TB for financial'!A:K,11,0) -> 0 | H20: =D20-I20 -> 0 | I20: 0 | J20: =+D20-H20-I20 -> 0 | L20: =F20-M20 -> 0 | M20: 0 | N20: =+F20-L20-M20 -> 0 | U20: Cur | W20: Current investments | Y20: Current Assets | Z20: Financial Assets | AA20: Investments | AC20: 0 | AD20: =+D20-AC20 -> 0 | AF20: 100555
A21: 100556 | B21: =VLOOKUP(A21,'TB for financial'!A:B,2,0) -> DSP ML Floating Fund - Gr | D21: =VLOOKUP(A21,'TB for financial'!A:F,6,0) -> 1.25 | F21: =VLOOKUP(A21,'TB for financial'!A:K,11,0) -> 1.25 | H21: =D21-I21 -> 1.25 | I21: 0 | J21: =+D21-H21-I21 -> 0 | L21: =F21-M21 -> 1.25 | M21: 0 | N21: =+F21-L21-M21 -> 0 | U21: Cur | W21: Current investments | Y21: Current Assets | Z21: Financial Assets | AA21: Investments | AC21: 0 | AD21: =+D21-AC21 -> 1.25 | AF21: 100556 | AQ21: =D21 -> 1.25
A22: 100557 | B22: =VLOOKUP(A22,'TB for financial'!A:B,2,0) -> Prudential ICICI Floating - Gr | D22: =VLOOKUP(A22,'TB for financial'!A:F,6,0) -> 0 | F22: =VLOOKUP(A22,'TB for financial'!A:K,11,0) -> 0 | H22: =D22-I22 -> 0 | I22: 0 | J22: =+D22-H22-I22 -> 0 | L22: =F22-M22 -> 0 | M22: 0 | N22: =+F22-L22-M22 -> 0 | U22: Cur | W22: Current investments | Y22: Current Assets | Z22: Financial Assets | AA22: Investments | AC22: 0 | AD22: =+D22-AC22 -> 0 | AF22: 100557
A23: 100558 | B23: =VLOOKUP(A23,'TB for financial'!A:B,2,0) -> Grindlays Cash Fund - IP - Gr | D23: =VLOOKUP(A23,'TB for financial'!A:F,6,0) -> 0 | F23: =VLOOKUP(A23,'TB for financial'!A:K,11,0) -> 0 | H23: =D23-I23 -> 0 | I23: 0 | J23: =+D23-H23-I23 -> 0 | L23: =F23-M23 -> 0 | M23: 0 | N23: =+F23-L23-M23 -> 0 | U23: Cur | W23: Current investments | Y23: Current Assets | Z23: Financial Assets | AA23: Investments | AC23: 0 | AD23: =+D23-AC23 -> 0 | AF23: 100558
A24: 100559 | B24: =VLOOKUP(A24,'TB for financial'!A:B,2,0) -> HSBC Cash Fund - Growth | D24: =VLOOKUP(A24,'TB for financial'!A:F,6,0) -> 0 | F24: =VLOOKUP(A24,'TB for financial'!A:K,11,0) -> 0 | H24: =D24-I24 -> 0 | I24: 0 | J24: =+D24-H24-I24 -> 0 | L24: =F24-M24 -> 0 | M24: 0 | N24: =+F24-L24-M24 -> 0 | U24: Cur | W24: Current investments | Y24: Current Assets | Z24: Financial Assets | AA24: Investments | AC24: 0 | AD24: =+D24-AC24 -> 0 | AF24: 100559
A25: 100560 | B25: =VLOOKUP(A25,'TB for financial'!A:B,2,0) -> Reliance Treasury - IP - Gr | D25: =VLOOKUP(A25,'TB for financial'!A:F,6,0) -> 0 | F25: =VLOOKUP(A25,'TB for financial'!A:K,11,0) -> 0 | H25: =D25-I25 -> 0 | I25: 0 | J25: =+D25-H25-I25 -> 0 | L25: =F25-M25 -> 0 | M25: 0 | N25: =+F25-L25-M25 -> 0 | U25: Cur | W25: Current investments | Y25: Current Assets | Z25: Financial Assets | AA25: Investments | AC25: 0 | AD25: =+D25-AC25 -> 0 | AF25: 100560
A26: 100561 | B26: =VLOOKUP(A26,'TB for financial'!A:B,2,0) -> Reliance STerm Fund - Gr | D26: =VLOOKUP(A26,'TB for financial'!A:F,6,0) -> 0 | F26: =VLOOKUP(A26,'TB for financial'!A:K,11,0) -> 0 | H26: =D26-I26 -> 0 | I26: 0 | J26: =+D26-H26-I26 -> 0 | L26: =F26-M26 -> 0 | M26: 0 | N26: =+F26-L26-M26 -> 0 | U26: Cur | W26: Current investments | Y26: Current Assets | Z26: Financial Assets | AA26: Investments | AC26: 0 | AD26: =+D26-AC26 -> 0 | AF26: 100561
A27: 100562 | B27: =VLOOKUP(A27,'TB for financial'!A:B,2,0) -> TLHG TATA Liquid HIF - Gr | D27: =VLOOKUP(A27,'TB for financial'!A:F,6,0) -> -1.2 | F27: =VLOOKUP(A27,'TB for financial'!A:K,11,0) -> -1.2 | H27: =D27-I27 -> -1.2 | I27: 0 | J27: =+D27-H27-I27 -> 0 | L27: =F27-M27 -> -1.2 | M27: 0 | N27: =+F27-L27-M27 -> 0 | U27: Cur | W27: Current investments | Y27: Current Assets | Z27: Financial Assets | AA27: Investments | AC27: 0 | AD27: =+D27-AC27 -> -1.2 | AF27: 100562 | AQ27: =D27 -> -1.2
A28: 100563 | B28: =VLOOKUP(A28,'TB for financial'!A:B,2,0) -> Kotak Liquid IP - Growth | D28: =VLOOKUP(A28,'TB for financial'!A:F,6,0) -> -0.080000015 | F28: =VLOOKUP(A28,'TB for financial'!A:K,11,0) -> -0.080000015 | H28: =D28-I28 -> -0.080000015 | I28: 0 | J28: =+D28-H28-I28 -> 0 | L28: =F28-M28 -> -0.080000015 | M28: 0 | N28: =+F28-L28-M28 -> 0 | U28: Cur | W28: Current investments | Y28: Current Assets | Z28: Financial Assets | AA28: Investments | AC28: 0 | AD28: =+D28-AC28 -> -0.080000015 | AF28: 100563 | AQ28: =D28 -> -0.080000015
A29: 100564 | B29: =VLOOKUP(A29,'TB for financial'!A:B,2,0) -> Principal Cash Mgmt Fund | D29: =VLOOKUP(A29,'TB for financial'!A:F,6,0) -> 0 | F29: =VLOOKUP(A29,'TB for financial'!A:K,11,0) -> 0 | H29: =D29-I29 -> 0 | I29: 0 | J29: =+D29-H29-I29 -> 0 | L29: =F29-M29 -> 0 | M29: 0 | N29: =+F29-L29-M29 -> 0 | U29: Cur | W29: Current investments | Y29: Current Assets | Z29: Financial Assets | AA29: Investments | AC29: 0 | AD29: =+D29-AC29 -> 0 | AF29: 100564
A30: 100565 | B30: =VLOOKUP(A30,'TB for financial'!A:B,2,0) -> JM Short Term Fund - IP | D30: =VLOOKUP(A30,'TB for financial'!A:F,6,0) -> 0 | F30: =VLOOKUP(A30,'TB for financial'!A:K,11,0) -> 0 | H30: =D30-I30 -> 0 | I30: 0 | J30: =+D30-H30-I30 -> 0 | L30: =F30-M30 -> 0 | M30: 0 | N30: =+F30-L30-M30 -> 0 | U30: Cur | W30: Current investments | Y30: Current Assets | Z30: Financial Assets | AA30: Investments | AC30: 0 | AD30: =+D30-AC30 -> 0 | AF30: 100565
A31: 100566 | B31: =VLOOKUP(A31,'TB for financial'!A:B,2,0) -> Birla Bond Plus IP - Gr | D31: =VLOOKUP(A31,'TB for financial'!A:F,6,0) -> 0 | F31: =VLOOKUP(A31,'TB for financial'!A:K,11,0) -> 0 | H31: =D31-I31 -> 0 | I31: 0 | J31: =+D31-H31-I31 -> 0 | L31: =F31-M31 -> 0 | M31: 0 | N31: =+F31-L31-M31 -> 0 | U31: Cur | W31: Current investments | Y31: Current Assets | Z31: Financial Assets | AA31: Investments | AC31: 0 | AD31: =+D31-AC31 -> 0 | AF31: 100566
A32: 100567 | B32: =VLOOKUP(A32,'TB for financial'!A:B,2,0) -> Birla Cash Plus - IP - Gr | D32: =VLOOKUP(A32,'TB for financial'!A:F,6,0) -> 0.13 | F32: =VLOOKUP(A32,'TB for financial'!A:K,11,0) -> 0.13 | H32: =D32-I32 -> 0.13 | I32: 0 | J32: =+D32-H32-I32 -> 0 | L32: =F32-M32 -> 0.13 | M32: 0 | N32: =+F32-L32-M32 -> 0 | U32: Cur | W32: Current investments | Y32: Current Assets | Z32: Financial Assets | AA32: Investments | AC32: 0 | AD32: =+D32-AC32 -> 0.13 | AF32: 100567 | AQ32: =D32 -> 0.13
A33: 100568 | B33: =VLOOKUP(A33,'TB for financial'!A:B,2,0) -> DSP ML ST Fund - Gr | D33: =VLOOKUP(A33,'TB for financial'!A:F,6,0) -> 0 | F33: =VLOOKUP(A33,'TB for financial'!A:K,11,0) -> 0 | H33: =D33-I33 -> 0 | I33: 0 | J33: =+D33-H33-I33 -> 0 | L33: =F33-M33 -> 0 | M33: 0 | N33: =+F33-L33-M33 -> 0 | U33: Cur | W33: Current investments | Y33: Current Assets | Z33: Financial Assets | AA33: Investments | AC33: 0 | AD33: =+D33-AC33 -> 0 | AF33: 100568
A34: 100569 | B34: =VLOOKUP(A34,'TB for financial'!A:B,2,0) -> Kotak KMMF - K Floater | D34: =VLOOKUP(A34,'TB for financial'!A:F,6,0) -> 0 | F34: =VLOOKUP(A34,'TB for financial'!A:K,11,0) -> 0 | H34: =D34-I34 -> 0 | I34: 0 | J34: =+D34-H34-I34 -> 0 | L34: =F34-M34 -> 0 | M34: 0 | N34: =+F34-L34-M34 -> 0 | U34: Cur | W34: Current investments | Y34: Current Assets | Z34: Financial Assets | AA34: Investments | AC34: 0 | AD34: =+D34-AC34 -> 0 | AF34: 100569
A35: 100570 | B35: =VLOOKUP(A35,'TB for financial'!A:B,2,0) -> Grindlays Floating Rate Fund - IP - Gr | D35: =VLOOKUP(A35,'TB for financial'!A:F,6,0) -> 0 | F35: =VLOOKUP(A35,'TB for financial'!A:K,11,0) -> 0 | H35: =D35-I35 -> 0 | I35: 0 | J35: =+D35-H35-I35 -> 0 | L35: =F35-M35 -> 0 | M35: 0 | N35: =+F35-L35-M35 -> 0 | U35: Cur | W35: Current investments | Y35: Current Assets | Z35: Financial Assets | AA35: Investments | AC35: 0 | AD35: =+D35-AC35 -> 0 | AF35: 100570
A36: 100571 | B36: =VLOOKUP(A36,'TB for financial'!A:B,2,0) -> Prudential ICICI Liquid - Gr | D36: =VLOOKUP(A36,'TB for financial'!A:F,6,0) -> -0.35 | F36: =VLOOKUP(A36,'TB for financial'!A:K,11,0) -> -0.35 | H36: =D36-I36 -> -0.35 | I36: 0 | J36: =+D36-H36-I36 -> 0 | L36: =F36-M36 -> -0.35 | M36: 0 | N36: =+F36-L36-M36 -> 0 | U36: Cur | W36: Current investments | Y36: Current Assets | Z36: Financial Assets | AA36: Investments | AC36: 0 | AD36: =+D36-AC36 -> -0.35 | AF36: 100571 | AQ36: =D36 -> -0.35
A37: 100572 | B37: =VLOOKUP(A37,'TB for financial'!A:B,2,0) -> Templeton India Tresury Management | D37: =VLOOKUP(A37,'TB for financial'!A:F,6,0) -> 0 | F37: =VLOOKUP(A37,'TB for financial'!A:K,11,0) -> 0 | H37: =D37-I37 -> 0 | I37: 0 | J37: =+D37-H37-I37 -> 0 | L37: =F37-M37 -> 0 | M37: 0 | N37: =+F37-L37-M37 -> 0 | U37: Cur | W37: Current investments | Y37: Current Assets | Z37: Financial Assets | AA37: Investments | AC37: 0 | AD37: =+D37-AC37 -> 0 | AF37: 100572
A38: 100573 | B38: =VLOOKUP(A38,'TB for financial'!A:B,2,0) -> HDFC Floating Rate Income Fund | D38: =VLOOKUP(A38,'TB for financial'!A:F,6,0) -> 0 | F38: =VLOOKUP(A38,'TB for financial'!A:K,11,0) -> 0 | H38: =D38-I38 -> 0 | I38: 0 | J38: =+D38-H38-I38 -> 0 | L38: =F38-M38 -> 0 | M38: 0 | N38: =+F38-L38-M38 -> 0 | U38: Cur | W38: Current investments | Y38: Current Assets | Z38: Financial Assets | AA38: Investments | AC38: 0 | AD38: =+D38-AC38 -> 0 | AF38: 100573
A39: 100574 | B39: =VLOOKUP(A39,'TB for financial'!A:B,2,0) -> Birla Floating Rate Fund | D39: =VLOOKUP(A39,'TB for financial'!A:F,6,0) -> 0 | F39: =VLOOKUP(A39,'TB for financial'!A:K,11,0) -> 0 | H39: =D39-I39 -> 0 | I39: 0 | J39: =+D39-H39-I39 -> 0 | L39: =F39-M39 -> 0 | M39: 0 | N39: =+F39-L39-M39 -> 0 | U39: Cur | W39: Current investments | Y39: Current Assets | Z39: Financial Assets | AA39: Investments | AC39: 0 | AD39: =+D39-AC39 -> 0 | AF39: 100574
A40: 100575 | B40: =VLOOKUP(A40,'TB for financial'!A:B,2,0) -> Deutsche Insta Cash Plus Fund | D40: =VLOOKUP(A40,'TB for financial'!A:F,6,0) -> 0 | F40: =VLOOKUP(A40,'TB for financial'!A:K,11,0) -> 0 | H40: =D40-I40 -> 0 | I40: 0 | J40: =+D40-H40-I40 -> 0 | L40: =F40-M40 -> 0 | M40: 0 | N40: =+F40-L40-M40 -> 0 | U40: Cur | W40: Current investments | Y40: Current Assets | Z40: Financial Assets | AA40: Investments | AC40: 0 | AD40: =+D40-AC40 -> 0 | AF40: 100575
A41: 100576 | B41: =VLOOKUP(A41,'TB for financial'!A:B,2,0) -> Templeton Floating Rate Income | D41: =VLOOKUP(A41,'TB for financial'!A:F,6,0) -> 0 | F41: =VLOOKUP(A41,'TB for financial'!A:K,11,0) -> 0 | H41: =D41-I41 -> 0 | I41: 0 | J41: =+D41-H41-I41 -> 0 | L41: =F41-M41 -> 0 | M41: 0 | N41: =+F41-L41-M41 -> 0 | U41: Cur | W41: Current investments | Y41: Current Assets | Z41: Financial Assets | AA41: Investments | AC41: 0 | AD41: =+D41-AC41 -> 0 | AF41: 100576
A42: 100577 | B42: =VLOOKUP(A42,'TB for financial'!A:B,2,0) -> Kotak Long Term Floater | D42: =VLOOKUP(A42,'TB for financial'!A:F,6,0) -> 0 | F42: =VLOOKUP(A42,'TB for financial'!A:K,11,0) -> 0 | H42: =D42-I42 -> 0 | I42: 0 | J42: =+D42-H42-I42 -> 0 | L42: =F42-M42 -> 0 | M42: 0 | N42: =+F42-L42-M42 -> 0 | U42: Cur | W42: Current investments | Y42: Current Assets | Z42: Financial Assets | AA42: Investments | AC42: 0 | AD42: =+D42-AC42 -> 0 | AF42: 100577
A43: 100578 | B43: =VLOOKUP(A43,'TB for financial'!A:B,2,0) -> Deutsche InstaCash Instit Plan | D43: =VLOOKUP(A43,'TB for financial'!A:F,6,0) -> 0 | F43: =VLOOKUP(A43,'TB for financial'!A:K,11,0) -> 0 | H43: =D43-I43 -> 0 | I43: 0 | J43: =+D43-H43-I43 -> 0 | L43: =F43-M43 -> 0 | M43: 0 | N43: =+F43-L43-M43 -> 0 | U43: Cur | W43: Current investments | Y43: Current Assets | Z43: Financial Assets | AA43: Investments | AC43: 0 | AD43: =+D43-AC43 -> 0 | AF43: 100578
A44: 100579 | B44: =VLOOKUP(A44,'TB for financial'!A:B,2,0) -> Birla Floating Rate Fund Long | D44: =VLOOKUP(A44,'TB for financial'!A:F,6,0) -> 0 | F44: =VLOOKUP(A44,'TB for financial'!A:K,11,0) -> 0 | H44: =D44-I44 -> 0 | I44: 0 | J44: =+D44-H44-I44 -> 0 | L44: =F44-M44 -> 0 | M44: 0 | N44: =+F44-L44-M44 -> 0 | U44: Cur | W44: Current investments | Y44: Current Assets | Z44: Financial Assets | AA44: Investments | AC44: 0 | AD44: =+D44-AC44 -> 0 | AF44: 100579
A45: 100580 | B45: =VLOOKUP(A45,'TB for financial'!A:B,2,0) -> Grindlays Floating Rate Fund L | D45: =VLOOKUP(A45,'TB for financial'!A:F,6,0) -> 0 | F45: =VLOOKUP(A45,'TB for financial'!A:K,11,0) -> 0 | H45: =D45-I45 -> 0 | I45: 0 | J45: =+D45-H45-I45 -> 0 | L45: =F45-M45 -> 0 | M45: 0 | N45: =+F45-L45-M45 -> 0 | U45: Cur | W45: Current investments | Y45: Current Assets | Z45: Financial Assets | AA45: Investments | AC45: 0 | AD45: =+D45-AC45 -> 0 | AF45: 100580
A46: 100581 | B46: =VLOOKUP(A46,'TB for financial'!A:B,2,0) -> HDFC High Int. Fund - Reg. Gr | D46: =VLOOKUP(A46,'TB for financial'!A:F,6,0) -> 0 | F46: =VLOOKUP(A46,'TB for financial'!A:K,11,0) -> 0 | H46: =D46-I46 -> 0 | I46: 0 | J46: =+D46-H46-I46 -> 0 | L46: =F46-M46 -> 0 | M46: 0 | N46: =+F46-L46-M46 -> 0 | U46: Cur | W46: Current investments | Y46: Current Assets | Z46: Financial Assets | AA46: Investments | AC46: 0 | AD46: =+D46-AC46 -> 0 | AF46: 100581
A47: 100582 | B47: =VLOOKUP(A47,'TB for financial'!A:B,2,0) -> Principal Floating Rate Fund | D47: =VLOOKUP(A47,'TB for financial'!A:F,6,0) -> 0 | F47: =VLOOKUP(A47,'TB for financial'!A:K,11,0) -> 0 | H47: =D47-I47 -> 0 | I47: 0 | J47: =+D47-H47-I47 -> 0 | L47: =F47-M47 -> 0 | M47: 0 | N47: =+F47-L47-M47 -> 0 | U47: Cur | W47: Current investments | Y47: Current Assets | Z47: Financial Assets | AA47: Investments | AC47: 0 | AD47: =+D47-AC47 -> 0 | AF47: 100582
A48: 100583 | B48: =VLOOKUP(A48,'TB for financial'!A:B,2,0) -> UTI Liquid Cash Plan Fund | D48: =VLOOKUP(A48,'TB for financial'!A:F,6,0) -> 0 | F48: =VLOOKUP(A48,'TB for financial'!A:K,11,0) -> 0 | H48: =D48-I48 -> 0 | I48: 0 | J48: =+D48-H48-I48 -> 0 | L48: =F48-M48 -> 0 | M48: 0 | N48: =+F48-L48-M48 -> 0 | U48: Cur | W48: Current investments | Y48: Current Assets | Z48: Financial Assets | AA48: Investments | AC48: 0 | AD48: =+D48-AC48 -> 0 | AF48: 100583
A49: 100584 | B49: =VLOOKUP(A49,'TB for financial'!A:B,2,0) -> SBI Magnum Ins Inc-Sa | D49: =VLOOKUP(A49,'TB for financial'!A:F,6,0) -> -9.24 | F49: =VLOOKUP(A49,'TB for financial'!A:K,11,0) -> -9.24 | H49: =D49-I49 -> -9.24 | I49: 0 | J49: =+D49-H49-I49 -> 0 | L49: =F49-M49 -> -9.24 | M49: 0 | N49: =+F49-L49-M49 -> 0 | U49: Cur | W49: Current investments | Y49: Current Assets | Z49: Financial Assets | AA49: Investments | AC49: 0 | AD49: =+D49-AC49 -> -9.24 | AF49: 100584 | AQ49: =D49 -> -9.24
A50: 100586 | B50: =VLOOKUP(A50,'TB for financial'!A:B,2,0) -> JM Floater Fund LTP P | D50: =VLOOKUP(A50,'TB for financial'!A:F,6,0) -> 0 | F50: =VLOOKUP(A50,'TB for financial'!A:K,11,0) -> 0 | H50: =D50-I50 -> 0 | I50: 0 | J50: =+D50-H50-I50 -> 0 | L50: =F50-M50 -> 0 | M50: 0 | N50: =+F50-L50-M50 -> 0 | U50: Cur | W50: Current investments | Y50: Current Assets | Z50: Financial Assets | AA50: Investments | AC50: 0 | AD50: =+D50-AC50 -> 0 | AF50: 100586
A51: 100587 | B51: =VLOOKUP(A51,'TB for financial'!A:B,2,0) -> Prudential ICICI STIP | D51: =VLOOKUP(A51,'TB for financial'!A:F,6,0) -> 0 | F51: =VLOOKUP(A51,'TB for financial'!A:K,11,0) -> 0 | H51: =D51-I51 -> 0 | I51: 0 | J51: =+D51-H51-I51 -> 0 | L51: =F51-M51 -> 0 | M51: 0 | N51: =+F51-L51-M51 -> 0 | U51: Cur | W51: Current investments | Y51: Current Assets | Z51: Financial Assets | AA51: Investments | AC51: 0 | AD51: =+D51-AC51 -> 0 | AF51: 100587
A52: 100588 | B52: =VLOOKUP(A52,'TB for financial'!A:B,2,0) -> Princ Float Rate Fund-FMP-IP-G | D52: =VLOOKUP(A52,'TB for financial'!A:F,6,0) -> 0 | F52: =VLOOKUP(A52,'TB for financial'!A:K,11,0) -> 0 | H52: =D52-I52 -> 0 | I52: 0 | J52: =+D52-H52-I52 -> 0 | L52: =F52-M52 -> 0 | M52: 0 | N52: =+F52-L52-M52 -> 0 | U52: Cur | W52: Current investments | Y52: Current Assets | Z52: Financial Assets | AA52: Investments | AC52: 0 | AD52: =+D52-AC52 -> 0 | AF52: 100588
A53: 100589 | B53: =VLOOKUP(A53,'TB for financial'!A:B,2,0) -> Prudential ICICI LT F | D53: =VLOOKUP(A53,'TB for financial'!A:F,6,0) -> 0 | F53: =VLOOKUP(A53,'TB for financial'!A:K,11,0) -> 0 | H53: =D53-I53 -> 0 | I53: 0 | J53: =+D53-H53-I53 -> 0 | L53: =F53-M53 -> 0 | M53: 0 | N53: =+F53-L53-M53 -> 0 | U53: Cur | W53: Current investments | Y53: Current Assets | Z53: Financial Assets | AA53: Investments | AC53: 0 | AD53: =+D53-AC53 -> 0 | AF53: 100589
A54: 100590 | B54: =VLOOKUP(A54,'TB for financial'!A:B,2,0) -> Prudential ICICI FMP | D54: =VLOOKUP(A54,'TB for financial'!A:F,6,0) -> 0 | F54: =VLOOKUP(A54,'TB for financial'!A:K,11,0) -> 0 | H54: =D54-I54 -> 0 | I54: 0 | J54: =+D54-H54-I54 -> 0 | L54: =F54-M54 -> 0 | M54: 0 | N54: =+F54-L54-M54 -> 0 | U54: Cur | W54: Current investments | Y54: Current Assets | Z54: Financial Assets | AA54: Investments | AC54: 0 | AD54: =+D54-AC54 -> 0 | AF54: 100590
A55: 100594 | B55: =VLOOKUP(A55,'TB for financial'!A:B,2,0) -> LICMF Liquid Fund | D55: =VLOOKUP(A55,'TB for financial'!A:F,6,0) -> 0 | F55: =VLOOKUP(A55,'TB for financial'!A:K,11,0) -> 0 | H55: =D55-I55 -> 0 | I55: 0 | J55: =+D55-H55-I55 -> 0 | L55: =F55-M55 -> 0 | M55: 0 | N55: =+F55-L55-M55 -> 0 | U55: Cur | W55: Current investments | Y55: Current Assets | Z55: Financial Assets | AA55: Investments | AC55: 0 | AD55: =+D55-AC55 -> 0 | AF55: 100594
A56: 100595 | B56: =VLOOKUP(A56,'TB for financial'!A:B,2,0) -> SCB Liquidity Manager Plus | D56: =VLOOKUP(A56,'TB for financial'!A:F,6,0) -> 0 | F56: =VLOOKUP(A56,'TB for financial'!A:K,11,0) -> 0 | H56: =D56-I56 -> 0 | I56: 0 | J56: =+D56-H56-I56 -> 0 | L56: =F56-M56 -> 0 | M56: 0 | N56: =+F56-L56-M56 -> 0 | U56: Cur | W56: Current investments | Y56: Current Assets | Z56: Financial Assets | AA56: Investments | AC56: 0 | AD56: =+D56-AC56 -> 0 | AF56: 100595
A57: 100597 | B57: =VLOOKUP(A57,'TB for financial'!A:B,2,0) -> Sundaram BNP Paribas MF | D57: =VLOOKUP(A57,'TB for financial'!A:F,6,0) -> 0.12 | F57: =VLOOKUP(A57,'TB for financial'!A:K,11,0) -> 0.12 | H57: =D57-I57 -> 0.12 | I57: 0 | J57: =+D57-H57-I57 -> 0 | L57: =F57-M57 -> 0.12 | M57: 0 | N57: =+F57-L57-M57 -> 0 | U57: Cur | W57: Current investments | Y57: Current Assets | Z57: Financial Assets | AA57: Investments | AC57: 0 | AD57: =+D57-AC57 -> 0.12 | AF57: 100597 | AQ57: =D57 -> 0.12
A58: 100598 | B58: =VLOOKUP(A58,'TB for financial'!A:B,2,0) -> ABN AMRO Mutual Func | D58: =VLOOKUP(A58,'TB for financial'!A:F,6,0) -> -0.01 | F58: =VLOOKUP(A58,'TB for financial'!A:K,11,0) -> -0.01 | H58: =D58-I58 -> -0.01 | I58: 0 | J58: =+D58-H58-I58 -> 0 | L58: =F58-M58 -> -0.01 | M58: 0 | N58: =+F58-L58-M58 -> 0 | U58: Cur | W58: Current investments | Y58: Current Assets | Z58: Financial Assets | AA58: Investments | AC58: 0 | AD58: =+D58-AC58 -> -0.01 | AF58: 100598 | AQ58: =D58 -> -0.01
A59: 100599 | B59: =VLOOKUP(A59,'TB for financial'!A:B,2,0) -> Religare MF | D59: =VLOOKUP(A59,'TB for financial'!A:F,6,0) -> 0.34 | F59: =VLOOKUP(A59,'TB for financial'!A:K,11,0) -> 0.34 | H59: =D59-I59 -> 0.34 | I59: 0 | J59: =+D59-H59-I59 -> 0 | L59: =F59-M59 -> 0.34 | M59: 0 | N59: =+F59-L59-M59 -> 0 | U59: Cur | W59: Current investments | Y59: Current Assets | Z59: Financial Assets | AA59: Investments | AC59: 0 | AD59: =+D59-AC59 -> 0.34 | AF59: 100599 | AQ59: =D59 -> 0.34
A60: 100601 | B60: =VLOOKUP(A60,'TB for financial'!A:B,2,0) -> JP Morgan MF | D60: =VLOOKUP(A60,'TB for financial'!A:F,6,0) -> 0 | F60: =VLOOKUP(A60,'TB for financial'!A:K,11,0) -> 0 | H60: =D60-I60 -> 0 | I60: 0 | J60: =+D60-H60-I60 -> 0 | L60: =F60-M60 -> 0 | M60: 0 | N60: =+F60-L60-M60 -> 0 | U60: Cur | W60: Current investments | Y60: Current Assets | Z60: Financial Assets | AA60: Investments | AC60: 0 | AD60: =+D60-AC60 -> 0 | AF60: 100601
A61: 100602 | B61: Union KBC MF | D61: =VLOOKUP(A61,'TB for financial'!A:F,6,0) -> 0 | F61: =VLOOKUP(A61,'TB for financial'!A:K,11,0) -> 0 | H61: =D61-I61 -> 0 | I61: 0 | J61: =+D61-H61-I61 -> 0 | L61: =F61-M61 -> 0 | M61: 0 | N61: =+F61-L61-M61 -> 0 | U61: Cur | W61: Current investments | Y61: Current Assets | Z61: Financial Assets | AA61: Investments | AC61: 0 | AD61: =+D61-AC61 -> 0 | AF61: 100602
A62: 100605 | B62: =VLOOKUP(A62,'TB for financial'!A:B,2,0) -> JP Morgan Treasury Stock | D62: =VLOOKUP(A62,'TB for financial'!A:F,6,0) -> 0 | F62: =VLOOKUP(A62,'TB for financial'!A:K,11,0) -> 0 | H62: =D62-I62 -> 0 | I62: 0 | J62: =+D62-H62-I62 -> 0 | L62: =F62-M62 -> 0 | M62: 0 | N62: =+F62-L62-M62 -> 0 | U62: Cur | W62: Current investments | Y62: Current Assets | Z62: Financial Assets | AA62: Investments | AC62: 0 | AD62: =+D62-AC62 -> 0 | AF62: 100605
A63: 100700 | B63: =VLOOKUP(A63,'TB for financial'!A:B,2,0) -> Mutual Fund - Investments | D63: =VLOOKUP(A63,'TB for financial'!A:F,6,0) -> 0 | F63: =VLOOKUP(A63,'TB for financial'!A:K,11,0) -> 0 | H63: =D63-I63 -> 0 | I63: 0 | J63: =+D63-H63-I63 -> 0 | L63: =F63-M63 -> 0 | M63: 0 | N63: =+F63-L63-M63 -> 0 | U63: Cur | W63: Current investments | Y63: Current Assets | Z63: Financial Assets | AA63: Investments | AC63: 0 | AD63: =+D63-AC63 -> 0 | AF63: 100700
A64: 100750 | B64: =VLOOKUP(A64,'TB for financial'!A:B,2,0) -> Mutual Fund - One Group | D64: =VLOOKUP(A64,'TB for financial'!A:F,6,0) -> 0 | F64: =VLOOKUP(A64,'TB for financial'!A:K,11,0) -> 0 | H64: =D64-I64 -> 0 | I64: 0 | J64: =+D64-H64-I64 -> 0 | L64: =F64-M64 -> 0 | M64: 0 | N64: =+F64-L64-M64 -> 0 | U64: Cur | W64: Current investments | Y64: Current Assets | Z64: Financial Assets | AA64: Investments | AC64: 0 | AD64: =+D64-AC64 -> 0 | AF64: 100750
A65: 100760 | B65: =VLOOKUP(A65,'TB for financial'!A:B,2,0) -> Mutual Fund-First Union Securi | D65: =VLOOKUP(A65,'TB for financial'!A:F,6,0) -> 0 | F65: =VLOOKUP(A65,'TB for financial'!A:K,11,0) -> 0 | H65: =D65-I65 -> 0 | I65: 0 | J65: =+D65-H65-I65 -> 0 | L65: =F65-M65 -> 0 | M65: 0 | N65: =+F65-L65-M65 -> 0 | U65: Cur | W65: Current investments | Y65: Current Assets | Z65: Financial Assets | AA65: Investments | AC65: 0 | AD65: =+D65-AC65 -> 0 | AF65: 100760
A66: 100761 | B66: =VLOOKUP(A66,'TB for financial'!A:B,2,0) -> Mutual Fund - Wells Fargo Bank | D66: =VLOOKUP(A66,'TB for financial'!A:F,6,0) -> 0 | F66: =VLOOKUP(A66,'TB for financial'!A:K,11,0) -> 0 | H66: =D66-I66 -> 0 | I66: 0 | J66: =+D66-H66-I66 -> 0 | L66: =F66-M66 -> 0 | M66: 0 | N66: =+F66-L66-M66 -> 0 | U66: Cur | W66: Current investments | Y66: Current Assets | Z66: Financial Assets | AA66: Investments | AC66: 0 | AD66: =+D66-AC66 -> 0 | AF66: 100761
A67: 100762 | B67: =VLOOKUP(A67,'TB for financial'!A:B,2,0) -> CSFB - Mutual Fund | D67: =VLOOKUP(A67,'TB for financial'!A:F,6,0) -> 0 | F67: =VLOOKUP(A67,'TB for financial'!A:K,11,0) -> 0 | H67: =D67-I67 -> 0 | I67: 0 | J67: =+D67-H67-I67 -> 0 | L67: =F67-M67 -> 0 | M67: 0 | N67: =+F67-L67-M67 -> 0 | U67: Cur | W67: Current investments | Y67: Current Assets | Z67: Financial Assets | AA67: Investments | AC67: 0 | AD67: =+D67-AC67 -> 0 | AF67: 100762
A68: 100763 | B68: =VLOOKUP(A68,'TB for financial'!A:B,2,0) -> Standard Federal | D68: =VLOOKUP(A68,'TB for financial'!A:F,6,0) -> 0 | F68: =VLOOKUP(A68,'TB for financial'!A:K,11,0) -> 0 | H68: =D68-I68 -> 0 | I68: 0 | J68: =+D68-H68-I68 -> 0 | L68: =F68-M68 -> 0 | M68: 0 | N68: =+F68-L68-M68 -> 0 | U68: Cur | W68: Current investments | Y68: Current Assets | Z68: Financial Assets | AA68: Investments | AC68: 0 | AD68: =+D68-AC68 -> 0 | AF68: 100763
A69: 100765 | B69: =VLOOKUP(A69,'TB for financial'!A:B,2,0) -> Mutual Fund - Salomon Smith | D69: =VLOOKUP(A69,'TB for financial'!A:F,6,0) -> 0 | F69: =VLOOKUP(A69,'TB for financial'!A:K,11,0) -> 0 | H69: =D69-I69 -> 0 | I69: 0 | J69: =+D69-H69-I69 -> 0 | L69: =F69-M69 -> 0 | M69: 0 | N69: =+F69-L69-M69 -> 0 | U69: Cur | W69: Current investments | Y69: Current Assets | Z69: Financial Assets | AA69: Investments | AC69: 0 | AD69: =+D69-AC69 -> 0 | AF69: 100765
A70: 100770 | B70: =VLOOKUP(A70,'TB for financial'!A:B,2,0) -> Bear Stearns Securities Corp. | D70: =VLOOKUP(A70,'TB for financial'!A:F,6,0) -> 0 | F70: =VLOOKUP(A70,'TB for financial'!A:K,11,0) -> 0 | H70: =D70-I70 -> 0 | I70: 0 | J70: =+D70-H70-I70 -> 0 | L70: =F70-M70 -> 0 | M70: 0 | N70: =+F70-L70-M70 -> 0 | U70: Cur | W70: Current investments | Y70: Current Assets | Z70: Financial Assets | AA70: Investments | AC70: 0 | AD70: =+D70-AC70 -> 0 | AF70: 100770
A71: 100780 | B71: =VLOOKUP(A71,'TB for financial'!A:B,2,0) -> Mutual Fund-Escrow Investments | D71: =VLOOKUP(A71,'TB for financial'!A:F,6,0) -> 0 | F71: =VLOOKUP(A71,'TB for financial'!A:K,11,0) -> 0 | H71: =D71-I71 -> 0 | I71: 0 | J71: =+D71-H71-I71 -> 0 | L71: =F71-M71 -> 0 | M71: 0 | N71: =+F71-L71-M71 -> 0 | U71: Cur | W71: Current investments | Y71: Current Assets | Z71: Financial Assets | AA71: Investments | AC71: 0 | AD71: =+D71-AC71 -> 0 | AF71: 100780
B73: Investments in Mutual Fund | D73: =SUM(D7:D72) -> -10.21 | F73: =SUM(F7:F72) -> -10.21 | H73: =SUM(H7:H72) -> -10.21 | I73: =SUM(I7:I72) -> 0 | J73: =SUM(J7:J72) -> 0 | L73: =SUM(L7:L72) -> -10.21 | M73: =SUM(M7:M72) -> 0 | N73: =SUM(N7:N72) -> 0
A75: 110510 | B75: =VLOOKUP(A75,'TB for financial'!A:B,2,0) -> Investment in Singapore | D75: =VLOOKUP(A75,'TB for financial'!A:F,6,0) -> 0 | F75: =VLOOKUP(A75,'TB for financial'!A:K,11,0) -> 0 | H75: =D75-I75 -> 0 | I75: 0 | J75: =+D75-H75-I75 -> 0 | L75: =F75-M75 -> 0 | M75: 0 | N75: =+F75-L75-M75 -> 0 | U75: Cur/Ncur | W75: Current investments | X75: Non current investments | Y75: Current/Non current assets | Z75: Financial Assets | AA75: Investments | AB75: Investments | AC75: 0 | AD75: =+D75-AC75 -> 0 | AF75: 110510
A76: 110520 | B76: =VLOOKUP(A76,'TB for financial'!A:B,2,0) -> Investment in India | D76: =VLOOKUP(A76,'TB for financial'!A:F,6,0) -> 0 | F76: =VLOOKUP(A76,'TB for financial'!A:K,11,0) -> 0 | H76: =D76-I76 -> 0 | I76: 0 | J76: =+D76-H76-I76 -> 0 | L76: =F76-M76 -> 0 | M76: 0 | N76: =+F76-L76-M76 -> 0 | U76: Cur/Ncur | W76: Current investments | X76: Non current investments | Y76: Current/Non current assets | Z76: Financial Assets | AA76: Investments | AB76: Investments | AC76: 0 | AD76: =+D76-AC76 -> 0 | AF76: 110520
A77: 110530 | B77: =VLOOKUP(A77,'TB for financial'!A:B,2,0) -> Investment in new2usa.com | D77: =VLOOKUP(A77,'TB for financial'!A:F,6,0) -> 0 | F77: =VLOOKUP(A77,'TB for financial'!A:K,11,0) -> 0 | H77: =D77-I77 -> 0 | I77: 0 | J77: =+D77-H77-I77 -> 0 | L77: =F77-M77 -> 0 | M77: 0 | N77: =+F77-L77-M77 -> 0 | U77: Cur/Ncur | W77: Current investments | X77: Non current investments | Y77: Current/Non current assets | Z77: Financial Assets | AA77: Investments | AB77: Investments | AC77: 0 | AD77: =+D77-AC77 -> 0 | AF77: 110530
A78: 110540 | B78: =VLOOKUP(A78,'TB for financial'!A:B,2,0) -> Investment in skillbay.com | D78: =VLOOKUP(A78,'TB for financial'!A:F,6,0) -> 0 | F78: =VLOOKUP(A78,'TB for financial'!A:K,11,0) -> 0 | H78: =D78-I78 -> 0 | I78: 0 | J78: =+D78-H78-I78 -> 0 | L78: =F78-M78 -> 0 | M78: 0 | N78: =+F78-L78-M78 -> 0 | U78: Cur/Ncur | W78: Current investments | X78: Non current investments | Y78: Current/Non current assets | Z78: Financial Assets | AA78: Investments | AB78: Investments | AC78: 0 | AD78: =+D78-AC78 -> 0 | AF78: 110540
A79: 110550 | B79: =VLOOKUP(A79,'TB for financial'!A:B,2,0) -> Investment in Textiles Online | D79: =VLOOKUP(A79,'TB for financial'!A:F,6,0) -> 0 | F79: =VLOOKUP(A79,'TB for financial'!A:K,11,0) -> 0 | H79: =D79-I79 -> 0 | I79: 0 | J79: =+D79-H79-I79 -> 0 | L79: =F79-M79 -> 0 | M79: 0 | N79: =+F79-L79-M79 -> 0 | U79: Cur/Ncur | W79: Current investments | X79: Non current investments | Y79: Current/Non current assets | Z79: Financial Assets | AA79: Investments | AB79: Investments | AC79: 0 | AD79: =+D79-AC79 -> 0 | AF79: 110550
A80: 110560 | B80: =VLOOKUP(A80,'TB for financial'!A:B,2,0) -> Investment in Vianetta Commun | D80: =VLOOKUP(A80,'TB for financial'!A:F,6,0) -> 0 | F80: =VLOOKUP(A80,'TB for financial'!A:K,11,0) -> 0 | H80: =D80-I80 -> 0 | I80: 0 | J80: =+D80-H80-I80 -> 0 | L80: =F80-M80 -> 0 | M80: 0 | N80: =+F80-L80-M80 -> 0 | U80: Cur/Ncur | W80: Current investments | X80: Non current investments | Y80: Current/Non current assets | Z80: Financial Assets | AA80: Investments | AB80: Investments | AC80: 0 | AD80: =+D80-AC80 -> 0 | AF80: 110560
A81: 110570 | B81: =VLOOKUP(A81,'TB for financial'!A:B,2,0) -> Investmnt in Utilitiesmart.com | D81: =VLOOKUP(A81,'TB for financial'!A:F,6,0) -> 0 | F81: =VLOOKUP(A81,'TB for financial'!A:K,11,0) -> 0 | H81: =D81-I81 -> 0 | I81: 0 | J81: =+D81-H81-I81 -> 0 | L81: =F81-M81 -> 0 | M81: 0 | N81: =+F81-L81-M81 -> 0 | U81: Cur/Ncur | W81: Current investments | X81: Non current investments | Y81: Current/Non current assets | Z81: Financial Assets | AA81: Investments | AB81: Investments | AC81: 0 | AD81: =+D81-AC81 -> 0 | AF81: 110570
A82: 110580 | B82: =VLOOKUP(A82,'TB for financial'!A:B,2,0) -> Investment in Convergent Appli | D82: =VLOOKUP(A82,'TB for financial'!A:F,6,0) -> 0 | F82: =VLOOKUP(A82,'TB for financial'!A:K,11,0) -> 0 | H82: =D82-I82 -> 0 | I82: 0 | J82: =+D82-H82-I82 -> 0 | L82: =F82-M82 -> 0 | M82: 0 | N82: =+F82-L82-M82 -> 0 | U82: Cur/Ncur | W82: Current investments | X82: Non current investments | Y82: Current/Non current assets | Z82: Financial Assets | AA82: Investments | AB82: Investments | AC82: 0 | AD82: =+D82-AC82 -> 0 | AF82: 110580
A83: 110590 | B83: =VLOOKUP(A83,'TB for financial'!A:B,2,0) -> Invst In Nekema.com | D83: =VLOOKUP(A83,'TB for financial'!A:F,6,0) -> 0 | F83: =VLOOKUP(A83,'TB for financial'!A:K,11,0) -> 0 | H83: =D83-I83 -> 0 | I83: 0 | J83: =+D83-H83-I83 -> 0 | L83: =F83-M83 -> 0 | M83: 0 | N83: =+F83-L83-M83 -> 0 | U83: Cur/Ncur | W83: Current investments | X83: Non current investments | Y83: Current/Non current assets | Z83: Financial Assets | AA83: Investments | AB83: Investments | AC83: 0 | AD83: =+D83-AC83 -> 0 | AF83: 110590
A84: 110591 | B84: =VLOOKUP(A84,'TB for financial'!A:B,2,0) -> Syntel International Pref.Sh.3 | D84: =VLOOKUP(A84,'TB for financial'!A:F,6,0) -> 0 | F84: =VLOOKUP(A84,'TB for financial'!A:K,11,0) -> 0 | H84: =D84-I84 -> 0 | I84: 0 | J84: =+D84-H84-I84 -> 0 | L84: =F84-M84 -> 0 | M84: 0 | N84: =+F84-L84-M84 -> 0 | U84: Cur/Ncur | W84: Current investments | X84: Non current investments | Y84: Current/Non current assets | Z84: Financial Assets | AA84: Investments | AB84: Investments | AC84: 0 | AD84: =+D84-AC84 -> 0 | AF84: 110591
A85: 110592 | B85: =VLOOKUP(A85,'TB for financial'!A:B,2,0) -> Syntel Sourcing Pref.Sh.3% | D85: =VLOOKUP(A85,'TB for financial'!A:F,6,0) -> 0 | F85: =VLOOKUP(A85,'TB for financial'!A:K,11,0) -> 0 | H85: =D85-I85 -> 0 | I85: 0 | J85: =+D85-H85-I85 -> 0 | L85: =F85-M85 -> 0 | M85: 0 | N85: =+F85-L85-M85 -> 0 | U85: Cur/Ncur | W85: Current investments | X85: Non current investments | Y85: Current/Non current assets | Z85: Financial Assets | AA85: Investments | AB85: Investments | AC85: 0 | AD85: =+D85-AC85 -> 0 | AF85: 110592
A86: 110593 | B86: =VLOOKUP(A86,'TB for financial'!A:B,2,0) -> 3% Pref Shares - SSBS | D86: =VLOOKUP(A86,'TB for financial'!A:F,6,0) -> 0 | F86: =VLOOKUP(A86,'TB for financial'!A:K,11,0) -> 0 | H86: =D86-I86 -> 0 | I86: 0 | J86: =+D86-H86-I86 -> 0 | L86: =F86-M86 -> 0 | M86: 0 | N86: =+F86-L86-M86 -> 0 | U86: Cur/Ncur | W86: Current investments | X86: Non current investments | Y86: Current/Non current assets | Z86: Financial Assets | AA86: Investments | AB86: Investments | AC86: 0 | AD86: =+D86-AC86 -> 0 | AF86: 110593
... A89: 110595 | B89: =VLOOKUP(A89,'TB for financial'!A:B,2,0) -> Investment in Syntel Germany | D89: =VLOOKUP(A89,'TB for financial'!A:F,6,0) -> 0 | F89: =VLOOKUP(A89,'TB for financial'!A:K,11,0) -> 0 | H89: =D89-I89 -> 0 | I89: 0 | J89: =+D89-H89-I89 -> 0 | L89: =F89-M89 -> 0 | M89: 0 | N89: =+F89-L89-M89 -> 0 | U89: Cur/Ncur | W89: Current investments | X89: Non current investments | Y89: Current/Non current assets | Z89: Financial Assets | AA89: Investments | AB89: Investments | AC89: 0 | AD89: =+D89-AC89 -> 0 | AF89: 110595
B90: Less : Share Application Money | D90: 0 | F90: 0 | H90: 0 | I90: 0 | J90: =+D90-H90-I90 -> 0 | L90: 0 | M90: 0 | N90: =+F90-L90-M90 -> 0 | W90: Current investments | X90: Non current investments
J91: =+D91-H91-I91 -> 0
B92: Investments | D92: =SUM(D75:D91) -> 0 | F92: =SUM(F75:F91) -> 0 | H92: =SUM(H75:H91) -> 0 | I92: =SUM(I75:I91) -> 0 | J92: =SUM(J75:J91) -> 0 | L92: =SUM(L75:L91) -> 0 | M92: =SUM(M75:M91) -> 0 | N92: =SUM(N75:N91) -> 0
A94: 120101 | B94: =VLOOKUP(A94,'TB for financial'!A:B,2,0) -> Goodwill-IMG | D94: =VLOOKUP(A94,'TB for financial'!A:F,6,0) -> 0 | F94: =VLOOKUP(A94,'TB for financial'!A:K,11,0) -> 0 | H94: =D94-I94 -> 0 | I94: 0 | J94: =+D94-H94-I94 -> 0 | L94: =F94-M94 -> 0 | M94: 0 | N94: =+F94-L94-M94 -> 0 | U94: Ncur | AC94: 0 | AD94: =+D94-AC94 -> 0 | AF94: 120101
A95: 120201 | B95: =VLOOKUP(A95,'TB for financial'!A:B,2,0) -> Goodwill Amortz-IMG | D95: =VLOOKUP(A95,'TB for financial'!A:F,6,0) -> 0 | F95: =VLOOKUP(A95,'TB for financial'!A:K,11,0) -> 0 | H95: =D95-I95 -> 0 | I95: 0 | J95: =+D95-H95-I95 -> 0 | L95: =F95-M95 -> 0 | M95: 0 | N95: =+F95-L95-M95 -> 0 | U95: Ncur | AC95: 0 | AD95: =+D95-AC95 -> 0 | AF95: 120201
I96: =+D96-H96 -> 0 | J96: =+D96-H96-I96 -> 0
B97: Goodwill | D97: =SUM(D94:D96) -> 0 | F97: =SUM(F94:F96) -> 0 | H97: =SUM(H94:H96) -> 0 | I97: =SUM(I94:I96) -> 0 | J97: =SUM(J94:J96) -> 0 | L97: =SUM(L94:L96) -> 0 | M97: =SUM(M94:M96) -> 0 | N97: =SUM(N94:N96) -> 0
A99: 101000 | B99: =VLOOKUP(A99,'TB for financial'!A:B,2,0) -> Accounts Receivable - Trade | D99: =VLOOKUP(A99,'TB for financial'!A:F,6,0) -> -7.438774 | F99: =VLOOKUP(A99,'TB for financial'!A:K,11,0) -> -7.438774 | H99: =D99-I99 -> -7.438774 | I99: 0 | J99: =+D99-H99-I99 -> 0 | L99: =F99-M99 -> -7.438774 | M99: 0 | N99: =+F99-L99-M99 -> 0 | U99: Cur | W99: Trade receivables | Y99: Current Assets | Z99: Financial Assets | AA99: Trade receivables | AC99: 0 | AD99: =+D99-AC99 -> -7.438774 | AF99: 101000 | AQ99: =D99 -> -7.438774
A100: 101001 | B100: =VLOOKUP(A100,'TB for financial'!A:B,2,0) -> Accounts Receivable-Trade-IMG | D100: =VLOOKUP(A100,'TB for financial'!A:F,6,0) -> 0 | F100: =VLOOKUP(A100,'TB for financial'!A:K,11,0) -> 0 | H100: =D100-I100 -> 0 | I100: 0 | J100: =+D100-H100-I100 -> 0 | L100: =F100-M100 -> 0 | M100: 0 | N100: =+F100-L100-M100 -> 0 | U100: Cur | Y100: Current Assets | Z100: Financial Assets | AA100: Trade receivables | AC100: 0 | AD100: =+D100-AC100 -> 0 | AF100: 101001
A101: 101002 | B101: =VLOOKUP(A101,'TB for financial'!A:B,2,0) -> Accts Receivable-Trade Metier | D101: =VLOOKUP(A101,'TB for financial'!A:F,6,0) -> 0 | F101: =VLOOKUP(A101,'TB for financial'!A:K,11,0) -> 0 | H101: =D101-I101 -> 0 | I101: 0 | J101: =+D101-H101-I101 -> 0 | L101: =F101-M101 -> 0 | M101: 0 | N101: =+F101-L101-M101 -> 0 | U101: Cur | Y101: Current Assets | Z101: Financial Assets | AA101: Trade receivables | AC101: 0 | AD101: =+D101-AC101 -> 0 | AF101: 101002
A102: 101003 | B102: =VLOOKUP(A102,'TB for financial'!A:B,2,0) -> Account receivable Inter Com | D102: =VLOOKUP(A102,'TB for financial'!A:F,6,0) -> 0 | F102: =VLOOKUP(A102,'TB for financial'!A:K,11,0) -> 0 | H102: =D102-I102 -> 0 | I102: 0 | J102: =+D102-H102-I102 -> 0 | L102: =F102-M102 -> 0 | M102: 0 | N102: =+F102-L102-M102 -> 0 | U102: Cur | W102: Trade receivables | Y102: Current Assets | Z102: Financial Assets | AA102: Trade receivables | AC102: 0 | AD102: =+D102-AC102 -> 0 | AF102: 101003
A103: 101060 | B103: =VLOOKUP(A103,'TB for financial'!A:B,2,0) -> Credit Reserve | D103: =VLOOKUP(A103,'TB for financial'!A:F,6,0) -> 0 | F103: =VLOOKUP(A103,'TB for financial'!A:K,11,0) -> 0 | H103: =D103-I103 -> 0 | I103: 0 | J103: =+D103-H103-I103 -> 0 | L103: =F103-M103 -> 0 | M103: 0 | N103: =+F103-L103-M103 -> 0 | U103: Cur | Y103: Current Assets | Z103: Financial Assets | AA103: Trade receivables | AC103: 0 | AD103: =+D103-AC103 -> 0 | AF103: 101060
A104: 101130 | B104: =VLOOKUP(A104,'TB for financial'!A:B,2,0) -> Accounts Receivables - Retaina | D104: =VLOOKUP(A104,'TB for financial'!A:F,6,0) -> 0 | F104: =VLOOKUP(A104,'TB for financial'!A:K,11,0) -> 0 | H104: =D104-I104 -> 0 | I104: 0 | J104: =+D104-H104-I104 -> 0 | L104: =F104-M104 -> 0 | M104: 0 | N104: =+F104-L104-M104 -> 0 | U104: Cur | Y104: Current Assets | Z104: Financial Assets | AA104: Trade receivables | AC104: 0 | AD104: =+D104-AC104 -> 0 | AF104: 101130
A105: 101170 | B105: =VLOOKUP(A105,'TB for financial'!A:B,2,0) -> A/R from Syntel UK | D105: =VLOOKUP(A105,'TB for financial'!A:F,6,0) -> 0 | F105: =VLOOKUP(A105,'TB for financial'!A:K,11,0) -> 0 | H105: =D105-I105 -> 0 | I105: 0 | J105: =+D105-H105-I105 -> 0 | L105: =F105-M105 -> 0 | M105: 0 | N105: =+F105-L105-M105 -> 0 | U105: Cur | Y105: Current Assets | Z105: Financial Assets | AA105: Trade receivables | AC105: 0 | AD105: =+D105-AC105 -> 0 | AF105: 101170
A106: 101180 | B106: =VLOOKUP(A106,'TB for financial'!A:B,2,0) -> A/R from Syntel Singapore | D106: =VLOOKUP(A106,'TB for financial'!A:F,6,0) -> 0 | F106: =VLOOKUP(A106,'TB for financial'!A:K,11,0) -> 0 | H106: =D106-I106 -> 0 | I106: 0 | J106: =+D106-H106-I106 -> 0 | L106: =F106-M106 -> 0 | M106: 0 | N106: =+F106-L106-M106 -> 0 | U106: Cur | Y106: Current Assets | Z106: Financial Assets | AA106: Trade receivables | AC106: 0 | AD106: =+D106-AC106 -> 0 | AF106: 101180
A107: 101066 | B107: =VLOOKUP(A107,'TB for financial'!A:B,2,0) -> Interco AR accruals | D107: =VLOOKUP(A107,'TB for financial'!A:F,6,0) -> 0 | F107: =VLOOKUP(A107,'TB for financial'!A:K,11,0) -> 0 | H107: =D107-I107 -> 0 | I107: 0 | J107: =+D107-H107-I107 -> 0 | L107: =F107-M107 -> 0 | M107: 0 | N107: =+F107-L107-M107 -> 0 | Y107: Current Assets | Z107: Financial Assets | AA107: Trade receivables | AC107: 0 | AD107: =+D107-AC107 -> 0
A108: 411450 | B108: =VLOOKUP(A108,'TB for financial'!A:B,2,0) -> TRADE RECEIVABLES - FOREIGN | D108: =VLOOKUP(A108,'TB for financial'!A:F,6,0) -> 8266047 | F108: =VLOOKUP(A108,'TB for financial'!A:K,11,0) -> 1816954.7 | H108: =D108-I108 -> 8266047 | I108: 0 | J108: =+D108-H108-I108 -> 0 | L108: =F108-M108 -> 1816954.7 | M108: 0 | N108: =+F108-L108-M108 -> 0 | Y108: Current Assets | Z108: Financial Assets | AA108: Trade receivables | AC108: 6500696.4 | AD108: =+D108-AC108 -> 1765350.5 | AF108: This is SAP Account | AQ108: =D108 -> 8266047
...

Sheet PL
A1: =+Master!B2 -> Syntel Solutions (India) Private Limited
A3: Statement of profit and loss for the year ended 31 March 2025
A4: =BS!A4 -> (Amounts are stated in ₹ Lakhs unless otherwise stated)
F6: Year ended | H6: Year ended
A7: Particular | D7: Notes | F7: =BS!G7 -> 45747 | H7: =BS!I7 -> 45382
A9: Revenue from operations
A10: - Software services | D10: ='18-26'!A8 -> 18 | E10: =ROUND(F10/10^5,0) -> 110 | F10: =+'Sch - PL'!E10+'Sch - PL'!E37 -> 10984519 | H10: =+'Sch - PL'!G10+'Sch - PL'!G37 -> 14480207 | T10: =+F10-H10 -> -3495688 | U10: =+F10-T10 -> 14480207 | X10: =H10-H15-H20 -> 146800
A11: Other income | D11: ='18-26'!A18 -> 19 | E11: =ROUND(F11/10^5,0) -> 159 | F11: =+'Sch - PL'!E41+'Sch - PL'!E18-'Sch - PL'!E37 -> 15903427 | H11: =+'Sch - PL'!G41+'Sch - PL'!G18-'Sch - PL'!G37 -> 36466002 | T11: =+F11-H11 -> -20562575 | U11: =+F11-T11 -> 36466002
A12: Total income | E12: =SUM(E10:E11) -> 269 | F12: =SUM(F10:F11) -> 26887946 | H12: =SUM(H10:H11) -> 50946209 | T12: =+F12-H12 -> -24058263 | W12: =H10-H15-H20 -> 146800
A14: Expenses
A15: Employee benefit expenses | D15: ='18-26'!A36 -> 20 | E15: =ROUND(F15/10^5,0) -> 71 | F15: =+'Sch - PL'!E53 -> 7068414 | H15: =+'Sch - PL'!G53 -> 8707022 | T15: =+F15-H15 -> -1638608 | U15: =+F15-T15 -> 8707022 | W15: =F10-F15-F20-F17 -> -7098846 | Y15: =H10-H15-H20 -> 146800
A16: Depreciation (#) | D16: ='3-4'!A7 -> 3 | E16: =ROUND(F16/10^5,0) -> 0 | F16: =ROUND('PL Gr'!E435/Master!$B$23,0) -> 0 | H16: =ROUND('PL Gr'!G435/Master!$B$23,0) -> 0 | T16: =+F16-H16 -> 0
A17: Depreciation and amortization | D17: ='3-4'!A47 -> 3A | E17: =ROUND(F17/10^5,0) -> 32 | F17: =ROUND('PL Gr'!E440/Master!$B$23,0) -> 3206674 | H17: =ROUND('PL Gr'!G440/Master!$B$23,0) -> 3180953 | T17: =+F17-H17 -> 25721 | U17: =+F17-T17 -> 3180953 | W17: =F10-F15-F17-F20 -> -7098846 | Y17: =H10-H15-H17-H20 -> -3034153
A18: Foreign travel expenses | D18: ='18-26'!A51 -> 21 | E18: =ROUND(F18/10^5,0) -> 0 | F18: =+'Sch - PL'!E72*0 -> 0 | H18: =+'Sch - PL'!G72*0 -> 0 | T18: =+F18-H18 -> 0
A19: Finance charges | D19: =+'18-26'!A65 -> 21 | E19: =ROUND(F19/10^5,0) -> 118 | F19: =ROUND(('PL Gr'!E377+'PL Gr'!E379+'PL Gr'!E452-'PL Gr'!E39+'PL Gr'!E400+'PL Gr'!E44)/Master!$B$23,0) -> 11760865 | H19: =ROUND(('PL Gr'!G377+'PL Gr'!G379+'PL Gr'!G452+'PL Gr'!G39+'PL Gr'!G400+'PL Gr'!G44)/Master!$B$23,0) -> 14031849 | T19: =+F19-H19 -> -2270984 | U19: =+F19-T19 -> 14031849
A20: Other expenses | D20: ='18-26'!A78 -> 22 | E20: =ROUND(F20/10^5,0) -> 78 | F20: =+'Sch - PL'!E108+'Sch - PL'!E72-'Sch - PL'!E18*0 -> 7808277 | H20: =+'Sch - PL'!G108+'Sch - PL'!G72-'Sch - PL'!G18*0-204068 -> 5626385 | T20: =+F20-H20 -> 2181892 | U20: =+F20-T20 -> 5626385
A21: Total expenses | E21: =SUM(E15:E20) -> 299 | F21: =SUM(F15:F20) -> 29844230 | H21: =SUM(H15:H20) -> 31546209 | T21: =+F21-H21 -> -1701979 | U21: =+T21-F21 -> -31546209
A23: Profit / (Loss) before exceptional and extraordinary items and tax | E23: =E12-E21 -> -30 | F23: =+F12-F21 -> -2956284 | H23: =+H12-H21 -> 19400000
A25: Extra Ordinary item
A26: Profit / (Loss) before tax | E26: =E23-E25 -> -30 | F26: =F23-SUM(F24:F25) -> -2956284 | H26: =H23-SUM(H24:H25) -> 19400000 | V26: =F26/F10 -> -0.26913186
U27: =75000 -> 75000 | V27: =ROUND(U27/100000,0) -> 1
A28: Tax expense | D28: ='18-26'!A189 -> 25 | U28: 50000 | V28: =ROUND(U28/100000,0) -> 1
A29: Current tax | E29: =ROUND(F29/10^5,0) -> 426 | F29: =+'Sch - PL'!E125+'Sch - PL'!E122 -> 42613709 | H29: =+'Sch - PL'!G125 -> 4035301 | J29: 15 | K29: 10639 | L29: =+F29-J29 -> 42613694 | M29: =+H29-K29 -> 4024662
A30: MAT credit entitlement | E30: =ROUND(F30/10^5,0) -> 0 | F30: =-'Sch - PL'!E122*0 -> 0 | H30: =-'Sch - PL'!G122*0-H31-1*0 -> 0 | J30: 5046 | K30: -168 | L30: =+F30-J30 -> -5046 | M30: =+H30-K30 -> 168
A31: MAT credit entitlement written off | E31: =ROUND(F31/10^5,0) -> 0 | H31: =ROUND(77348338.6220272/Master!$B$23,0)*0 -> 0 | K31: 77348 | L31: =+F31-J31 -> 0 | M31: =+H31-K31 -> -77348
A32: Deferred tax [net of MAT credit ₹ 31 ( 31 March 2024 : ₹ 4)] (refer note no 14) | E32: =ROUND(F32/10^5,0) -> 35 | F32: =+'Sch - PL'!E127-'Sch - PL'!E122+'Sch - PL'!E129 -> 3452021 | H32: =+'Sch - PL'!G127++'Sch - PL'!G129 -> -26030840 | J32: 107 | K32: -13 | L32: =+F32-J32 -> 3451914 | M32: =+H32-K32 -> -26030827 | T32: =+F32-H32 -> 29482861
A33: Buy back tax | F33: =+'Sch - PL'!E129*0 -> 0 | H33: =+'Sch - PL'!G129*0 -> 0 | J33: 0 | K33: 0 | L33: =+F33-J33 -> 0 | M33: =+H33-K33 -> 0
L34: =+F34-J34 -> 0 | M34: =+H34-K34 -> 0
A35: Total tax expenses | E35: =SUM(E29:E34) -> 461 | F35: =SUM(F29:F34) -> 46065730 | H35: =SUM(H29:H34) -> -21995539 | J35: 5168 | K35: 87806 | L35: =+F35-J35 -> 46060562 | M35: =+H35-K35 -> -22083345 | T35: =+F35-H35 -> 68061269 | U35: =+T35-F35 -> 21995539
A37: Profit / (Loss) after tax (A) | E37: =+E26-E35 -> -491 | F37: =+F26-F35 -> -49022014 | H37: =+H26-H35 -> 41395539 | I37: =+'PL Gr'!E459 -> -48218703 | J37: =+F37-I37 -> -803311.47 | T37: =+F37-H37 -> -90417553 | V37: =+'PL Gr'!E459 -> -48218703 | W37: =+F37-V37 -> -803311.47
A39: Other comprehensive income
A40: Items that will not be reclassified subsequently to profit or loss
A41: Remeasurement of the actuarial gain on defined benefit obligation (#) | E41: =ROUND(F41/10^5,0) -> 0 | F41: =-OCI!U5 -> -46765 | H41: =-OCI!S5 -> -30176 | T41: =+F41-H41 -> -16589
A42: Tax impact on above items (#) | E42: =ROUND(F42/10^5,0) -> 0 | F42: =-OCI!U6 -> 13010 | H42: =-OCI!S6 -> 8395 | T42: =+F42-H42 -> 4615
A43: Other comprehensive income / (loss) for the year (B) | E43: =SUM(E41:E42) -> 0 | F43: =SUM(F41:F42) -> -33755 | H43: =SUM(H41:H42) -> -21781 | T43: =+F43-H43 -> -11974
A45: Items that will be reclassified subsequently to profit or loss | H45: 0
A47: Other comprehensive income for the year | F47: 0 | H47: 0
A48: Total Other comprehensive income / (loss) for the year (A+B) | E48: =E37+E43 -> -491 | F48: =F37+F43 -> -49055769 | H48: =H37+H43 -> 41373758 | T48: =+F48-H48 -> -90429527 | U48: =+F48-T48 -> 41373758 | W48: =+'Sch - BS'!G223 -> -109379
W49: =+W48+F37 -> -49131393
A50: Basic and diluted earning / (loss) per equity share (₹) | D50: =+'Notes 28-35'!A261 -> 29 | F50: ='Notes 28-35'!J267 -> -4902.2014 | H50: ='Notes 28-35'!K267 -> 4139.5539 | W50: )
A51: (Face value of ₹ 10 each)
U53: =+U52-F37 -> 49022014
A56: (#) Zero represents amount less than ₹ 0.5 lakhs
A57: Summary of material accounting policies and other explanatory information | D57: 2
A58: The accompanying notes are integral part of the financial statements
A59: As per our report of even date
A61: For Walker Chandiok & Co LLP | H61: For and on behalf of the Board of Directors of
A62: Chartered Accountants | H62: =BS!I79 -> 0
A63: Firm Registration No: 001076N/N500013 | H63: =BS!I80 -> CIN: U72900PN2010FTC137168

Sheet PL Gr
A1: =+Master!B2 -> Syntel Solutions (India) Private Limited | C1: Ind AS account codes
A2: ="Profit & Loss Grouping for the period ended " &Master!$B$5 -> Profit & Loss Grouping for the period ended 31st March 2025
A4: GL Code | B4: Account description | C4: PL Grouping | E4: =+'Sch - PL'!E5 -> 2025 | G4: =+'Sch - PL'!G5 -> 2024 | J4: Apr-20 to Dec-20 Fin | K4: Jan-21 to Mar-21 Fin | L4: Apr to Dec 19 Fin | M4: Mar 20 Fin | N4: Total IFRS Fin | O4: Difference
A6: 400010 | B6: =VLOOKUP(A6,'TB for financial'!A:B,2,0) -> Onsite/Offsite Revenues | C6: Revenue from operations | E6: =-VLOOKUP(A6,'TB for financial'!A:F,6,0) -> 0 | G6: =-VLOOKUP(A6,'TB for financial'!A:K,11,0) -> 0 | H6: 400010 | I6: 0 | J6: 0 | K6: 0 | L6: 0 | M6: 0 | N6: =+J6+K6 -> 0 | O6: =+E6-N6 -> 0 | Q6: #N/A
A7: 400020 | B7: =VLOOKUP(A7,'TB for financial'!A:B,2,0) -> Revenue Adjustments | C7: Revenue from operations | E7: =-VLOOKUP(A7,'TB for financial'!A:F,6,0) -> 0 | G7: =-VLOOKUP(A7,'TB for financial'!A:K,11,0) -> 0 | H7: #N/A | I7: #N/A | J7: 0 | K7: 0 | L7: 0 | M7: 0 | N7: =+J7+K7 -> 0 | O7: =+E7-N7 -> 0
A8: 400030 | B8: =VLOOKUP(A8,'TB for financial'!A:B,2,0) -> Offshore Revenue | C8: Revenue from operations | E8: =-VLOOKUP(A8,'TB for financial'!A:F,6,0) -> 0 | G8: =-VLOOKUP(A8,'TB for financial'!A:K,11,0) -> 0 | H8: 400030 | I8: 0 | J8: 0 | K8: 0 | L8: 0 | M8: 0 | N8: =+J8+K8 -> 0 | O8: =+E8-N8 -> 0
A9: 400050 | B9: =VLOOKUP(A9,'TB for financial'!A:B,2,0) -> Reimbursement of Expenses-REVE | C9: Revenue from operations | E9: =-VLOOKUP(A9,'TB for financial'!A:F,6,0) -> 0 | G9: =-VLOOKUP(A9,'TB for financial'!A:K,11,0) -> 0 | H9: 400050 | I9: 0 | J9: 0 | K9: 0 | L9: 0 | M9: 0 | N9: =+J9+K9 -> 0 | O9: =+E9-N9 -> 0
A10: 400060 | B10: =VLOOKUP(A10,'TB for financial'!A:B,2,0) -> Sales Incentives | C10: Revenue from operations | E10: =-VLOOKUP(A10,'TB for financial'!A:F,6,0) -> 0 | G10: =-VLOOKUP(A10,'TB for financial'!A:K,11,0) -> 0 | H10: #N/A | I10: #N/A | J10: 0 | K10: 0 | L10: 0 | M10: 0 | N10: =+J10+K10 -> 0 | O10: =+E10-N10 -> 0
A11: 400061 | B11: =VLOOKUP(A11,'TB for financial'!A:B,2,0) -> Volume Discount/Rebates | C11: Revenue from operations | E11: =-VLOOKUP(A11,'TB for financial'!A:F,6,0) -> 0 | G11: =-VLOOKUP(A11,'TB for financial'!A:K,11,0) -> 0 | H11: #N/A | I11: #N/A | J11: 0 | K11: 0 | L11: 0 | M11: 0 | N11: =+J11+K11 -> 0 | O11: =+E11-N11 -> 0
A12: 400110 | B12: =VLOOKUP(A12,'TB for financial'!A:B,2,0) -> Inter Unit Onsite/Offsite Reve | C12: Revenue from operations | E12: =-VLOOKUP(A12,'TB for financial'!A:F,6,0) -> 0 | G12: =-VLOOKUP(A12,'TB for financial'!A:K,11,0) -> 0 | H12: 400110 | I12: 0 | J12: 0 | K12: 0 | L12: 0 | M12: 0 | N12: =+J12+K12 -> 0 | O12: =+E12-N12 -> 0
A13: 400130 | B13: =VLOOKUP(A13,'TB for financial'!A:B,2,0) -> Inter Unit Offshore Revenue | C13: Revenue from operations | D13: 400130 | E13: =-VLOOKUP(A13,'TB for financial'!A:F,6,0) -> 0 | G13: =-VLOOKUP(A13,'TB for financial'!A:K,11,0) -> 0 | H13: 400130 | I13: 12678976 | J13: 8465942.5 | K13: 3718537.5 | L13: 0 | M13: 0 | N13: =+J13+K13 -> 12184480 | O13: =+E13-N13 -> -12184480 | P13: 400130 | Q13: #N/A | R13: =+E13-Q13 -> #N/A
A14: 400040 | B14: =VLOOKUP(A14,'TB for financial'!A:B,2,0) -> Domestic Direct Revenue | C14: Revenue from operations | E14: =-VLOOKUP(A14,'TB for financial'!A:F,6,0) -> 0 | G14: =-VLOOKUP(A14,'TB for financial'!A:K,11,0) -> 0 | H14: #N/A | I14: #N/A | J14: 0 | K14: 0 | L14: 0 | M14: 0 | N14: =+J14+K14 -> 0 | O14: =+E14-N14 -> 0
A15: 706361 | B15: =VLOOKUP(A15,'TB for financial'!A:B,2,0) -> Sales of Services. Interco EXP | C15: Revenue from operations | D15: 706361 | E15: =-VLOOKUP(A15,'TB for financial'!A:F,6,0) -> 10587551 | G15: =-VLOOKUP(A15,'TB for financial'!A:K,11,0) -> 13298075 | H15: 706361 | I15: -9954016.9 | J15: 0 | K15: 0 | L15: 0 | M15: 0 | N15: =+J15+K15 -> 0 | O15: =+E15-N15 -> 10587551
A16: 779000 | B16: =VLOOKUP(A16,'TB for financial'!A:B,2,0) -> Revenue Offshore Netting Billing | C16: Revenue from operations | E16: =-VLOOKUP(A16,'TB for financial'!A:F,6,0) -> 396967.87 | G16: =-VLOOKUP(A16,'TB for financial'!A:K,11,0) -> 1182131.3 | H16: 779000
B18: Sale of services | E18: =SUM(E6:E17) -> 10984519 | G18: =SUM(G6:G17) -> 14480207 | J18: =SUM(J6:J17) -> 8465942.5 | K18: =SUM(K6:K17) -> 3718537.5 | L18: =SUM(L6:L17) -> 0 | M18: =SUM(M6:M17) -> 0 | N18: =SUM(N6:N17) -> 12184480 | O18: =SUM(O6:O17) -> -1596929.2
A20: 400021 | B20: =VLOOKUP(A20,'TB for financial'!A:B,2,0) -> Local Sales - India | C20: Revenue from operations | D20: 400021 | E20: =-VLOOKUP(A20,'TB for financial'!A:F,6,0) -> 0 | G20: =-VLOOKUP(A20,'TB for financial'!A:K,11,0) -> 0 | H20: 400021 | I20: 705115.68 | J20: 541150.19 | K20: 0 | L20: 0 | M20: 0 | N20: =+J20+K20 -> 541150.19 | O20: =+E20-N20 -> -541150.19 | P20: 400021 | Q20: #N/A | R20: =+E20-Q20 -> #N/A
A21: 400140 | B21: =VLOOKUP(A21,'TB for financial'!A:B,2,0) -> Finder Fees - Inter company | C21: Revenue from operations | E21: =-VLOOKUP(A21,'TB for financial'!A:F,6,0) -> 0 | G21: =-VLOOKUP(A21,'TB for financial'!A:K,11,0) -> 0 | H21: 400140 | I21: 0 | J21: 0 | K21: 0 | L21: 0 | M21: 0 | N21: =+J21+K21 -> 0 | O21: =+E21-N21 -> 0 | P21: 400140 | Q21: #N/A | R21: =+E21-Q21 -> #N/A
A22: 400141 | B22: =VLOOKUP(A22,'TB for financial'!A:B,2,0) -> Finder Fee-InterCompany Domes | C22: Revenue from operations | E22: =-VLOOKUP(A22,'TB for financial'!A:F,6,0) -> 0 | G22: =-VLOOKUP(A22,'TB for financial'!A:K,11,0) -> 0 | H22: 400141 | I22: 0 | J22: 0 | K22: 0 | L22: 0 | M22: 0 | N22: =+J22+K22 -> 0 | O22: =+E22-N22 -> 0
B24: Other operating income | E24: =SUM(E20:E23) -> 0 | G24: =SUM(G20:G23) -> 0 | J24: =SUM(J20:J23) -> 541150.19 | K24: =SUM(K20:K23) -> 0 | L24: =SUM(L20:L23) -> 0 | M24: =SUM(M20:M23) -> 0 | N24: =SUM(N20:N23) -> 541150.19 | O24: =SUM(O20:O23) -> -541150.19
A26: 601010 | B26: =VLOOKUP(A26,'TB for financial'!A:B,2,0) -> Interest Income Taxable | C26: Other income | D26: 601010 | E26: =-VLOOKUP(A26,'TB for financial'!A:F,6,0) -> 0 | G26: =-VLOOKUP(A26,'TB for financial'!A:K,11,0) -> 0 | H26: 601010 | I26: -5109640.7 | J26: 6200594.7 | K26: 1519151.1 | L26: 0 | M26: 0 | N26: =+J26+K26 -> 7719745.8 | O26: =+E26-N26 -> -7719745.8
A27: 601011 | B27: =VLOOKUP(A27,'TB for financial'!A:B,2,0) -> Interest Income Non Taxable | C27: Other income | E27: =-VLOOKUP(A27,'TB for financial'!A:F,6,0) -> 0 | G27: =-VLOOKUP(A27,'TB for financial'!A:K,11,0) -> 0 | H27: 601011 | I27: 0 | J27: 0 | K27: 0 | L27: 0 | M27: 0 | N27: =+J27+K27 -> 0 | O27: =+E27-N27 -> 0
A28: 601012 | B28: =VLOOKUP(A28,'TB for financial'!A:B,2,0) -> Dividend Income | C28: Other income | E28: =-VLOOKUP(A28,'TB for financial'!A:F,6,0) -> 0 | G28: =-VLOOKUP(A28,'TB for financial'!A:K,11,0) -> 0 | H28: 601012 | I28: 0 | J28: 0 | K28: 0 | L28: 0 | M28: 0 | N28: =+J28+K28 -> 0 | O28: =+E28-N28 -> 0
A29: 601013 | B29: =VLOOKUP(A29,'TB for financial'!A:B,2,0) -> Profit on redemption of mutual fund | C29: Other income | E29: =-VLOOKUP(A29,'TB for financial'!A:F,6,0) -> 0 | G29: =-VLOOKUP(A29,'TB for financial'!A:K,11,0) -> 0 | H29: 601013 | I29: 0 | J29: 1.4551915e-11 | K29: 0 | L29: 0 | M29: 0 | N29: =+J29+K29 -> 1.4551915e-11 | O29: =+E29-N29 -> -1.4551915e-11 | P29: 601013 | Q29: #N/A | R29: =+E29-Q29 -> #N/A
A30: 601033 | B30: =VLOOKUP(A30,'TB for financial'!A:B,2,0) -> MF unrealised gain (IndAS) | C30: Other income | E30: =-VLOOKUP(A30,'TB for financial'!A:F,6,0) -> 0 | G30: =-VLOOKUP(A30,'TB for financial'!A:K,11,0) -> 0 | H30: 601033 | I30: 0 | J30: 0 | K30: 0 | L30: 0 | M30: 0 | N30: =+J30+K30 -> 0 | O30: =+E30-N30 -> 0 | P30: 601033
A31: 601014 | B31: =VLOOKUP(A31,'TB for financial'!A:B,2,0) -> Miscellaneous Income | C31: Other income | E31: =-VLOOKUP(A31,'TB for financial'!A:F,6,0) -> 0 | G31: =-VLOOKUP(A31,'TB for financial'!A:K,11,0) -> 0 | H31: 601014 | I31: 0 | J31: 100000 | K31: -22105.98 | L31: 0 | M31: 0 | N31: =+J31+K31 -> 77894.02 | O31: =+E31-N31 -> -77894.02
A32: 601017 | B32: =VLOOKUP(A32,'TB for financial'!A:B,2,0) -> Forex Interest Income Taxable | C32: Other income | E32: =-VLOOKUP(A32,'TB for financial'!A:F,6,0) -> 0 | G32: =-VLOOKUP(A32,'TB for financial'!A:K,11,0) -> 0 | H32: 601017 | I32: 0 | J32: 0 | K32: 0 | L32: 0 | M32: 0 | N32: =+J32+K32 -> 0 | O32: =+E32-N32 -> 0
A33: 601015 | B33: =VLOOKUP(A33,'TB for financial'!A:B,2,0) -> Dividend - Interco | C33: Other income | E33: =-VLOOKUP(A33,'TB for financial'!A:F,6,0) -> 0 | G33: =-VLOOKUP(A33,'TB for financial'!A:K,11,0) -> 0 | H33: #N/A | I33: #N/A | J33: 0 | K33: 0 | L33: 0 | M33: 0 | N33: =+J33+K33 -> 0 | O33: =+E33-N33 -> 0
A34: 601016 | B34: =VLOOKUP(A34,'TB for financial'!A:B,2,0) -> Inter-Company Revenue | C34: Other income | E34: =-VLOOKUP(A34,'TB for financial'!A:F,6,0) -> 0 | G34: =-VLOOKUP(A34,'TB for financial'!A:K,11,0) -> 0 | H34: #N/A | I34: #N/A | J34: 0 | K34: 0 | L34: 0 | M34: 0 | N34: =+J34+K34 -> 0 | O34: =+E34-N34 -> 0
A35: 601018 | B35: =VLOOKUP(A35,'TB for financial'!A:B,2,0) -> Employee - Interest on Loan | C35: Other income | D35: 601018 | E35: =-VLOOKUP(A35,'TB for financial'!A:F,6,0) -> 0 | G35: =-VLOOKUP(A35,'TB for financial'!A:K,11,0) -> 0 | H35: 601018 | I35: -1375 | J35: 42 | K35: 0 | L35: 0 | M35: 0 | N35: =+J35+K35 -> 42 | O35: =+E35-N35 -> -42
A36: 601020 | B36: Other Income - Non Taxable | C36: Other income | E36: =-VLOOKUP(A36,'TB for financial'!A:F,6,0) -> 0 | G36: =-VLOOKUP(A36,'TB for financial'!A:K,11,0) -> 0 | H36: #N/A | I36: #N/A | J36: 0 | K36: 0 | L36: 0 | M36: 0 | N36: =+J36+K36 -> 0 | O36: =+E36-N36 -> 0
A37: 601090 | B37: =VLOOKUP(A37,'TB for financial'!A:B,2,0) -> Interco Rent - Income | C37: Other income | E37: =-VLOOKUP(A37,'TB for financial'!A:F,6,0) -> 0 | G37: =-VLOOKUP(A37,'TB for financial'!A:K,11,0) -> 0 | H37: 601090 | I37: 0 | J37: 0 | K37: 0 | L37: 0 | M37: 0 | N37: =+J37+K37 -> 0 | O37: =+E37-N37 -> 0
A38: 601032 | B38: =VLOOKUP(A38,'TB for financial'!A:B,2,0) -> Interest income IC Dep (IndAS) | C38: Other income | E38: =-VLOOKUP(A38,'TB for financial'!A:F,6,0) -> 0 | G38: =-VLOOKUP(A38,'TB for financial'!A:K,11,0) -> 0 | H38: 601032 | I38: 0 | J38: 0 | K38: 0 | L38: 0 | M38: 0 | N38: =+J38+K38 -> 0 | O38: =+E38-N38 -> 0 | P38: 601032
A39: 601023 | B39: =VLOOKUP(A39,'TB for financial'!A:B,2,0) -> Interest Exp on Lease Liab | C39: Finance | E39: =-VLOOKUP(A39,'TB for financial'!A:F,6,0) -> 0 | G39: =-VLOOKUP(A39,'TB for financial'!A:K,11,0) -> 0 | H39: 601023 | I39: 0
A40: 704040 | B40: =VLOOKUP(A40,'TB for financial'!A:B,2,0) -> Interest income on Cash at Bank-Other | C40: Other income | D40: 704040 | E40: =-VLOOKUP(A40,'TB for financial'!A:F,6,0) -> -4094148.5 | G40: =-VLOOKUP(A40,'TB for financial'!A:K,11,0) -> 15878069 | H40: 704040 | I40: -13661470 | J40: 0 | K40: 0 | L40: 0 | M40: 0 | N40: =+J40+K40 -> 0 | O40: =+E40-N40 -> -4094148.5
A41: 704670 | B41: =VLOOKUP(A41,'TB for financial'!A:B,2,0) -> Other Financial Income | C41: Other income | E41: =-VLOOKUP(A41,'TB for financial'!A:F,6,0) -> 0 | G41: =-VLOOKUP(A41,'TB for financial'!A:K,11,0) -> 20393931
A42: 762510 | B42: =VLOOKUP(A42,'TB for financial'!A:B,2,0) -> Int Income-Personal Loan | C42: Other income | D42: 762510 | E42: =-VLOOKUP(A42,'TB for financial'!A:F,6,0) -> 6928 | G42: =-VLOOKUP(A42,'TB for financial'!A:K,11,0) -> 5679 | H42: 762510 | I42: -2167 | J42: 0 | K42: 0 | L42: 0 | M42: 0 | N42: =+J42+K42 -> 0 | O42: =+E42-N42 -> 6928
A43: 762511 | B43: =VLOOKUP(A43,'TB for financial'!A:B,2,0) -> Interest Income-Deposits | C43: Other income | D43: 762511 | E43: =-VLOOKUP(A43,'TB for financial'!A:F,6,0) -> 217626.97 | G43: =-VLOOKUP(A43,'TB for financial'!A:K,11,0) -> 188322.99 | H43: 762511 | I43: -304021.7
A44: 664011 | B44: =VLOOKUP(A44,'TB for financial'!A:B,2,0) -> Financial interests on lease liability Real estate | C44: Finance costs | D44: 664011 | E44: =VLOOKUP(A44,'TB for financial'!A:F,6,0) -> 401655.69 | G44: =VLOOKUP(A44,'TB for financial'!A:K,11,0) -> 638521.58 | H44: 664011 | I44: 180595.34
A45: 764501 | B45: FIN INC TERM DEPO | C45: Finance costs | E45: =-VLOOKUP(A45,'TB for financial'!A:F,6,0) -> 19689988
B47: Other Income | E47: =SUM(E26:E46) -> 16222051 | G47: =SUM(G26:G46) -> 37104524 | J47: =SUM(J26:J46) -> 6300636.7 | K47: =SUM(K26:K46) -> 1497045.1 | L47: =SUM(L26:L46) -> 0 | M47: =SUM(M26:M46) -> 0 | N47: =SUM(N26:N46) -> 7797681.8 | O47: =SUM(O26:O46) -> -11884902
A49: 500010 | B49: =VLOOKUP(A49,'TB for financial'!A:B,2,0) -> Payroll - Corporate | C49: Employee benefits expenses | E49: =VLOOKUP(A49,'TB for financial'!A:F,6,0) -> 0 | G49: =VLOOKUP(A49,'TB for financial'!A:K,11,0) -> 0 | H49: 500010 | I49: 0 | J49: 0 | K49: 0 | L49: 0 | M49: 0 | N49: =+J49+K49 -> 0 | O49: =+E49-N49 -> 0
A50: 500080 | B50: =VLOOKUP(A50,'TB for financial'!A:B,2,0) -> Payroll - Encash. of Earned Leave | C50: Employee benefits expenses | D50: 500080 | E50: =VLOOKUP(A50,'TB for financial'!A:F,6,0) -> 0 | G50: =VLOOKUP(A50,'TB for financial'!A:K,11,0) -> 0 | H50: 500080 | I50: -62541 | J50: -67537 | K50: 59754 | L50: 0 | M50: 0 | N50: =+J50+K50 -> -7783 | O50: =+E50-N50 -> 7783 | P50: 500080
A51: 500015 | B51: =VLOOKUP(A51,'TB for financial'!A:B,2,0) -> Payroll - Consultants | C51: Employee benefits expenses | E51: =VLOOKUP(A51,'TB for financial'!A:F,6,0) -> 0 | G51: =VLOOKUP(A51,'TB for financial'!A:K,11,0) -> 0 | H51: #N/A | I51: #N/A | J51: 0 | K51: 0 | L51: 0 | M51: 0 | N51: =+J51+K51 -> 0 | O51: =+E51-N51 -> 0
A52: 500020 | B52: =VLOOKUP(A52,'TB for financial'!A:B,2,0) -> City Allowance | C52: Employee benefits expenses | E52: =VLOOKUP(A52,'TB for financial'!A:F,6,0) -> 0 | G52: =VLOOKUP(A52,'TB for financial'!A:K,11,0) -> 0 | H52: #N/A | I52: #N/A | J52: 0 | K52: 0 | L52: 0 | M52: 0 | N52: =+J52+K52 -> 0 | O52: =+E52-N52 -> 0
A53: 500025 | B53: =VLOOKUP(A53,'TB for financial'!A:B,2,0) -> Payroll - Vacation | C53: Employee benefits expenses | E53: =VLOOKUP(A53,'TB for financial'!A:F,6,0) -> 0 | G53: =VLOOKUP(A53,'TB for financial'!A:K,11,0) -> 0 | H53: #N/A | I53: #N/A | J53: 0 | K53: 0 | L53: 0 | M53: 0 | N53: =+J53+K53 -> 0 | O53: =+E53-N53 -> 0
A54: 500026 | B54: =VLOOKUP(A54,'TB for financial'!A:B,2,0) -> Payroll - Cost Deferral | C54: Employee benefits expenses | E54: =VLOOKUP(A54,'TB for financial'!A:F,6,0) -> 0 | G54: =VLOOKUP(A54,'TB for financial'!A:K,11,0) -> 0 | H54: 500026 | I54: 0 | J54: 0 | K54: 0 | L54: 0 | M54: 0 | N54: =+J54+K54 -> 0 | O54: =+E54-N54 -> 0
A55: 500030 | B55: =VLOOKUP(A55,'TB for financial'!A:B,2,0) -> Payroll - Retro Payments | C55: Employee benefits expenses | E55: =VLOOKUP(A55,'TB for financial'!A:F,6,0) -> 0 | G55: =VLOOKUP(A55,'TB for financial'!A:K,11,0) -> 0 | H55: #N/A | I55: #N/A | J55: 0 | K55: 0 | L55: 0 | M55: 0 | N55: =+J55+K55 -> 0 | O55: =+E55-N55 -> 0
A56: 500035 | B56: =VLOOKUP(A56,'TB for financial'!A:B,2,0) -> Payroll - Restricted Stock | C56: Employee benefits expenses | E56: =VLOOKUP(A56,'TB for financial'!A:F,6,0) -> 0 | G56: =VLOOKUP(A56,'TB for financial'!A:K,11,0) -> 0 | H56: #N/A | I56: #N/A | J56: 0 | K56: 0 | L56: 0 | M56: 0 | N56: =+J56+K56 -> 0 | O56: =+E56-N56 -> 0
A57: 500036 | B57: =VLOOKUP(A57,'TB for financial'!A:B,2,0) -> FAS 123R expenses | C57: Employee benefits expenses | E57: =VLOOKUP(A57,'TB for financial'!A:F,6,0) -> 0 | G57: =VLOOKUP(A57,'TB for financial'!A:K,11,0) -> 0 | H57: #N/A | I57: #N/A | J57: 0 | K57: 0 | L57: 0 | M57: 0 | N57: =+J57+K57 -> 0 | O57: =+E57-N57 -> 0
A58: 500040 | B58: =VLOOKUP(A58,'TB for financial'!A:B,2,0) -> Payroll - Overtime | C58: Employee benefits expenses | E58: =VLOOKUP(A58,'TB for financial'!A:F,6,0) -> 0 | G58: =VLOOKUP(A58,'TB for financial'!A:K,11,0) -> 0 | H58: #N/A | I58: #N/A | J58: 0 | K58: 0 | L58: 0 | M58: 0 | N58: =+J58+K58 -> 0 | O58: =+E58-N58 -> 0
A59: 500060 | B59: =VLOOKUP(A59,'TB for financial'!A:B,2,0) -> Payroll - Misc Bonuses | C59: Employee benefits expenses | E59: =VLOOKUP(A59,'TB for financial'!A:F,6,0) -> 0 | G59: =VLOOKUP(A59,'TB for financial'!A:K,11,0) -> 0 | H59: 500060 | I59: 0 | J59: 0 | K59: 0 | L59: 0 | M59: 0 | N59: =+J59+K59 -> 0 | O59: =+E59-N59 -> 0
A60: 500065 | B60: =VLOOKUP(A60,'TB for financial'!A:B,2,0) -> Payroll - Management Bonuses | C60: Employee benefits expenses | E60: =VLOOKUP(A60,'TB for financial'!A:F,6,0) -> 0 | G60: =VLOOKUP(A60,'TB for financial'!A:K,11,0) -> 0 | H60: #N/A | I60: #N/A | J60: 0 | K60: 0 | L60: 0 | M60: 0 | N60: =+J60+K60 -> 0 | O60: =+E60-N60 -> 0
A61: 500077 | B61: =VLOOKUP(A61,'TB for financial'!A:B,2,0) -> Payroll - Recovered | C61: Employee benefits expenses | E61: =VLOOKUP(A61,'TB for financial'!A:F,6,0) -> 0 | G61: =VLOOKUP(A61,'TB for financial'!A:K,11,0) -> 0 | H61: #N/A | I61: #N/A | J61: 0 | K61: 0 | L61: 0 | M61: 0 | N61: =+J61+K61 -> 0 | O61: =+E61-N61 -> 0
A62: 500078 | B62: =VLOOKUP(A62,'TB for financial'!A:B,2,0) -> Payroll - Notice Period Reimb. | C62: Employee benefits expenses | E62: =VLOOKUP(A62,'TB for financial'!A:F,6,0) -> 0 | G62: =VLOOKUP(A62,'TB for financial'!A:K,11,0) -> 0 | H62: 500078 | I62: 0 | J62: 0 | K62: 0 | L62: 0 | M62: 0 | N62: =+J62+K62 -> 0 | O62: =+E62-N62 -> 0
A63: 500079 | B63: =VLOOKUP(A63,'TB for financial'!A:B,2,0) -> Payroll - Notice Pay Recovery | C63: Employee benefits expenses | E63: =VLOOKUP(A63,'TB for financial'!A:F,6,0) -> 0 | G63: =VLOOKUP(A63,'TB for financial'!A:K,11,0) -> 0 | H63: 500079 | I63: 0 | J63: 0 | K63: 0 | L63: 0 | M63: 0 | N63: =+J63+K63 -> 0 | O63: =+E63-N63 -> 0 | P63: 500079 | Q63: Payroll IGAAP Entry | R63: =+E63-Q63 -> #VALUE!
A64: 500081 | B64: =VLOOKUP(A64,'TB for financial'!A:B,2,0) -> Payroll - Gratuity | C64: Employee benefits expenses | D64: 500081 | E64: =VLOOKUP(A64,'TB for financial'!A:F,6,0) -> 0 | G64: =VLOOKUP(A64,'TB for financial'!A:K,11,0) -> 0 | H64: 500081 | I64: 348503.66 | J64: 380564 | K64: 111858 | L64: 0 | M64: 0 | N64: =+J64+K64 -> 492422 | O64: =+E64-N64 -> -492422 | P64: 500081
A65: 500082 | B65: =VLOOKUP(A65,'TB for financial'!A:B,2,0) -> Payroll - P.F. Allowance | C65: Employee benefits expenses | E65: =VLOOKUP(A65,'TB for financial'!A:F,6,0) -> 0 | G65: =VLOOKUP(A65,'TB for financial'!A:K,11,0) -> 0 | H65: #N/A | I65: #N/A | J65: 0 | K65: 0 | L65: 0 | M65: 0 | N65: =+J65+K65 -> 0 | O65: =+E65-N65 -> 0
A66: 500083 | B66: =VLOOKUP(A66,'TB for financial'!A:B,2,0) -> Payroll - Salary & Allowances | C66: Employee benefits expenses | D66: 500083 | E66: =VLOOKUP(A66,'TB for financial'!A:F,6,0) -> 0 | G66: =VLOOKUP(A66,'TB for financial'!A:K,11,0) -> 0 | H66: 500083 | I66: 5348214 | J66: 6232827 | K66: 2478224 | L66: 0 | M66: 0 | N66: =+J66+K66 -> 8711051 | O66: =+E66-N66 -> -8711051 | P66: 500083 | Q66: #N/A | R66: =+E66-Q66 -> #N/A
A67: 500084 | B67: =VLOOKUP(A67,'TB for financial'!A:B,2,0) -> Payroll - Med. & Trans. Allow. | C67: Employee benefits expenses | E67: =VLOOKUP(A67,'TB for financial'!A:F,6,0) -> 0 | G67: =VLOOKUP(A67,'TB for financial'!A:K,11,0) -> 0 | H67: 500084 | I67: 0 | J67: -36 | K67: 0 | L67: 0 | M67: 0 | N67: =+J67+K67 -> -36 | O67: =+E67-N67 -> 36 | P67: 500084 | Q67: #N/A | R67: =+E67-Q67 -> #N/A
A68: 500085 | B68: =VLOOKUP(A68,'TB for financial'!A:B,2,0) -> Payroll - Special Allowance | C68: Employee benefits expenses | E68: =VLOOKUP(A68,'TB for financial'!A:F,6,0) -> 0 | G68: =VLOOKUP(A68,'TB for financial'!A:K,11,0) -> 0 | H68: #N/A | I68: #N/A | J68: 0 | K68: 0 | L68: 0 | M68: 0 | N68: =+J68+K68 -> 0 | O68: =+E68-N68 -> 0
A69: 500086 | B69: =VLOOKUP(A69,'TB for financial'!A:B,2,0) -> Payroll - House Rent Allowance | C69: Employee benefits expenses | E69: =VLOOKUP(A69,'TB for financial'!A:F,6,0) -> 0 | G69: =VLOOKUP(A69,'TB for financial'!A:K,11,0) -> 0 | H69: #N/A | I69: #N/A | J69: 0 | K69: 0 | L69: 0 | M69: 0 | N69: =+J69+K69 -> 0 | O69: =+E69-N69 -> 0
A70: 500087 | B70: =VLOOKUP(A70,'TB for financial'!A:B,2,0) -> Payroll - Incentives | C70: Employee benefits expenses | D70: 500087 | E70: =VLOOKUP(A70,'TB for financial'!A:F,6,0) -> 0 | G70: =VLOOKUP(A70,'TB for financial'!A:K,11,0) -> 0 | H70: 500087 | I70: 631955 | J70: 187259 | K70: -20038 | L70: 0 | M70: 0 | N70: =+J70+K70 -> 167221 | O70: =+E70-N70 -> -167221 | P70: 500087 | Q70: #N/A | R70: =+E70-Q70 -> #N/A
A71: 500088 | B71: =VLOOKUP(A71,'TB for financial'!A:B,2,0) -> Payroll - Leave Travel Allowance | C71: Employee benefits expenses | D71: 500088 | E71: =VLOOKUP(A71,'TB for financial'!A:F,6,0) -> 0 | G71: =VLOOKUP(A71,'TB for financial'!A:K,11,0) -> 0 | H71: 500088 | I71: 4 | J71: -157.51 | K71: 0 | L71: 0 | M71: 0 | N71: =+J71+K71 -> -157.51 | O71: =+E71-N71 -> 157.51 | P71: 500088 | Q71: #N/A | R71: =+E71-Q71 -> #N/A
A72: 500090 | B72: =VLOOKUP(A72,'TB for financial'!A:B,2,0) -> Payroll - Other Payments | C72: Employee benefits expenses | D72: 500090 | E72: =VLOOKUP(A72,'TB for financial'!A:F,6,0) -> 0 | G72: =VLOOKUP(A72,'TB for financial'!A:K,11,0) -> 0 | H72: 500090 | I72: 59350 | J72: 73574 | K72: 34433 | L72: 0 | M72: 0 | N72: =+J72+K72 -> 108007 | O72: =+E72-N72 -> -108007 | P72: 500090 | Q72: Payroll IGAAP Entry | R72: =+E72-Q72 -> #VALUE!
A73: 500091 | B73: =VLOOKUP(A73,'TB for financial'!A:B,2,0) -> Payroll - Technical Allowances | C73: Employee benefits expenses | E73: =VLOOKUP(A73,'TB for financial'!A:F,6,0) -> 0 | G73: =VLOOKUP(A73,'TB for financial'!A:K,11,0) -> 0 | H73: #N/A | I73: #N/A | J73: 0 | K73: 0 | L73: 0 | M73: 0 | N73: =+J73+K73 -> 0 | O73: =+E73-N73 -> 0
A74: 500092 | B74: =VLOOKUP(A74,'TB for financial'!A:B,2,0) -> Payroll - Bond Recovery | C74: Employee benefits expenses | E74: =VLOOKUP(A74,'TB for financial'!A:F,6,0) -> 0 | G74: =VLOOKUP(A74,'TB for financial'!A:K,11,0) -> 0 | H74: 500092 | I74: 0 | J74: 0 | K74: 0 | L74: 0 | M74: 0 | N74: =+J74+K74 -> 0 | O74: =+E74-N74 -> 0 | P74: 500092 | Q74: Payroll IGAAP Entry | R74: =+E74-Q74 -> #VALUE!
A75: 500093 | B75: =VLOOKUP(A75,'TB for financial'!A:B,2,0) -> Payroll - Transport A | C75: Employee benefits expenses | E75: =VLOOKUP(A75,'TB for financial'!A:F,6,0) -> 0 | G75: =VLOOKUP(A75,'TB for financial'!A:K,11,0) -> 0 | H75: 500093 | I75: 0 | J75: -47 | K75: 0 | L75: 0 | M75: 0 | N75: =+J75+K75 -> -47 | O75: =+E75-N75 -> 47 | P75: 500093 | Q75: #N/A | R75: =+E75-Q75 -> #N/A
A76: 500094 | B76: =VLOOKUP(A76,'TB for financial'!A:B,2,0) -> Payroll - Meal Alloawnce | C76: Employee benefits expenses | D76: 500094 | E76: =VLOOKUP(A76,'TB for financial'!A:F,6,0) -> 0 | G76: =VLOOKUP(A76,'TB for financial'!A:K,11,0) -> 0 | H76: 500094 | I76: 19800 | J76: 15356 | K76: 3300 | L76: 0 | M76: 0 | N76: =+J76+K76 -> 18656 | O76: =+E76-N76 -> -18656 | P76: 500094 | Q76: #N/A | R76: =+E76-Q76 -> #N/A
A77: 500100 | B77: =VLOOKUP(A77,'TB for financial'!A:B,2,0) -> Payroll - Troy | C77: Employee benefits expenses | E77: =VLOOKUP(A77,'TB for financial'!A:F,6,0) -> 0 | G77: =VLOOKUP(A77,'TB for financial'!A:K,11,0) -> 0 | H77: 500100 | I77: 0 | J77: 0 | K77: 0 | L77: 0 | M77: 0 | N77: =+J77+K77 -> 0 | O77: =+E77-N77 -> 0
A78: 500101 | B78: =VLOOKUP(A78,'TB for financial'!A:B,2,0) -> Payroll - Bonus Leadership | C78: Employee benefits expenses | E78: =VLOOKUP(A78,'TB for financial'!A:F,6,0) -> 0 | G78: =VLOOKUP(A78,'TB for financial'!A:K,11,0) -> 0 | H78: #N/A | I78: #N/A | J78: 0 | K78: 0 | L78: 0 | M78: 0 | N78: =+J78+K78 -> 0 | O78: =+E78-N78 -> 0
A79: 500102 | B79: =VLOOKUP(A79,'TB for financial'!A:B,2,0) -> Payroll - Bonus Vertical Team | C79: Employee benefits expenses | E79: =VLOOKUP(A79,'TB for financial'!A:F,6,0) -> 0 | G79: =VLOOKUP(A79,'TB for financial'!A:K,11,0) -> 0 | H79: #N/A | I79: #N/A | J79: 0 | K79: 0 | L79: 0 | M79: 0 | N79: =+J79+K79 -> 0 | O79: =+E79-N79 -> 0
A80: 500103 | B80: =VLOOKUP(A80,'TB for financial'!A:B,2,0) -> Payroll - Bonus Practice Team | C80: Employee benefits expenses | E80: =VLOOKUP(A80,'TB for financial'!A:F,6,0) -> 0 | G80: =VLOOKUP(A80,'TB for financial'!A:K,11,0) -> 0 | H80: #N/A | I80: #N/A | J80: 0 | K80: 0 | L80: 0 | M80: 0 | N80: =+J80+K80 -> 0 | O80: =+E80-N80 -> 0
A81: 500104 | B81: =VLOOKUP(A81,'TB for financial'!A:B,2,0) -> Payroll - Bonus Engagement Mgr | C81: Employee benefits expenses | E81: =VLOOKUP(A81,'TB for financial'!A:F,6,0) -> 0 | G81: =VLOOKUP(A81,'TB for financial'!A:K,11,0) -> 0 | H81: #N/A | I81: #N/A | J81: 0 | K81: 0 | L81: 0 | M81: 0 | N81: =+J81+K81 -> 0 | O81: =+E81-N81 -> 0
A82: 500105 | B82: =VLOOKUP(A82,'TB for financial'!A:B,2,0) -> Payroll - Bonus TIA for Revenu | C82: Employee benefits expenses | E82: =VLOOKUP(A82,'TB for financial'!A:F,6,0) -> 0 | G82: =VLOOKUP(A82,'TB for financial'!A:K,11,0) -> 0 | H82: #N/A | I82: #N/A | J82: 0 | K82: 0 | L82: 0 | M82: 0 | N82: =+J82+K82 -> 0 | O82: =+E82-N82 -> 0
A83: 500106 | B83: =VLOOKUP(A83,'TB for financial'!A:B,2,0) -> Payroll - Bonus TIA for TCV | C83: Employee benefits expenses | E83: =VLOOKUP(A83,'TB for financial'!A:F,6,0) -> 0 | G83: =VLOOKUP(A83,'TB for financial'!A:K,11,0) -> 0 | H83: #N/A | I83: #N/A | J83: 0 | K83: 0 | L83: 0 | M83: 0 | N83: =+J83+K83 -> 0 | O83: =+E83-N83 -> 0
A84: 500107 | B84: =VLOOKUP(A84,'TB for financial'!A:B,2,0) -> Payroll - Bonus Billable | C84: Employee benefits expenses | E84: =VLOOKUP(A84,'TB for financial'!A:F,6,0) -> 0 | G84: =VLOOKUP(A84,'TB for financial'!A:K,11,0) -> 0 | H84: #N/A | I84: #N/A | J84: 0 | K84: 0 | L84: 0 | M84: 0 | N84: =+J84+K84 -> 0 | O84: =+E84-N84 -> 0
A85: 500108 | B85: =VLOOKUP(A85,'TB for financial'!A:B,2,0) -> Payroll - Bonus Corporate | C85: Employee benefits expenses | E85: =VLOOKUP(A85,'TB for financial'!A:F,6,0) -> 0 | G85: =VLOOKUP(A85,'TB for financial'!A:K,11,0) -> 0 | H85: #N/A | I85: #N/A | J85: 0 | K85: 0 | L85: 0 | M85: 0 | N85: =+J85+K85 -> 0 | O85: =+E85-N85 -> 0
A86: 500109 | B86: =VLOOKUP(A86,'TB for financial'!A:B,2,0) -> Payroll - Bonus Others | C86: Employee benefits expenses | D86: 500109 | E86: =VLOOKUP(A86,'TB for financial'!A:F,6,0) -> 0 | G86: =VLOOKUP(A86,'TB for financial'!A:K,11,0) -> 0 | H86: 500109 | I86: 23022 | J86: 21592 | K86: 8622 | L86: 0 | M86: 0 | N86: =+J86+K86 -> 30214 | O86: =+E86-N86 -> -30214 | P86: 500109 | Q86: #N/A | R86: =+E86-Q86 -> #N/A
A87: 500110 | B87: =VLOOKUP(A87,'TB for financial'!A:B,2,0) -> Payroll - Bonus CEO | C87: Employee benefits expenses | E87: =VLOOKUP(A87,'TB for financial'!A:F,6,0) -> 0 | G87: =VLOOKUP(A87,'TB for financial'!A:K,11,0) -> 0 | H87: #N/A | I87: #N/A | J87: 0 | K87: 0 | L87: 0 | M87: 0 | N87: =+J87+K87 -> 0 | O87: =+E87-N87 -> 0
A88: 500111 | B88: =VLOOKUP(A88,'TB for financial'!A:B,2,0) -> Payroll - Awards | C88: Employee benefits expenses | D88: 500111 | E88: =VLOOKUP(A88,'TB for financial'!A:F,6,0) -> 0 | G88: =VLOOKUP(A88,'TB for financial'!A:K,11,0) -> 0 | H88: 500111 | I88: 40256 | J88: 57190 | K88: -36507 | L88: 0 | M88: 0 | N88: =+J88+K88 -> 20683 | O88: =+E88-N88 -> -20683 | P88: 500111 | Q88: #N/A | R88: =+E88-Q88 -> #N/A
A89: 500114 | B89: =VLOOKUP(A89,'TB for financial'!A:B,2,0) -> HCA Billable Bonus | C89: Employee benefits expenses | E89: =VLOOKUP(A89,'TB for financial'!A:F,6,0) -> 0 | G89: =VLOOKUP(A89,'TB for financial'!A:K,11,0) -> 0 | H89: #N/A | I89: #N/A | J89: 0 | K89: 0 | L89: 0 | M89: 0 | N89: =+J89+K89 -> 0 | O89: =+E89-N89 -> 0
A90: 500115 | B90: =VLOOKUP(A90,'TB for financial'!A:B,2,0) -> Increment - Comp/Bonus | C90: Employee benefits expenses | E90: =VLOOKUP(A90,'TB for financial'!A:F,6,0) -> 0 | G90: =VLOOKUP(A90,'TB for financial'!A:K,11,0) -> 0 | H90: #N/A | I90: #N/A | J90: 0 | K90: 0 | L90: 0 | M90: 0 | N90: =+J90+K90 -> 0 | O90: =+E90-N90 -> 0
A91: 500117 | B91: =VLOOKUP(A91,'TB for financial'!A:B,2,0) -> Payroll Long term incentive Plan | C91: Employee benefits expenses | E91: =VLOOKUP(A91,'TB for financial'!A:F,6,0) -> 0 | G91: =VLOOKUP(A91,'TB for financial'!A:K,11,0) -> 0 | H91: #N/A | I91: #N/A | J91: 0 | K91: 0 | L91: 0 | M91: 0 | N91: =+J91+K91 -> 0 | O91: =+E91-N91 -> 0
A92: 500123 | B92: =VLOOKUP(A92,'TB for financial'!A:B,2,0) -> Employee Referral Bonus Comp | C92: Employee benefits expenses | E92: =VLOOKUP(A92,'TB for financial'!A:F,6,0) -> 0 | G92: =VLOOKUP(A92,'TB for financial'!A:K,11,0) -> 0 | H92: #N/A | I92: #N/A | J92: 0 | K92: 0 | L92: 0 | M92: 0 | N92: =+J92+K92 -> 0 | O92: =+E92-N92 -> 0
A93: 641100 | B93: =VLOOKUP(A93,'TB for financial'!A:B,2,0) -> WAGES AND SALARIES | C93: Employee benefits expenses | D93: 641100 | E93: =VLOOKUP(A93,'TB for financial'!A:F,6,0) -> 2194721 | G93: =VLOOKUP(A93,'TB for financial'!A:K,11,0) -> 836707 | H93: 641100 | I93: -99059 | J93: 0 | K93: 0 | L93: 0 | M93: 0 | N93: =+J93+K93 -> 0 | O93: =+E93-N93 -> 2194721
A94: 641111 | B94: SHIFT ALLOWANCES | C94: Employee benefits expenses | E94: =VLOOKUP(A94,'TB for financial'!A:F,6,0) -> 21600 | G94: =VLOOKUP(A94,'TB for financial'!A:K,11,0) -> 4250
A95: 641203 | B95: =VLOOKUP(A95,'TB for financial'!A:B,2,0) -> VACATION LEAVE PAYMENTS - GEN&ADM | C95: Employee benefits expenses | D95: 641203 | E95: =VLOOKUP(A95,'TB for financial'!A:F,6,0) -> 54162 | G95: =VLOOKUP(A95,'TB for financial'!A:K,11,0) -> 43143 | H95: 641203 | I95: 37421 | J95: 0 | K95: 0 | L95: 0 | M95: 0 | N95: =+J95+K95 -> 0 | O95: =+E95-N95 -> 54162
A96: 641300 | B96: =VLOOKUP(A96,'TB for financial'!A:B,2,0) -> INCENTIVE WAGES AND BONUSES | C96: Employee benefits expenses | D96: 641300 | E96: =VLOOKUP(A96,'TB for financial'!A:F,6,0) -> 276811 | G96: =VLOOKUP(A96,'TB for financial'!A:K,11,0) -> 531646.71 | H96: 641300 | I96: -351550 | J96: 0 | K96: 0 | L96: 0 | M96: 0 | N96: =+J96+K96 -> 0 | O96: =+E96-N96 -> 276811
A97: 641310 | B97: =VLOOKUP(A97,'TB for financial'!A:B,2,0) -> YEAR-END BONUSES | C97: Employee benefits expenses | D97: 641310 | E97: =VLOOKUP(A97,'TB for financial'!A:F,6,0) -> 0 | G97: =VLOOKUP(A97,'TB for financial'!A:K,11,0) -> 0 | H97: 641310 | I97: 0 | J97: 0 | K97: 0 | L97: 0 | M97: 0 | N97: =+J97+K97 -> 0 | O97: =+E97-N97 -> 0
A98: 641404 | B98: HOUSING ALLOWANCE | C98: Employee benefits expenses | E98: =VLOOKUP(A98,'TB for financial'!A:F,6,0) -> 378582 | G98: =VLOOKUP(A98,'TB for financial'!A:K,11,0) -> 61908
A99: 641702 | B99: =VLOOKUP(A99,'TB for financial'!A:B,2,0) -> Allowance 2 | C99: Employee benefits expenses | D99: 641702 | E99: =VLOOKUP(A99,'TB for financial'!A:F,6,0) -> 3461072 | G99: =VLOOKUP(A99,'TB for financial'!A:K,11,0) -> 6502081 | H99: 641702 | I99: -5095246 | J99: 0 | K99: 0 | L99: 0 | M99: 0 | N99: =+J99+K99 -> 0 | O99: =+E99-N99 -> 3461072
A100: 641711 | B100: =VLOOKUP(A100,'TB for financial'!A:B,2,0) -> Gratuity | C100: Employee benefits expenses | D100: 641711 | E100: =VLOOKUP(A100,'TB for financial'!A:F,6,0) -> 248295 | G100: =VLOOKUP(A100,'TB for financial'!A:K,11,0) -> 293948 | H100: 641711 | I100: -344035 | J100: 0 | K100: 0 | L100: 0 | M100: 0 | N100: =+J100+K100 -> 0 | O100: =+E100-N100 -> 248295
A101: 658013 | B101: =VLOOKUP(A101,'TB for financial'!A:B,2,0) -> Compensation Awards | C101: Employee benefits expenses | D101: 658013 | E101: =VLOOKUP(A101,'TB for financial'!A:F,6,0) -> 17829 | G101: =VLOOKUP(A101,'TB for financial'!A:K,11,0) -> 23000 | H101: 658013 | I101: 49059 | J101: 0 | K101: 0 | L101: 0 | M101: 0 | N101: =+J101+K101 -> 0 | O101: =+E101-N101 -> 17829
A102: 641704 | B102: =VLOOKUP(A102,'TB for financial'!A:B,2,0) -> LTA | C102: Employee benefits expenses | D102: 658013 | E102: =VLOOKUP(A102,'TB for financial'!A:F,6,0) -> 6250 | G102: =VLOOKUP(A102,'TB for financial'!A:K,11,0) -> 18750 | H102: 641704
B104: Salaries | E104: =SUM(E48:E103) -> 6659322 | G104: =SUM(G48:G103) -> 8315433.7 | J104: =SUM(J48:J103) -> 6900584.5 | K104: =SUM(K48:K103) -> 2639646 | L104: =SUM(L48:L103) -> 0 | M104: =SUM(M48:M103) -> 0 | N104: =SUM(N48:N103) -> 9540230.5 | O104: =SUM(O48:O103) -> -3287340.5
A106: 501110 | B106: =VLOOKUP(A106,'TB for financial'!A:B,2,0) -> Payroll Taxes | C106: Employee benefits expenses | E106: =VLOOKUP(A106,'TB for financial'!A:F,6,0) -> 0 | G106: =VLOOKUP(A106,'TB for financial'!A:K,11,0) -> 0 | H106: 501110 | I106: 0 | J106: 0 | K106: 0 | L106: 0 | M106: 0 | N106: =+J106+K106 -> 0 | O106: =+E106-N106 -> 0
A107: 501111 | B107: =VLOOKUP(A107,'TB for financial'!A:B,2,0) -> Payroll-Tax on Perquisites | C107: Employee benefits expenses | E107: =VLOOKUP(A107,'TB for financial'!A:F,6,0) -> 0 | G107: =VLOOKUP(A107,'TB for financial'!A:K,11,0) -> 0 | H107: 501111 | I107: 0 | J107: 0 | K107: 0 | L107: 0 | M107: 0 | N107: =+J107+K107 -> 0 | O107: =+E107-N107 -> 0 | P107: 501111 | Q107: Payroll IGAAP Entry | R107: =+E107-Q107 -> #VALUE!
A108: 501115 | B108: =VLOOKUP(A108,'TB for financial'!A:B,2,0) -> Health Insurance | C108: Employee benefits expenses | D108: 501115 | E108: =VLOOKUP(A108,'TB for financial'!A:F,6,0) -> 0 | G108: =VLOOKUP(A108,'TB for financial'!A:K,11,0) -> 0 | H108: 501115 | I108: 120842.15 | J108: 19751.004 | K108: 21481.64 | L108: 0 | M108: 0 | N108: =+J108+K108 -> 41232.644 | O108: =+E108-N108 -> -41232.644 | P108: 501115 | Q108: #N/A | R108: =+E108-Q108 -> #N/A
A109: 501116 | B109: =VLOOKUP(A109,'TB for financial'!A:B,2,0) -> Accident Insurance | C109: Employee benefits expenses | E109: =VLOOKUP(A109,'TB for financial'!A:F,6,0) -> 0 | G109: =VLOOKUP(A109,'TB for financial'!A:K,11,0) -> 0 | H109: #N/A | I109: #N/A | J109: 0 | K109: 0 | L109: 0 | M109: 0 | N109: =+J109+K109 -> 0 | O109: =+E109-N109 -> 0
A110: 501117 | B110: =VLOOKUP(A110,'TB for financial'!A:B,2,0) -> Life Insurance | C110: Employee benefits expenses | E110: =VLOOKUP(A110,'TB for financial'!A:F,6,0) -> 0 | G110: =VLOOKUP(A110,'TB for financial'!A:K,11,0) -> 0 | H110: #N/A | I110: #N/A | J110: 0 | K110: 0 | L110: 0 | M110: 0 | N110: =+J110+K110 -> 0 | O110: =+E110-N110 -> 0
...

Sheet Macro1

Sheet Sch - PL
A1: =+Master!$B$2 -> Syntel Solutions (India) Private Limited
A2: ="Notes forming part of financial statements for the period ended " &Master!$B$5 -> Notes forming part of financial statements for the period ended 31st March 2025
G4: =+Master!B24 -> (Rs.)
E5: =+Master!$B$7 -> 2025 | G5: =+Master!$B$13 -> 2024
A6: Revenue
A7: Revenue | E7: =ROUND(('PL Gr'!E18)/Master!$B$23,0)+ROUND(('PL Gr'!E20)/Master!$B$23,0) -> 10984519 | G7: =ROUND(('PL Gr'!G18)/Master!$B$23,0)+ROUND(('PL Gr'!G20)/Master!$B$23,0) -> 14480207
A8: Other operating income | E8: =ROUND(('PL Gr'!E24)/Master!$B$23,0)-ROUND(('PL Gr'!E20)/Master!$B$23,0) -> 0 | G8: =ROUND(('PL Gr'!G24)/Master!$B$23,0)-ROUND(('PL Gr'!G20)/Master!$B$23,0) -> 0
E10: =SUM(E6:E9) -> 10984519 | G10: =SUM(G6:G9) -> 14480207
A12: Gain(Loss) on Exchange Fluctation
A14: Exchange gain(loss) - notional
A15: Exchange gain(loss) - actual | E15: =-(-ROUND(('PL Gr'!E414+'PL Gr'!E418+'PL Gr'!E420+'PL Gr'!E421+'PL Gr'!E422+'PL Gr'!E423)/Master!$B$23,0)-ROUND(('PL Gr'!E415+'PL Gr'!E419+'PL Gr'!E424+'PL Gr'!E425+'PL Gr'!E426)/Master!$B$23,0)) -> 83032
A16: Exchange gain(loss) - derivatives | E16: =ROUND('PL Gr'!E417/Master!$B$23,0) -> 0 | G16: =ROUND('PL Gr'!G417/Master!$B$23,0) -> 0
A18: Total | E18: =SUM(E13:E17) -> 83032 | G18: =SUM(G13:G17) -> 0
A22: Other Income
A23: Interest Income
A24: Bank Deposit and income tax refund | E24: =ROUND(SUM('PL Gr'!E26+'PL Gr'!E27+'PL Gr'!E32+'PL Gr'!E40+'PL Gr'!E42+'PL Gr'!E45)/Master!$B$23,0) -> 15602768 | G24: =ROUND(SUM('PL Gr'!G26+'PL Gr'!G27+'PL Gr'!G32+'PL Gr'!G40+'PL Gr'!G42)/Master!$B$23,0) -> 15883748
A25: Unwinding of discount on security deposits | E25: =ROUND(('PL Gr'!E38+'PL Gr'!E43)/Master!$B$23,0) -> 217627 | G25: =ROUND(('PL Gr'!G38+'PL Gr'!G43)/Master!$B$23,0) -> 188323
A26: Others | E26: =ROUND('PL Gr'!E35/Master!$B$23,0) -> 0 | G26: =ROUND('PL Gr'!G35/Master!$B$23,0) -> 0
E27: =SUM(E24:E26) -> 15820395 | G27: =SUM(G24:G26) -> 16072071
A28: Dividend Income
A29: Preference Shares | E29: =ROUND(SUM('PL Gr'!E28+'PL Gr'!E33)/Master!$B$23,0) -> 0 | G29: =ROUND(SUM('PL Gr'!G28+'PL Gr'!G33)/Master!$B$23,0) -> 0
A31: Net Gain (Loss) on sale of Investments
A32: Profit on sale of mutual fund units | E32: =ROUND('PL Gr'!E29/Master!$B$23,0) -> 0 | G32: =ROUND('PL Gr'!G29/Master!$B$23,0) -> 0
A33: Unrealised gain on mutual fund units | E33: =ROUND('PL Gr'!E30/Master!$B$23,0) -> 0 | G33: =ROUND('PL Gr'!G30/Master!$B$23,0) -> 0
A34: Interest income from financial assets at amortised cost | E34: =ROUND('PL Gr'!E34/Master!$B$23,0) -> 0 | G34: =ROUND('PL Gr'!G34/Master!$B$23,0) -> 0
A36: Profit on sale of fixed asset | E36: =IF('PL Gr'!E358>0,ROUND('PL Gr'!E358/Master!$B$23,0),0) -> 0 | G36: =IF('PL Gr'!G358>0,ROUND('PL Gr'!G358/Master!$B$23,0),0) -> 0
A37: Rent Income | E37: =ROUND((+'PL Gr'!E37)/Master!$B$23,0) -> 0 | G37: =ROUND((+'PL Gr'!G37)/Master!$B$23,0) -> 0
A39: Miscellaneous Income | E39: =ROUND(('PL Gr'!E31+'PL Gr'!E41)/Master!$B$23,0) -> 0 | G39: =ROUND(('PL Gr'!G31+'PL Gr'!G41)/Master!$B$23,0) -> 20393931
A41: Total | E41: =SUM(E27:F40) -> 15820395 | G41: =SUM(G27:G40) -> 36466002
A46: Employee benefit expenses
A47: Salary, wages and bonus | E47: =ROUND('PL Gr'!E104/Master!$B$23,0)-E48-E49 -> 6356865 | G47: =ROUND('PL Gr'!G104/Master!$B$23,0)-G48-G49 -> 7978343 | I47: =E47-G47 -> -1621478
A48: Gratuity Expenses | E48: =ROUND(('PL Gr'!E64+'PL Gr'!E100)/Master!$B$23,0) -> 248295 | G48: =ROUND(('PL Gr'!G64+'PL Gr'!G100)/Master!$B$23,0) -> 293948 | I48: =E48-G48 -> -45653
A49: Compensated absences | E49: =ROUND(('PL Gr'!E50+'PL Gr'!E95)/Master!$B$23,0) -> 54162 | G49: =ROUND(('PL Gr'!G50+'PL Gr'!G95)/Master!$B$23,0) -> 43143 | I49: =E49-G49 -> 11019
A50: Contribution to Provident and other funds | E50: =ROUND('PL Gr'!E150/Master!$B$23,0) -> 115383 | G50: =ROUND('PL Gr'!G150/Master!$B$23,0) -> 143256 | I50: =E50-G50 -> -27873
A51: Staff Welfare Expenses | E51: =ROUND('PL Gr'!E134/Master!$B$23,0) -> 293709 | G51: =ROUND('PL Gr'!G134/Master!$B$23,0) -> 248332 | I51: =E51-G51 -> 45377
A53: Total | E53: =SUM(E47:E52) -> 7068414 | G53: =SUM(G47:G52) -> 8707022 | I53: =SUM(I47:I52) -> -1638608
A56: Finance Costs
A57: Bank charges
A58: Interest on shortfall of payment of advance tax
A59: Interest paid
A61: Total | E61: =SUM(E60:E60) -> 0 | G61: =SUM(G60:G60) -> 0
A64: Foreign travel expenses
A65: Foreign living expense | E65: =ROUND('PL Gr'!E291/Master!$B$23,0) -> 0 | G65: =ROUND('PL Gr'!G291/Master!$B$23,0) -> 0 | H65: =E65-G65 -> 0
A66: Onsite Employment Tax | E66: =ROUND('PL Gr'!E292/Master!$B$23,0) -> 0 | G66: =ROUND('PL Gr'!G292/Master!$B$23,0) -> 0 | H66: =E66-G66 -> 0
A67: Foreign travel expense | E67: =ROUND('PL Gr'!E293/Master!$B$23,0) -> 0 | G67: =ROUND('PL Gr'!G293/Master!$B$23,0) -> 0 | H67: =E67-G67 -> 0
A68: Visa Expenses | E68: =ROUND('PL Gr'!E294/Master!$B$23,0) -> 0 | G68: =ROUND('PL Gr'!G294/Master!$B$23,0) -> 0 | H68: =E68-G68 -> 0
A69: Onsite Insurance expense | E69: =ROUND('PL Gr'!E295/Master!$B$23,0) -> 0 | G69: =ROUND('PL Gr'!G295/Master!$B$23,0) -> 0 | H69: =E69-G69 -> 0
A70: Other Expenses | E70: =ROUND('PL Gr'!E296/Master!$B$23,0) -> 0 | G70: =ROUND('PL Gr'!G296/Master!$B$23,0) -> 0 | H70: =E70-G70 -> 0
A72: Total | E72: =SUM(E65:E71) -> 0 | G72: =SUM(G65:G71) -> 0
A75: Technical consultancy charges
A76: Billable Outside Consulting | E76: =ROUND(SUM('PL Gr'!E191:E192)/Master!$B$23,0) -> 0 | G76: =ROUND(SUM('PL Gr'!G191:G192)/Master!$B$23,0) -> 0
A77: Inter-Co. Service charges | E77: =ROUND('PL Gr'!E193/Master!$B$23,0) -> 0 | G77: =ROUND('PL Gr'!G193/Master!$B$23,0) -> 0
A78: Other technical expenses | E78: =ROUND('PL Gr'!E201/Master!$B$23,0)-E77-E76 -> 0 | G78: =ROUND('PL Gr'!G201/Master!$B$23,0)-G77-G76 -> 0
A81: Total | E81: =SUM(E76:E80) -> 0 | G81: =SUM(G76:G80) -> 0
A84: Operating and other expenses
A85: Rent | E85: =ROUND('PL Gr'!E162/Master!$B$23,0) -> 207 | G85: =ROUND('PL Gr'!G162/Master!$B$23,0) -> 26385 | H85: =E85-G85 -> -26178
A86: Rates and Taxes | E86: =ROUND('PL Gr'!E176/Master!$B$23,0)*0 -> 0 | G86: =ROUND('PL Gr'!G176/Master!$B$23,0)*0 -> 0 | H86: =E86-G86 -> 0
A87: Insurance | E87: =ROUND('PL Gr'!E335/Master!$B$23,0)*0 -> 0 | G87: =ROUND('PL Gr'!G335/Master!$B$23,0)*0 -> 0 | H87: =E87-G87 -> 0
A88: Travel and conveyance | E88: =ROUND('PL Gr'!E313/Master!$B$23,0)*0 -> 0 | G88: =ROUND('PL Gr'!G313/Master!$B$23,0)*0 -> 0 | H88: =E88-G88 -> 0
A89: Communication Expenses | E89: =ROUND('PL Gr'!E189/Master!$B$23,0)*0 -> 0 | G89: =ROUND('PL Gr'!G189/Master!$B$23,0)*0 -> 0 | H89: =E89-G89 -> 0
A90: Printing and Stationery | E90: =ROUND('PL Gr'!E237/Master!$B$23,0) -> 0 | G90: =ROUND('PL Gr'!G237/Master!$B$23,0) -> 0 | H90: =E90-G90 -> 0
A91: Power and Fuel | E91: =ROUND('PL Gr'!E181/Master!$B$23,0) -> 404310 | G91: =ROUND('PL Gr'!G181/Master!$B$23,0) -> 414275 | H91: =E91-G91 -> -9965
A92: Repairs and Maintenance | H92: =E92-G92 -> 0
A93: - Machinery | E93: =ROUND('PL Gr'!E219/Master!$B$23,0) -> 0 | G93: =ROUND('PL Gr'!G219/Master!$B$23,0) -> 0 | H93: =E93-G93 -> 0
A94: - Others | E94: =ROUND('PL Gr'!E229/Master!$B$23,0) -> 226298 | G94: =ROUND('PL Gr'!G229/Master!$B$23,0) -> 167219 | H94: =E94-G94 -> 59079
A95: Marketing Fees | E95: =ROUND('PL Gr'!E353/Master!$B$23,0) -> 0 | G95: =ROUND('PL Gr'!G353/Master!$B$23,0) -> 0 | H95: =E95-G95 -> 0
A96: Legal and Professional charges | E96: =ROUND('PL Gr'!E214/Master!$B$23,0)+ROUND('PL Gr'!E325/Master!$B$23,0) -> 1731898 | G96: =ROUND('PL Gr'!G214/Master!$B$23,0)+ROUND('PL Gr'!G325/Master!$B$23,0) -> 1184666 | H96: =E96-G96 -> 547232
A97: Loss / (gain) on sale of fixed assets (net) | E97: =IF('PL Gr'!E358<0,ROUND('PL Gr'!E358/Master!$B$23,0),0) -> 0 | G97: =IF('PL Gr'!G358<0,ROUND('PL Gr'!G358/Master!$B$23,0),0) -> 0 | H97: =E97-G97 -> 0
A98: Loss on exchange fluctuations | G98: =-ROUND(('PL Gr'!G414+'PL Gr'!G418+'PL Gr'!G420+'PL Gr'!G421+'PL Gr'!G422+'PL Gr'!G423)/Master!$B$23,0)-ROUND(('PL Gr'!G415+'PL Gr'!G419+'PL Gr'!G424+'PL Gr'!G425+'PL Gr'!G426)/Master!$B$23,0) -> 232456 | H98: =E98-G98 -> -232456
A99: (Write back of provision)/Provision of doubtful trade receivable | E99: =ROUND(0/Master!$B$23,0) -> 0 | G99: =ROUND(0/Master!$B$23,0) -> 0 | H99: =E99-G99 -> 0
A100: Bad debts written off | E100: =ROUND(('PL Gr'!E382+'PL Gr'!E410)/Master!$B$23,0) -> 98431 | G100: =ROUND(('PL Gr'!G382)/Master!$B$23,0) -> 0 | H100: =E100-G100 -> 98431
A101: Provision for doubtful loans and advances | E101: =ROUND((+'PL Gr'!E385+'PL Gr'!E386+'PL Gr'!E383)/Master!$B$23,0)-E99 -> 0 | G101: =ROUND(('PL Gr'!G385+'PL Gr'!G386+'PL Gr'!G383)/Master!$B$23,0)-G99 -> 0 | H101: =E101-G101 -> 0
A102: (Gain) / Loss on Exchange Fluctuations (net) | H102: =E102-G102 -> 0
A103: Corporate social responsibility expenditure | E103: =ROUND(('PL Gr'!E388+'PL Gr'!E380)/Master!$B$23,0) -> 0 | G103: =ROUND(('PL Gr'!G388+'PL Gr'!G380)/Master!$B$23,0) -> 0
A104: Support cost from group companies | E104: =ROUND(('PL Gr'!E391+'PL Gr'!E402)/Master!$B$23,0) -> 4728160 | G104: =ROUND(('PL Gr'!G391+'PL Gr'!G402)/Master!$B$23,0) -> 3351781
A105: Security charges | E105: =ROUND(('PL Gr'!E378+'PL Gr'!E399)/Master!$B$23,0) -> 68095 | G105: =ROUND(('PL Gr'!G378+'PL Gr'!G399)/Master!$B$23,0) -> 103148
A106: Miscellaneous Expenses | E106: =ROUND(('PL Gr'!E412-'PL Gr'!E377-'PL Gr'!E379-'PL Gr'!E400-'PL Gr'!E399*0)/Master!$B$23,0)-E101-E99-E100-E103-E104-E105+ROUND(('PL Gr'!E176+'PL Gr'!E335+'PL Gr'!E313+'PL Gr'!E189)/Master!$B$23,0) -> 550878 | G106: =ROUND(('PL Gr'!G412-'PL Gr'!G377-'PL Gr'!G379-'PL Gr'!G400)/Master!$B$23,0)-G101-G99-G100-G103-G104-G105+ROUND(('PL Gr'!G176+'PL Gr'!G335+'PL Gr'!G313+'PL Gr'!G189)/Master!$B$23,0) -> 350523 | H106: =E106-G106 -> 200355
A108: Total | E108: =SUM(E85:E107) -> 7808277 | G108: =SUM(G85:G107) -> 5830453
A111: Tax Expenses
A112: Foreign Tax
A113: State Income Taxes | E113: =ROUND('PL Gr'!E443/Master!$B$23,0) -> 0 | G113: =ROUND('PL Gr'!G443/Master!$B$23,0) -> 0
A114: Canada - State Income Tax | E114: =ROUND('PL Gr'!E444/Master!$B$23,0) -> 0 | G114: =ROUND('PL Gr'!G444/Master!$B$23,0) -> 0
A115: Federal Income Taxes | E115: =ROUND('PL Gr'!E445/Master!$B$23,0) -> 0 | G115: =ROUND('PL Gr'!G445/Master!$B$23,0) -> 0
A116: Canada - Federal Income Tax | E116: =ROUND('PL Gr'!E446/Master!$B$23,0) -> 0 | G116: =ROUND('PL Gr'!G446/Master!$B$23,0) -> 0
A117: UK Corporation Tax | E117: =ROUND('PL Gr'!E450/Master!$B$23,0) -> 0 | G117: =ROUND('PL Gr'!G450/Master!$B$23,0) -> 0
A118: City Corporate Income Tax | E118: =ROUND('PL Gr'!E451/Master!$B$23,0) -> 0 | G118: =ROUND('PL Gr'!G451/Master!$B$23,0) -> 0
A119: Foreign Earned Income Tax Prov | E119: =ROUND('PL Gr'!E447/Master!$B$23,0) -> 0 | G119: =ROUND('PL Gr'!G447/Master!$B$23,0) -> 0
E120: =SUM(E113:E119) -> 0 | G120: =SUM(G113:G119) -> 0
A121: Indian Income taxes | E121: =ROUND(('PL Gr'!E448+'PL Gr'!E454)/Master!$B$23,0)+E122 -> 42613709 | G121: =ROUND(('PL Gr'!G448+'PL Gr'!G454)/Master!$B$23,0)+E122 -> 4035301
A122: Less : MAT Credit entitlement | E122: =ROUND(('BS Gr'!D875-'BS Gr'!F875)/Master!B23,0)*0 -> 0 | G122: =ROUND(0/Master!B23,0) -> 0
A123: Net Indian Income Tax | E123: =+E121-E122 -> 42613709 | G123: =+G121-G122 -> 4035301
A125: Current Tax | E125: =+E120+E123 -> 42613709 | G125: =+G120+G123 -> 4035301
A127: Deferred Tax | E127: =ROUND(('PL Gr'!E449+'PL Gr'!E455)/Master!$B$23,0) -> 3452021 | G127: =ROUND(('PL Gr'!G449+'PL Gr'!G455)/Master!$B$23,0) -> -26030840
A129: Fringe Benefit Tax | E129: =ROUND('PL Gr'!E453/Master!$B$23,0) -> 0 | G129: =ROUND('PL Gr'!G453/Master!$B$23,0) -> 0
A131: Total | E131: =+E125+E127+E129 -> 46065730 | G131: =+G125+G127+G129 -> -21995539
A133: Difference in Notes and PL Tab | E133: =+E10+E18+E41-E53-E61-E108-E131-'Sch - FA'!K31-E72-E81 -> -34054475 | G133: =+G10+G18+G41-G53-G61-G108-G131-'Sch - FA'!K25-G72-G81 -> 58404273 | I133: =-'Sch - FA'!K31-E72-E81 -> 0

Sheet Sch - BS
A1: =+Master!$B$2 -> Syntel Solutions (India) Private Limited
A2: =BS!A2 -> 0
A4: ="Notes forming part of financial statements as at " &Master!$B$5 -> Notes forming part of financial statements as at 31st March 2025 | G4: =+Master!B24 -> (Rs.)
G5: =+Master!$B$7 -> 2025 | I5: =Master!$B$13 -> 2024
A6: Non Currents assets
A8: Property, Plant and Equipment
A9: Property, Plant and Equipment | G9: =+ROUND(SUM('BS Gr'!D543+'BS Gr'!D565)/Master!$B$23,0) -> -1 | I9: =+ROUND(SUM('BS Gr'!F543+'BS Gr'!F565)/Master!$B$23,0) -> -1 | J9: =+G9-I9 -> 0
A10: Intangible assets | G10: =+ROUND((SUM('BS Gr'!D571)+SUM('BS Gr'!D576)+1)/Master!$B$23,0) -> 0 | I10: =+ROUND((SUM('BS Gr'!F571)+SUM('BS Gr'!F576)+1)/Master!$B$23,0) -> 0 | J10: =+G10-I10 -> 0
A11: Capital working in progress | G11: =ROUND('BS Gr'!D591/Master!$B$23,0) -> 0 | I11: =ROUND('BS Gr'!F591/Master!$B$23,0) -> 0 | J11: =+G11-I11 -> 0
A13: Total | G13: =SUM(G8:G12) -> -1 | I13: =SUM(I8:I12) -> -1 | J13: =+G13-I13 -> 0
A15: Financial assets
A16: Investments
A17: Investment in 3% Cumulative Redeemable Preference shares
A18: -Syntel International Private Limited | G18: =ROUND('BS Gr'!I84/Master!$B$23,0)-G28 -> 0 | I18: =ROUND('BS Gr'!M84/Master!$B$23,0)-I28 -> 0
A19: 93,900 (2016 - 54,200) shares of Rs.10 each fully paid-up
A21: -Trizetto Syntel Services (India) Private Limited | G21: =ROUND('BS Gr'!I88/Master!$B$23,0) -> 0 | I21: =ROUND('BS Gr'!M88/Master!$B$23,0) -> 0
A22: 11,200 (2016 - 11,200) shares of Rs. 10 each fully paid-up
A24: -Syntel Global Private Limited | G24: =ROUND('BS Gr'!I87/Master!$B$23,0) -> 0 | I24: =ROUND('BS Gr'!M87/Master!$B$23,0) -> 0
A25: Nil (2016 - Nil) shares of Rs. 10 each fully paid-up
A27: 0% Cumulative Redeemable Preference shares
A28: -Syntel International Private Limited | G28: =ROUND(0/Master!$B$23,0) -> 0 | I28: =ROUND(0/Master!$B$23,0) -> 0
A29: 284,777 (2016 - 437,301) shares of Rs.10 each fully paid-up
A31: Total | G31: =SUM(G14:G30) -> 0 | I31: =SUM(I14:I30) -> 0
A33: Loans | G33: =ROUND('BS Gr'!M257/Master!$B$23,0) -> 0 | I33: =ROUND('BS Gr'!M257/Master!$B$23,0) -> 0
A35: Total | G35: =SUM(G33:G34) -> 0 | I35: =SUM(I33:I34) -> 0
A37: Other financial assets
A38: Security deposits | G38: =ROUND('BS Gr'!I502/Master!$B$23,0) -> 0 | I38: =ROUND('BS Gr'!M502/Master!$B$23,0) -> 0 | J38: =+G38-I38 -> 0
A39: Rental deposits | J39: =+G39-I39 -> 0
A40: to parties other than related parties | G40: =ROUND(('BS Gr'!I462)/Master!$B$23,0)-G42-G41-G69 -> 0 | I40: =ROUND(('BS Gr'!M462)/Master!$B$23,0)-I42-I41-I69 -> 0 | J40: =+G40-I40 -> 0
A41: to related parties | G41: =ROUND('BS Gr'!I462/Master!$B$23,0)-G69 -> 0 | I41: =ROUND('BS Gr'!M462/Master!$B$23,0)-I69 -> 2602786 | J41: =+G41-I41 -> -2602786 | K41: =+J41+CF!F17+36105 -> -2784308
A42: Doubtful | G42: =+-ROUND('BS Gr'!I449/Master!$B$23,0) -> 0 | I42: =+-ROUND('BS Gr'!M449/Master!$B$23,0) -> 0 | J42: =+G42-I42 -> 0
G43: =SUM(G40:G42) -> 0 | I43: =SUM(I40:I42) -> 2602786 | J43: =+G43-I43 -> -2602786
A44: Less: Provision for doubtful deposits | G44: =-G42 -> 0 | I44: =-I42 -> 0 | J44: =+G44-I44 -> 0
G45: =SUM(G43:G44) -> 0 | I45: =SUM(I43:I44) -> 2602786 | J45: =+G45-I45 -> -2602786
J46: =+G46-I46 -> 0
A47: Total | G47: =G38+G45 -> 0 | I47: =I38+I45 -> 2602786 | J47: =+G47-I47 -> -2602786
A49: Deferred tax assets (net) | G49: =ROUND(('BS Gr'!I882-'BS Gr'!I871*0)/Master!$B$23,0)-G51 -> -3328863 | I49: =ROUND(('BS Gr'!M882-'BS Gr'!M871*0)/Master!$B$23,0)-I51 -> -6767874 | J49: =+G49-I49 -> 3439011
A50: MAT Credit entitlement | G50: =-ROUND('BS Gr'!I376/Master!$B$23,0) -> 0 | I50: =-ROUND('BS Gr'!M376/Master!$B$23,0) -> 0
A51: Tax on buy back pf preference shares | G51: =ROUND(('BS Gr'!I879+'BS Gr'!I876)/Master!$B$23,0) -> 0 | I51: =ROUND(('BS Gr'!M879+'BS Gr'!M876)/Master!$B$23,0) -> 0
J52: =+G52-I52 -> 0
A53: Total | G53: =SUM(G49:G52) -> -3328863 | I53: =SUM(I49:I52) -> -6767874 | J53: =+G53-I53 -> 3439011
A55: Other non-current assets
A56: Capital Advance for fixed assets
A57: Secured, considered good
A58: Unsecured, considered good | G58: =ROUND('BS Gr'!I597/Master!$B$23,0) -> 0 | I58: =ROUND('BS Gr'!M597/Master!$B$23,0) -> 0
A59: Doubtful
G60: =SUM(G57:G59) -> 0 | I60: =SUM(I57:I59) -> 0
A61: Less: Provision for doubtful capital advances | G61: =-G59 -> 0 | I61: =-I59 -> 0
G62: =SUM(G60:G61) -> 0 | I62: =SUM(I60:I61) -> 0
A64: Prepaid Expenses | G64: =ROUND('BS Gr'!I281/Master!$B$23,0) -> 0 | I64: =ROUND('BS Gr'!M281/Master!$B$23,0) -> 0
A65: Advance to employees | G65: =ROUND('BS Gr'!I302/Master!$B$23,0) -> 0 | I65: =ROUND('BS Gr'!M302/Master!$B$23,0) -> 0
A66: Indirect tax recoverable | G66: =ROUND(('BS Gr'!I423+'BS Gr'!I351+(5071372))/Master!$B$23,0) -> 11703040 | I66: =ROUND(('BS Gr'!M423+'BS Gr'!M351+5071372)/Master!$B$23,0) -> 11703040 | J66: =+G66-I66 -> 0 | K66: =-1-1+1-1-1 -> -3 | L66: =-1-1+1-1-1-2 -> -5 | M66: =-1-1+1-1-1-2+4 -> -1
A67: MAT credit entitlement | G67: =ROUND('BS Gr'!I376/Master!$B$23,0)*0 -> 0 | I67: =ROUND('BS Gr'!M376/Master!$B$23,0)*0 -> 0 | J67: =+G67-I67 -> 0
A68: Other Advances | J68: =+G68-I68 -> 0
A69: Deferred lease expense | G69: =ROUND('BS Gr'!I458/Master!$B$23,0) -> 0 | I69: =ROUND('BS Gr'!M458/Master!$B$23,0) -> 0 | J69: =+G69-I69 -> 0
A70: Deposits | G70: =ROUND('BS Gr'!I446/Master!$B$23,0) -> 0 | I70: =ROUND('BS Gr'!M446/Master!$B$23,0) -> 0 | J70: =+G70-I70 -> 0
A71: Lease equalisation | G71: =ROUND('BS Gr'!I351/Master!$B$23,0)*0 -> 0 | I71: =ROUND('BS Gr'!M351/Master!$B$23,0)*0 -> 0 | J71: =+G71-I71 -> 0
G72: =SUM(G64:G71) -> 11703040 | I72: =SUM(I64:I71) -> 11703040 | J72: =+G72-I72 -> 0
A73: Less: Provision for doubtful advance | G73: =ROUND('BS Gr'!I430/Master!$B$23,0) -> -399960 | I73: =ROUND('BS Gr'!M430/Master!$B$23,0) -> -399960 | J73: =+G73-I73 -> 0
G74: =SUM(G72:G73) -> 11303080 | I74: =SUM(I72:I73) -> 11303080 | J74: =+G74-I74 -> 0
J75: =+G75-I75 -> 0
A76: Total | G76: =G62+G74 -> 11303080 | I76: =I62+I74 -> 11303080 | J76: =+G76-I76 -> 0
A79: Income tax assets (net)
A80: Advance income tax (net of Income tax provision) | G80: =+ROUND('BS Gr'!I522/Master!$B$23,0) -> -839640 | I80: =+ROUND('BS Gr'!M522/Master!$B$23,0) -> 40668266 | J80: =+G80-I80 -> -41507906 | K80: =366585-137000 -> 229585
J81: =+G81-I81 -> 0
A82: Total | G82: =SUM(G80:G81) -> -839640 | I82: =SUM(I80:I81) -> 40668266 | J82: =+G82-I82 -> -41507906
A84: Current assets
A85: Financial assets
A86: Investments
A87: Investment in Mutual Funds | G87: =ROUND('BS Gr'!H73/Master!$B$23,0) -> -10 | I87: =ROUND('BS Gr'!L73/Master!$B$23,0) -> -10 | J87: =+G87-I87 -> 0
A89: Investment in 3% Cumulative Redeemable Preference shares
A90: -Syntel International Private Limited | G90: =ROUND('BS Gr'!H84/Master!$B$23,0) -> 0 | I90: =ROUND('BS Gr'!L84/Master!$B$23,0) -> 0
A91: Nil (2016 - 46,450) shares of Rs. 10 each fully paid-up
A92: -Syntel Global Private Limited | G92: =ROUND('BS Gr'!H87/Master!$B$23,0) -> 0 | I92: =ROUND('BS Gr'!L87/Master!$B$23,0) -> 0
A93: Nil (2016 - Nil) shares of Rs. 10 each fully paid-up
G94: =SUM(G90:G93) -> 0 | I94: =SUM(I90:I93) -> 0
A96: Total | G96: =+G87+G94 -> -10 | I96: =+I87+I94 -> -10 | J96: =+G96-I96 -> 0
A98: Trade receivables
A99: -Outstanding for a period exceeding six months after due date of payment
A100: Unsecured, considered good | G100: =ROUND('BS Gr'!H127/Master!$B$23,0) -> 0 | I100: =ROUND('BS Gr'!L127/Master!$B$23,0) -> 0
A101: Unsecured considered doubtful | G101: =ROUND('BS Gr'!H128/Master!$B$23,0) -> 0 | I101: =ROUND('BS Gr'!L128/Master!$B$23,0) -> 0
G102: =SUM(G99:G101) -> 0 | I102: =SUM(I99:I101) -> 0
A103: Less: Provision for doubtful debtors | G103: =-G101 -> 0 | I103: =-I101 -> 0
G104: =SUM(G102:G103) -> 0 | I104: =SUM(I102:I103) -> 0
A106: -Other Debtors
A107: Unsecured, considered good | G107: =ROUND('BS Gr'!H129/Master!$B$23,0) -> 8393535 | I107: =ROUND('BS Gr'!L129+100000/Master!$B$23,0) -> 1953218 | J107: =+G107-I107 -> 6440317
A108: Unbilled revenue | G108: =ROUND('BS Gr'!H473/Master!$B$23,0) -> 213964 | I108: =ROUND('BS Gr'!L473/Master!$B$23,0) -> 59269
A109: Unsecured, considered doubtful | G109: 0 | I109: 0 | J109: =+G109-I109 -> 0
G110: =SUM(G106:G109) -> 8607499 | I110: =SUM(I106:I109) -> 2012487 | J110: =+G110-I110 -> 6595012
A111: Less: Provision for Doubtful debtors | G111: =-G109 -> 0 | I111: =-I109 -> 0 | J111: =+G111-I111 -> 0
G112: =SUM(G110:G111) -> 8607499 | I112: =SUM(I110:I111) -> 2012487 | J112: =+G112-I112 -> 6595012
J113: =+G113-I113 -> 0
A114: Total | G114: =+G104+G112 -> 8607499 | I114: =+I104+I112 -> 2012487 | J114: =+G114-I114 -> 6595012
A116: Cash and cash equivalents
A117: Cash on Hand | G117: =ROUND(('BS Gr'!H145)/Master!$B$23,0) -> 0 | I117: =ROUND(('BS Gr'!L145)/Master!$B$23,0) -> 0 | J117: =+G117-I117 -> 0
A118: Balance in current accounts | G118: =ROUND(('BS Gr'!H209)/Master!$B$23,0)-ROUND('BS Gr'!H189/Master!$B$23,0) -> 409518 | I118: =ROUND(('BS Gr'!F209)/Master!$B$23,0)-ROUND(('BS Gr'!F189)/Master!$B$23,0) -> 605184 | J118: =+G118-I118 -> -195666
A119: Term deposits having original maturity less than 3 months | G119: =ROUND('BS Gr'!H242/Master!$B$23,0) -> 243250000 | I119: =ROUND('BS Gr'!L242/Master!$B$23,0) -> 243200000 | J119: =+G119-I119 -> 50000
A120: Cheques/Draft on hand | G120: 0 | I120: 0 | J120: =+G120-I120 -> 0
J121: =+G121-I121 -> 0
A122: Total | G122: =SUM(G116:G120) -> 243659518 | I122: =SUM(I116:I120) -> 243805184 | J122: =+G122-I122 -> -145666
...

Sheet TB for financial
A1: =+Master!B2 -> Syntel Solutions (India) Private Limited | D1: Ind AS account codes
A2: ="Annexure to Grouping " &Master!$B$5 -> Annexure to Grouping 31st March 2025
A4: GL Code | B4: Particulars | C4: Opening Balance 01-Apr-24 | D4: Transaction | E4: Entries including IND AS entries | F4: Closing Balance 31-Mar-25 | H4: Opening Balance 01-Apr-23 | I4: Transaction | J4: Entries including IND AS entries | K4: Closing Balance 31-Mar-24 | L4: Check | M4: Count | N4: Diff in opening | O4: 1 | P4: 2 | Q4: 3 | S4: As per file
A5: 100000 | B5: TDR reclassed > 3 months | C5: =K5 -> 0 | D5: 0 | E5: =SUMIF('Entries 24-25'!$B:$B,A:A,'Entries 24-25'!$D:$D)-SUMIF('Entries 24-25'!$B:$B,A:A,'Entries 24-25'!$E:$E)+SUMIF('IND AS entries 24-25'!$B:$B,A:A,'IND AS entries 24-25'!$D:$D)-SUMIF('IND AS entries 24-25'!$B:$B,A:A,'IND AS entries 24-25'!$E:$E) -> 0 | F5: =SUM(C5:E5) -> 0 | H5: 0 | I5: 0 | J5: 0 | K5: =SUM(H5:J5) -> 0 | L5: =VLOOKUP(A5,'BS Gr'!A:A,1,FALSE) -> 100000 | M5: =COUNTIF(A:A,A5) -> 1 | N5: =C5-K5 -> 0 | O5: =C5-K5 -> 0 | P5: 0 | Q5: =+K5-P5 -> 0 | S5: =SUMIF('[105]TB for financial'!$A:$A,A5,'[105]TB for financial'!$E:$E) -> #VALUE!
A6: 100001 | B6: TDR above 1 year - Non current ass | C6: =K6 -> 0 | D6: 0 | E6: =SUMIF('Entries 24-25'!$B:$B,A:A,'Entries 24-25'!$D:$D)-SUMIF('Entries 24-25'!$B:$B,A:A,'Entries 24-25'!$E:$E)+SUMIF('IND AS entries 24-25'!$B:$B,A:A,'IND AS entries 24-25'!$D:$D)-SUMIF('IND AS entries 24-25'!$B:$B,A:A,'IND AS entries 24-25'!$E:$E) -> 0 | F6: =SUM(C6:E6) -> 0 | H6: 0 | I6: 0 | J6: 0 | K6: =SUM(H6:J6) -> 0 | L6: =VLOOKUP(A6,'BS Gr'!A:A,1,FALSE) -> #N/A | M6: =COUNTIF(A:A,A6) -> 1 | N6: =C6-K6 -> 0 | O6: =C6-K6 -> 0 | P6: 0 | Q6: =+K6-P6 -> 0 | S6: =SUMIF('[105]TB for financial'!$A:$A,A6,'[105]TB for financial'!$E:$E) -> #VALUE!
A7: 100300 | B7: Bank-Dean Witter | C7: =K7 -> 0 | D7: 0 | E7: =SUMIF('Entries 24-25'!$B:$B,A:A,'Entries 24-25'!$D:$D)-SUMIF('Entries 24-25'!$B:$B,A:A,'Entries 24-25'!$E:$E)+SUMIF('IND AS entries 24-25'!$B:$B,A:A,'IND AS entries 24-25'!$D:$D)-SUMIF('IND AS entries 24-25'!$B:$B,A:A,'IND AS entries 24-25'!$E:$E) -> 0 | F7: =SUM(C7:E7) -> 0 | H7: 0 | I7: 0 | J7: 0 | K7: =SUM(H7:J7) -> 0 | L7: =VLOOKUP(A7,'BS Gr'!A:A,1,FALSE) -> 100300 | M7: =COUNTIF(A:A,A7) -> 1 | N7: =C7-K7 -> 0 | O7: =C7-K7 -> 0 | P7: 0 | Q7: =+K7-P7 -> 0 | S7: =SUMIF('[105]TB for financial'!$A:$A,A7,'[105]TB for financial'!$E:$E) -> #VALUE!
A8: 100301 | B8: JP Morgan - CAD Bank Account | C8: =K8 -> 0 | D8: 0 | E8: =SUMIF('Entries 24-25'!$B:$B,A:A,'Entries 24-25'!$D:$D)-SUMIF('Entries 24-25'!$B:$B,A:A,'Entries 24-25'!$E:$E)+SUMIF('IND AS entries 24-25'!$B:$B,A:A,'IND AS entries 24-25'!$D:$D)-SUMIF('IND AS entries 24-25'!$B:$B,A:A,'IND AS entries 24-25'!$E:$E) -> 0 | F8: =SUM(C8:E8) -> 0 | H8: 0 | I8: 0 | J8: 0 | K8: =SUM(H8:J8) -> 0 | L8: =VLOOKUP(A8,'BS Gr'!A:A,1,FALSE) -> 100301 | M8: =COUNTIF(A:A,A8) -> 1 | N8: =C8-K8 -> 0 | O8: =C8-K8 -> 0 | P8: 0 | Q8: =+K8-P8 -> 0 | S8: =SUMIF('[105]TB for financial'!$A:$A,A8,'[105]TB for financial'!$E:$E) -> #VALUE!
A9: 100302 | B9: Barclays Bank PLC - Wealth | C9: =K9 -> 0 | D9: 0 | E9: =SUMIF('Entries 24-25'!$B:$B,A:A,'Entries 24-25'!$D:$D)-SUMIF('Entries 24-25'!$B:$B,A:A,'Entries 24-25'!$E:$E)+SUMIF('IND AS entries 24-25'!$B:$B,A:A,'IND AS entries 24-25'!$D:$D)-SUMIF('IND AS entries 24-25'!$B:$B,A:A,'IND AS entries 24-25'!$E:$E) -> 0 | F9: =SUM(C9:E9) -> 0 | H9: 0 | I9: 0 | J9: 0 | K9: =SUM(H9:J9) -> 0 | L9: =VLOOKUP(A9,'BS Gr'!A:A,1,FALSE) -> 100302 | M9: =COUNTIF(A:A,A9) -> 1 | N9: =C9-K9 -> 0 | O9: =C9-K9 -> 0 | P9: 0 | Q9: =+K9-P9 -> 0 | S9: =SUMIF('[105]TB for financial'!$A:$A,A9,'[105]TB for financial'!$E:$E) -> #VALUE!
A10: 100303 | B10: Barclays Bank PLC - USD EEFC | C10: =K10 -> 0 | D10: 0 | E10: =SUMIF('Entries 24-25'!$B:$B,A:A,'Entries 24-25'!$D:$D)-SUMIF('Entries 24-25'!$B:$B,A:A,'Entries 24-25'!$E:$E)+SUMIF('IND AS entries 24-25'!$B:$B,A:A,'IND AS entries 24-25'!$D:$D)-SUMIF('IND AS entries 24-25'!$B:$B,A:A,'IND AS entries 24-25'!$E:$E) -> 0 | F10: =SUM(C10:E10) -> 0 | H10: 0 | I10: 0 | J10: 0 | K10: =SUM(H10:J10) -> 0 | L10: =VLOOKUP(A10,'BS Gr'!A:A,1,FALSE) -> 100303 | M10: =COUNTIF(A:A,A10) -> 1 | N10: =C10-K10 -> 0 | O10: =C10-K10 -> 0 | P10: 0 | Q10: =+K10-P10 -> 0 | S10: =SUMIF('[105]TB for financial'!$A:$A,A10,'[105]TB for financial'!$E:$E) -> #VALUE!
A11: 100304 | B11: Barclays Bank PLC - USD FC | C11: =K11 -> 0 | D11: 0 | E11: =SUMIF('Entries 24-25'!$B:$B,A:A,'Entries 24-25'!$D:$D)-SUMIF('Entries 24-25'!$B:$B,A:A,'Entries 24-25'!$E:$E)+SUMIF('IND AS entries 24-25'!$B:$B,A:A,'IND AS entries 24-25'!$D:$D)-SUMIF('IND AS entries 24-25'!$B:$B,A:A,'IND AS entries 24-25'!$E:$E) -> 0 | F11: =SUM(C11:E11) -> 0 | H11: 0 | I11: 0 | J11: 0 | K11: =SUM(H11:J11) -> 0 | L11: =VLOOKUP(A11,'BS Gr'!A:A,1,FALSE) -> 100304 | M11: =COUNTIF(A:A,A11) -> 1 | N11: =C11-K11 -> 0 | O11: =C11-K11 -> 0 | P11: 0 | Q11: =+K11-P11 -> 0 | S11: =SUMIF('[105]TB for financial'!$A:$A,A11,'[105]TB for financial'!$E:$E) -> #VALUE!
A12: 100305 | B12: Bank One Canada-Syntel Inc | C12: =K12 -> 0 | D12: 0 | E12: =SUMIF('Entries 24-25'!$B:$B,A:A,'Entries 24-25'!$D:$D)-SUMIF('Entries 24-25'!$B:$B,A:A,'Entries 24-25'!$E:$E)+SUMIF('IND AS entries 24-25'!$B:$B,A:A,'IND AS entries 24-25'!$D:$D)-SUMIF('IND AS entries 24-25'!$B:$B,A:A,'IND AS entries 24-25'!$E:$E) -> 0 | F12: =SUM(C12:E12) -> 0 | H12: 0 | I12: 0 | J12: 0 | K12: =SUM(H12:J12) -> 0 | L12: =VLOOKUP(A12,'BS Gr'!A:A,1,FALSE) -> 100305 | M12: =COUNTIF(A:A,A12) -> 1 | N12: =C12-K12 -> 0 | O12: =C12-K12 -> 0 | P12: 0 | Q12: =+K12-P12 -> 0 | S12: =SUMIF('[105]TB for financial'!$A:$A,A12,'[105]TB for financial'!$E:$E) -> #VALUE!
A13: 100314 | B13: Axis Bank - USD FCY | C13: =K13 -> 0 | D13: 0 | E13: =SUMIF('Entries 24-25'!$B:$B,A:A,'Entries 24-25'!$D:$D)-SUMIF('Entries 24-25'!$B:$B,A:A,'Entries 24-25'!$E:$E)+SUMIF('IND AS entries 24-25'!$B:$B,A:A,'IND AS entries 24-25'!$D:$D)-SUMIF('IND AS entries 24-25'!$B:$B,A:A,'IND AS entries 24-25'!$E:$E) -> 0 | F13: =SUM(C13:E13) -> 0 | H13: 0 | I13: 0 | J13: 0 | K13: =SUM(H13:J13) -> 0 | L13: =VLOOKUP(A13,'BS Gr'!A:A,1,FALSE) -> 100314 | M13: =COUNTIF(A:A,A13) -> 1 | N13: =C13-K13 -> 0 | O13: =C13-K13 -> 0 | P13: 0 | Q13: =+K13-P13 -> 0 | S13: =SUMIF('[105]TB for financial'!$A:$A,A13,'[105]TB for financial'!$E:$E) -> #VALUE!
A14: 100320 | B14: HDFC Bank -USD EEFC | C14: =K14 -> 0 | D14: 0 | E14: =SUMIF('Entries 24-25'!$B:$B,A:A,'Entries 24-25'!$D:$D)-SUMIF('Entries 24-25'!$B:$B,A:A,'Entries 24-25'!$E:$E)+SUMIF('IND AS entries 24-25'!$B:$B,A:A,'IND AS entries 24-25'!$D:$D)-SUMIF('IND AS entries 24-25'!$B:$B,A:A,'IND AS entries 24-25'!$E:$E) -> 0 | F14: =SUM(C14:E14) -> 0 | H14: 0 | I14: 0 | J14: 0 | K14: =SUM(H14:J14) -> 0 | L14: =VLOOKUP(A14,'BS Gr'!A:A,1,FALSE) -> 100320 | M14: =COUNTIF(A:A,A14) -> 1 | N14: =C14-K14 -> 0 | O14: =C14-K14 -> 0 | P14: 0 | Q14: =+K14-P14 -> 0 | S14: =SUMIF('[105]TB for financial'!$A:$A,A14,'[105]TB for financial'!$E:$E) -> #VALUE!
A15: 100325 | B15: HDFC Bank -USD FC | C15: =K15 -> 0 | D15: 0 | E15: =SUMIF('Entries 24-25'!$B:$B,A:A,'Entries 24-25'!$D:$D)-SUMIF('Entries 24-25'!$B:$B,A:A,'Entries 24-25'!$E:$E)+SUMIF('IND AS entries 24-25'!$B:$B,A:A,'IND AS entries 24-25'!$D:$D)-SUMIF('IND AS entries 24-25'!$B:$B,A:A,'IND AS entries 24-25'!$E:$E) -> 0 | F15: =SUM(C15:E15) -> 0 | H15: 0 | I15: 0 | J15: 0 | K15: =SUM(H15:J15) -> 0 | L15: =VLOOKUP(A15,'BS Gr'!A:A,1,FALSE) -> 100325 | M15: =COUNTIF(A:A,A15) -> 1 | N15: =C15-K15 -> 0 | O15: =C15-K15 -> 0 | P15: 0 | Q15: =+K15-P15 -> 0 | S15: =SUMIF('[105]TB for financial'!$A:$A,A15,'[105]TB for financial'!$E:$E) -> #VALUE!
A16: 100327 | B16: Standard Chartered -USD FC | C16: =K16 -> 0 | D16: 0 | E16: =SUMIF('Entries 24-25'!$B:$B,A:A,'Entries 24-25'!$D:$D)-SUMIF('Entries 24-25'!$B:$B,A:A,'Entries 24-25'!$E:$E)+SUMIF('IND AS entries 24-25'!$B:$B,A:A,'IND AS entries 24-25'!$D:$D)-SUMIF('IND AS entries 24-25'!$B:$B,A:A,'IND AS entries 24-25'!$E:$E) -> 0 | F16: =SUM(C16:E16) -> 0 | H16: 0 | I16: 0 | J16: 0 | K16: =SUM(H16:J16) -> 0 | L16: =VLOOKUP(A16,'BS Gr'!A:A,1,FALSE) -> 100327 | M16: =COUNTIF(A:A,A16) -> 1 | N16: =C16-K16 -> 0 | O16: =C16-K16 -> 0 | P16: 0 | Q16: =+K16-P16 -> 0 | S16: =SUMIF('[105]TB for financial'!$A:$A,A16,'[105]TB for financial'!$E:$E) -> #VALUE!
... A20: 100450 | B20: Bank-NBD A/P Checks | C20: =K20 -> 0 | D20: 0 | E20: =SUMIF('Entries 24-25'!$B:$B,A:A,'Entries 24-25'!$D:$D)-SUMIF('Entries 24-25'!$B:$B,A:A,'Entries 24-25'!$E:$E)+SUMIF('IND AS entries 24-25'!$B:$B,A:A,'IND AS entries 24-25'!$D:$D)-SUMIF('IND AS entries 24-25'!$B:$B,A:A,'IND AS entries 24-25'!$E:$E) -> 0 | F20: =SUM(C20:E20) -> 0 | H20: 0 | I20: 0 | J20: 0 | K20: =SUM(H20:J20) -> 0 | L20: =VLOOKUP(A20,'BS Gr'!A:A,1,FALSE) -> 100450 | M20: =COUNTIF(A:A,A20) -> 1 | N20: =C20-K20 -> 0 | O20: =C20-K20 -> 0 | P20: 0 | Q20: =+K20-P20 -> 0 | S20: =SUMIF('[105]TB for financial'!$A:$A,A20,'[105]TB for financial'!$E:$E) -> #VALUE!
A21: 100451 | B21: JPMorgan Chase Bank N.A. Curre | C21: =K21 -> 0 | D21: 0 | E21: =SUMIF('Entries 24-25'!$B:$B,A:A,'Entries 24-25'!$D:$D)-SUMIF('Entries 24-25'!$B:$B,A:A,'Entries 24-25'!$E:$E)+SUMIF('IND AS entries 24-25'!$B:$B,A:A,'IND AS entries 24-25'!$D:$D)-SUMIF('IND AS entries 24-25'!$B:$B,A:A,'IND AS entries 24-25'!$E:$E) -> 0 | F21: =SUM(C21:E21) -> 0 | H21: 0 | I21: 0 | J21: 0 | K21: =SUM(H21:J21) -> 0 | L21: =VLOOKUP(A21,'BS Gr'!A:A,1,FALSE) -> 100451 | M21: =COUNTIF(A:A,A21) -> 1 | N21: =C21-K21 -> 0 | O21: =C21-K21 -> 0 | S21: =SUMIF('[105]TB for financial'!$A:$A,A21,'[105]TB for financial'!$E:$E) -> #VALUE!
A22: 100452 | B22: JPMorgan Chase Bank N.A. Payro | C22: =K22 -> 0 | D22: 0 | E22: =SUMIF('Entries 24-25'!$B:$B,A:A,'Entries 24-25'!$D:$D)-SUMIF('Entries 24-25'!$B:$B,A:A,'Entries 24-25'!$E:$E)+SUMIF('IND AS entries 24-25'!$B:$B,A:A,'IND AS entries 24-25'!$D:$D)-SUMIF('IND AS entries 24-25'!$B:$B,A:A,'IND AS entries 24-25'!$E:$E) -> 0 | F22: =SUM(C22:E22) -> 0 | H22: 0 | I22: 0 | J22: 0 | K22: =SUM(H22:J22) -> 0 | L22: =VLOOKUP(A22,'BS Gr'!A:A,1,FALSE) -> 100452 | M22: =COUNTIF(A:A,A22) -> 1 | N22: =C22-K22 -> 0 | O22: =C22-K22 -> 0 | S22: =SUMIF('[105]TB for financial'!$A:$A,A22,'[105]TB for financial'!$E:$E) -> #VALUE!
A23: 100454 | B23: JPMorgan Chase Bank N.A. FCY A | C23: =K23 -> 0 | D23: 0 | E23: =SUMIF('Entries 24-25'!$B:$B,A:A,'Entries 24-25'!$D:$D)-SUMIF('Entries 24-25'!$B:$B,A:A,'Entries 24-25'!$E:$E)+SUMIF('IND AS entries 24-25'!$B:$B,A:A,'IND AS entries 24-25'!$D:$D)-SUMIF('IND AS entries 24-25'!$B:$B,A:A,'IND AS entries 24-25'!$E:$E) -> 0 | F23: =SUM(C23:E23) -> 0 | H23: 0 | I23: 0 | J23: 0 | K23: =SUM(H23:J23) -> 0 | L23: =VLOOKUP(A23,'BS Gr'!A:A,1,FALSE) -> 100454 | M23: =COUNTIF(A:A,A23) -> 1 | N23: =C23-K23 -> 0 | O23: =C23-K23 -> 0 | S23: =SUMIF('[105]TB for financial'!$A:$A,A23,'[105]TB for financial'!$E:$E) -> #VALUE!
A24: 100460 | B24: Bank-NBD Expense Checks | C24: =K24 -> 0 | D24: 0 | E24: =SUMIF('Entries 24-25'!$B:$B,A:A,'Entries 24-25'!$D:$D)-SUMIF('Entries 24-25'!$B:$B,A:A,'Entries 24-25'!$E:$E)+SUMIF('IND AS entries 24-25'!$B:$B,A:A,'IND AS entries 24-25'!$D:$D)-SUMIF('IND AS entries 24-25'!$B:$B,A:A,'IND AS entries 24-25'!$E:$E) -> 0 | F24: =SUM(C24:E24) -> 0 | H24: 0 | I24: 0 | J24: 0 | K24: =SUM(H24:J24) -> 0 | L24: =VLOOKUP(A24,'BS Gr'!A:A,1,FALSE) -> 100460 | M24: =COUNTIF(A:A,A24) -> 1 | N24: =C24-K24 -> 0 | O24: =C24-K24 -> 0 | P24: 0 | Q24: =+K24-P24 -> 0 | S24: =SUMIF('[105]TB for financial'!$A:$A,A24,'[105]TB for financial'!$E:$E) -> #VALUE!
A25: 100470 | B25: Bank-NBD Flexible Spending Ckg | C25: =K25 -> 0 | D25: 0 | E25: =SUMIF('Entries 24-25'!$B:$B,A:A,'Entries 24-25'!$D:$D)-SUMIF('Entries 24-25'!$B:$B,A:A,'Entries 24-25'!$E:$E)+SUMIF('IND AS entries 24-25'!$B:$B,A:A,'IND AS entries 24-25'!$D:$D)-SUMIF('IND AS entries 24-25'!$B:$B,A:A,'IND AS entries 24-25'!$E:$E) -> 0 | F25: =SUM(C25:E25) -> 0 | H25: 0 | I25: 0 | J25: 0 | K25: =SUM(H25:J25) -> 0 | L25: =VLOOKUP(A25,'BS Gr'!A:A,1,FALSE) -> 100470 | M25: =COUNTIF(A:A,A25) -> 1 | N25: =C25-K25 -> 0 | O25: =C25-K25 -> 0 | P25: 0 | Q25: =+K25-P25 -> 0 | S25: =SUMIF('[105]TB for financial'!$A:$A,A25,'[105]TB for financial'!$E:$E) -> #VALUE!
A26: 100480 | B26: Bank-NBD Escrow Checking Acct | C26: =K26 -> 0 | D26: 0 | E26: =SUMIF('Entries 24-25'!$B:$B,A:A,'Entries 24-25'!$D:$D)-SUMIF('Entries 24-25'!$B:$B,A:A,'Entries 24-25'!$E:$E)+SUMIF('IND AS entries 24-25'!$B:$B,A:A,'IND AS entries 24-25'!$D:$D)-SUMIF('IND AS entries 24-25'!$B:$B,A:A,'IND AS entries 24-25'!$E:$E) -> 0 | F26: =SUM(C26:E26) -> 0 | H26: 0 | I26: 0 | J26: 0 | K26: =SUM(H26:J26) -> 0 | L26: =VLOOKUP(A26,'BS Gr'!A:A,1,FALSE) -> 100480 | M26: =COUNTIF(A:A,A26) -> 1 | N26: =C26-K26 -> 0 | O26: =C26-K26 -> 0 | P26: 0 | Q26: =+K26-P26 -> 0 | S26: =SUMIF('[105]TB for financial'!$A:$A,A26,'[105]TB for financial'!$E:$E) -> #VALUE!
A27: 100490 | B27: Syntel Earthquake Relief Fund | C27: =K27 -> 0 | D27: 0 | E27: =SUMIF('Entries 24-25'!$B:$B,A:A,'Entries 24-25'!$D:$D)-SUMIF('Entries 24-25'!$B:$B,A:A,'Entries 24-25'!$E:$E)+SUMIF('IND AS entries 24-25'!$B:$B,A:A,'IND AS entries 24-25'!$D:$D)-SUMIF('IND AS entries 24-25'!$B:$B,A:A,'IND AS entries 24-25'!$E:$E) -> 0 | F27: =SUM(C27:E27) -> 0 | H27: 0 | I27: 0 | J27: 0 | K27: =SUM(H27:J27) -> 0 | L27: =VLOOKUP(A27,'BS Gr'!A:A,1,FALSE) -> 100490 | M27: =COUNTIF(A:A,A27) -> 1 | N27: =C27-K27 -> 0 | O27: =C27-K27 -> 0 | P27: 0 | Q27: =+K27-P27 -> 0 | S27: =SUMIF('[105]TB for financial'!$A:$A,A27,'[105]TB for financial'!$E:$E) -> #VALUE!
A28: 100491 | B28: Bank Of India - USD FCY | C28: =K28 -> 5.8207661e-10 | D28: 0 | E28: =SUMIF('Entries 24-25'!$B:$B,A:A,'Entries 24-25'!$D:$D)-SUMIF('Entries 24-25'!$B:$B,A:A,'Entries 24-25'!$E:$E)+SUMIF('IND AS entries 24-25'!$B:$B,A:A,'IND AS entries 24-25'!$D:$D)-SUMIF('IND AS entries 24-25'!$B:$B,A:A,'IND AS entries 24-25'!$E:$E) -> 0 | F28: =SUM(C28:E28) -> 5.8207661e-10 | H28: 5.8207661e-10 | I28: 0 | J28: 0 | K28: =SUM(H28:J28) -> 5.8207661e-10 | L28: =VLOOKUP(A28,'BS Gr'!A:A,1,FALSE) -> 100491 | M28: =COUNTIF(A:A,A28) -> 1 | N28: =C28-K28 -> 0 | O28: =C28-K28 -> 0 | P28: 458319.35 | Q28: =+K28-P28 -> -458319.35 | S28: =SUMIF('[105]TB for financial'!$A:$A,A28,'[105]TB for financial'!$E:$E) -> #VALUE!
A29: 100492 | B29: Allahabad Bank FD A/c | C29: =K29 -> 0 | D29: 0 | E29: =SUMIF('Entries 24-25'!$B:$B,A:A,'Entries 24-25'!$D:$D)-SUMIF('Entries 24-25'!$B:$B,A:A,'Entries 24-25'!$E:$E)+SUMIF('IND AS entries 24-25'!$B:$B,A:A,'IND AS entries 24-25'!$D:$D)-SUMIF('IND AS entries 24-25'!$B:$B,A:A,'IND AS entries 24-25'!$E:$E) -> 0 | F29: =SUM(C29:E29) -> 0 | H29: 0 | I29: 0 | J29: 0 | K29: =SUM(H29:J29) -> 0 | L29: =VLOOKUP(A29,'BS Gr'!A:A,1,FALSE) -> 100492 | M29: =COUNTIF(A:A,A29) -> 1 | N29: =C29-K29 -> 0 | O29: =C29-K29 -> 0 | P29: 0 | Q29: =+K29-P29 -> 0 | S29: =SUMIF('[105]TB for financial'!$A:$A,A29,'[105]TB for financial'!$E:$E) -> #VALUE!
A30: 100493 | B30: Yes Bank Limited – FD A/c | C30: =K30 -> 0 | D30: 0 | E30: =SUMIF('Entries 24-25'!$B:$B,A:A,'Entries 24-25'!$D:$D)-SUMIF('Entries 24-25'!$B:$B,A:A,'Entries 24-25'!$E:$E)+SUMIF('IND AS entries 24-25'!$B:$B,A:A,'IND AS entries 24-25'!$D:$D)-SUMIF('IND AS entries 24-25'!$B:$B,A:A,'IND AS entries 24-25'!$E:$E) -> 0 | F30: =SUM(C30:E30) -> 0 | H30: 0 | I30: 0 | J30: 0 | K30: =SUM(H30:J30) -> 0 | L30: =VLOOKUP(A30,'BS Gr'!A:A,1,FALSE) -> 100493 | M30: =COUNTIF(A:A,A30) -> 1 | N30: =C30-K30 -> 0 | O30: =C30-K30 -> 0 | P30: 0 | Q30: =+K30-P30 -> 0 | S30: =SUMIF('[105]TB for financial'!$A:$A,A30,'[105]TB for financial'!$E:$E) -> #VALUE!
A31: 100500 | B31: Metier Checking | C31: =K31 -> 0 | D31: 0 | E31: =SUMIF('Entries 24-25'!$B:$B,A:A,'Entries 24-25'!$D:$D)-SUMIF('Entries 24-25'!$B:$B,A:A,'Entries 24-25'!$E:$E)+SUMIF('IND AS entries 24-25'!$B:$B,A:A,'IND AS entries 24-25'!$D:$D)-SUMIF('IND AS entries 24-25'!$B:$B,A:A,'IND AS entries 24-25'!$E:$E) -> 0 | F31: =SUM(C31:E31) -> 0 | H31: 0 | I31: 0 | J31: 0 | K31: =SUM(H31:J31) -> 0 | L31: =VLOOKUP(A31,'BS Gr'!A:A,1,FALSE) -> 100500 | M31: =COUNTIF(A:A,A31) -> 1 | N31: =C31-K31 -> 0 | O31: =C31-K31 -> 0 | P31: 0 | Q31: =+K31-P31 -> 0 | S31: =SUMIF('[105]TB for financial'!$A:$A,A31,'[105]TB for financial'!$E:$E) -> #VALUE!
A32: 100501 | B32: Credit Agricole Indosuez INR | C32: =K32 -> 0 | D32: 0 | E32: =SUMIF('Entries 24-25'!$B:$B,A:A,'Entries 24-25'!$D:$D)-SUMIF('Entries 24-25'!$B:$B,A:A,'Entries 24-25'!$E:$E)+SUMIF('IND AS entries 24-25'!$B:$B,A:A,'IND AS entries 24-25'!$D:$D)-SUMIF('IND AS entries 24-25'!$B:$B,A:A,'IND AS entries 24-25'!$E:$E) -> 0 | F32: =SUM(C32:E32) -> 0 | H32: 0 | I32: 0 | J32: 0 | K32: =SUM(H32:J32) -> 0 | L32: =VLOOKUP(A32,'BS Gr'!A:A,1,FALSE) -> 100501 | M32: =COUNTIF(A:A,A32) -> 1 | N32: =C32-K32 -> 0 | O32: =C32-K32 -> 0 | P32: 0 | Q32: =+K32-P32 -> 0 | S32: =SUMIF('[105]TB for financial'!$A:$A,A32,'[105]TB for financial'!$E:$E) -> #VALUE!
A33: 100502 | B33: Bank of India - INR | C33: =K33 -> 0 | D33: 0 | E33: =SUMIF('Entries 24-25'!$B:$B,A:A,'Entries 24-25'!$D:$D)-SUMIF('Entries 24-25'!$B:$B,A:A,'Entries 24-25'!$E:$E)+SUMIF('IND AS entries 24-25'!$B:$B,A:A,'IND AS entries 24-25'!$D:$D)-SUMIF('IND AS entries 24-25'!$B:$B,A:A,'IND AS entries 24-25'!$E:$E) -> 0 | F33: =SUM(C33:E33) -> 0 | H33: 0 | I33: 0 | J33: 0 | K33: =SUM(H33:J33) -> 0 | L33: =VLOOKUP(A33,'BS Gr'!A:A,1,FALSE) -> 100502 | M33: =COUNTIF(A:A,A33) -> 1 | N33: =C33-K33 -> 0 | O33: =C33-K33 -> 0 | P33: 5371685.5 | Q33: =+K33-P33 -> -5371685.5 | S33: =SUMIF('[105]TB for financial'!$A:$A,A33,'[105]TB for financial'!$E:$E) -> #VALUE!
A34: 100503 | B34: State Bank of India - INR | C34: =K34 -> 0 | D34: 0 | E34: =SUMIF('Entries 24-25'!$B:$B,A:A,'Entries 24-25'!$D:$D)-SUMIF('Entries 24-25'!$B:$B,A:A,'Entries 24-25'!$E:$E)+SUMIF('IND AS entries 24-25'!$B:$B,A:A,'IND AS entries 24-25'!$D:$D)-SUMIF('IND AS entries 24-25'!$B:$B,A:A,'IND AS entries 24-25'!$E:$E) -> 0 | F34: =SUM(C34:E34) -> 0 | H34: 0 | I34: 0 | J34: 0 | K34: =SUM(H34:J34) -> 0 | L34: =VLOOKUP(A34,'BS Gr'!A:A,1,FALSE) -> 100503 | M34: =COUNTIF(A:A,A34) -> 1 | N34: =C34-K34 -> 0 | O34: =C34-K34 -> 0 | P34: 0 | Q34: =+K34-P34 -> 0 | S34: =SUMIF('[105]TB for financial'!$A:$A,A34,'[105]TB for financial'!$E:$E) -> #VALUE!
A35: 100504 | B35: Standard Chartered - INR Mumbai | C35: =K35 -> 0 | D35: 0 | E35: =SUMIF('Entries 24-25'!$B:$B,A:A,'Entries 24-25'!$D:$D)-SUMIF('Entries 24-25'!$B:$B,A:A,'Entries 24-25'!$E:$E)+SUMIF('IND AS entries 24-25'!$B:$B,A:A,'IND AS entries 24-25'!$D:$D)-SUMIF('IND AS entries 24-25'!$B:$B,A:A,'IND AS entries 24-25'!$E:$E) -> 0 | F35: =SUM(C35:E35) -> 0 | H35: 0 | I35: 0 | J35: 0 | K35: =SUM(H35:J35) -> 0 | L35: =VLOOKUP(A35,'BS Gr'!A:A,1,FALSE) -> 100504 | M35: =COUNTIF(A:A,A35) -> 1 | N35: =C35-K35 -> 0 | O35: =C35-K35 -> 0 | P35: 0 | Q35: =+K35-P35 -> 0 | S35: =SUMIF('[105]TB for financial'!$A:$A,A35,'[105]TB for financial'!$E:$E) -> #VALUE!
... A149: 101065 | B149: Accounts Receivable - Accrued | C149: =K149 -> 0.010000015 | D149: 0 | E149: =SUMIF('Entries 24-25'!$B:$B,A:A,'Entries 24-25'!$D:$D)-SUMIF('Entries 24-25'!$B:$B,A:A,'Entries 24-25'!$E:$E)+SUMIF('IND AS entries 24-25'!$B:$B,A:A,'IND AS entries 24-25'!$D:$D)-SUMIF('IND AS entries 24-25'!$B:$B,A:A,'IND AS entries 24-25'!$E:$E) -> 0 | F149: =SUM(C149:E149) -> 0.010000015 | H149: 0.010000015 | I149: 0 | J149: 0 | K149: =SUM(H149:J149) -> 0.010000015 | L149: =VLOOKUP(A149,'BS Gr'!A:A,1,FALSE) -> 101065 | M149: =COUNTIF(A:A,A149) -> 1 | N149: =C149-K149 -> 0 | O149: =C149-K149 -> 0 | P149: 0.010000015 | Q149: =+K149-P149 -> 0 | S149: =SUMIF('[105]TB for financial'!$A:$A,A149,'[105]TB for financial'!$E:$E) -> #VALUE!
A150: 101066 | B150: Interco AR accruals | C150: =K150 -> 0 | D150: 0 | E150: =SUMIF('Entries 24-25'!$B:$B,A:A,'Entries 24-25'!$D:$D)-SUMIF('Entries 24-25'!$B:$B,A:A,'Entries 24-25'!$E:$E)+SUMIF('IND AS entries 24-25'!$B:$B,A:A,'IND AS entries 24-25'!$D:$D)-SUMIF('IND AS entries 24-25'!$B:$B,A:A,'IND AS entries 24-25'!$E:$E) -> 0 | F150: =SUM(C150:E150) -> 0 | H150: 0 | I150: 0 | J150: 0 | K150: =SUM(H150:J150) -> 0 | L150: =VLOOKUP(A150,'BS Gr'!A:A,1,FALSE) -> 101066 | M150: =COUNTIF(A:A,A150) -> 1 | N150: =C150-K150 -> 0 | O150: =C150-K150 -> 0 | Q150: =+K150-P150 -> 0 | S150: =SUMIF('[105]TB for financial'!$A:$A,A150,'[105]TB for financial'!$E:$E) -> #VALUE!
A151: 101090 | B151: AR - Volume Rebate | C151: =K151 -> 1.62 | D151: 0 | E151: =SUMIF('Entries 24-25'!$B:$B,A:A,'Entries 24-25'!$D:$D)-SUMIF('Entries 24-25'!$B:$B,A:A,'Entries 24-25'!$E:$E)+SUMIF('IND AS entries 24-25'!$B:$B,A:A,'IND AS entries 24-25'!$D:$D)-SUMIF('IND AS entries 24-25'!$B:$B,A:A,'IND AS entries 24-25'!$E:$E) -> 0 | F151: =SUM(C151:E151) -> 1.62 | H151: 1.62 | I151: 0 | J151: 0 | K151: =SUM(H151:J151) -> 1.62 | L151: =VLOOKUP(A151,'BS Gr'!A:A,1,FALSE) -> 101090 | M151: =COUNTIF(A:A,A151) -> 1 | N151: =C151-K151 -> 0 | O151: =C151-K151 -> 0 | P151: 1.62 | Q151: =+K151-P151 -> 0 | S151: =SUMIF('[105]TB for financial'!$A:$A,A151,'[105]TB for financial'!$E:$E) -> #VALUE!
A152: 101120 | B152: Accounts Receivable - Advance | C152: =K152 -> 0 | D152: 0 | E152: =SUMIF('Entries 24-25'!$B:$B,A:A,'Entries 24-25'!$D:$D)-SUMIF('Entries 24-25'!$B:$B,A:A,'Entries 24-25'!$E:$E)+SUMIF('IND AS entries 24-25'!$B:$B,A:A,'IND AS entries 24-25'!$D:$D)-SUMIF('IND AS entries 24-25'!$B:$B,A:A,'IND AS entries 24-25'!$E:$E) -> 0 | F152: =SUM(C152:E152) -> 0 | H152: 0 | I152: 0 | J152: 0 | K152: =SUM(H152:J152) -> 0 | L152: =VLOOKUP(A152,'BS Gr'!A:A,1,FALSE) -> 101120 | M152: =COUNTIF(A:A,A152) -> 1 | N152: =C152-K152 -> 0 | O152: =C152-K152 -> 0 | P152: 0 | Q152: =+K152-P152 -> 0 | S152: =SUMIF('[105]TB for financial'!$A:$A,A152,'[105]TB for financial'!$E:$E) -> #VALUE!
A153: 101130 | B153: Accounts Receivables - Retaina | C153: =K153 -> 0 | D153: 0 | E153: =SUMIF('Entries 24-25'!$B:$B,A:A,'Entries 24-25'!$D:$D)-SUMIF('Entries 24-25'!$B:$B,A:A,'Entries 24-25'!$E:$E)+SUMIF('IND AS entries 24-25'!$B:$B,A:A,'IND AS entries 24-25'!$D:$D)-SUMIF('IND AS entries 24-25'!$B:$B,A:A,'IND AS entries 24-25'!$E:$E) -> 0 | F153: =SUM(C153:E153) -> 0 | H153: 0 | I153: 0 | J153: 0 | K153: =SUM(H153:J153) -> 0 | L153: =VLOOKUP(A153,'BS Gr'!A:A,1,FALSE) -> 101130 | M153: =COUNTIF(A:A,A153) -> 1 | N153: =C153-K153 -> 0 | O153: =C153-K153 -> 0 | P153: 0 | Q153: =+K153-P153 -> 0 | S153: =SUMIF('[105]TB for financial'!$A:$A,A153,'[105]TB for financial'!$E:$E) -> #VALUE!
A154: 101150 | B154: Accounts Receivable Other | C154: =K154 -> 0 | D154: 0 | E154: =SUMIF('Entries 24-25'!$B:$B,A:A,'Entries 24-25'!$D:$D)-SUMIF('Entries 24-25'!$B:$B,A:A,'Entries 24-25'!$E:$E)+SUMIF('IND AS entries 24-25'!$B:$B,A:A,'IND AS entries 24-25'!$D:$D)-SUMIF('IND AS entries 24-25'!$B:$B,A:A,'IND AS entries 24-25'!$E:$E) -> 0 | F154: =SUM(C154:E154) -> 0 | H154: 0 | I154: 0 | J154: 0 | K154: =SUM(H154:J154) -> 0 | L154: =VLOOKUP(A154,'BS Gr'!A:A,1,FALSE) -> 101150 | M154: =COUNTIF(A:A,A154) -> 1 | N154: =C154-K154 -> 0 | O154: =C154-K154 -> 0 | P154: 0 | Q154: =+K154-P154 -> 0 | S154: =SUMIF('[105]TB for financial'!$A:$A,A154,'[105]TB for financial'!$E:$E) -> #VALUE!
A155: 101160 | B155: Interest Receivable | C155: =K155 -> 0 | D155: 0 | E155: =SUMIF('Entries 24-25'!$B:$B,A:A,'Entries 24-25'!$D:$D)-SUMIF('Entries 24-25'!$B:$B,A:A,'Entries 24-25'!$E:$E)+SUMIF('IND AS entries 24-25'!$B:$B,A:A,'IND AS entries 24-25'!$D:$D)-SUMIF('IND AS entries 24-25'!$B:$B,A:A,'IND AS entries 24-25'!$E:$E) -> 0 | F155: =SUM(C155:E155) -> 0 | H155: 0 | I155: 0 | J155: 0 | K155: =SUM(H155:J155) -> 0 | L155: =VLOOKUP(A155,'BS Gr'!A:A,1,FALSE) -> 101160 | M155: =COUNTIF(A:A,A155) -> 1 | N155: =C155-K155 -> 0 | O155: =C155-K155 -> 0 | P155: 10347875 | Q155: =+K155-P155 -> -10347875 | S155: =SUMIF('[105]TB for financial'!$A:$A,A155,'[105]TB for financial'!$E:$E) -> #VALUE!
A156: 101170 | B156: A/R from Syntel UK | C156: =K156 -> 0 | D156: 0 | E156: =SUMIF('Entries 24-25'!$B:$B,A:A,'Entries 24-25'!$D:$D)-SUMIF('Entries 24-25'!$B:$B,A:A,'Entries 24-25'!$E:$E)+SUMIF('IND AS entries 24-25'!$B:$B,A:A,'IND AS entries 24-25'!$D:$D)-SUMIF('IND AS entries 24-25'!$B:$B,A:A,'IND AS entries 24-25'!$E:$E) -> 0 | F156: =SUM(C156:E156) -> 0 | H156: 0 | I156: 0 | J156: 0 | K156: =SUM(H156:J156) -> 0 | L156: =VLOOKUP(A156,'BS Gr'!A:A,1,FALSE) -> 101170 | M156: =COUNTIF(A:A,A156) -> 1 | N156: =C156-K156 -> 0 | O156: =C156-K156 -> 0 | P156: 0 | Q156: =+K156-P156 -> 0 | S156: =SUMIF('[105]TB for financial'!$A:$A,A156,'[105]TB for financial'!$E:$E) -> #VALUE!
A157: 101180 | B157: A/R from Syntel Singapore | C157: =K157 -> 0 | D157: 0 | E157: =SUMIF('Entries 24-25'!$B:$B,A:A,'Entries 24-25'!$D:$D)-SUMIF('Entries 24-25'!$B:$B,A:A,'Entries 24-25'!$E:$E)+SUMIF('IND AS entries 24-25'!$B:$B,A:A,'IND AS entries 24-25'!$D:$D)-SUMIF('IND AS entries 24-25'!$B:$B,A:A,'IND AS entries 24-25'!$E:$E) -> 0 | F157: =SUM(C157:E157) -> 0 | H157: 0 | I157: 0 | J157: 0 | K157: =SUM(H157:J157) -> 0 | L157: =VLOOKUP(A157,'BS Gr'!A:A,1,FALSE) -> 101180 | M157: =COUNTIF(A:A,A157) -> 1 | N157: =C157-K157 -> 0 | O157: =C157-K157 -> 0 | P157: 0 | Q157: =+K157-P157 -> 0 | S157: =SUMIF('[105]TB for financial'!$A:$A,A157,'[105]TB for financial'!$E:$E) -> #VALUE!
A158: 101190 | B158: Employee Loans | C158: =K158 -> 0 | D158: 0 | E158: =SUMIF('Entries 24-25'!$B:$B,A:A,'Entries 24-25'!$D:$D)-SUMIF('Entries 24-25'!$B:$B,A:A,'Entries 24-25'!$E:$E)+SUMIF('IND AS entries 24-25'!$B:$B,A:A,'IND AS entries 24-25'!$D:$D)-SUMIF('IND AS entries 24-25'!$B:$B,A:A,'IND AS entries 24-25'!$E:$E) -> 0 | F158: =SUM(C158:E158) -> 0 | H158: 0 | I158: 0 | J158: 0 | K158: =SUM(H158:J158) -> 0 | L158: =VLOOKUP(A158,'BS Gr'!A:A,1,FALSE) -> 101190 | M158: =COUNTIF(A:A,A158) -> 1 | N158: =C158-K158 -> 0 | O158: =C158-K158 -> 0 | P158: 0 | Q158: =+K158-P158 -> 0 | S158: =SUMIF('[105]TB for financial'!$A:$A,A158,'[105]TB for financial'!$E:$E) -> #VALUE!
A159: 101200 | B159: Transition Cost Defferal | C159: =K159 -> 0 | D159: 0 | E159: =SUMIF('Entries 24-25'!$B:$B,A:A,'Entries 24-25'!$D:$D)-SUMIF('Entries 24-25'!$B:$B,A:A,'Entries 24-25'!$E:$E)+SUMIF('IND AS entries 24-25'!$B:$B,A:A,'IND AS entries 24-25'!$D:$D)-SUMIF('IND AS entries 24-25'!$B:$B,A:A,'IND AS entries 24-25'!$E:$E) -> 0 | F159: =SUM(C159:E159) -> 0 | H159: 0 | I159: 0 | J159: 0 | K159: =SUM(H159:J159) -> 0 | L159: =VLOOKUP(A159,'BS Gr'!A:A,1,FALSE) -> 101200 | M159: =COUNTIF(A:A,A159) -> 1 | N159: =C159-K159 -> 0 | O159: =C159-K159 -> 0 | P159: 0 | Q159: =+K159-P159 -> 0 | S159: =SUMIF('[105]TB for financial'!$A:$A,A159,'[105]TB for financial'!$E:$E) -> #VALUE!
A160: 101201 | B160: No Sow- Cost Deferred | C160: =K160 -> 0 | D160: 0 | E160: =SUMIF('Entries 24-25'!$B:$B,A:A,'Entries 24-25'!$D:$D)-SUMIF('Entries 24-25'!$B:$B,A:A,'Entries 24-25'!$E:$E)+SUMIF('IND AS entries 24-25'!$B:$B,A:A,'IND AS entries 24-25'!$D:$D)-SUMIF('IND AS entries 24-25'!$B:$B,A:A,'IND AS entries 24-25'!$E:$E) -> 0 | F160: =SUM(C160:E160) -> 0 | H160: 0 | I160: 0 | J160: 0 | K160: =SUM(H160:J160) -> 0 | L160: =VLOOKUP(A160,'BS Gr'!A:A,1,FALSE) -> 101201 | M160: =COUNTIF(A:A,A160) -> 1 | N160: =C160-K160 -> 0 | O160: =C160-K160 -> 0 | P160: 0 | Q160: =+K160-P160 -> 0 | S160: =SUMIF('[105]TB for financial'!$A:$A,A160,'[105]TB for financial'!$E:$E) -> #VALUE!
A161: 101202 | B161: Deferred Cost-WIP | C161: =K161 -> 0 | D161: 0 | E161: =SUMIF('Entries 24-25'!$B:$B,A:A,'Entries 24-25'!$D:$D)-SUMIF('Entries 24-25'!$B:$B,A:A,'Entries 24-25'!$E:$E)+SUMIF('IND AS entries 24-25'!$B:$B,A:A,'IND AS entries 24-25'!$D:$D)-SUMIF('IND AS entries 24-25'!$B:$B,A:A,'IND AS entries 24-25'!$E:$E) -> 0 | F161: =SUM(C161:E161) -> 0 | H161: 0 | I161: 0 | J161: 0 | K161: =SUM(H161:J161) -> 0 | L161: =VLOOKUP(A161,'BS Gr'!A:A,1,FALSE) -> 101202 | M161: =COUNTIF(A:A,A161) -> 1 | N161: =C161-K161 -> 0 | O161: =C161-K161 -> 0 | P161: 0 | Q161: =+K161-P161 -> 0 | S161: =SUMIF('[105]TB for financial'!$A:$A,A161,'[105]TB for financial'!$E:$E) -> #VALUE!
A162: 101309 | B162: Employee F. Travel Adv-Jersey | C162: =K162 -> 0 | D162: 0 | E162: =SUMIF('Entries 24-25'!$B:$B,A:A,'Entries 24-25'!$D:$D)-SUMIF('Entries 24-25'!$B:$B,A:A,'Entries 24-25'!$E:$E)+SUMIF('IND AS entries 24-25'!$B:$B,A:A,'IND AS entries 24-25'!$D:$D)-SUMIF('IND AS entries 24-25'!$B:$B,A:A,'IND AS entries 24-25'!$E:$E) -> 0 | F162: =SUM(C162:E162) -> 0 | H162: 0 | I162: 0 | J162: 0 | K162: =SUM(H162:J162) -> 0 | L162: =VLOOKUP(A162,'BS Gr'!A:A,1,FALSE) -> 101309 | M162: =COUNTIF(A:A,A162) -> 1 | N162: =C162-K162 -> 0 | O162: =C162-K162 -> 0 | P162: 0 | Q162: =+K162-P162 -> 0 | S162: =SUMIF('[105]TB for financial'!$A:$A,A162,'[105]TB for financial'!$E:$E) -> #VALUE!
... A253: 101495 | B253: Early Paymt Disc Def. - Int Co | C253: =K253 -> 0 | D253: 0 | E253: =SUMIF('Entries 24-25'!$B:$B,A:A,'Entries 24-25'!$D:$D)-SUMIF('Entries 24-25'!$B:$B,A:A,'Entries 24-25'!$E:$E)+SUMIF('IND AS entries 24-25'!$B:$B,A:A,'IND AS entries 24-25'!$D:$D)-SUMIF('IND AS entries 24-25'!$B:$B,A:A,'IND AS entries 24-25'!$E:$E) -> 0 | F253: =SUM(C253:E253) -> 0 | H253: 0 | I253: 0 | J253: 0 | K253: =SUM(H253:J253) -> 0 | L253: =VLOOKUP(A253,'BS Gr'!A:A,1,FALSE) -> 101495 | M253: =COUNTIF(A:A,A253) -> 1 | N253: =C253-K253 -> 0 | O253: =C253-K253 -> 0 | P253: 0 | Q253: =+K253-P253 -> 0 | S253: =SUMIF('[105]TB for financial'!$A:$A,A253,'[105]TB for financial'!$E:$E) -> #VALUE!
A254: 101701 | B254: MAH. SEZ - SGST Recoverable | C254: =K254 -> 0 | D254: 0 | E254: =SUMIF('Entries 24-25'!$B:$B,A:A,'Entries 24-25'!$D:$D)-SUMIF('Entries 24-25'!$B:$B,A:A,'Entries 24-25'!$E:$E)+SUMIF('IND AS entries 24-25'!$B:$B,A:A,'IND AS entries 24-25'!$D:$D)-SUMIF('IND AS entries 24-25'!$B:$B,A:A,'IND AS entries 24-25'!$E:$E) -> 0 | F254: =SUM(C254:E254) -> 0 | H254: 0 | I254: 0 | J254: 0 | K254: =SUM(H254:J254) -> 0 | L254: =VLOOKUP(A254,'BS Gr'!A:A,1,FALSE) -> 101701 | M254: =COUNTIF(A:A,A254) -> 1 | N254: =C254-K254 -> 0 | O254: =C254-K254 -> 0 | S254: =SUMIF('[105]TB for financial'!$A:$A,A254,'[105]TB for financial'!$E:$E) -> #VALUE!
A255: 101702 | B255: MAH. SEZ - CGST Recoverable | C255: =K255 -> 0 | D255: 0 | E255: =SUMIF('Entries 24-25'!$B:$B,A:A,'Entries 24-25'!$D:$D)-SUMIF('Entries 24-25'!$B:$B,A:A,'Entries 24-25'!$E:$E)+SUMIF('IND AS entries 24-25'!$B:$B,A:A,'IND AS entries 24-25'!$D:$D)-SUMIF('IND AS entries 24-25'!$B:$B,A:A,'IND AS entries 24-25'!$E:$E) -> 0 | F255: =SUM(C255:E255) -> 0 | H255: 0 | I255: 0 | J255: 0 | K255: =SUM(H255:J255) -> 0 | L255: =VLOOKUP(A255,'BS Gr'!A:A,1,FALSE) -> 101702 | M255: =COUNTIF(A:A,A255) -> 1 | N255: =C255-K255 -> 0 | O255: =C255-K255 -> 0 | S255: =SUMIF('[105]TB for financial'!$A:$A,A255,'[105]TB for financial'!$E:$E) -> #VALUE!
A256: 101703 | B256: MAH. SEZ - IGST Recoverable | C256: =K256 -> 0 | D256: 0 | E256: =SUMIF('Entries 24-25'!$B:$B,A:A,'Entries 24-25'!$D:$D)-SUMIF('Entries 24-25'!$B:$B,A:A,'Entries 24-25'!$E:$E)+SUMIF('IND AS entries 24-25'!$B:$B,A:A,'IND AS entries 24-25'!$D:$D)-SUMIF('IND AS entries 24-25'!$B:$B,A:A,'IND AS entries 24-25'!$E:$E) -> 0 | F256: =SUM(C256:E256) -> 0 | H256: 0 | I256: 0 | J256: 0 | K256: =SUM(H256:J256) -> 0 | L256: =VLOOKUP(A256,'BS Gr'!A:A,1,FALSE) -> 101703 | M256: =COUNTIF(A:A,A256) -> 1 | N256: =C256-K256 -> 0 | O256: =C256-K256 -> 0 | S256: =SUMIF('[105]TB for financial'!$A:$A,A256,'[105]TB for financial'!$E:$E) -> #VALUE!
A257: 101704 | B257: MAH. NSEZ - SGST Recoverable | C257: =K257 -> 1 | D257: 0 | E257: =SUMIF('Entries 24-25'!$B:$B,A:A,'Entries 24-25'!$D:$D)-SUMIF('Entries 24-25'!$B:$B,A:A,'Entries 24-25'!$E:$E)+SUMIF('IND AS entries 24-25'!$B:$B,A:A,'IND AS entries 24-25'!$D:$D)-SUMIF('IND AS entries 24-25'!$B:$B,A:A,'IND AS entries 24-25'!$E:$E) -> 0 | F257: =SUM(C257:E257) -> 1 | H257: 1 | I257: 0 | J257: 0 | K257: =SUM(H257:J257) -> 1 | L257: =VLOOKUP(A257,'BS Gr'!A:A,1,FALSE) -> 101704 | M257: =COUNTIF(A:A,A257) -> 1 | N257: =C257-K257 -> 0 | O257: =C257-K257 -> 0 | S257: =SUMIF('[105]TB for financial'!$A:$A,A257,'[105]TB for financial'!$E:$E) -> #VALUE!
A258: 101705 | B258: MAH. NSEZ - CGST Recoverable | C258: =K258 -> 1 | D258: 0 | E258: =SUMIF('Entries 24-25'!$B:$B,A:A,'Entries 24-25'!$D:$D)-SUMIF('Entries 24-25'!$B:$B,A:A,'Entries 24-25'!$E:$E)+SUMIF('IND AS entries 24-25'!$B:$B,A:A,'IND AS entries 24-25'!$D:$D)-SUMIF('IND AS entries 24-25'!$B:$B,A:A,'IND AS entries 24-25'!$E:$E) -> 0 | F258: =SUM(C258:E258) -> 1 | H258: 1 | I258: 0 | J258: 0 | K258: =SUM(H258:J258) -> 1 | L258: =VLOOKUP(A258,'BS Gr'!A:A,1,FALSE) -> 101705 | M258: =COUNTIF(A:A,A258) -> 1 | N258: =C258-K258 -> 0 | O258: =C258-K258 -> 0 | S258: =SUMIF('[105]TB for financial'!$A:$A,A258,'[105]TB for financial'!$E:$E) -> #VALUE!
A259: 101741 | B259: Contra control account | C259: =K259 -> 0 | D259: 0 | E259: =SUMIF('Entries 24-25'!$B:$B,A:A,'Entries 24-25'!$D:$D)-SUMIF('Entries 24-25'!$B:$B,A:A,'Entries 24-25'!$E:$E)+SUMIF('IND AS entries 24-25'!$B:$B,A:A,'IND AS entries 24-25'!$D:$D)-SUMIF('IND AS entries 24-25'!$B:$B,A:A,'IND AS entries 24-25'!$E:$E) -> 0 | F259: =SUM(C259:E259) -> 0 | H259: 0 | I259: 0 | J259: 0 | K259: =SUM(H259:J259) -> 0 | L259: =VLOOKUP(A259,'BS Gr'!A:A,1,FALSE) -> #N/A | M259: =COUNTIF(A:A,A259) -> 1 | N259: =C259-K259 -> 0 | O259: =C259-K259 -> 0 | P259: 0 | Q259: =+K259-P259 -> 0 | S259: =SUMIF('[105]TB for financial'!$A:$A,A259,'[105]TB for financial'!$E:$E) -> #VALUE!
A260: 101750 | B260: Service Tax Recoverable - non | C260: =K260 -> 0 | D260: 0 | E260: =SUMIF('Entries 24-25'!$B:$B,A:A,'Entries 24-25'!$D:$D)-SUMIF('Entries 24-25'!$B:$B,A:A,'Entries 24-25'!$E:$E)+SUMIF('IND AS entries 24-25'!$B:$B,A:A,'IND AS entries 24-25'!$D:$D)-SUMIF('IND AS entries 24-25'!$B:$B,A:A,'IND AS entries 24-25'!$E:$E) -> 0 | F260: =SUM(C260:E260) -> 0 | H260: 0 | I260: 0 | J260: 0 | K260: =SUM(H260:J260) -> 0 | L260: =VLOOKUP(A260,'BS Gr'!A:A,1,FALSE) -> 101750 | M260: =COUNTIF(A:A,A260) -> 1 | N260: =C260-K260 -> 0 | O260: =C260-K260 -> 0 | S260: =SUMIF('[105]TB for financial'!$A:$A,A260,'[105]TB for financial'!$E:$E) -> #VALUE!
A261: 101760 | B261: Service Tax Recoverable - non | C261: =K261 -> 0 | D261: 0 | E261: =SUMIF('Entries 24-25'!$B:$B,A:A,'Entries 24-25'!$D:$D)-SUMIF('Entries 24-25'!$B:$B,A:A,'Entries 24-25'!$E:$E)+SUMIF('IND AS entries 24-25'!$B:$B,A:A,'IND AS entries 24-25'!$D:$D)-SUMIF('IND AS entries 24-25'!$B:$B,A:A,'IND AS entries 24-25'!$E:$E) -> 0 | F261: =SUM(C261:E261) -> 0 | H261: 0 | I261: 0 | J261: 0 | K261: =SUM(H261:J261) -> 0 | L261: =VLOOKUP(A261,'BS Gr'!A:A,1,FALSE) -> 101760 | M261: =COUNTIF(A:A,A261) -> 1 | N261: =C261-K261 -> 0 | O261: =C261-K261 -> 0 | S261: =SUMIF('[105]TB for financial'!$A:$A,A261,'[105]TB for financial'!$E:$E) -> #VALUE!
A262: 101751 | B262: Service Tax Refundable | C262: =K262 -> 0 | D262: 0 | E262: =SUMIF('Entries 24-25'!$B:$B,A:A,'Entries 24-25'!$D:$D)-SUMIF('Entries 24-25'!$B:$B,A:A,'Entries 24-25'!$E:$E)+SUMIF('IND AS entries 24-25'!$B:$B,A:A,'IND AS entries 24-25'!$D:$D)-SUMIF('IND AS entries 24-25'!$B:$B,A:A,'IND AS entries 24-25'!$E:$E) -> 0 | F262: =SUM(C262:E262) -> 0 | H262: 0 | I262: 0 | J262: 0 | K262: =SUM(H262:J262) -> 0 | L262: =VLOOKUP(A262,'BS Gr'!A:A,1,FALSE) -> 101751 | M262: =COUNTIF(A:A,A262) -> 1 | N262: =C262-K262 -> 0 | O262: =C262-K262 -> 0 | P262: 0 | Q262: =+K262-P262 -> 0 | S262: =SUMIF('[105]TB for financial'!$A:$A,A262,'[105]TB for financial'!$E:$E) -> #VALUE!
A263: 101780 | B263: Deferred Tax Assets - Current | C263: =K263 -> 0.00443 | D263: 0 | E263: =SUMIF('Entries 24-25'!$B:$B,A:A,'Entries 24-25'!$D:$D)-SUMIF('Entries 24-25'!$B:$B,A:A,'Entries 24-25'!$E:$E)+SUMIF('IND AS entries 24-25'!$B:$B,A:A,'IND AS entries 24-25'!$D:$D)-SUMIF('IND AS entries 24-25'!$B:$B,A:A,'IND AS entries 24-25'!$E:$E) -> 0 | F263: =SUM(C263:E263) -> 0.00443 | H263: 0.00443 | I263: 0 | J263: 0 | K263: =SUM(H263:J263) -> 0.00443 | L263: =VLOOKUP(A263,'BS Gr'!A:A,1,FALSE) -> 101780 | M263: =COUNTIF(A:A,A263) -> 1 | N263: =C263-K263 -> 0 | O263: =C263-K263 -> 0 | P263: 102741.07 | Q263: =+K263-P263 -> -102741.07 | S263: =SUMIF('[105]TB for financial'!$A:$A,A263,'[105]TB for financial'!$E:$E) -> #VALUE!
A264: 101785 | B264: Line of Credit-New2usa.com | C264: =K264 -> 0 | D264: 0 | E264: =SUMIF('Entries 24-25'!$B:$B,A:A,'Entries 24-25'!$D:$D)-SUMIF('Entries 24-25'!$B:$B,A:A,'Entries 24-25'!$E:$E)+SUMIF('IND AS entries 24-25'!$B:$B,A:A,'IND AS entries 24-25'!$D:$D)-SUMIF('IND AS entries 24-25'!$B:$B,A:A,'IND AS entries 24-25'!$E:$E) -> 0 | F264: =SUM(C264:E264) -> 0 | H264: 0 | I264: 0 | J264: 0 | K264: =SUM(H264:J264) -> 0 | L264: =VLOOKUP(A264,'BS Gr'!A:A,1,FALSE) -> 101785 | M264: =COUNTIF(A:A,A264) -> 1 | N264: =C264-K264 -> 0 | O264: =C264-K264 -> 0 | P264: 0 | Q264: =+K264-P264 -> 0 | S264: =SUMIF('[105]TB for financial'!$A:$A,A264,'[105]TB for financial'!$E:$E) -> #VALUE!
A265: 101788 | B265: Educational Cess Recoverable | C265: =K265 -> -0.0052 | D265: 0 | E265: =SUMIF('Entries 24-25'!$B:$B,A:A,'Entries 24-25'!$D:$D)-SUMIF('Entries 24-25'!$B:$B,A:A,'Entries 24-25'!$E:$E)+SUMIF('IND AS entries 24-25'!$B:$B,A:A,'IND AS entries 24-25'!$D:$D)-SUMIF('IND AS entries 24-25'!$B:$B,A:A,'IND AS entries 24-25'!$E:$E) -> 0 | F265: =SUM(C265:E265) -> -0.0052 | H265: -0.0052 | I265: 0 | J265: 0 | K265: =SUM(H265:J265) -> -0.0052 | L265: =VLOOKUP(A265,'BS Gr'!A:A,1,FALSE) -> 101788 | M265: =COUNTIF(A:A,A265) -> 1 | N265: =C265-K265 -> 0 | O265: =C265-K265 -> 0 | P265: -0.0052 | Q265: =+K265-P265 -> 0 | S265: =SUMIF('[105]TB for financial'!$A:$A,A265,'[105]TB for financial'!$E:$E) -> #VALUE!
A266: 101789 | B266: Derivative Assets | C266: =K266 -> 0 | D266: 0 | E266: =SUMIF('Entries 24-25'!$B:$B,A:A,'Entries 24-25'!$D:$D)-SUMIF('Entries 24-25'!$B:$B,A:A,'Entries 24-25'!$E:$E)+SUMIF('IND AS entries 24-25'!$B:$B,A:A,'IND AS entries 24-25'!$D:$D)-SUMIF('IND AS entries 24-25'!$B:$B,A:A,'IND AS entries 24-25'!$E:$E) -> 0 | F266: =SUM(C266:E266) -> 0 | H266: 0 | I266: 0 | J266: 0 | K266: =SUM(H266:J266) -> 0 | L266: =VLOOKUP(A266,'BS Gr'!A:A,1,FALSE) -> 101789 | M266: =COUNTIF(A:A,A266) -> 1 | N266: =C266-K266 -> 0 | O266: =C266-K266 -> 0 | P266: 0 | Q266: =+K266-P266 -> 0 | S266: =SUMIF('[105]TB for financial'!$A:$A,A266,'[105]TB for financial'!$E:$E) -> #VALUE!
A267: 101790 | B267: Advance Tax Payments | C267: =K267 -> -0.00494048 | D267: 0 | E267: =SUMIF('Entries 24-25'!$B:$B,A:A,'Entries 24-25'!$D:$D)-SUMIF('Entries 24-25'!$B:$B,A:A,'Entries 24-25'!$E:$E)+SUMIF('IND AS entries 24-25'!$B:$B,A:A,'IND AS entries 24-25'!$D:$D)-SUMIF('IND AS entries 24-25'!$B:$B,A:A,'IND AS entries 24-25'!$E:$E) -> 0 | F267: =SUM(C267:E267) -> -0.00494048 | H267: -0.00494048 | I267: 0 | J267: 0 | K267: =SUM(H267:J267) -> -0.00494048 | L267: =VLOOKUP(A267,'BS Gr'!A:A,1,FALSE) -> 101790 | M267: =COUNTIF(A:A,A267) -> 1 | N267: =C267-K267 -> 0 | O267: =C267-K267 -> 0 | P267: -0.00494048 | Q267: =+K267-P267 -> 0 | S267: =SUMIF('[105]TB for financial'!$A:$A,A267,'[105]TB for financial'!$E:$E) -> #VALUE!
A268: 101791 | B268: CST Refundable | C268: =K268 -> 0 | D268: 0 | E268: =SUMIF('Entries 24-25'!$B:$B,A:A,'Entries 24-25'!$D:$D)-SUMIF('Entries 24-25'!$B:$B,A:A,'Entries 24-25'!$E:$E)+SUMIF('IND AS entries 24-25'!$B:$B,A:A,'IND AS entries 24-25'!$D:$D)-SUMIF('IND AS entries 24-25'!$B:$B,A:A,'IND AS entries 24-25'!$E:$E) -> 0 | F268: =SUM(C268:E268) -> 0 | H268: 0 | I268: 0 | J268: 0 | K268: =SUM(H268:J268) -> 0 | L268: =VLOOKUP(A268,'BS Gr'!A:A,1,FALSE) -> 101791 | M268: =COUNTIF(A:A,A268) -> 1 | N268: =C268-K268 -> 0 | O268: =C268-K268 -> 0 | P268: 0 | Q268: =+K268-P268 -> 0 | S268: =SUMIF('[105]TB for financial'!$A:$A,A268,'[105]TB for financial'!$E:$E) -> #VALUE!
A269: 101792 | B269: Vat recoverable | C269: =K269 -> 0 | D269: 0 | E269: =SUMIF('Entries 24-25'!$B:$B,A:A,'Entries 24-25'!$D:$D)-SUMIF('Entries 24-25'!$B:$B,A:A,'Entries 24-25'!$E:$E)+SUMIF('IND AS entries 24-25'!$B:$B,A:A,'IND AS entries 24-25'!$D:$D)-SUMIF('IND AS entries 24-25'!$B:$B,A:A,'IND AS entries 24-25'!$E:$E) -> 0 | F269: =SUM(C269:E269) -> 0 | H269: 0 | I269: 0 | J269: 0 | K269: =SUM(H269:J269) -> 0 | L269: =VLOOKUP(A269,'BS Gr'!A:A,1,FALSE) -> 101792 | M269: =COUNTIF(A:A,A269) -> 1 | N269: =C269-K269 -> 0 | O269: =C269-K269 -> 0 | P269: 0 | Q269: =+K269-P269 -> 0 | S269: =SUMIF('[105]TB for financial'!$A:$A,A269,'[105]TB for financial'!$E:$E) -> #VALUE!
A270: 101365 | B270: Service Tax Accrual Account | C270: =K270 -> 0 | D270: 0 | E270: =SUMIF('Entries 24-25'!$B:$B,A:A,'Entries 24-25'!$D:$D)-SUMIF('Entries 24-25'!$B:$B,A:A,'Entries 24-25'!$E:$E)+SUMIF('IND AS entries 24-25'!$B:$B,A:A,'IND AS entries 24-25'!$D:$D)-SUMIF('IND AS entries 24-25'!$B:$B,A:A,'IND AS entries 24-25'!$E:$E) -> 0 | F270: =SUM(C270:E270) -> 0 | H270: 0 | I270: 0 | J270: 0 | K270: =SUM(H270:J270) -> 0 | L270: =VLOOKUP(A270,'BS Gr'!A:A,1,FALSE) -> 101365 | M270: =COUNTIF(A:A,A270) -> 1 | N270: =C270-K270 -> 0 | O270: =C270-K270 -> 0 | P270: 0 | Q270: =+K270-P270 -> 0 | S270: =SUMIF('[105]TB for financial'!$A:$A,A270,'[105]TB for financial'!$E:$E) -> #VALUE!
A271: 101793 | B271: Service Tax Recoverable | C271: =K271 -> 0 | D271: 0 | E271: =SUMIF('Entries 24-25'!$B:$B,A:A,'Entries 24-25'!$D:$D)-SUMIF('Entries 24-25'!$B:$B,A:A,'Entries 24-25'!$E:$E)+SUMIF('IND AS entries 24-25'!$B:$B,A:A,'IND AS entries 24-25'!$D:$D)-SUMIF('IND AS entries 24-25'!$B:$B,A:A,'IND AS entries 24-25'!$E:$E) -> 0 | F271: =SUM(C271:E271) -> 0 | H271: 0 | I271: 0 | J271: 0 | K271: =SUM(H271:J271) -> 0 | L271: =VLOOKUP(A271,'BS Gr'!A:A,1,FALSE) -> 101793 | M271: =COUNTIF(A:A,A271) -> 1 | N271: =C271-K271 -> 0 | O271: =C271-K271 -> 0 | P271: 6220514.3 | Q271: =+K271-P271 -> -6220514.3 | S271: =SUMIF('[105]TB for financial'!$A:$A,A271,'[105]TB for financial'!$E:$E) -> #VALUE!
A272: 101794 | B272: Sales Tax Recoverable | C272: =K272 -> 0 | D272: 0 | E272: =SUMIF('Entries 24-25'!$B:$B,A:A,'Entries 24-25'!$D:$D)-SUMIF('Entries 24-25'!$B:$B,A:A,'Entries 24-25'!$E:$E)+SUMIF('IND AS entries 24-25'!$B:$B,A:A,'IND AS entries 24-25'!$D:$D)-SUMIF('IND AS entries 24-25'!$B:$B,A:A,'IND AS entries 24-25'!$E:$E) -> 0 | F272: =SUM(C272:E272) -> 0 | H272: 0 | I272: 0 | J272: 0 | K272: =SUM(H272:J272) -> 0 | L272: =VLOOKUP(A272,'BS Gr'!A:A,1,FALSE) -> 101794 | M272: =COUNTIF(A:A,A272) -> 1 | N272: =C272-K272 -> 0 | O272: =C272-K272 -> 0 | P272: 0 | Q272: =+K272-P272 -> 0 | S272: =SUMIF('[105]TB for financial'!$A:$A,A272,'[105]TB for financial'!$E:$E) -> #VALUE!
A273: 101795 | B273: Preliminary Expenses | C273: =K273 -> 0 | D273: 0 | E273: =SUMIF('Entries 24-25'!$B:$B,A:A,'Entries 24-25'!$D:$D)-SUMIF('Entries 24-25'!$B:$B,A:A,'Entries 24-25'!$E:$E)+SUMIF('IND AS entries 24-25'!$B:$B,A:A,'IND AS entries 24-25'!$D:$D)-SUMIF('IND AS entries 24-25'!$B:$B,A:A,'IND AS entries 24-25'!$E:$E) -> 0 | F273: =SUM(C273:E273) -> 0 | H273: 0 | I273: 0 | J273: 0 | K273: =SUM(H273:J273) -> 0 | L273: =VLOOKUP(A273,'BS Gr'!A:A,1,FALSE) -> 101795 | M273: =COUNTIF(A:A,A273) -> 1 | N273: =C273-K273 -> 0 | O273: =C273-K273 -> 0 | P273: 0 | Q273: =+K273-P273 -> 0 | S273: =SUMIF('[105]TB for financial'!$A:$A,A273,'[105]TB for financial'!$E:$E) -> #VALUE!
... A292: 101816 | B292: Deposits - Office Premises | C292: =K292 -> 0 | D292: 0 | E292: =SUMIF('Entries 24-25'!$B:$B,A:A,'Entries 24-25'!$D:$D)-SUMIF('Entries 24-25'!$B:$B,A:A,'Entries 24-25'!$E:$E)+SUMIF('IND AS entries 24-25'!$B:$B,A:A,'IND AS entries 24-25'!$D:$D)-SUMIF('IND AS entries 24-25'!$B:$B,A:A,'IND AS entries 24-25'!$E:$E) -> 0 | F292: =SUM(C292:E292) -> 0 | H292: 0 | I292: 0 | J292: 0 | K292: =SUM(H292:J292) -> 0 | L292: =VLOOKUP(A292,'BS Gr'!A:A,1,FALSE) -> 101816 | M292: =COUNTIF(A:A,A292) -> 1 | N292: =C292-K292 -> 0 | O292: =C292-K292 -> 0 | P292: 17047470 | Q292: =+K292-P292 -> -17047470 | S292: =SUMIF('[105]TB for financial'!$A:$A,A292,'[105]TB for financial'!$E:$E) -> #VALUE!
A293: 101861 | B293: JPMorgan Chase Bank FD | C293: =K293 -> 0 | D293: 0 | E293: =SUMIF('Entries 24-25'!$B:$B,A:A,'Entries 24-25'!$D:$D)-SUMIF('Entries 24-25'!$B:$B,A:A,'Entries 24-25'!$E:$E)+SUMIF('IND AS entries 24-25'!$B:$B,A:A,'IND AS entries 24-25'!$D:$D)-SUMIF('IND AS entries 24-25'!$B:$B,A:A,'IND AS entries 24-25'!$E:$E) -> 0 | F293: =SUM(C293:E293) -> 0 | H293: 0 | I293: 0 | J293: 0 | K293: =SUM(H293:J293) -> 0 | L293: =VLOOKUP(A293,'BS Gr'!A:A,1,FALSE) -> 101861 | M293: =COUNTIF(A:A,A293) -> 1 | N293: =C293-K293 -> 0 | O293: =C293-K293 -> 0 | S293: =SUMIF('[105]TB for financial'!$A:$A,A293,'[105]TB for financial'!$E:$E) -> #VALUE!
A294: 101872 | B294: Prepaid rent - intrnl deposits | C294: =K294 -> 0 | D294: 0 | E294: =SUMIF('Entries 24-25'!$B:$B,A:A,'Entries 24-25'!$D:$D)-SUMIF('Entries 24-25'!$B:$B,A:A,'Entries 24-25'!$E:$E)+SUMIF('IND AS entries 24-25'!$B:$B,A:A,'IND AS entries 24-25'!$D:$D)-SUMIF('IND AS entries 24-25'!$B:$B,A:A,'IND AS entries 24-25'!$E:$E) -> 0 | F294: =SUM(C294:E294) -> 0 | H294: 0 | I294: 0 | J294: 0 | K294: =SUM(H294:J294) -> 0 | L294: =VLOOKUP(A294,'BS Gr'!A:A,1,FALSE) -> 101872 | M294: =COUNTIF(A:A,A294) -> 1 | N294: =C294-K294 -> 0 | O294: =C294-K294 -> 0 | S294: =SUMIF('[105]TB for financial'!$A:$A,A294,'[105]TB for financial'!$E:$E) -> #VALUE!
A295: 101817 | B295: Deposits - Guest House | C295: =K295 -> 0 | D295: 0 | E295: =SUMIF('Entries 24-25'!$B:$B,A:A,'Entries 24-25'!$D:$D)-SUMIF('Entries 24-25'!$B:$B,A:A,'Entries 24-25'!$E:$E)+SUMIF('IND AS entries 24-25'!$B:$B,A:A,'IND AS entries 24-25'!$D:$D)-SUMIF('IND AS entries 24-25'!$B:$B,A:A,'IND AS entries 24-25'!$E:$E) -> 0 | F295: =SUM(C295:E295) -> 0 | H295: 0 | I295: 0 | J295: 0 | K295: =SUM(H295:J295) -> 0 | L295: =VLOOKUP(A295,'BS Gr'!A:A,1,FALSE) -> 101817 | M295: =COUNTIF(A:A,A295) -> 1 | N295: =C295-K295 -> 0 | O295: =C295-K295 -> 0 | P295: 0 | Q295: =+K295-P295 -> 0 | S295: =SUMIF('[105]TB for financial'!$A:$A,A295,'[105]TB for financial'!$E:$E) -> #VALUE!
A296: 101818 | B296: Deposits - Flat for Employees | C296: =K296 -> 0 | D296: 0 | E296: =SUMIF('Entries 24-25'!$B:$B,A:A,'Entries 24-25'!$D:$D)-SUMIF('Entries 24-25'!$B:$B,A:A,'Entries 24-25'!$E:$E)+SUMIF('IND AS entries 24-25'!$B:$B,A:A,'IND AS entries 24-25'!$D:$D)-SUMIF('IND AS entries 24-25'!$B:$B,A:A,'IND AS entries 24-25'!$E:$E) -> 0 | F296: =SUM(C296:E296) -> 0 | H296: 0 | I296: 0 | J296: 0 | K296: =SUM(H296:J296) -> 0 | L296: =VLOOKUP(A296,'BS Gr'!A:A,1,FALSE) -> 101818 | M296: =COUNTIF(A:A,A296) -> 1 | N296: =C296-K296 -> 0 | O296: =C296-K296 -> 0 | P296: 0 | Q296: =+K296-P296 -> 0 | S296: =SUMIF('[105]TB for financial'!$A:$A,A296,'[105]TB for financial'!$E:$E) -> #VALUE!
A297: 101819 | B297: Deposits - Petrol Pumps | C297: =K297 -> 0 | D297: 0 | E297: =SUMIF('Entries 24-25'!$B:$B,A:A,'Entries 24-25'!$D:$D)-SUMIF('Entries 24-25'!$B:$B,A:A,'Entries 24-25'!$E:$E)+SUMIF('IND AS entries 24-25'!$B:$B,A:A,'IND AS entries 24-25'!$D:$D)-SUMIF('IND AS entries 24-25'!$B:$B,A:A,'IND AS entries 24-25'!$E:$E) -> 0 | F297: =SUM(C297:E297) -> 0 | H297: 0 | I297: 0 | J297: 0 | K297: =SUM(H297:J297) -> 0 | L297: =VLOOKUP(A297,'BS Gr'!A:A,1,FALSE) -> 101819 | M297: =COUNTIF(A:A,A297) -> 1 | N297: =C297-K297 -> 0 | O297: =C297-K297 -> 0 | P297: 0 | Q297: =+K297-P297 -> 0 | S297: =SUMIF('[105]TB for financial'!$A:$A,A297,'[105]TB for financial'!$E:$E) -> #VALUE!
A298: 101820 | B298: Deposits - F & F Hired | C298: =K298 -> 0 | D298: 0 | E298: =SUMIF('Entries 24-25'!$B:$B,A:A,'Entries 24-25'!$D:$D)-SUMIF('Entries 24-25'!$B:$B,A:A,'Entries 24-25'!$E:$E)+SUMIF('IND AS entries 24-25'!$B:$B,A:A,'IND AS entries 24-25'!$D:$D)-SUMIF('IND AS entries 24-25'!$B:$B,A:A,'IND AS entries 24-25'!$E:$E) -> 0 | F298: =SUM(C298:E298) -> 0 | H298: 0 | I298: 0 | J298: 0 | K298: =SUM(H298:J298) -> 0 | L298: =VLOOKUP(A298,'BS Gr'!A:A,1,FALSE) -> 101820 | M298: =COUNTIF(A:A,A298) -> 1 | N298: =C298-K298 -> 0 | O298: =C298-K298 -> 0 | P298: 0 | Q298: =+K298-P298 -> 0 | S298: =SUMIF('[105]TB for financial'!$A:$A,A298,'[105]TB for financial'!$E:$E) -> #VALUE!
A299: 101821 | B299: Deposits - Plants Hired | C299: =K299 -> 0 | D299: 0 | E299: =SUMIF('Entries 24-25'!$B:$B,A:A,'Entries 24-25'!$D:$D)-SUMIF('Entries 24-25'!$B:$B,A:A,'Entries 24-25'!$E:$E)+SUMIF('IND AS entries 24-25'!$B:$B,A:A,'IND AS entries 24-25'!$D:$D)-SUMIF('IND AS entries 24-25'!$B:$B,A:A,'IND AS entries 24-25'!$E:$E) -> 0 | F299: =SUM(C299:E299) -> 0 | H299: 0 | I299: 0 | J299: 0 | K299: =SUM(H299:J299) -> 0 | L299: =VLOOKUP(A299,'BS Gr'!A:A,1,FALSE) -> 101821 | M299: =COUNTIF(A:A,A299) -> 1 | N299: =C299-K299 -> 0 | O299: =C299-K299 -> 0 | P299: 0 | Q299: =+K299-P299 -> 0 | S299: =SUMIF('[105]TB for financial'!$A:$A,A299,'[105]TB for financial'!$E:$E) -> #VALUE!
A300: 101822 | B300: Deposits - Oriental - F Travel | C300: =K300 -> 0 | D300: 0 | E300: =SUMIF('Entries 24-25'!$B:$B,A:A,'Entries 24-25'!$D:$D)-SUMIF('Entries 24-25'!$B:$B,A:A,'Entries 24-25'!$E:$E)+SUMIF('IND AS entries 24-25'!$B:$B,A:A,'IND AS entries 24-25'!$D:$D)-SUMIF('IND AS entries 24-25'!$B:$B,A:A,'IND AS entries 24-25'!$E:$E) -> 0 | F300: =SUM(C300:E300) -> 0 | H300: 0 | I300: 0 | J300: 0 | K300: =SUM(H300:J300) -> 0 | L300: =VLOOKUP(A300,'BS Gr'!A:A,1,FALSE) -> 101822 | M300: =COUNTIF(A:A,A300) -> 1 | N300: =C300-K300 -> 0 | O300: =C300-K300 -> 0 | P300: 0 | Q300: =+K300-P300 -> 0 | S300: =SUMIF('[105]TB for financial'!$A:$A,A300,'[105]TB for financial'!$E:$E) -> #VALUE!
A301: 101823 | B301: Deposits - Oriental - Others | C301: =K301 -> 0 | D301: 0 | E301: =SUMIF('Entries 24-25'!$B:$B,A:A,'Entries 24-25'!$D:$D)-SUMIF('Entries 24-25'!$B:$B,A:A,'Entries 24-25'!$E:$E)+SUMIF('IND AS entries 24-25'!$B:$B,A:A,'IND AS entries 24-25'!$D:$D)-SUMIF('IND AS entries 24-25'!$B:$B,A:A,'IND AS entries 24-25'!$E:$E) -> 0 | F301: =SUM(C301:E301) -> 0 | H301: 0 | I301: 0 | J301: 0 | K301: =SUM(H301:J301) -> 0 | L301: =VLOOKUP(A301,'BS Gr'!A:A,1,FALSE) -> 101823 | M301: =COUNTIF(A:A,A301) -> 1 | N301: =C301-K301 -> 0 | O301: =C301-K301 -> 0 | P301: 0 | Q301: =+K301-P301 -> 0 | S301: =SUMIF('[105]TB for financial'!$A:$A,A301,'[105]TB for financial'!$E:$E) -> #VALUE!
A302: 101824 | B302: Deposits - Books | C302: =K302 -> 0 | D302: 0 | E302: =SUMIF('Entries 24-25'!$B:$B,A:A,'Entries 24-25'!$D:$D)-SUMIF('Entries 24-25'!$B:$B,A:A,'Entries 24-25'!$E:$E)+SUMIF('IND AS entries 24-25'!$B:$B,A:A,'IND AS entries 24-25'!$D:$D)-SUMIF('IND AS entries 24-25'!$B:$B,A:A,'IND AS entries 24-25'!$E:$E) -> 0 | F302: =SUM(C302:E302) -> 0 | H302: 0 | I302: 0 | J302: 0 | K302: =SUM(H302:J302) -> 0 | L302: =VLOOKUP(A302,'BS Gr'!A:A,1,FALSE) -> 101824 | M302: =COUNTIF(A:A,A302) -> 1 | N302: =C302-K302 -> 0 | O302: =C302-K302 -> 0 | P302: 0 | Q302: =+K302-P302 -> 0 | S302: =SUMIF('[105]TB for financial'!$A:$A,A302,'[105]TB for financial'!$E:$E) -> #VALUE!
A303: 101825 | B303: Deposits - Hospitals | C303: =K303 -> 0 | D303: 0 | E303: =SUMIF('Entries 24-25'!$B:$B,A:A,'Entries 24-25'!$D:$D)-SUMIF('Entries 24-25'!$B:$B,A:A,'Entries 24-25'!$E:$E)+SUMIF('IND AS entries 24-25'!$B:$B,A:A,'IND AS entries 24-25'!$D:$D)-SUMIF('IND AS entries 24-25'!$B:$B,A:A,'IND AS entries 24-25'!$E:$E) -> 0 | F303: =SUM(C303:E303) -> 0 | H303: 0 | I303: 0 | J303: 0 | K303: =SUM(H303:J303) -> 0 | L303: =VLOOKUP(A303,'BS Gr'!A:A,1,FALSE) -> 101825 | M303: =COUNTIF(A:A,A303) -> 1 | N303: =C303-K303 -> 0 | O303: =C303-K303 -> 0 | P303: 0 | Q303: =+K303-P303 -> 0 | S303: =SUMIF('[105]TB for financial'!$A:$A,A303,'[105]TB for financial'!$E:$E) -> #VALUE!
A304: 101826 | B304: Deposits - Membership | C304: =K304 -> 0 | D304: 0 | E304: =SUMIF('Entries 24-25'!$B:$B,A:A,'Entries 24-25'!$D:$D)-SUMIF('Entries 24-25'!$B:$B,A:A,'Entries 24-25'!$E:$E)+SUMIF('IND AS entries 24-25'!$B:$B,A:A,'IND AS entries 24-25'!$D:$D)-SUMIF('IND AS entries 24-25'!$B:$B,A:A,'IND AS entries 24-25'!$E:$E) -> 0 | F304: =SUM(C304:E304) -> 0 | H304: 0 | I304: 0 | J304: 0 | K304: =SUM(H304:J304) -> 0 | L304: =VLOOKUP(A304,'BS Gr'!A:A,1,FALSE) -> 101826 | M304: =COUNTIF(A:A,A304) -> 1 | N304: =C304-K304 -> 0 | O304: =C304-K304 -> 0 | P304: 15000 | Q304: =+K304-P304 -> -15000 | S304: =SUMIF('[105]TB for financial'!$A:$A,A304,'[105]TB for financial'!$E:$E) -> #VALUE!
A305: 101827 | B305: Deposits - Security Dep. | C305: =K305 -> 0 | D305: 0 | E305: =SUMIF('Entries 24-25'!$B:$B,A:A,'Entries 24-25'!$D:$D)-SUMIF('Entries 24-25'!$B:$B,A:A,'Entries 24-25'!$E:$E)+SUMIF('IND AS entries 24-25'!$B:$B,A:A,'IND AS entries 24-25'!$D:$D)-SUMIF('IND AS entries 24-25'!$B:$B,A:A,'IND AS entries 24-25'!$E:$E) -> 0 | F305: =SUM(C305:E305) -> 0 | H305: 0 | I305: 0 | J305: 0 | K305: =SUM(H305:J305) -> 0 | L305: =VLOOKUP(A305,'BS Gr'!A:A,1,FALSE) -> 101827 | M305: =COUNTIF(A:A,A305) -> 1 | N305: =C305-K305 -> 0 | O305: =C305-K305 -> 0 | P305: 0 | Q305: =+K305-P305 -> 0 | S305: =SUMIF('[105]TB for financial'!$A:$A,A305,'[105]TB for financial'!$E:$E) -> #VALUE!
A306: 101828 | B306: Deposits - Pagers | C306: =K306 -> 0 | D306: 0 | E306: =SUMIF('Entries 24-25'!$B:$B,A:A,'Entries 24-25'!$D:$D)-SUMIF('Entries 24-25'!$B:$B,A:A,'Entries 24-25'!$E:$E)+SUMIF('IND AS entries 24-25'!$B:$B,A:A,'IND AS entries 24-25'!$D:$D)-SUMIF('IND AS entries 24-25'!$B:$B,A:A,'IND AS entries 24-25'!$E:$E) -> 0 | F306: =SUM(C306:E306) -> 0 | H306: 0 | I306: 0 | J306: 0 | K306: =SUM(H306:J306) -> 0 | L306: =VLOOKUP(A306,'BS Gr'!A:A,1,FALSE) -> 101828 | M306: =COUNTIF(A:A,A306) -> 1 | N306: =C306-K306 -> 0 | O306: =C306-K306 -> 0 | P306: 0 | Q306: =+K306-P306 -> 0 | S306: =SUMIF('[105]TB for financial'!$A:$A,A306,'[105]TB for financial'!$E:$E) -> #VALUE!
... A317: 101839 | B317: Deposit-Futur Gener Life Insur | C317: =K317 -> 0 | D317: 0 | E317: =SUMIF('Entries 24-25'!$B:$B,A:A,'Entries 24-25'!$D:$D)-SUMIF('Entries 24-25'!$B:$B,A:A,'Entries 24-25'!$E:$E)+SUMIF('IND AS entries 24-25'!$B:$B,A:A,'IND AS entries 24-25'!$D:$D)-SUMIF('IND AS entries 24-25'!$B:$B,A:A,'IND AS entries 24-25'!$E:$E) -> 0 | F317: =SUM(C317:E317) -> 0 | H317: 0 | I317: 0 | J317: 0 | K317: =SUM(H317:J317) -> 0 | L317: =VLOOKUP(A317,'BS Gr'!A:A,1,FALSE) -> 101839 | M317: =COUNTIF(A:A,A317) -> 1 | N317: =C317-K317 -> 0 | O317: =C317-K317 -> 0 | P317: 0 | Q317: =+K317-P317 -> 0 | S317: =SUMIF('[105]TB for financial'!$A:$A,A317,'[105]TB for financial'!$E:$E) -> #VALUE!
A318: 101843 | B318: Regrou Non Cur Advanc Tax less | C318: =K318 -> 0 | D318: 0 | E318: =SUMIF('Entries 24-25'!$B:$B,A:A,'Entries 24-25'!$D:$D)-SUMIF('Entries 24-25'!$B:$B,A:A,'Entries 24-25'!$E:$E)+SUMIF('IND AS entries 24-25'!$B:$B,A:A,'IND AS entries 24-25'!$D:$D)-SUMIF('IND AS entries 24-25'!$B:$B,A:A,'IND AS entries 24-25'!$E:$E) -> 0 | F318: =SUM(C318:E318) -> 0 | H318: 0 | I318: 0 | J318: 0 | K318: =SUM(H318:J318) -> 0 | L318: =VLOOKUP(A318,'BS Gr'!A:A,1,FALSE) -> 101843 | M318: =COUNTIF(A:A,A318) -> 1 | N318: =C318-K318 -> 0 | O318: =C318-K318 -> 0 | S318: =SUMIF('[105]TB for financial'!$A:$A,A318,'[105]TB for financial'!$E:$E) -> #VALUE!
A319: 101848 | B319: Regrou Non Cur Advance Tax add | C319: =K319 -> 0 | D319: 0 | E319: =SUMIF('Entries 24-25'!$B:$B,A:A,'Entries 24-25'!$D:$D)-SUMIF('Entries 24-25'!$B:$B,A:A,'Entries 24-25'!$E:$E)+SUMIF('IND AS entries 24-25'!$B:$B,A:A,'IND AS entries 24-25'!$D:$D)-SUMIF('IND AS entries 24-25'!$B:$B,A:A,'IND AS entries 24-25'!$E:$E) -> 0 | F319: =SUM(C319:E319) -> 0 | H319: 0 | I319: 0 | J319: 0 | K319: =SUM(H319:J319) -> 0 | L319: =VLOOKUP(A319,'BS Gr'!A:A,1,FALSE) -> 101848 | M319: =COUNTIF(A:A,A319) -> 1 | N319: =C319-K319 -> 0 | O319: =C319-K319 -> 0 | S319: =SUMIF('[105]TB for financial'!$A:$A,A319,'[105]TB for financial'!$E:$E) -> #VALUE!
A320: 101850 | B320: Deposits - Inter Corporate | C320: =K320 -> 0 | D320: 0 | E320: =SUMIF('Entries 24-25'!$B:$B,A:A,'Entries 24-25'!$D:$D)-SUMIF('Entries 24-25'!$B:$B,A:A,'Entries 24-25'!$E:$E)+SUMIF('IND AS entries 24-25'!$B:$B,A:A,'IND AS entries 24-25'!$D:$D)-SUMIF('IND AS entries 24-25'!$B:$B,A:A,'IND AS entries 24-25'!$E:$E) -> 0 | F320: =SUM(C320:E320) -> 0 | H320: 0 | I320: 0 | J320: 0 | K320: =SUM(H320:J320) -> 0 | L320: =VLOOKUP(A320,'BS Gr'!A:A,1,FALSE) -> 101850 | M320: =COUNTIF(A:A,A320) -> 1 | N320: =C320-K320 -> 0 | O320: =C320-K320 -> 0 | P320: 0 | Q320: =+K320-P320 -> 0 | S320: =SUMIF('[105]TB for financial'!$A:$A,A320,'[105]TB for financial'!$E:$E) -> #VALUE!
A321: 101851 | B321: Provision for Doubtful Deposits | C321: =K321 -> 0 | D321: 0 | E321: =SUMIF('Entries 24-25'!$B:$B,A:A,'Entries 24-25'!$D:$D)-SUMIF('Entries 24-25'!$B:$B,A:A,'Entries 24-25'!$E:$E)+SUMIF('IND AS entries 24-25'!$B:$B,A:A,'IND AS entries 24-25'!$D:$D)-SUMIF('IND AS entries 24-25'!$B:$B,A:A,'IND AS entries 24-25'!$E:$E) -> 0 | F321: =SUM(C321:E321) -> 0 | H321: 0 | I321: 0 | J321: 0 | K321: =SUM(H321:J321) -> 0 | L321: =VLOOKUP(A321,'BS Gr'!A:A,1,FALSE) -> 101851 | M321: =COUNTIF(A:A,A321) -> 1 | N321: =C321-K321 -> 0 | O321: =C321-K321 -> 0 | P321: 0 | Q321: =+K321-P321 -> 0 | S321: =SUMIF('[105]TB for financial'!$A:$A,A321,'[105]TB for financial'!$E:$E) -> #VALUE!
A322: 101852 | B322: Deposit - Kotak M Old Mut Life | C322: =K322 -> 0 | D322: 0 | E322: =SUMIF('Entries 24-25'!$B:$B,A:A,'Entries 24-25'!$D:$D)-SUMIF('Entries 24-25'!$B:$B,A:A,'Entries 24-25'!$E:$E)+SUMIF('IND AS entries 24-25'!$B:$B,A:A,'IND AS entries 24-25'!$D:$D)-SUMIF('IND AS entries 24-25'!$B:$B,A:A,'IND AS entries 24-25'!$E:$E) -> 0 | F322: =SUM(C322:E322) -> 0 | H322: 0 | I322: 0 | J322: 0 | K322: =SUM(H322:J322) -> 0 | L322: =VLOOKUP(A322,'BS Gr'!A:A,1,FALSE) -> 101852 | M322: =COUNTIF(A:A,A322) -> 1 | N322: =C322-K322 -> 0 | O322: =C322-K322 -> 0 | P322: 0 | Q322: =+K322-P322 -> 0 | S322: =SUMIF('[105]TB for financial'!$A:$A,A322,'[105]TB for financial'!$E:$E) -> #VALUE!
A323: 101853 | B323: Deposit - United India Ins. | C323: =K323 -> 0 | D323: 0 | E323: =SUMIF('Entries 24-25'!$B:$B,A:A,'Entries 24-25'!$D:$D)-SUMIF('Entries 24-25'!$B:$B,A:A,'Entries 24-25'!$E:$E)+SUMIF('IND AS entries 24-25'!$B:$B,A:A,'IND AS entries 24-25'!$D:$D)-SUMIF('IND AS entries 24-25'!$B:$B,A:A,'IND AS entries 24-25'!$E:$E) -> 0 | F323: =SUM(C323:E323) -> 0 | H323: 0 | I323: 0 | J323: 0 | K323: =SUM(H323:J323) -> 0 | L323: =VLOOKUP(A323,'BS Gr'!A:A,1,FALSE) -> 101853 | M323: =COUNTIF(A:A,A323) -> 1 | N323: =C323-K323 -> 0 | O323: =C323-K323 -> 0 | P323: 0 | Q323: =+K323-P323 -> 0 | S323: =SUMIF('[105]TB for financial'!$A:$A,A323,'[105]TB for financial'!$E:$E) -> #VALUE!
A324: 101858 | B324: Deposit-National India Insuran | C324: =K324 -> 0 | D324: 0 | E324: =SUMIF('Entries 24-25'!$B:$B,A:A,'Entries 24-25'!$D:$D)-SUMIF('Entries 24-25'!$B:$B,A:A,'Entries 24-25'!$E:$E)+SUMIF('IND AS entries 24-25'!$B:$B,A:A,'IND AS entries 24-25'!$D:$D)-SUMIF('IND AS entries 24-25'!$B:$B,A:A,'IND AS entries 24-25'!$E:$E) -> 0 | F324: =SUM(C324:E324) -> 0 | H324: 0 | I324: 0 | J324: 0 | K324: =SUM(H324:J324) -> 0 | L324: =VLOOKUP(A324,'BS Gr'!A:A,1,FALSE) -> 101858 | M324: =COUNTIF(A:A,A324) -> 1 | N324: =C324-K324 -> 0 | O324: =C324-K324 -> 0 | S324: =SUMIF('[105]TB for financial'!$A:$A,A324,'[105]TB for financial'!$E:$E) -> #VALUE!
A325: 110020 | B325: Automobiles | C325: =K325 -> 0 | D325: 0 | E325: =SUMIF('Entries 24-25'!$B:$B,A:A,'Entries 24-25'!$D:$D)-SUMIF('Entries 24-25'!$B:$B,A:A,'Entries 24-25'!$E:$E)+SUMIF('IND AS entries 24-25'!$B:$B,A:A,'IND AS entries 24-25'!$D:$D)-SUMIF('IND AS entries 24-25'!$B:$B,A:A,'IND AS entries 24-25'!$E:$E) -> 0 | F325: =SUM(C325:E325) -> 0 | H325: 0 | I325: 0 | J325: 0 | K325: =SUM(H325:J325) -> 0 | L325: =VLOOKUP(A325,'BS Gr'!A:A,1,FALSE) -> 110020 | M325: =COUNTIF(A:A,A325) -> 1 | N325: =C325-K325 -> 0 | O325: =C325-K325 -> 0 | P325: 0 | Q325: =+K325-P325 -> 0 | S325: =SUMIF('[105]TB for financial'!$A:$A,A325,'[105]TB for financial'!$E:$E) -> #VALUE!
A326: 110025 | B326: Automobile-Emp Vehicle Policy | C326: =K326 -> 0 | D326: 0 | E326: =SUMIF('Entries 24-25'!$B:$B,A:A,'Entries 24-25'!$D:$D)-SUMIF('Entries 24-25'!$B:$B,A:A,'Entries 24-25'!$E:$E)+SUMIF('IND AS entries 24-25'!$B:$B,A:A,'IND AS entries 24-25'!$D:$D)-SUMIF('IND AS entries 24-25'!$B:$B,A:A,'IND AS entries 24-25'!$E:$E) -> 0 | F326: =SUM(C326:E326) -> 0 | H326: 0 | I326: 0 | J326: 0 | K326: =SUM(H326:J326) -> 0 | L326: =VLOOKUP(A326,'BS Gr'!A:A,1,FALSE) -> 110025 | M326: =COUNTIF(A:A,A326) -> 1 | N326: =C326-K326 -> 0 | O326: =C326-K326 -> 0 | P326: 0 | Q326: =+K326-P326 -> 0 | S326: =SUMIF('[105]TB for financial'!$A:$A,A326,'[105]TB for financial'!$E:$E) -> #VALUE!
A327: 110030 | B327: Computer Equipment | C327: =K327 -> 0 | D327: 0 | E327: =SUMIF('Entries 24-25'!$B:$B,A:A,'Entries 24-25'!$D:$D)-SUMIF('Entries 24-25'!$B:$B,A:A,'Entries 24-25'!$E:$E)+SUMIF('IND AS entries 24-25'!$B:$B,A:A,'IND AS entries 24-25'!$D:$D)-SUMIF('IND AS entries 24-25'!$B:$B,A:A,'IND AS entries 24-25'!$E:$E) -> 0 | F327: =SUM(C327:E327) -> 0 | H327: 0 | I327: 0 | J327: 0 | K327: =SUM(H327:J327) -> 0 | L327: =VLOOKUP(A327,'BS Gr'!A:A,1,FALSE) -> 110030 | M327: =COUNTIF(A:A,A327) -> 1 | N327: =C327-K327 -> 0 | O327: =C327-K327 -> 0 | P327: 13485280 | Q327: =+K327-P327 -> -13485280 | S327: =SUMIF('[105]TB for financial'!$A:$A,A327,'[105]TB for financial'!$E:$E) -> #VALUE!
A328: 110031 | B328: CWIP – Computers | C328: =K328 -> 0 | D328: 0 | E328: =SUMIF('Entries 24-25'!$B:$B,A:A,'Entries 24-25'!$D:$D)-SUMIF('Entries 24-25'!$B:$B,A:A,'Entries 24-25'!$E:$E)+SUMIF('IND AS entries 24-25'!$B:$B,A:A,'IND AS entries 24-25'!$D:$D)-SUMIF('IND AS entries 24-25'!$B:$B,A:A,'IND AS entries 24-25'!$E:$E) -> 0 | F328: =SUM(C328:E328) -> 0 | H328: 0 | I328: 0 | J328: 0 | K328: =SUM(H328:J328) -> 0 | L328: =VLOOKUP(A328,'BS Gr'!A:A,1,FALSE) -> 110031 | M328: =COUNTIF(A:A,A328) -> 1 | N328: =C328-K328 -> 0 | O328: =C328-K328 -> 0 | P328: 0 | Q328: =+K328-P328 -> 0 | S328: =SUMIF('[105]TB for financial'!$A:$A,A328,'[105]TB for financial'!$E:$E) -> #VALUE!
A329: 110035 | B329: Office Building | C329: =K329 -> 0 | D329: 0 | E329: =SUMIF('Entries 24-25'!$B:$B,A:A,'Entries 24-25'!$D:$D)-SUMIF('Entries 24-25'!$B:$B,A:A,'Entries 24-25'!$E:$E)+SUMIF('IND AS entries 24-25'!$B:$B,A:A,'IND AS entries 24-25'!$D:$D)-SUMIF('IND AS entries 24-25'!$B:$B,A:A,'IND AS entries 24-25'!$E:$E) -> 0 | F329: =SUM(C329:E329) -> 0 | H329: 0 | I329: 0 | J329: 0 | K329: =SUM(H329:J329) -> 0 | L329: =VLOOKUP(A329,'BS Gr'!A:A,1,FALSE) -> 110035 | M329: =COUNTIF(A:A,A329) -> 1 | N329: =C329-K329 -> 0 | O329: =C329-K329 -> 0 | P329: 0 | Q329: =+K329-P329 -> 0 | S329: =SUMIF('[105]TB for financial'!$A:$A,A329,'[105]TB for financial'!$E:$E) -> #VALUE!
A330: 110040 | B330: Furniture and Fixtures | C330: =K330 -> 0 | D330: 0 | E330: =SUMIF('Entries 24-25'!$B:$B,A:A,'Entries 24-25'!$D:$D)-SUMIF('Entries 24-25'!$B:$B,A:A,'Entries 24-25'!$E:$E)+SUMIF('IND AS entries 24-25'!$B:$B,A:A,'IND AS entries 24-25'!$D:$D)-SUMIF('IND AS entries 24-25'!$B:$B,A:A,'IND AS entries 24-25'!$E:$E) -> 0 | F330: =SUM(C330:E330) -> 0 | H330: 0 | I330: 0 | J330: 0 | K330: =SUM(H330:J330) -> 0 | L330: =VLOOKUP(A330,'BS Gr'!A:A,1,FALSE) -> 110040 | M330: =COUNTIF(A:A,A330) -> 1 | N330: =C330-K330 -> 0 | O330: =C330-K330 -> 0 | P330: 0 | Q330: =+K330-P330 -> 0 | S330: =SUMIF('[105]TB for financial'!$A:$A,A330,'[105]TB for financial'!$E:$E) -> #VALUE!
A331: 110050 | B331: Leasehold Improvements | C331: =K331 -> 0 | D331: 0 | E331: =SUMIF('Entries 24-25'!$B:$B,A:A,'Entries 24-25'!$D:$D)-SUMIF('Entries 24-25'!$B:$B,A:A,'Entries 24-25'!$E:$E)+SUMIF('IND AS entries 24-25'!$B:$B,A:A,'IND AS entries 24-25'!$D:$D)-SUMIF('IND AS entries 24-25'!$B:$B,A:A,'IND AS entries 24-25'!$E:$E) -> 0 | F331: =SUM(C331:E331) -> 0 | H331: 0 | I331: 0 | J331: 0 | K331: =SUM(H331:J331) -> 0 | L331: =VLOOKUP(A331,'BS Gr'!A:A,1,FALSE) -> 110050 | M331: =COUNTIF(A:A,A331) -> 1 | N331: =C331-K331 -> 0 | O331: =C331-K331 -> 0 | P331: 0 | Q331: =+K331-P331 -> 0 | S331: =SUMIF('[105]TB for financial'!$A:$A,A331,'[105]TB for financial'!$E:$E) -> #VALUE!
A332: 110055 | B332: Leasehold Land - GDC | C332: =K332 -> 0 | D332: 0 | E332: =SUMIF('Entries 24-25'!$B:$B,A:A,'Entries 24-25'!$D:$D)-SUMIF('Entries 24-25'!$B:$B,A:A,'Entries 24-25'!$E:$E)+SUMIF('IND AS entries 24-25'!$B:$B,A:A,'IND AS entries 24-25'!$D:$D)-SUMIF('IND AS entries 24-25'!$B:$B,A:A,'IND AS entries 24-25'!$E:$E) -> 0 | F332: =SUM(C332:E332) -> 0 | H332: 0 | I332: 0 | J332: 0 | K332: =SUM(H332:J332) -> 0 | L332: =VLOOKUP(A332,'BS Gr'!A:A,1,FALSE) -> 110055 | M332: =COUNTIF(A:A,A332) -> 1 | N332: =C332-K332 -> 0 | O332: =C332-K332 -> 0 | P332: 0 | Q332: =+K332-P332 -> 0 | S332: =SUMIF('[105]TB for financial'!$A:$A,A332,'[105]TB for financial'!$E:$E) -> #VALUE!
A333: 110060 | B333: Communications Equipment | C333: =K333 -> 0 | D333: 0 | E333: =SUMIF('Entries 24-25'!$B:$B,A:A,'Entries 24-25'!$D:$D)-SUMIF('Entries 24-25'!$B:$B,A:A,'Entries 24-25'!$E:$E)+SUMIF('IND AS entries 24-25'!$B:$B,A:A,'IND AS entries 24-25'!$D:$D)-SUMIF('IND AS entries 24-25'!$B:$B,A:A,'IND AS entries 24-25'!$E:$E) -> 0 | F333: =SUM(C333:E333) -> 0 | H333: 0 | I333: 0 | J333: 0 | K333: =SUM(H333:J333) -> 0 | L333: =VLOOKUP(A333,'BS Gr'!A:A,1,FALSE) -> 110060 | M333: =COUNTIF(A:A,A333) -> 1 | N333: =C333-K333 -> 0 | O333: =C333-K333 -> 0 | P333: 0 | Q333: =+K333-P333 -> 0 | S333: =SUMIF('[105]TB for financial'!$A:$A,A333,'[105]TB for financial'!$E:$E) -> #VALUE!
A334: 110061 | B334: Air Conditioners | C334: =K334 -> 0 | D334: 0 | E334: =SUMIF('Entries 24-25'!$B:$B,A:A,'Entries 24-25'!$D:$D)-SUMIF('Entries 24-25'!$B:$B,A:A,'Entries 24-25'!$E:$E)+SUMIF('IND AS entries 24-25'!$B:$B,A:A,'IND AS entries 24-25'!$D:$D)-SUMIF('IND AS entries 24-25'!$B:$B,A:A,'IND AS entries 24-25'!$E:$E) -> 0 | F334: =SUM(C334:E334) -> 0 | H334: 0 | I334: 0 | J334: 0 | K334: =SUM(H334:J334) -> 0 | L334: =VLOOKUP(A334,'BS Gr'!A:A,1,FALSE) -> 110061 | M334: =COUNTIF(A:A,A334) -> 1 | N334: =C334-K334 -> 0 | O334: =C334-K334 -> 0 | P334: 0 | Q334: =+K334-P334 -> 0 | S334: =SUMIF('[105]TB for financial'!$A:$A,A334,'[105]TB for financial'!$E:$E) -> #VALUE!
A335: 110062 | B335: Electrical Equipments | C335: =K335 -> 0 | D335: 0 | E335: =SUMIF('Entries 24-25'!$B:$B,A:A,'Entries 24-25'!$D:$D)-SUMIF('Entries 24-25'!$B:$B,A:A,'Entries 24-25'!$E:$E)+SUMIF('IND AS entries 24-25'!$B:$B,A:A,'IND AS entries 24-25'!$D:$D)-SUMIF('IND AS entries 24-25'!$B:$B,A:A,'IND AS entries 24-25'!$E:$E) -> 0 | F335: =SUM(C335:E335) -> 0 | H335: 0 | I335: 0 | J335: 0 | K335: =SUM(H335:J335) -> 0 | L335: =VLOOKUP(A335,'BS Gr'!A:A,1,FALSE) -> 110062 | M335: =COUNTIF(A:A,A335) -> 1 | N335: =C335-K335 -> 0 | O335: =C335-K335 -> 0 | P335: 0 | Q335: =+K335-P335 -> 0 | S335: =SUMIF('[105]TB for financial'!$A:$A,A335,'[105]TB for financial'!$E:$E) -> #VALUE!
...

Sheet CF
A1: =+Master!B2 -> Syntel Solutions (India) Private Limited
A3: Cash Flow Statement for the year ended 31 March 2025
F5: Year ended | H5: Year ended
B6: Particular | F6: =BS!$G$7 -> 45747 | H6: =BS!$I$7 -> 45382
A8: A | B8: Cash flow from operating activities
B11: Net profit before tax | F11: =+PL!F26 -> -2956284 | H11: =+PL!H26 -> 19400000 | I11: -89 | J11: =+F11-I11 -> -2956195 | L11: -21 | M11: =+F11-L11 -> -2956263 | O11: -5695155 | P11: =+O11/100000 -> -56.95155 | Q11: =+F11-P11 -> -2956227
B12: Adjustments for: | J12: =+F12-I12 -> 0 | Q12: =+F12-P12 -> 0
B13: Depreciation and amortization | F13: =+PL!F16+PL!F17 -> 3206674 | H13: =+PL!H16+PL!H17 -> 3180953 | I13: 32 | J13: =+F13-I13 -> 3206642 | L13: 0 | M13: =+F13-L13 -> 3206674 | O13: 3173732 | P13: =+O13/100000 -> 31.73732 | Q13: =+F13-P13 -> 3206642.3
B14: Gain on disposal of property, plant and equipment, net | F14: =+'Sch - PL'!E97-'Sch - PL'!E36 -> 0 | H14: =+'Sch - PL'!G97-'Sch - PL'!G36 -> 0 | I14: 0 | J14: =+F14-I14 -> 0 | L14: 0 | O14: 0 | P14: =+O14/100000 -> 0 | Q14: =+F14-P14 -> 0
B15: Interest income | F15: =-'Sch - PL'!E24-'Sch - PL'!E26 -> -15602768 | H15: =-'Sch - PL'!G24-'Sch - PL'!G26-1 -> -15883749 | I15: -71 | J15: =+F15-I15 -> -15602697 | L15: -104 | M15: =+F15-L15 -> -15602664 | O15: -11684341 | P15: =+O15/100000 -> -116.84341 | Q15: =+F15-P15 -> -15602651
B16: Gain on modification of financial liability | F16: =-'18-26'!I29 -> 0 | H16: =-'18-26'!I29 -> 0
B17: Unwinding of discount on security deposits | F17: =-'Sch - PL'!E25 -> -217627 | H17: =-'Sch - PL'!G25 -> -188323 | I17: 0 | J17: =+F17-I17 -> -217627 | L17: 0 | O17: -158934 | P17: =+O17/100000 -> -1.58934 | Q17: =+F17-P17 -> -217625.41
B18: Profit on sale of mutual fund units (including fair value changes) | F18: =-'Sch - PL'!E32-'Sch - PL'!E33*0 -> 0 | H18: =-'Sch - PL'!G32-'Sch - PL'!G33*0 -> 0 | I18: 0 | J18: =+F18-I18 -> 0 | L18: -84 | M18: =+F18-L18 -> 84 | O18: 0 | P18: =+O18/100000 -> 0 | Q18: =+F18-P18 -> 0
